Workbook

Sheet 変更履歴
B2: システム名 | H2: 業務分類 | L2: システム分類 | R2: ドキュメント種別 | X2: ドキュメント名 | AK2: 試験対象 | AX2: 作成日 | BB2: 作成者 | BF2: 更新日 | BJ2: 更新者
B3: 受発注システム | H3: =LEFT($X$3,FIND("_",$X$3)-1) -> 請求売掛 | L3: 受発注 | R3: =MID($X$3,FIND("_",$X$3,FIND("_",$X$3)+1)+1,LEN($X$3)-FIND("_",$X$3,FIND("_",$X$3)+1)) -> 結合試験項目 | X3: =REPLACE(LEFT(CELL("filename",$B$2),FIND(".x",CELL("filename",$B$2))-1),1,FIND("[",CELL("filename",$B$2)),) -> 請求売掛_しまむら直納伝票請求書_結合試験項目 | AK3: =MID($X$3,FIND("_",$X$3)+1,FIND("_",$X$3,FIND("_",$X$3)+1)-FIND("_",$X$3)-1) -> しまむら直納伝票請求書 | AX3: 45628 | BB3: 児玉 | BF3: 45628 | BJ3: 児玉
C7: 変更履歴
C8: 日付 | G8: 版数 | K8: 担当 | O8: 変更箇所 | Y8: 内容
C9: 45628 | G9: 1.0.0 | O9: - | Y9: 新規作成

Sheet 画面
B2: システム名 | H2: 業務分類 | L2: システム分類 | R2: ドキュメント種別 | X2: ドキュメント名 | AK2: 試験対象 | AX2: 作成日 | BB2: 作成者 | BF2: 更新日 | BJ2: 更新者
B3: =変更履歴!B3 -> 受発注システム | H3: =変更履歴!H3 -> 請求売掛 | L3: =変更履歴!L3 -> 受発注 | R3: =変更履歴!R3 -> 結合試験項目 | X3: =変更履歴!X3 -> 請求売掛_しまむら直納伝票請求書_結合試験項目 | AK3: =変更履歴!AK3 -> しまむら直納伝票請求書 | AX3: =変更履歴!AX3 -> 45628 | BB3: =変更履歴!BB3 -> 児玉 | BF3: =変更履歴!BF3 -> 45628 | BJ3: =変更履歴!BJ3 -> 児玉
BE7: 件数 | BG7: 合計 | BI7: 終了 | BK7: 残
AO8: １回目 | AU8: 2回目 | BG8: =COUNTA(C10:C56) -> 47 | BI8: =COUNTIF(AS10:AT56,"OK")+COUNTIF(AY10:AZ56,"OK") -> 47 | BK8: =BG8-BI8 -> 0
C9: No. | D9: 大項目 | H9: 中項目 | L9: 小項目 | P9: 確認手順 | X9: 確認観点 | AF9: 補足事項(テスト項目補足、テストデータ等) | AO9: 確認日 | AQ9: 確認者 | AS9: 結果 | AU9: 確認日 | AW9: 確認者 | AY9: 結果 | BA9: 試験結果備考
C10: =ROW()-9 -> 1 | D10: 画面 | H10: 初期表示 | L10: 請求日付 | P10: メニューよりしまむら直納伝票請求書を起動する | X10: 入力欄が活性、かつ、空欄であること | AO10: 45665 | AQ10: 松村 | AS10: NG | AU10: 45695 | AW10: 児玉 | AY10: OK | BA10: 再表示時に前のデータが残る
C11: =ROW()-9 -> 2 | L11: 締日 | P11: メニューよりしまむら直納伝票請求書を起動する | X11: 入力欄が活性、かつ、空欄であること | AO11: 45665 | AQ11: 松村 | AS11: NG | AU11: 45695 | AW11: 児玉 | AY11: OK | BA11: 再表示時に前のデータが残る
C12: =ROW()-9 -> 3 | L12: 請求期間 | P12: メニューよりしまむら直納伝票請求書を起動する | X12: 入力欄が非活性、かつ、空欄であること | AO12: 45665 | AQ12: 松村 | AS12: NG | AU12: 45695 | AW12: 児玉 | AY12: OK | BA12: 再表示時に前のデータが残る
C13: =ROW()-9 -> 4 | L13: 得意先1 | P13: メニューよりしまむら直納伝票請求書を起動する | X13: 入力欄が活性、かつ、空欄であること | AO13: 45665 | AQ13: 松村 | AS13: NG | AU13: 45695 | AW13: 児玉 | AY13: OK | BA13: 再表示時に前のデータが残る
C14: =ROW()-9 -> 5 | L14: 得意先2 | P14: メニューよりしまむら直納伝票請求書を起動する | X14: 入力欄が非活性、かつ、空欄であること | AO14: 45665 | AQ14: 松村 | AS14: NG | AU14: 45695 | AW14: 児玉 | AY14: OK | BA14: 再表示時に前のデータが残る
C15: =ROW()-9 -> 6 | L15: 得意先3 | P15: メニューよりしまむら直納伝票請求書を起動する | X15: 入力欄が非活性、かつ、空欄であること | AO15: 45665 | AQ15: 松村 | AS15: NG | AU15: 45695 | AW15: 児玉 | AY15: OK | BA15: 再表示時に前のデータが残る
C16: =ROW()-9 -> 7 | L16: 伝票種類(左) | P16: メニューよりしまむら直納伝票請求書を起動する | X16: 入力欄が活性、かつ、空欄であること | AO16: 45665 | AQ16: 松村 | AS16: NG | AU16: 45695 | AW16: 児玉 | AY16: OK | BA16: 再表示時に前のデータが残る
C17: =ROW()-9 -> 8 | L17: 伝票種類(右) | P17: メニューよりしまむら直納伝票請求書を起動する | X17: 入力欄が非活性、かつ、区分の説明が表示されていること。 | AF17: 2:直納 3:mail消耗品 4:mail直納 | AO17: 45665 | AQ17: 松村 | AS17: OK
C18: =ROW()-9 -> 9 | L18: 内容区分(左) | P18: メニューよりしまむら直納伝票請求書を起動する | X18: 入力欄が活性、かつ、空欄であること | AO18: 45665 | AQ18: 松村 | AS18: NG | AU18: 45695 | AW18: 児玉 | AY18: OK | BA18: 初期値が0である・入力必須でない
C19: =ROW()-9 -> 10 | L19: 内容区分(右) | P19: メニューよりしまむら直納伝票請求書を起動する | X19: 入力欄が非活性、かつ、区分の説明が表示されていること。 | AF19: 0:なし 1:ﾃﾞｨﾊﾞﾛ 2:台湾3:システム開発 | AO19: 45665 | AQ19: 松村 | AS19: OK
C20: =ROW()-9 -> 11 | L20: 送料のみ(左) | P20: メニューよりしまむら直納伝票請求書を起動する | X20: 入力欄が活性、かつ、空欄であること | AO20: 45665 | AQ20: 松村 | AS20: NG | AU20: 45695 | AW20: 児玉 | AY20: OK | BA20: 初期値が0である・入力必須でない
C21: =ROW()-9 -> 12 | L21: 送料のみ(右) | P21: メニューよりしまむら直納伝票請求書を起動する | X21: 入力欄が非活性、かつ、区分の説明が表示されていること。 | AF21: 0:送料以外 1:送料のみ(Z012) | AO21: 45665 | AQ21: 松村 | AS21: OK
C22: =ROW()-9 -> 13 | L22: 並び順(左) | P22: メニューよりしまむら直納伝票請求書を起動する | X22: 入力欄が活性、かつ、空欄であること | AO22: 45665 | AQ22: 松村 | AS22: NG | AU22: 45695 | AW22: 児玉 | AY22: OK | BA22: 初期値が0である・入力必須でない
C23: =ROW()-9 -> 14 | L23: 並び順(右) | P23: メニューよりしまむら直納伝票請求書を起動する | X23: 入力欄が非活性、かつ、区分の説明が表示されていること。 | AF23: 0:伝票番号 1:納品日付 | AO23: 45665 | AQ23: 松村 | AS23: OK
C24: =ROW()-9 -> 15 | L24: 発行日付 | P24: メニューよりしまむら直納伝票請求書を起動する | X24: 入力欄が活性、かつ、空欄であること | AO24: 45665 | AQ24: 松村 | AS24: NG | AU24: 45695 | AW24: 児玉 | AY24: OK | BA24: 再表示時に前のデータが残る
C25: =ROW()-9 -> 16 | H25: 動作確認 | L25: 請求日付・締め日 | P25: 請求日付と締め日を入力する | X25: 請求期間(To)に請求日付と締日で設定した日付が入力される | AO25: 45665 | AQ25: 松村 | AS25: OK
C26: =ROW()-9 -> 17 | X26: 請求期間(From)に請求日付と締日で設定した日付から30日前の日付が入力される | AO26: 45665 | AQ26: 松村 | AS26: OK
C27: =ROW()-9 -> 18 | L27: 得意先1 虫眼鏡 | P27: 虫眼鏡を押下する | X27: 得意先CD検索のダイアログが立ち上がること | AO27: 45665 | AQ27: 松村 | AS27: OK
C28: =ROW()-9 -> 19 | P28: 得意先CD検索画面で得意先を検索し、得意先CDを選択する。 | X28: 以下の項目に選択した得意先CDの該当情報が表示されること 得意先2 得意先3 | AO28: 45665 | AQ28: 松村 | AS28: OK
C29: =ROW()-9 -> 20 | X29: 以下の項目が得意先CD入力前と同じであること 請求日付 締日 請求期間 得意先1 伝票種類 内容区分 送料のみ 並び順 発行日付 | AO29: 45665 | AQ29: 松村 | AS29: OK
C30: =ROW()-9 -> 21 | L30: 得意先1 入力時 | P30: 得意先1に存在する得意先CDを入力する | X30: 以下の項目に選択した得意先CDの該当情報が表示されること 得意先2 得意先3 | AO30: 45665 | AQ30: 松村 | AS30: OK
C31: =ROW()-9 -> 22 | X31: 以下の項目が得意先CD入力前と同じであること 請求日付 締日 請求期間 得意先1 伝票種類 内容区分 送料のみ 並び順 発行日付 | AO31: 45665 | AQ31: 松村 | AS31: OK
C32: =ROW()-9 -> 23 | L32: 得意先1 ×ボタン | P32: 得意先CD欄に得意先CDが入力されている状態で得意先範囲の×ボタンを押下 | X32: 以下の項目が空欄になること 得意先2 得意先3 | AO32: 45665 | AQ32: 松村 | AS32: OK
C33: =ROW()-9 -> 24 | X33: 以下の項目が×ボタン押下前と同じであること 請求日付 締日 請求期間 得意先1 伝票種類 内容区分 送料のみ 並び順 発行日付 | AO33: 45665 | AQ33: 松村 | AS33: OK
C34: =ROW()-9 -> 25 | L34: 伝票種類 | P34: 2を入力して出力する | X34: 現行システムと同じデータが出力されること | AO34: 45665 | AQ34: 松村 | AS34: OK
C35: =ROW()-9 -> 26 | P35: 3を入力して出力する | X35: 現行システムと同じデータが出力されること | AO35: 45665 | AQ35: 松村 | AS35: OK
C36: =ROW()-9 -> 27 | P36: 4を入力して出力する | X36: 現行システムと同じデータが出力されること | AO36: 45665 | AQ36: 松村 | AS36: OK
C37: =ROW()-9 -> 28 | L37: 内容区分 | P37: 0を入力して出力する | X37: 現行システムと同じデータが出力されること | AO37: 45665 | AQ37: 松村 | AS37: OK
C38: =ROW()-9 -> 29 | P38: 1を入力して出力する | X38: 現行システムと同じデータが出力されること | AO38: 45665 | AQ38: 松村 | AS38: NG | AU38: 45695 | AW38: 児玉 | AY38: OK | BA38: 出力ボタンを押下すると内容区分が0になる（出力されるExcelファイルも0の時のもの）
C39: =ROW()-9 -> 30 | P39: 2を入力して出力する | X39: 現行システムと同じデータが出力されること | AO39: 45665 | AQ39: 松村 | AS39: NG | AU39: 45695 | AW39: 児玉 | AY39: OK | BA39: 出力ボタンを押下すると内容区分が0になる（出力されるExcelファイルも0の時のもの）
C40: =ROW()-9 -> 31 | P40: 3を入力して出力する | X40: 現行システムと同じデータが出力されること | AO40: 45665 | AQ40: 松村 | AS40: NG | AU40: 45695 | AW40: 児玉 | AY40: OK | BA40: 出力ボタンを押下すると内容区分が0になる（出力されるExcelファイルも0の時のもの）
C41: =ROW()-9 -> 32 | L41: 送料のみ | P41: 0を入力して出力する | X41: 現行システムと同じデータが出力されること | AO41: 45665 | AQ41: 松村 | AS41: OK
C42: =ROW()-9 -> 33 | P42: 1を入力して出力する | X42: 現行システムと同じデータが出力されること | AO42: 45665 | AQ42: 松村 | AS42: OK
C43: =ROW()-9 -> 34 | L43: 並び順 | P43: 0を入力して出力する | X43: 現行システムと同じデータが出力されること | AO43: 45665 | AQ43: 松村 | AS43: OK
C44: =ROW()-9 -> 35 | P44: 1を入力して出力する | X44: 現行システムと同じデータが出力されること | AO44: 45665 | AQ44: 松村 | AS44: OK
C45: =ROW()-9 -> 36 | L45: 出力ボタン | P45: 出力ボタン押下 | X45: Excelで出力されること | AO45: 45665 | AQ45: 松村 | AS45: OK
C46: =ROW()-9 -> 37 | L46: 終了ボタン | P46: 終了ボタンを押下する | X46: ダイアログが終了すること | AO46: 45665 | AQ46: 松村 | AS46: OK
C47: =ROW()-9 -> 38 | H47: エラー確認 | L47: 請求日付 | P47: 未入力で出力ボタンを押下する。 | X47: エラーメッセージが出力され、帳票が出力されないこと | AO47: 45665 | AQ47: 松村 | AS47: OK
C48: =ROW()-9 -> 39 | L48: 締日 | P48: 未入力で出力ボタンを押下する。 | X48: エラーメッセージが出力され、帳票が出力されないこと | AO48: 45665 | AQ48: 松村 | AS48: OK
C49: =ROW()-9 -> 40 | L49: 得意先1 | P49: 未入力で出力ボタンを押下する。 | X49: エラーメッセージが出力され、帳票が出力されないこと | AO49: 45665 | AQ49: 松村 | AS49: OK
C50: =ROW()-9 -> 41 | L50: 伝票種類 | P50: 未入力で出力ボタンを押下する。 | X50: エラーメッセージが出力され、帳票が出力されないこと | AO50: 45665 | AQ50: 松村 | AS50: OK
C51: =ROW()-9 -> 42 | L51: 伝票種類 | P51: 未入力で出力ボタンを押下する。 | X51: エラーメッセージが出力され、帳票が出力されないこと | AO51: 45665 | AQ51: 松村 | AS51: OK
C52: =ROW()-9 -> 43 | L52: 内容区分 | P52: 未入力で出力ボタンを押下する。 | X52: エラーメッセージが出力され、帳票が出力されないこと | AO52: 45665 | AQ52: 松村 | AS52: NG | AU52: 45695 | AW52: 児玉 | AY52: OK | BA52: Excelファイルが作成されてしまう
C53: =ROW()-9 -> 44 | L53: 送料のみ | P53: 未入力で出力ボタンを押下する。 | X53: エラーメッセージが出力され、帳票が出力されないこと | AO53: 45665 | AQ53: 松村 | AS53: NG | AU53: 45695 | AW53: 児玉 | AY53: OK | BA53: Excelファイルが作成されてしまう
C54: =ROW()-9 -> 45 | L54: 並び順 | P54: 未入力で出力ボタンを押下する。 | X54: エラーメッセージが出力され、帳票が出力されないこと | AO54: 45665 | AQ54: 松村 | AS54: NG | AU54: 45695 | AW54: 児玉 | AY54: OK | BA54: Excelファイルが作成されてしまう
C55: =ROW()-9 -> 46 | L55: 発行日付 | P55: 未入力で出力ボタンを押下する。 | X55: エラーメッセージが出力され、帳票が出力されないこと | AO55: 45665 | AQ55: 松村 | AS55: OK
C56: =ROW()-9 -> 47 | L56: 請求期限 | P56: 該当データが存在しない範囲で出力ボタンを押下する。 | X56: メッセージが出力され、帳票が出力されないこと | AO56: 45665 | AQ56: 松村 | AS56: OK

Sheet 帳票
B2: システム名 | H2: 業務分類 | L2: システム分類 | R2: ドキュメント種別 | X2: ドキュメント名 | AK2: 試験対象 | AX2: 作成日 | BB2: 作成者 | BF2: 更新日 | BJ2: 更新者
B3: =変更履歴!B3 -> 受発注システム | H3: =変更履歴!H3 -> 請求売掛 | L3: =変更履歴!L3 -> 受発注 | R3: =変更履歴!R3 -> 結合試験項目 | X3: =変更履歴!X3 -> 請求売掛_しまむら直納伝票請求書_結合試験項目 | AK3: =変更履歴!AK3 -> しまむら直納伝票請求書 | AX3: =変更履歴!AX3 -> 45628 | BB3: =変更履歴!BB3 -> 児玉 | BF3: =変更履歴!BF3 -> 45628 | BJ3: =変更履歴!BJ3 -> 児玉
BE7: 件数 | BG7: 合計 | BI7: 終了 | BK7: 残
AO8: １回目 | AU8: 2回目 | BG8: =COUNTA(C10:C45) -> 36 | BI8: =COUNTIF(AS10:AT45,"OK")+COUNTIF(AY10:AZ45,"OK") -> 36 | BK8: =BG8-BI8 -> 0
C9: No. | D9: 大項目 | H9: 中項目 | L9: 小項目 | P9: 確認手順 | X9: 確認観点 | AF9: 補足事項(テスト項目補足、テストデータ等) | AO9: 確認日 | AQ9: 確認者 | AS9: 結果 | AU9: 確認日 | AW9: 確認者 | AY9: 結果 | BA9: 試験結果備考
C10: =ROW()-9 -> 1 | D10: 帳票 | H10: 出力バリエーション | L10: 伝票種類 | P10: 2を入力して出力する | X10: 現行システムと同じデータが出力されること | AF10: 詳細情報 SU0700_しまむら直納伝票請求書_帳票設計書.xlsx | AO10: 45665 | AQ10: 松村 | AS10: OK
C11: =ROW()-9 -> 2 | P11: 3を入力して出力する | X11: 現行システムと同じデータが出力されること | AO11: 45665 | AQ11: 松村 | AS11: OK
C12: =ROW()-9 -> 3 | P12: 4を入力して出力する | X12: 現行システムと同じデータが出力されること | AO12: 45665 | AQ12: 松村 | AS12: OK
C13: =ROW()-9 -> 4 | L13: 内容区分 | P13: 0を入力して出力する | X13: 現行システムと同じデータが出力されること | AO13: 45665 | AQ13: 松村 | AS13: OK
C14: =ROW()-9 -> 5 | P14: 1を入力して出力する | X14: 現行システムと同じデータが出力されること | AO14: 45665 | AQ14: 松村 | AS14: NG | AU14: 45695 | AW14: 児玉 | AY14: OK | BA14: 出力ボタンを押下すると内容区分が0になる（出力されるExcelファイルも0の時のもの）
C15: =ROW()-9 -> 6 | P15: 2を入力して出力する | X15: 現行システムと同じデータが出力されること | AO15: 45665 | AQ15: 松村 | AS15: NG | AU15: 45695 | AW15: 児玉 | AY15: OK | BA15: 出力ボタンを押下すると内容区分が0になる（出力されるExcelファイルも0の時のもの）
C16: =ROW()-9 -> 7 | P16: 3を入力して出力する | X16: 現行システムと同じデータが出力されること | AO16: 45665 | AQ16: 松村 | AS16: NG | AU16: 45695 | AW16: 児玉 | AY16: OK | BA16: 出力ボタンを押下すると内容区分が0になる（出力されるExcelファイルも0の時のもの）
C17: =ROW()-9 -> 8 | L17: 送料のみ | P17: 0を入力して出力する | X17: 現行システムと同じデータが出力されること | AO17: 45665 | AQ17: 松村 | AS17: OK
C18: =ROW()-9 -> 9 | P18: 1を入力して出力する | X18: 現行システムと同じデータが出力されること | AO18: 45665 | AQ18: 松村 | AS18: OK
C19: =ROW()-9 -> 10 | L19: 並び順 | P19: 0を入力して出力する | X19: 現行システムと同じデータが出力されること | AO19: 45665 | AQ19: 松村 | AS19: OK
C20: =ROW()-9 -> 11 | P20: 1を入力して出力する | X20: 現行システムと同じデータが出力されること | AO20: 45665 | AQ20: 松村 | AS20: OK
C21: =ROW()-9 -> 12 | H21: 出力種類 | L21: 出力ボタン | P21: 出力ボタン押下 | X21: Excelで帳票がDLされること | AO21: 45665 | AQ21: 松村 | AS21: OK
C22: =ROW()-9 -> 13 | X22: Excelにパスワードが設定されていること | AO22: 45665 | AQ22: 松村 | AS22: NG | AU22: 45695 | AW22: 児玉 | AY22: OK | BA22: Excelにパスワードが設定されていない
C23: =ROW()-9 -> 14 | H23: 出力確認 | L23: 作成日 | P23: 出力ボタン押下 | X23: 現行システムと同じデータが出力されること | AO23: 45665 | AQ23: 松村 | AS23: OK
C24: =ROW()-9 -> 15 | L24: 得意先名1 | P24: 出力ボタン押下 | X24: 現行システムと同じデータが出力されること | AO24: 45665 | AQ24: 松村 | AS24: OK
C25: =ROW()-9 -> 16 | L25: 得意先名2 | P25: 出力ボタン押下 | X25: 現行システムと同じデータが出力されること | AO25: 45665 | AQ25: 松村 | AS25: OK
C26: =ROW()-9 -> 17 | L26: 見積金額 | P26: 出力ボタン押下 | X26: 現行システムと同じデータが出力されること | AO26: 45665 | AQ26: 松村 | AS26: OK
C27: =ROW()-9 -> 18 | L27: 消費税見出し | P27: 出力ボタン押下 | X27: 現行システムと同じデータが出力されること | AO27: 45665 | AQ27: 松村 | AS27: OK
C28: =ROW()-9 -> 19 | L28: 消費税額 | P28: 出力ボタン押下 | X28: 現行システムと同じデータが出力されること | AO28: 45665 | AQ28: 松村 | AS28: OK
C29: =ROW()-9 -> 20 | L29: 合計金額 | P29: 出力ボタン押下 | X29: 現行システムと同じデータが出力されること | AO29: 45665 | AQ29: 松村 | AS29: OK
C30: =ROW()-9 -> 21 | L30: 送料 | P30: 出力ボタン押下 | X30: 現行システムと同じデータが出力されること | AO30: 45665 | AQ30: 松村 | AS30: OK
C31: =ROW()-9 -> 22 | L31: 見積件名 | P31: 出力ボタン押下 | X31: 現行システムと同じデータが出力されること | AO31: 45665 | AQ31: 松村 | AS31: OK
C32: =ROW()-9 -> 23 | L32: 納期 | P32: 出力ボタン押下 | X32: 現行システムと同じデータが出力されること | AO32: 45665 | AQ32: 松村 | AS32: OK
C33: =ROW()-9 -> 24 | L33: 受渡地 | P33: 出力ボタン押下 | X33: 現行システムと同じデータが出力されること | AO33: 45665 | AQ33: 松村 | AS33: OK
C34: =ROW()-9 -> 25 | L34: 支払条件 | P34: 出力ボタン押下 | X34: 現行システムと同じデータが出力されること | AO34: 45665 | AQ34: 松村 | AS34: OK
C35: =ROW()-9 -> 26 | L35: 備考 | P35: 出力ボタン押下 | X35: 現行システムと同じデータが出力されること | AO35: 45665 | AQ35: 松村 | AS35: OK
... C45: =ROW()-9 -> 36 | L45: 数量 | P45: 出力ボタン押下 | X45: 現行システムと同じデータが出力されること | AO45: 45665 | AQ45: 松村 | AS45: OK
C46: =ROW()-9 -> 37 | H46: ページ確認 | L46: 単ページ | P46: 複数ページとならないデータで出力ボタンを押下 | X46: 現行システムと同じデータが出力されること | AO46: 45665 | AQ46: 松村 | AS46: OK
C47: =ROW()-9 -> 38 | L47: 複数ページ | P47: 複数ページとなるデータで出力ボタンを押下 | X47: 現行システムと同じデータが出力されること | AO47: 45665 | AQ47: 松村 | AS47: OK

Sheet 参照
A1: ラベル
A2: インプット
A3: ボタン
A4: ラジオ
