Workbook

Sheet 変更履歴
B2: システム名 | H2: 業務分類 | L2: システム分類 | R2: ドキュメント種別 | X2: ドキュメント名 | AK2: 試験対象 | AX2: 作成日 | BB2: 作成者 | BF2: 更新日 | BJ2: 更新者
B3: 受発注システム | H3: =LEFT($X$3,FIND("_",$X$3)-1) -> 請求売掛 | L3: 受発注 | R3: =MID($X$3,FIND("_",$X$3,FIND("_",$X$3)+1)+1,LEN($X$3)-FIND("_",$X$3,FIND("_",$X$3)+1)) -> 結合試験項目 | X3: =REPLACE(LEFT(CELL("filename",$B$2),FIND(".x",CELL("filename",$B$2))-1),1,FIND("[",CELL("filename",$B$2)),) -> 請求売掛_請求一覧表_結合試験項目 | AK3: =MID($X$3,FIND("_",$X$3)+1,FIND("_",$X$3,FIND("_",$X$3)+1)-FIND("_",$X$3)-1) -> 請求一覧表 | AX3: 45628 | BB3: 児玉 | BF3: 45628 | BJ3: 児玉
C7: 変更履歴
C8: 日付 | G8: 版数 | K8: 担当 | O8: 変更箇所 | Y8: 内容
C9: 45628 | G9: 1.0.0 | O9: - | Y9: 新規作成

Sheet 画面
B2: システム名 | H2: 業務分類 | L2: システム分類 | R2: ドキュメント種別 | X2: ドキュメント名 | AK2: 試験対象 | AX2: 作成日 | BB2: 作成者 | BF2: 更新日 | BJ2: 更新者
B3: =変更履歴!B3 -> 受発注システム | H3: =変更履歴!H3 -> 請求売掛 | L3: =変更履歴!L3 -> 受発注 | R3: =変更履歴!R3 -> 結合試験項目 | X3: =変更履歴!X3 -> 請求売掛_請求一覧表_結合試験項目 | AK3: =変更履歴!AK3 -> 請求一覧表 | AX3: =変更履歴!AX3 -> 45628 | BB3: =変更履歴!BB3 -> 児玉 | BF3: =変更履歴!BF3 -> 45628 | BJ3: =変更履歴!BJ3 -> 児玉
BE7: 件数 | BG7: 合計 | BI7: 終了 | BK7: 残
AO8: １回目 | AU8: 2回目 | BG8: =COUNTA(C10:C30) -> 21 | BI8: =COUNTIF(AS10:AT30,"OK")+COUNTIF(AY10:AZ30,"OK") -> 21 | BK8: =BG8-BI8 -> 0
C9: No. | D9: 大項目 | H9: 中項目 | L9: 小項目 | P9: 確認手順 | X9: 確認観点 | AF9: 補足事項(テスト項目補足、テストデータ等) | AO9: 確認日 | AQ9: 確認者 | AS9: 結果 | AU9: 確認日 | AW9: 確認者 | AY9: 結果 | BA9: 試験結果備考
C10: =ROW()-9 -> 1 | D10: 画面 | H10: 初期表示 | L10: 請求年月 | P10: メニューより請求一覧表を起動する | X10: 入力欄が活性、かつ、今日日付が入力されていること | AO10: 45664 | AQ10: 松村 | AS10: OK
C11: =ROW()-9 -> 2 | L11: 得意先CD(From) | P11: メニューより請求一覧表を起動する | X11: 入力欄が活性、かつ、空欄であること | AO11: 45664 | AQ11: 松村 | AS11: NG | AU11: 45695 | AW11: 児玉 | AY11: OK | BA11: データを入力した後、再度起動すると前回のデータが残っている
C12: =ROW()-9 -> 3 | L12: 得意先CD(To) | P12: メニューより請求一覧表を起動する | X12: 入力欄が活性、かつ、空欄であること | AO12: 45664 | AQ12: 松村 | AS12: NG | AU12: 45695 | AW12: 児玉 | AY12: OK | BA12: データを入力した後、再度起動すると前回のデータが残っている
C13: =ROW()-9 -> 4 | L13: 設定ボタン | P13: メニューより請求一覧表を起動する | X13: 設定ボタンが表示されていないこと | AO13: 45664 | AQ13: 松村 | AS13: OK
C14: =ROW()-9 -> 5 | H14: 動作確認 | L14: 得意先CD(From) 虫眼鏡 | P14: 虫眼鏡を押下する | X14: 得意先検索のダイアログが立ち上がること | AO14: 45664 | AQ14: 松村 | AS14: OK
C15: =ROW()-9 -> 6 | P15: 得意先検索画面で得意先を検索し、得意先を選択する | X15: 以下の項目に選択した得意先の該当情報が表示されること 得意先CD(From)(活性） | AO15: 45664 | AQ15: 松村 | AS15: OK
C16: =ROW()-9 -> 7 | X16: 以下の項目が得意先入力前と同じであること 請求年月 得意先CD(To) | AO16: 45664 | AQ16: 松村 | AS16: OK
C17: =ROW()-9 -> 8 | L17: 得意先CD(To) 虫眼鏡 | P17: 虫眼鏡を押下する | X17: 得意先検索のダイアログが立ち上がること | AO17: 45664 | AQ17: 松村 | AS17: OK
C18: =ROW()-9 -> 9 | P18: 得意先検索画面で得意先を検索し、得意先を選択する | X18: 以下の項目に選択した得意先の該当情報が表示されること 得意先CD(To)(活性） | AO18: 45664 | AQ18: 松村 | AS18: OK
C19: =ROW()-9 -> 10 | X19: 以下の項目が得意先入力前と同じであること 請求年月 得意先CD(From) | AO19: 45664 | AQ19: 松村 | AS19: OK
C20: =ROW()-9 -> 11 | L20: 得意先CD(From) ×ボタン | P20: 得意先CDに値が入力されている状態で得意先CDの×ボタンを押下 | X20: 以下の項目が空欄になること 得意先CD(From)(活性） | AO20: 45664 | AQ20: 松村 | AS20: OK
C21: =ROW()-9 -> 12 | X21: 以下の項目が得意先入力前と同じであること 請求年月 得意先CD(To) | AO21: 45664 | AQ21: 松村 | AS21: OK
C22: =ROW()-9 -> 13 | L22: 得意先CD(To) ×ボタン | P22: 得意先CDに値が入力されている状態で得意先CDの×ボタンを押下 | X22: 以下の項目が空欄になること 得意先CD(To)(活性） | AO22: 45664 | AQ22: 松村 | AS22: OK
C23: =ROW()-9 -> 14 | X23: 以下の項目が得意先入力前と同じであること 請求年月 得意先CD(From) | AO23: 45664 | AQ23: 松村 | AS23: OK
C24: =ROW()-9 -> 15 | L24: 印刷ボタン | P24: 印刷ボタンを押下する | X24: PDFで出力されること | AO24: 45664 | AQ24: 松村 | AS24: OK
C25: =ROW()-9 -> 16 | L25: プレビューボタン | P25: プレビューボタンを押下する | X25: プレビューが表示されること | AF25: 実装なし | AO25: 45664 | AQ25: 松村 | AS25: NG | AU25: 45695 | AW25: 児玉 | AY25: OK | BA25: プレビューボタンが表示されていない
C26: =ROW()-9 -> 17 | L26: 終了ボタン | P26: 終了ボタンを押下する | X26: ダイアログが終了すること | AO26: 45664 | AQ26: 松村 | AS26: OK
C27: =ROW()-9 -> 18 | H27: エラー確認 | L27: 印刷ボタン | P27: 該当するデータがない範囲を指定して印刷ボタンを押下する | X27: メッセージが出力され、印刷されないこと | AO27: 45664 | AQ27: 松村 | AS27: OK
C28: =ROW()-9 -> 19 | L28: プレビューボタン | P28: 該当するデータがない範囲を指定してプレビューボタンを押下する | X28: メッセージが出力され、プレビューが表示されないこと | AF28: 実装なし | AO28: 45664 | AQ28: 松村 | AS28: NG | AU28: 45695 | AW28: 児玉 | AY28: OK | BA28: プレビューボタンが表示されていない
C29: =ROW()-9 -> 20 | L29: 請求年月 | P29: 年月日の値が空の状態で出力ボタンを押下する | X29: エラーメッセージが表示されること | AO29: 45664 | AQ29: 松村 | AS29: OK
C30: =ROW()-9 -> 21 | L30: 得意先CD | P30: Fromの値がToの値より大きい場合に出力ボタンを押下する | X30: エラーメッセージが表示されること | AO30: 45664 | AQ30: 松村 | AS30: OK

Sheet 帳票
B2: システム名 | H2: 業務分類 | L2: システム分類 | R2: ドキュメント種別 | X2: ドキュメント名 | AK2: 試験対象 | AX2: 作成日 | BB2: 作成者 | BF2: 更新日 | BJ2: 更新者
B3: =変更履歴!B3 -> 受発注システム | H3: =変更履歴!H3 -> 請求売掛 | L3: =変更履歴!L3 -> 受発注 | R3: =変更履歴!R3 -> 結合試験項目 | X3: =変更履歴!X3 -> 請求売掛_請求一覧表_結合試験項目 | AK3: =変更履歴!AK3 -> 請求一覧表 | AX3: =変更履歴!AX3 -> 45628 | BB3: =変更履歴!BB3 -> 児玉 | BF3: =変更履歴!BF3 -> 45628 | BJ3: =変更履歴!BJ3 -> 児玉
BE7: 件数 | BG7: 合計 | BI7: 終了 | BK7: 残
AO8: １回目 | AU8: 2回目 | BG8: =COUNTA(C10:C46) -> 37 | BI8: =COUNTIF(AS10:AT46,"OK")+COUNTIF(AY10:AZ46,"OK") -> 37 | BK8: =BG8-BI8 -> 0
C9: No. | D9: 大項目 | H9: 中項目 | L9: 小項目 | P9: 確認手順 | X9: 確認観点 | AF9: 補足事項(テスト項目補足、テストデータ等) | AO9: 確認日 | AQ9: 確認者 | AS9: 結果 | AU9: 確認日 | AW9: 確認者 | AY9: 結果 | BA9: 試験結果備考
C10: =ROW()-9 -> 1 | D10: 帳票 | H10: 出力バリエーション | L10: 得意先CD | P10: Fromにのみ値を入力して印刷ボタンを押下 | X10: 現行システムと同じデータが出力されること | AO10: 45664 | AQ10: 松村 | AS10: OK
C11: =ROW()-9 -> 2 | P11: Toにのみ値を入力して印刷ボタンを押下 | X11: 現行システムと同じデータが出力されること | AO11: 45664 | AQ11: 松村 | AS11: OK
C12: =ROW()-9 -> 3 | P12: From,Toどちらにも値を入力して印刷ボタンを押下 | X12: 現行システムと同じデータが出力されること | AO12: 45664 | AQ12: 松村 | AS12: OK
C13: =ROW()-9 -> 4 | P13: From,Toどちらにも値を入力せずに印刷ボタンを押下 | X13: 現行システムと同じデータが出力されること | AO13: 45664 | AQ13: 松村 | AS13: OK
C14: =ROW()-9 -> 5 | H14: 出力種類 | L14: 印刷ボタン | P14: 印刷ボタンを押下 | X14: PDFで帳票が印刷されること | AO14: 45664 | AQ14: 松村 | AS14: OK
C15: =ROW()-9 -> 6 | H15: 出力内容 | L15: 作成日 | P15: 印刷ボタンを押下 | X15: 現行システムと同じデータが出力されること | AF15: 詳細情報 SU0400_請求一覧表_帳票設計書.xlsx | AO15: 45664 | AQ15: 松村 | AS15: OK
C16: =ROW()-9 -> 7 | L16: 請求日付 | P16: 印刷ボタンを押下 | X16: 現行システムと同じデータが出力されること | AO16: 45664 | AQ16: 松村 | AS16: OK
C17: =ROW()-9 -> 8 | L17: 開始CD | P17: 印刷ボタンを押下 | X17: 現行システムと同じデータが出力されること | AO17: 45664 | AQ17: 松村 | AS17: OK
C18: =ROW()-9 -> 9 | L18: 終了CD | P18: 印刷ボタンを押下 | X18: 現行システムと同じデータが出力されること | AO18: 45664 | AQ18: 松村 | AS18: OK
C19: =ROW()-9 -> 10 | L19: 得意先CD | P19: 印刷ボタンを押下 | X19: 現行システムと同じデータが出力されること | AO19: 45664 | AQ19: 松村 | AS19: OK
C20: =ROW()-9 -> 11 | L20: 得意先名1 | P20: 印刷ボタンを押下 | X20: 現行システムと同じデータが出力されること | AO20: 45664 | AQ20: 松村 | AS20: OK
C21: =ROW()-9 -> 12 | L21: 得意先名2 | P21: 印刷ボタンを押下 | X21: 現行システムと同じデータが出力されること | AO21: 45664 | AQ21: 松村 | AS21: OK
C22: =ROW()-9 -> 13 | L22: 前月残高 | P22: 印刷ボタンを押下 | X22: 現行システムと同じデータが出力されること | AO22: 45664 | AQ22: 松村 | AS22: OK
C23: =ROW()-9 -> 14 | L23: 入金金額 | P23: 印刷ボタンを押下 | X23: 現行システムと同じデータが出力されること | AO23: 45664 | AQ23: 松村 | AS23: OK
C24: =ROW()-9 -> 15 | L24: 調整金額 | P24: 印刷ボタンを押下 | X24: 現行システムと同じデータが出力されること | AO24: 45664 | AQ24: 松村 | AS24: OK
C25: =ROW()-9 -> 16 | L25: 差引繰越額 | P25: 印刷ボタンを押下 | X25: 現行システムと同じデータが出力されること | AO25: 45664 | AQ25: 松村 | AS25: OK
C26: =ROW()-9 -> 17 | L26: 売上金額 | P26: 印刷ボタンを押下 | X26: 現行システムと同じデータが出力されること | AO26: 45664 | AQ26: 松村 | AS26: OK
C27: =ROW()-9 -> 18 | L27: 返品金額 | P27: 印刷ボタンを押下 | X27: 現行システムと同じデータが出力されること | AO27: 45664 | AQ27: 松村 | AS27: OK
... C44: =ROW()-9 -> 35 | L44: 当月請求額計 | P44: 印刷ボタンを押下 | X44: 現行システムと同じデータが出力されること | AO44: 45664 | AQ44: 松村 | AS44: OK
C45: =ROW()-9 -> 36 | H45: ページ確認 | L45: 単ページ | P45: 複数ページとならないデータで印刷ボタンを押下 | X45: 現行システムと同じデータが出力されること | AO45: 45664 | AQ45: 松村 | AS45: OK
C46: =ROW()-9 -> 37 | L46: 複数ページ | P46: 複数ページとなるデータで印刷ボタンを押下 | X46: 現行システムと同じデータが出力されること | AO46: 45664 | AQ46: 松村 | AS46: OK

Sheet プレビュー
B2: システム名 | H2: 業務分類 | L2: システム分類 | R2: ドキュメント種別 | X2: ドキュメント名 | AK2: 試験対象 | AX2: 作成日 | BB2: 作成者 | BF2: 更新日 | BJ2: 更新者
B3: =変更履歴!B3 -> 受発注システム | H3: =変更履歴!H3 -> 請求売掛 | L3: =変更履歴!L3 -> 受発注 | R3: =変更履歴!R3 -> 結合試験項目 | X3: =変更履歴!X3 -> 請求売掛_請求一覧表_結合試験項目 | AK3: =変更履歴!AK3 -> 請求一覧表 | AX3: =変更履歴!AX3 -> 45628 | BB3: =変更履歴!BB3 -> 児玉 | BF3: =変更履歴!BF3 -> 45628 | BJ3: =変更履歴!BJ3 -> 児玉
BE7: 件数 | BG7: 合計 | BI7: 終了 | BK7: 残
AO8: １回目 | AU8: 2回目 | BG8: =COUNTA(C10:C46) -> 37 | BI8: =COUNTIF(AS10:AT46,"OK")+COUNTIF(AY10:AZ46,"OK") -> 37 | BK8: =BG8-BI8 -> 0
C9: No. | D9: 大項目 | H9: 中項目 | L9: 小項目 | P9: 確認手順 | X9: 確認観点 | AF9: 補足事項(テスト項目補足、テストデータ等) | AO9: 確認日 | AQ9: 確認者 | AS9: 結果 | AU9: 確認日 | AW9: 確認者 | AY9: 結果 | BA9: 試験結果備考
C10: =ROW()-9 -> 1 | D10: プレビュー | H10: 出力バリエーション | L10: 得意先CD | P10: Fromにのみ値を入力してプレビューボタンを押下 | X10: 現行システムと同じデータが出力されること | AO10: 45664 | AQ10: 松村 | AS10: OK
C11: =ROW()-9 -> 2 | P11: Toにのみ値を入力してプレビューボタンを押下 | X11: 現行システムと同じデータが出力されること | AO11: 45664 | AQ11: 松村 | AS11: OK
C12: =ROW()-9 -> 3 | P12: From,Toどちらにも値を入力してプレビューボタンを押下 | X12: 現行システムと同じデータが出力されること | AO12: 45664 | AQ12: 松村 | AS12: OK
C13: =ROW()-9 -> 4 | P13: From,Toどちらにも値を入力せずにプレビューボタンを押下 | X13: 現行システムと同じデータが出力されること | AO13: 45664 | AQ13: 松村 | AS13: OK
C14: =ROW()-9 -> 5 | H14: 出力種類 | L14: プレビューボタン | P14: プレビューボタンを押下 | X14: PDFで帳票がプレビューされること | AO14: 45664 | AQ14: 松村 | AS14: OK
C15: =ROW()-9 -> 6 | H15: 出力内容 | L15: 作成日 | P15: プレビューボタンを押下 | X15: 現行システムと同じデータが出力されること | AF15: 詳細情報 SU0400_請求一覧表_帳票設計書.xlsx | AO15: 45664 | AQ15: 松村 | AS15: OK
C16: =ROW()-9 -> 7 | L16: 請求日付 | P16: プレビューボタンを押下 | X16: 現行システムと同じデータが出力されること | AO16: 45664 | AQ16: 松村 | AS16: OK
C17: =ROW()-9 -> 8 | L17: 開始CD | P17: プレビューボタンを押下 | X17: 現行システムと同じデータが出力されること | AO17: 45664 | AQ17: 松村 | AS17: OK
C18: =ROW()-9 -> 9 | L18: 終了CD | P18: プレビューボタンを押下 | X18: 現行システムと同じデータが出力されること | AO18: 45664 | AQ18: 松村 | AS18: OK
C19: =ROW()-9 -> 10 | L19: 得意先CD | P19: プレビューボタンを押下 | X19: 現行システムと同じデータが出力されること | AO19: 45664 | AQ19: 松村 | AS19: OK
C20: =ROW()-9 -> 11 | L20: 得意先名1 | P20: プレビューボタンを押下 | X20: 現行システムと同じデータが出力されること | AO20: 45664 | AQ20: 松村 | AS20: OK
C21: =ROW()-9 -> 12 | L21: 得意先名2 | P21: プレビューボタンを押下 | X21: 現行システムと同じデータが出力されること | AO21: 45664 | AQ21: 松村 | AS21: OK
C22: =ROW()-9 -> 13 | L22: 前月残高 | P22: プレビューボタンを押下 | X22: 現行システムと同じデータが出力されること | AO22: 45664 | AQ22: 松村 | AS22: OK
C23: =ROW()-9 -> 14 | L23: 入金金額 | P23: プレビューボタンを押下 | X23: 現行システムと同じデータが出力されること | AO23: 45664 | AQ23: 松村 | AS23: OK
C24: =ROW()-9 -> 15 | L24: 調整金額 | P24: プレビューボタンを押下 | X24: 現行システムと同じデータが出力されること | AO24: 45664 | AQ24: 松村 | AS24: OK
C25: =ROW()-9 -> 16 | L25: 差引繰越額 | P25: プレビューボタンを押下 | X25: 現行システムと同じデータが出力されること | AO25: 45664 | AQ25: 松村 | AS25: OK
C26: =ROW()-9 -> 17 | L26: 売上金額 | P26: プレビューボタンを押下 | X26: 現行システムと同じデータが出力されること | AO26: 45664 | AQ26: 松村 | AS26: OK
C27: =ROW()-9 -> 18 | L27: 返品金額 | P27: プレビューボタンを押下 | X27: 現行システムと同じデータが出力されること | AO27: 45664 | AQ27: 松村 | AS27: OK
... C44: =ROW()-9 -> 35 | L44: 当月請求額計 | P44: プレビューボタンを押下 | X44: 現行システムと同じデータが出力されること | AO44: 45664 | AQ44: 松村 | AS44: OK
C45: =ROW()-9 -> 36 | H45: ページ確認 | L45: 単ページ | P45: 複数ページとならないデータでプレビューボタンを押下 | X45: 現行システムと同じデータが出力されること | AO45: 45664 | AQ45: 松村 | AS45: OK
C46: =ROW()-9 -> 37 | L46: 複数ページ | P46: 複数ページとなるデータでプレビューボタンを押下 | X46: 現行システムと同じデータが出力されること | AO46: 45664 | AQ46: 松村 | AS46: OK

Sheet 参照
A1: ラベル
A2: インプット
A3: ボタン
A4: ラジオ
