Workbook
Name TukiNamePos: #REF!
Name TukiNamePos_SS: #REF!
Name TukiRetu_SS: #REF!
Name TukiRetu_zen: #REF!
Name TukiRetu_顧客: 商研!$L:$N
Name TukiRetu_工事: #REF!
Name サービス_営業外費_貨物: DB!$DA$3:$DA$65423
Name サービス_営業外費_物流: DB!$DC$3:$DC$65423
Name サービス_原額_貨物自_サンプラ: DB!$BU$3:$BU$65423
Name サービス_原額_貨物自_その他: DB!$CA$3:$CA$65423
Name サービス_原額_貨物自_トラン: DB!$BY$3:$BY$65423
Name サービス_原額_貨物自_三シャ: DB!$BW$3:$BW$65423
Name サービス_原額_貨物自_三商: DB!$BQ$3:$BQ$65423
Name サービス_原額_貨物自_事故: DB!$CC$3:$CC$65423
Name サービス_原額_貨物自_店装: DB!$BS$3:$BS$65423
Name サービス_原額_貨物庸_サンプラ: DB!$CI$3:$CI$65423
Name サービス_原額_貨物庸_その他: DB!$CO$3:$CO$65423
Name サービス_原額_貨物庸_トラン: DB!$CM$3:$CM$65423
Name サービス_原額_貨物庸_三シャ: DB!$CK$3:$CK$65423
Name サービス_原額_貨物庸_三商: DB!$CE$3:$CE$65423
Name サービス_原額_貨物庸_事故: DB!$CQ$3:$CQ$65423
Name サービス_原額_貨物庸_店装: DB!$CG$3:$CG$65423
Name サービス_原額_物流_その他: DB!$CW$3:$CW$65423
Name サービス_原額_物流_ルート: DB!$CS$3:$CS$65423
Name サービス_原額_物流_丸和: DB!$CU$3:$CU$65423
Name サービス_原額_物流_事故: DB!$CY$3:$CY$65423
Name サービス_人件一般費_貨物: DB!$CZ$3:$CZ$65423
Name サービス_人件一般費_物流: DB!$DB$3:$DB$65423
Name サービス_年月: DB!$BO$3:$BO$65423
Name サービス_売額_貨物自_サンプラ: DB!$BT$3:$BT$65423
Name サービス_売額_貨物自_その他: DB!$BZ$3:$BZ$65423
Name サービス_売額_貨物自_トラン: DB!$BX$3:$BX$65423
Name サービス_売額_貨物自_三シャ: DB!$BV$3:$BV$65423
Name サービス_売額_貨物自_三商: DB!$BP$3:$BP$65423
Name サービス_売額_貨物自_事故: DB!$CB$3:$CB$65423
Name サービス_売額_貨物自_店装: DB!$BR$3:$BR$65423
Name サービス_売額_貨物庸_サンプラ: DB!$CH$3:$CH$65423
Name サービス_売額_貨物庸_その他: DB!$CN$3:$CN$65423
Name サービス_売額_貨物庸_トラン: DB!$CL$3:$CL$65423
Name サービス_売額_貨物庸_三シャ: DB!$CJ$3:$CJ$65423
Name サービス_売額_貨物庸_三商: DB!$CD$3:$CD$65423
Name サービス_売額_貨物庸_事故: DB!$CP$3:$CP$65423
Name サービス_売額_貨物庸_店装: DB!$CF$3:$CF$65423
Name サービス_売額_物流_その他: DB!$CV$3:$CV$65423
Name サービス_売額_物流_ルート: DB!$CR$3:$CR$65423
Name サービス_売額_物流_丸和: DB!$CT$3:$CT$65423
Name サービス_売額_物流_事故: DB!$CX$3:$CX$65423
Name サービス予測_年月: DB!$BA$3:$BA$65423
Name サービス予測_予測原価金額_貨物: DB!$BC$3:$BC$65423
Name サービス予測_予測原価金額_物流: DB!$BE$3:$BE$65423
Name サービス予測_予測売上金額_貨物: DB!$BB$3:$BB$65423
Name サービス予測_予測売上金額_物流: DB!$BD$3:$BD$65423
Name フロント_営業外費: DB!$BL$3:$BL$65423
Name フロント_原価税抜金額: DB!$BJ$3:$BJ$65423
Name フロント_人件一般費: DB!$BK$3:$BK$65423
Name フロント_年月: DB!$BH$3:$BH$65423
Name フロント_売上税抜金額: DB!$BI$3:$BI$65423
Name フロント予測_年月: DB!$AV$3:$AV$65423
Name フロント予測_予測原価金額: DB!$AX$3:$AX$65423
Name フロント予測_予測売上金額: DB!$AW$3:$AW$65423

Sheet DB
A1: 顧客別 売上・原価 | J1: 工事 売上・原価 | Y1: 入出庫 | AE1: 三研 売上（円） | AL1: 2016年 担当別原価埋込 | AQ1: 三研予測(円) | AV1: フロント予測(円) | BA1: サービス予測(円) | BH1: フロント 売上（円） | BO1: サービス 売上（円） | DF1: 営業担当別経費 | DM1: 部署別 売上・原価
A2: 営業担当CD | B2: 番号 | C2: 集計CD | D2: 年月日 | E2: 作業区分CD | F2: 売上税抜金額 | G2: 原価税抜金額 | J2: 工事担当CD | K2: 番号 | L2: 集計CD（未使用） | M2: 年月日 | N2: 作業区分CD | O2: 売上税抜金額 | P2: 原価税抜金額 | Y2: 集計CD | Z2: 年月日 | AA2: 出庫金額 | AB2: 入庫金額 | AE2: 年月日 | AF2: 売上税抜金額 | AG2: 原価税抜金額 | AH2: 人件一般費 | AI2: 営業外費 | AL2: チームCD | AM2: 年月日 | AN2: 原価金額 | AQ2: 年月日 | AR2: 予測売上金額 | AS2: 予測原価金額 | AV2: 年月日 | AW2: 予測売上金額 | AX2: 予測原価金額 | BA2: 年月日 | BB2: 予測売上額_貨物 | BC2: 予測原価額_貨物 | BD2: 予測売上額_物流 | BE2: 予測原価額_物流 | BH2: 年月日 | BI2: 売上税抜金額 | BJ2: 原価税抜金額 | BK2: 人件一般費 | BL2: 営業外費 | BO2: 年月日 | BP2: 売額_貨物自_三商 | BQ2: 原額_貨物自_三商 | BR2: 売額_貨物自_店装 | BS2: 原額_貨物自_店装 | BT2: 売額_貨物自_サンプラ | BU2: 原額_貨物自_サンプラ | BV2: 売額_貨物自_三シャ | BW2: 原額_貨物自_三シャ | BX2: 売額_貨物自_トラン | BY2: 原額_貨物自_トラン | BZ2: 売額_貨物自_その他 | CA2: 原額_貨物自_その他 | CB2: 売額_貨物自_事故 | CC2: 原額_貨物自_事故 | CD2: 売額_貨物庸_三商 | CE2: 原額_貨物庸_三商 | CF2: 売額_貨物庸_店装 | CG2: 原額_貨物庸_店装 | CH2: 売額_貨物庸_サンプラ | CI2: 原額_貨物庸_サンプラ | CJ2: 売額_貨物庸_三シャ | CK2: 原額_貨物庸_三シャ | CL2: 売額_貨物庸_トラン | CM2: 原額_貨物庸_トラン | CN2: 売額_貨物庸_その他 | CO2: 原額_貨物庸_その他 | CP2: 売額_貨物庸_事故 | CQ2: 原額_貨物庸_事故 | CR2: 売額_物流_ルート | CS2: 原額_物流_ルート | CT2: 売額_物流_丸和 | CU2: 原額_物流_丸和 | CV2: 売額_物流_その他 | CW2: 原額_物流_その他 | CX2: 売額_物流_事故 | CY2: 原額_物流_事故 | CZ2: 人件一般費_貨物 | DA2: 営業外費_貨物 | DB2: 人件一般費_物流 | DC2: 営業外費_物流 | DF2: 業種区分 | DG2: 部CD（未使用） | DH2: 年月日 | DI2: 人件費一般費 | DM2: 部署 | DN2: 年月日 | DO2: 作業区分CD | DP2: 売上税抜金額 | DQ2: 原価税抜金額

Sheet 商研
A1: 営業チーム統計
A2: 項目 | F2: =YEAR(I2)-1978+1&"期" -> 46期 | I2: 45170
F3: 原価 | H3: 売上 | I3: 原価 | K3: 売上
A4: 売上 | C4: 0 | F4: =SUM(I4:N4) -> 0 | I4: =SUMIF($C10:$C36,$C4,I10:I36) -> 0 | J4: =SUMIF($C9:$C35,$C4,J9:J35) -> 0 | K4: =SUMIF($C9:$C35,$C4,K9:K35) -> 0
A5: 原価 | C5: 1 | H5: =SUM(I5:N5) -> 0 | K5: =SUMIF($C10:$C36,$C5,K10:K36) -> 0
A6: 売上総利益 | F6: =SUMIF(I$3:N$3,$F$3,I6:N6) -> 0 | H6: =IF(ISERROR(F6/F4),0,F6/F4) -> 0 | I6: =I4-K5 -> 0 | K6: =IF(ISERROR(I6/I4),0,I6/I4) -> 0
A7: 販管費 | C7: 0 | F7: =SUMIF(I$3:N$3,$F$3,I7:N7) -> 0 | H7: =IF(ISERROR(F7/F4),0,F7/F4) -> 0 | I7: =IFERROR(INDEX(DB!統計集計先_人件費一般費,MATCH($C7&"-"&I$2,INDEX(DB!統計集計先_CD&"-"&DB!統計集計先_年月,),0)),0) -> 0 | K7: =IF(ISERROR(I7/I4),0,I7/I4) -> 0
A8: 営業利益 | F8: =SUMIF(I$3:N$3,$F$3,I8:N8) -> 0 | H8: =IF(ISERROR(F8/F4),0,F8/F4) -> 0 | I8: =I6-I7 -> 0 | K8: =IF(ISERROR(I8/I4),0,I8/I4) -> 0
B9: 在庫 | E9: 20 | F9: =SUMIF(I$3:N$3,$F$3,I9:N9) -> 0 | G9: ⇔ | H9: =SUMIF(I$3:N$3,$H$3,I9:N9) -> 0 | I9: =SUMIF($B$37:$B$100,$B9,I$37:I$100) -> 0 | J9: ⇔ | K9: =SUMIF($B$37:$B$100,$B9,K$37:K$100) -> 0
A10: 売上 | C10: 0 | F10: =SUM(H13:H18) -> 0 | I10: =SUM(K13:K18) -> 0
A11: 原価 | C11: 1 | H11: =SUM(I11:N11) -> 0 | K11: =SUM(I13:I18) -> 0
A12: 売上総利益 | F12: =F10-H11 -> 0 | H12: =IF(ISERROR(F12/F10),0,F12/F10) -> 0 | I12: =I10-K11 -> 0 | K12: =IF(ISERROR(I12/I10),0,I12/I10) -> 0
A13: 営業１部 | B13: 営業 | D13: 1 | E13: 0 | F13: =SUMIF(I$3:N$3,$F$3,I13:N13) -> 0 | G13: =IF(ISERROR(F13/H13),0,F13/H13) -> 0 | H13: =SUMIF(I$3:N$3,$H$3,I13:N13) -> 0 | I13: =IFERROR(INDEX(DB!$DQ$3:$DQ$65423,MATCH($D13&"-"&I$2&"-"&$E13,INDEX(DB!$DM$3:$DM$65423&"-"&DB!$DN$3:$DN$65423&"-"&DB!$DO$3:$DO$65423,),0)),0) -> 0 | J13: =IF(ISERROR(I13/K13),0,I13/K13) -> 0 | K13: =IFERROR(INDEX(DB!$DP$3:$DP$65423,MATCH($D13&"-"&I$2&"-"&$E13,INDEX(DB!$DM$3:$DM$65423&"-"&DB!$DN$3:$DN$65423&"-"&DB!$DO$3:$DO$65423,),0)),0) -> 0
B14: 工事 | D14: 1 | E14: 1 | F14: =SUMIF(I$3:N$3,$F$3,I14:N14) -> 0 | G14: =IF(ISERROR(F14/H14),0,F14/H14) -> 0 | H14: =SUMIF(I$3:N$3,$H$3,I14:N14) -> 0 | I14: =IFERROR(INDEX(DB!$DQ$3:$DQ$65423,MATCH($D14&"-"&I$2&"-"&$E14,INDEX(DB!$DM$3:$DM$65423&"-"&DB!$DN$3:$DN$65423&"-"&DB!$DO$3:$DO$65423,),0)),0) -> 0 | J14: =IF(ISERROR(I14/K14),0,I14/K14) -> 0 | K14: =IFERROR(INDEX(DB!$DP$3:$DP$65423,MATCH($D14&"-"&I$2&"-"&$E14,INDEX(DB!$DM$3:$DM$65423&"-"&DB!$DN$3:$DN$65423&"-"&DB!$DO$3:$DO$65423,),0)),0) -> 0
B15: コール | D15: 1 | E15: 2 | F15: =SUMIF(I$3:N$3,$F$3,I15:N15) -> 0 | G15: =IF(ISERROR(F15/H15),0,F15/H15) -> 0 | H15: =SUMIF(I$3:N$3,$H$3,I15:N15) -> 0 | I15: =IFERROR(INDEX(DB!$DQ$3:$DQ$65423,MATCH($D15&"-"&I$2&"-"&$E15,INDEX(DB!$DM$3:$DM$65423&"-"&DB!$DN$3:$DN$65423&"-"&DB!$DO$3:$DO$65423,),0)),0) -> 0 | J15: =IF(ISERROR(I15/K15),0,I15/K15) -> 0 | K15: =IFERROR(INDEX(DB!$DP$3:$DP$65423,MATCH($D15&"-"&I$2&"-"&$E15,INDEX(DB!$DM$3:$DM$65423&"-"&DB!$DN$3:$DN$65423&"-"&DB!$DO$3:$DO$65423,),0)),0) -> 0
B16: 店装 | D16: 1 | E16: 3 | F16: =SUMIF(I$3:N$3,$F$3,I16:N16) -> 0 | G16: =IF(ISERROR(F16/H16),0,F16/H16) -> 0 | H16: =SUMIF(I$3:N$3,$H$3,I16:N16) -> 0 | I16: =IFERROR(INDEX(DB!$DQ$3:$DQ$65423,MATCH($D16&"-"&I$2&"-"&$E16,INDEX(DB!$DM$3:$DM$65423&"-"&DB!$DN$3:$DN$65423&"-"&DB!$DO$3:$DO$65423,),0)),0) -> 0 | J16: =IF(ISERROR(I16/K16),0,I16/K16) -> 0 | K16: =IFERROR(INDEX(DB!$DP$3:$DP$65423,MATCH($D16&"-"&I$2&"-"&$E16,INDEX(DB!$DM$3:$DM$65423&"-"&DB!$DN$3:$DN$65423&"-"&DB!$DO$3:$DO$65423,),0)),0) -> 0
B17: 委託 | D17: 1 | E17: 106 | F17: =SUMIF(I$3:N$3,$F$3,I17:N17) -> 0 | G17: =IF(ISERROR(F17/H17),0,F17/H17) -> 0 | H17: =SUMIF(I$3:N$3,$H$3,I17:N17) -> 0 | I17: =IFERROR(INDEX(DB!$DQ$3:$DQ$65423,MATCH($D17&"-"&I$2&"-"&$E17,INDEX(DB!$DM$3:$DM$65423&"-"&DB!$DN$3:$DN$65423&"-"&DB!$DO$3:$DO$65423,),0)),0) -> 0 | J17: =IF(ISERROR(I17/K17),0,I17/K17) -> 0 | K17: =IFERROR(INDEX(DB!$DP$3:$DP$65423,MATCH($D17&"-"&I$2&"-"&$E17,INDEX(DB!$DM$3:$DM$65423&"-"&DB!$DN$3:$DN$65423&"-"&DB!$DO$3:$DO$65423,),0)),0) -> 0
B18: クレーム | D18: 1 | E18: 4 | F18: =SUMIF(I$3:N$3,$F$3,I18:N18) -> 0 | G18: =IF(ISERROR(F18/H18),0,F18/H18) -> 0 | H18: =SUMIF(I$3:N$3,$H$3,I18:N18) -> 0 | I18: =IFERROR(INDEX(DB!$DQ$3:$DQ$65423,MATCH($D18&"-"&I$2&"-"&$E18,INDEX(DB!$DM$3:$DM$65423&"-"&DB!$DN$3:$DN$65423&"-"&DB!$DO$3:$DO$65423,),0)),0) -> 0 | J18: =IF(ISERROR(I18/K18),0,I18/K18) -> 0 | K18: =IFERROR(INDEX(DB!$DP$3:$DP$65423,MATCH($D18&"-"&I$2&"-"&$E18,INDEX(DB!$DM$3:$DM$65423&"-"&DB!$DN$3:$DN$65423&"-"&DB!$DO$3:$DO$65423,),0)),0) -> 0
A19: 売上 | C19: 0 | F19: =SUM(H22:H27) -> 0 | I19: =SUM(K22:K27) -> 0
A20: 原価 | C20: 1 | H20: =SUM(I20:N20) -> 0 | K20: =SUM(I22:I27) -> 0
A21: 売上総利益 | F21: =F19-H20 -> 0 | H21: =IF(ISERROR(F21/F19),0,F21/F19) -> 0 | I21: =I19-K20 -> 0 | K21: =IF(ISERROR(I21/I19),0,I21/I19) -> 0
A22: 営業２部 | B22: 営業 | D22: 2 | E22: 0 | F22: =SUMIF(I$3:N$3,$F$3,I22:N22) -> 0 | G22: =IF(ISERROR(F22/H22),0,F22/H22) -> 0 | H22: =SUMIF(I$3:N$3,$H$3,I22:N22) -> 0 | I22: =IFERROR(INDEX(DB!$DQ$3:$DQ$65423,MATCH($D22&"-"&I$2&"-"&$E22,INDEX(DB!$DM$3:$DM$65423&"-"&DB!$DN$3:$DN$65423&"-"&DB!$DO$3:$DO$65423,),0)),0) -> 0 | J22: =IF(ISERROR(I22/K22),0,I22/K22) -> 0 | K22: =IFERROR(INDEX(DB!$DP$3:$DP$65423,MATCH($D22&"-"&I$2&"-"&$E22,INDEX(DB!$DM$3:$DM$65423&"-"&DB!$DN$3:$DN$65423&"-"&DB!$DO$3:$DO$65423,),0)),0) -> 0
B23: 工事 | D23: 2 | E23: 1 | F23: =SUMIF(I$3:N$3,$F$3,I23:N23) -> 0 | G23: =IF(ISERROR(F23/H23),0,F23/H23) -> 0 | H23: =SUMIF(I$3:N$3,$H$3,I23:N23) -> 0 | I23: =IFERROR(INDEX(DB!$DQ$3:$DQ$65423,MATCH($D23&"-"&I$2&"-"&$E23,INDEX(DB!$DM$3:$DM$65423&"-"&DB!$DN$3:$DN$65423&"-"&DB!$DO$3:$DO$65423,),0)),0) -> 0 | J23: =IF(ISERROR(I23/K23),0,I23/K23) -> 0 | K23: =IFERROR(INDEX(DB!$DP$3:$DP$65423,MATCH($D23&"-"&I$2&"-"&$E23,INDEX(DB!$DM$3:$DM$65423&"-"&DB!$DN$3:$DN$65423&"-"&DB!$DO$3:$DO$65423,),0)),0) -> 0
B24: コール | D24: 2 | E24: 2 | F24: =SUMIF(I$3:N$3,$F$3,I24:N24) -> 0 | G24: =IF(ISERROR(F24/H24),0,F24/H24) -> 0 | H24: =SUMIF(I$3:N$3,$H$3,I24:N24) -> 0 | I24: =IFERROR(INDEX(DB!$DQ$3:$DQ$65423,MATCH($D24&"-"&I$2&"-"&$E24,INDEX(DB!$DM$3:$DM$65423&"-"&DB!$DN$3:$DN$65423&"-"&DB!$DO$3:$DO$65423,),0)),0) -> 0 | J24: =IF(ISERROR(I24/K24),0,I24/K24) -> 0 | K24: =IFERROR(INDEX(DB!$DP$3:$DP$65423,MATCH($D24&"-"&I$2&"-"&$E24,INDEX(DB!$DM$3:$DM$65423&"-"&DB!$DN$3:$DN$65423&"-"&DB!$DO$3:$DO$65423,),0)),0) -> 0
B25: 店装 | D25: 2 | E25: 3 | F25: =SUMIF(I$3:N$3,$F$3,I25:N25) -> 0 | G25: =IF(ISERROR(F25/H25),0,F25/H25) -> 0 | H25: =SUMIF(I$3:N$3,$H$3,I25:N25) -> 0 | I25: =IFERROR(INDEX(DB!$DQ$3:$DQ$65423,MATCH($D25&"-"&I$2&"-"&$E25,INDEX(DB!$DM$3:$DM$65423&"-"&DB!$DN$3:$DN$65423&"-"&DB!$DO$3:$DO$65423,),0)),0) -> 0 | J25: =IF(ISERROR(I25/K25),0,I25/K25) -> 0 | K25: =IFERROR(INDEX(DB!$DP$3:$DP$65423,MATCH($D25&"-"&I$2&"-"&$E25,INDEX(DB!$DM$3:$DM$65423&"-"&DB!$DN$3:$DN$65423&"-"&DB!$DO$3:$DO$65423,),0)),0) -> 0
B26: 委託 | D26: 2 | E26: 106 | F26: =SUMIF(I$3:N$3,$F$3,I26:N26) -> 0 | G26: =IF(ISERROR(F26/H26),0,F26/H26) -> 0 | H26: =SUMIF(I$3:N$3,$H$3,I26:N26) -> 0 | I26: =IFERROR(INDEX(DB!$DQ$3:$DQ$65423,MATCH($D26&"-"&I$2&"-"&$E26,INDEX(DB!$DM$3:$DM$65423&"-"&DB!$DN$3:$DN$65423&"-"&DB!$DO$3:$DO$65423,),0)),0) -> 0 | J26: =IF(ISERROR(I26/K26),0,I26/K26) -> 0 | K26: =IFERROR(INDEX(DB!$DP$3:$DP$65423,MATCH($D26&"-"&I$2&"-"&$E26,INDEX(DB!$DM$3:$DM$65423&"-"&DB!$DN$3:$DN$65423&"-"&DB!$DO$3:$DO$65423,),0)),0) -> 0
B27: クレーム | D27: 2 | E27: 4 | F27: =SUMIF(I$3:N$3,$F$3,I27:N27) -> 0 | G27: =IF(ISERROR(F27/H27),0,F27/H27) -> 0 | H27: =SUMIF(I$3:N$3,$H$3,I27:N27) -> 0 | I27: =IFERROR(INDEX(DB!$DQ$3:$DQ$65423,MATCH($D27&"-"&I$2&"-"&$E27,INDEX(DB!$DM$3:$DM$65423&"-"&DB!$DN$3:$DN$65423&"-"&DB!$DO$3:$DO$65423,),0)),0) -> 0 | J27: =IF(ISERROR(I27/K27),0,I27/K27) -> 0 | K27: =IFERROR(INDEX(DB!$DP$3:$DP$65423,MATCH($D27&"-"&I$2&"-"&$E27,INDEX(DB!$DM$3:$DM$65423&"-"&DB!$DN$3:$DN$65423&"-"&DB!$DO$3:$DO$65423,),0)),0) -> 0
A28: 売上 | C28: 0 | F28: =SUM(H31:H36) -> 0 | I28: =SUM(K31:K36) -> 0
A29: 原価 | C29: 1 | H29: =SUM(I29:N29) -> 0 | K29: =SUM(I31:I36) -> 0
A30: 売上総利益 | F30: =F28-H29 -> 0 | H30: =IF(ISERROR(F30/F28),0,F30/F28) -> 0 | I30: =I28-K29 -> 0 | K30: =IF(ISERROR(I30/I28),0,I30/I28) -> 0
A31: 営業３部 | B31: 営業 | D31: 3 | E31: 0 | F31: =SUMIF(I$3:N$3,$F$3,I31:N31) -> 0 | G31: =IF(ISERROR(F31/H31),0,F31/H31) -> 0 | H31: =SUMIF(I$3:N$3,$H$3,I31:N31) -> 0 | I31: =IFERROR(INDEX(DB!$DQ$3:$DQ$65423,MATCH($D31&"-"&I$2&"-"&$E31,INDEX(DB!$DM$3:$DM$65423&"-"&DB!$DN$3:$DN$65423&"-"&DB!$DO$3:$DO$65423,),0)),0) -> 0 | J31: =IF(ISERROR(I31/K31),0,I31/K31) -> 0 | K31: =IFERROR(INDEX(DB!$DP$3:$DP$65423,MATCH($D31&"-"&I$2&"-"&$E31,INDEX(DB!$DM$3:$DM$65423&"-"&DB!$DN$3:$DN$65423&"-"&DB!$DO$3:$DO$65423,),0)),0) -> 0
B32: 工事 | D32: 3 | E32: 1 | F32: =SUMIF(I$3:N$3,$F$3,I32:N32) -> 0 | G32: =IF(ISERROR(F32/H32),0,F32/H32) -> 0 | H32: =SUMIF(I$3:N$3,$H$3,I32:N32) -> 0 | I32: =IFERROR(INDEX(DB!$DQ$3:$DQ$65423,MATCH($D32&"-"&I$2&"-"&$E32,INDEX(DB!$DM$3:$DM$65423&"-"&DB!$DN$3:$DN$65423&"-"&DB!$DO$3:$DO$65423,),0)),0) -> 0 | J32: =IF(ISERROR(I32/K32),0,I32/K32) -> 0 | K32: =IFERROR(INDEX(DB!$DP$3:$DP$65423,MATCH($D32&"-"&I$2&"-"&$E32,INDEX(DB!$DM$3:$DM$65423&"-"&DB!$DN$3:$DN$65423&"-"&DB!$DO$3:$DO$65423,),0)),0) -> 0
B33: コール | D33: 3 | E33: 2 | F33: =SUMIF(I$3:N$3,$F$3,I33:N33) -> 0 | G33: =IF(ISERROR(F33/H33),0,F33/H33) -> 0 | H33: =SUMIF(I$3:N$3,$H$3,I33:N33) -> 0 | I33: =IFERROR(INDEX(DB!$DQ$3:$DQ$65423,MATCH($D33&"-"&I$2&"-"&$E33,INDEX(DB!$DM$3:$DM$65423&"-"&DB!$DN$3:$DN$65423&"-"&DB!$DO$3:$DO$65423,),0)),0) -> 0 | J33: =IF(ISERROR(I33/K33),0,I33/K33) -> 0 | K33: =IFERROR(INDEX(DB!$DP$3:$DP$65423,MATCH($D33&"-"&I$2&"-"&$E33,INDEX(DB!$DM$3:$DM$65423&"-"&DB!$DN$3:$DN$65423&"-"&DB!$DO$3:$DO$65423,),0)),0) -> 0
B34: 店装 | D34: 3 | E34: 3 | F34: =SUMIF(I$3:N$3,$F$3,I34:N34) -> 0 | G34: =IF(ISERROR(F34/H34),0,F34/H34) -> 0 | H34: =SUMIF(I$3:N$3,$H$3,I34:N34) -> 0 | I34: =IFERROR(INDEX(DB!$DQ$3:$DQ$65423,MATCH($D34&"-"&I$2&"-"&$E34,INDEX(DB!$DM$3:$DM$65423&"-"&DB!$DN$3:$DN$65423&"-"&DB!$DO$3:$DO$65423,),0)),0) -> 0 | J34: =IF(ISERROR(I34/K34),0,I34/K34) -> 0 | K34: =IFERROR(INDEX(DB!$DP$3:$DP$65423,MATCH($D34&"-"&I$2&"-"&$E34,INDEX(DB!$DM$3:$DM$65423&"-"&DB!$DN$3:$DN$65423&"-"&DB!$DO$3:$DO$65423,),0)),0) -> 0
B35: 委託 | D35: 3 | E35: 106 | F35: =SUMIF(I$3:N$3,$F$3,I35:N35) -> 0 | G35: =IF(ISERROR(F35/H35),0,F35/H35) -> 0 | H35: =SUMIF(I$3:N$3,$H$3,I35:N35) -> 0 | I35: =IFERROR(INDEX(DB!$DQ$3:$DQ$65423,MATCH($D35&"-"&I$2&"-"&$E35,INDEX(DB!$DM$3:$DM$65423&"-"&DB!$DN$3:$DN$65423&"-"&DB!$DO$3:$DO$65423,),0)),0) -> 0 | J35: =IF(ISERROR(I35/K35),0,I35/K35) -> 0 | K35: =IFERROR(INDEX(DB!$DP$3:$DP$65423,MATCH($D35&"-"&I$2&"-"&$E35,INDEX(DB!$DM$3:$DM$65423&"-"&DB!$DN$3:$DN$65423&"-"&DB!$DO$3:$DO$65423,),0)),0) -> 0
B36: クレーム | D36: 3 | E36: 4 | F36: =SUMIF(I$3:N$3,$F$3,I36:N36) -> 0 | G36: =IF(ISERROR(F36/H36),0,F36/H36) -> 0 | H36: =SUMIF(I$3:N$3,$H$3,I36:N36) -> 0 | I36: =IFERROR(INDEX(DB!$DQ$3:$DQ$65423,MATCH($D36&"-"&I$2&"-"&$E36,INDEX(DB!$DM$3:$DM$65423&"-"&DB!$DN$3:$DN$65423&"-"&DB!$DO$3:$DO$65423,),0)),0) -> 0 | J36: =IF(ISERROR(I36/K36),0,I36/K36) -> 0 | K36: =IFERROR(INDEX(DB!$DP$3:$DP$65423,MATCH($D36&"-"&I$2&"-"&$E36,INDEX(DB!$DM$3:$DM$65423&"-"&DB!$DN$3:$DN$65423&"-"&DB!$DO$3:$DO$65423,),0)),0) -> 0
A37: W | B37: 原/売 | D37: 2401 | F37: =SUMIF(I$3:N$3,$F$3,I37:N37) -> 0 | G37: =IF(ISERROR(F37/H37),0,F37/H37) -> 0 | H37: =SUMIF(I$3:N$3,$H$3,I37:N37) -> 0 | I37: =SUMIF($D38:$D43,$D37,I38:I43) -> 0 | J37: =IF(ISERROR(I37/K37),0,I37/K37) -> 0 | K37: =SUM(K38:K43) -> 0
B38: 営業 | C38: 0 | D38: 2401 | E38: 0 | F38: =SUMIF(I$3:N$3,$F$3,I38:N38) -> 0 | G38: =IF(ISERROR(F38/H38),0,F38/H38) -> 0 | H38: =SUMIF(I$3:N$3,$H$3,I38:N38) -> 0 | I38: =IFERROR(INDEX(DB!$G$3:$G$65423,MATCH($C38&"-"&$D38&"-"&I$2&"-"&$E38,INDEX(DB!$A$3:$A$65423&"-"&DB!$C$3:$C$65423&"-"&DB!$D$3:$D$65423&"-"&DB!$E$3:$E$65423,),0)),0) -> 0 | J38: =IF(ISERROR(I38/K38),0,I38/K38) -> 0 | K38: =IFERROR(INDEX(DB!$F$3:$F$65423,MATCH($C38&"-"&$D38&"-"&I$2&"-"&$E38,INDEX(DB!$A$3:$A$65423&"-"&DB!$C$3:$C$65423&"-"&DB!$D$3:$D$65423&"-"&DB!$E$3:$E$65423,),0)),0) -> 0
B39: 工事 | C39: 0 | D39: 2401 | E39: 1 | F39: =SUMIF(I$3:N$3,$F$3,I39:N39) -> 0 | G39: =IF(ISERROR(F39/H39),0,F39/H39) -> 0 | H39: =SUMIF(I$3:N$3,$H$3,I39:N39) -> 0 | I39: =IFERROR(INDEX(DB!$G$3:$G$65423,MATCH($C39&"-"&$D39&"-"&I$2&"-"&$E39,INDEX(DB!$A$3:$A$65423&"-"&DB!$C$3:$C$65423&"-"&DB!$D$3:$D$65423&"-"&DB!$E$3:$E$65423,),0)),0) -> 0 | J39: =IF(ISERROR(I39/K39),0,I39/K39) -> 0 | K39: =IFERROR(INDEX(DB!$F$3:$F$65423,MATCH($C39&"-"&$D39&"-"&I$2&"-"&$E39,INDEX(DB!$A$3:$A$65423&"-"&DB!$C$3:$C$65423&"-"&DB!$D$3:$D$65423&"-"&DB!$E$3:$E$65423,),0)),0) -> 0
B40: コール | C40: 0 | D40: 2401 | E40: 2 | F40: =SUMIF(I$3:N$3,$F$3,I40:N40) -> 0 | G40: =IF(ISERROR(F40/H40),0,F40/H40) -> 0 | H40: =SUMIF(I$3:N$3,$H$3,I40:N40) -> 0 | I40: =IFERROR(INDEX(DB!$G$3:$G$65423,MATCH($C40&"-"&$D40&"-"&I$2&"-"&$E40,INDEX(DB!$A$3:$A$65423&"-"&DB!$C$3:$C$65423&"-"&DB!$D$3:$D$65423&"-"&DB!$E$3:$E$65423,),0)),0) -> 0 | J40: =IF(ISERROR(I40/K40),0,I40/K40) -> 0 | K40: =IFERROR(INDEX(DB!$F$3:$F$65423,MATCH($C40&"-"&$D40&"-"&I$2&"-"&$E40,INDEX(DB!$A$3:$A$65423&"-"&DB!$C$3:$C$65423&"-"&DB!$D$3:$D$65423&"-"&DB!$E$3:$E$65423,),0)),0) -> 0
B41: 店装 | C41: 0 | D41: 2401 | E41: 3 | F41: =SUMIF(I$3:N$3,$F$3,I41:N41) -> 0 | G41: =IF(ISERROR(F41/H41),0,F41/H41) -> 0 | H41: =SUMIF(I$3:N$3,$H$3,I41:N41) -> 0 | I41: =IFERROR(INDEX(DB!$G$3:$G$65423,MATCH($C41&"-"&$D41&"-"&I$2&"-"&$E41,INDEX(DB!$A$3:$A$65423&"-"&DB!$C$3:$C$65423&"-"&DB!$D$3:$D$65423&"-"&DB!$E$3:$E$65423,),0)),0) -> 0 | J41: =IF(ISERROR(I41/K41),0,I41/K41) -> 0 | K41: =IFERROR(INDEX(DB!$F$3:$F$65423,MATCH($C41&"-"&$D41&"-"&I$2&"-"&$E41,INDEX(DB!$A$3:$A$65423&"-"&DB!$C$3:$C$65423&"-"&DB!$D$3:$D$65423&"-"&DB!$E$3:$E$65423,),0)),0) -> 0
B42: 委託 | C42: 0 | D42: 2401 | E42: 106 | F42: =SUMIF(I$3:N$3,$F$3,I42:N42) -> 0 | G42: =IF(ISERROR(F42/H42),0,F42/H42) -> 0 | H42: =SUMIF(I$3:N$3,$H$3,I42:N42) -> 0 | I42: =IFERROR(INDEX(DB!$G$3:$G$65423,MATCH($C42&"-"&$D42&"-"&I$2&"-"&$E42,INDEX(DB!$A$3:$A$65423&"-"&DB!$C$3:$C$65423&"-"&DB!$D$3:$D$65423&"-"&DB!$E$3:$E$65423,),0)),0) -> 0 | J42: =IF(ISERROR(I42/K42),0,I42/K42) -> 0 | K42: =IFERROR(INDEX(DB!$F$3:$F$65423,MATCH($C42&"-"&$D42&"-"&I$2&"-"&$E42,INDEX(DB!$A$3:$A$65423&"-"&DB!$C$3:$C$65423&"-"&DB!$D$3:$D$65423&"-"&DB!$E$3:$E$65423,),0)),0) -> 0
B43: クレーム | C43: 0 | D43: 2401 | E43: 4 | F43: =SUMIF(I$3:N$3,$F$3,I43:N43) -> 0 | G43: =IF(ISERROR(F43/H43),0,F43/H43) -> 0 | H43: =SUMIF(I$3:N$3,$H$3,I43:N43) -> 0 | I43: =IFERROR(INDEX(DB!$G$3:$G$65423,MATCH($C43&"-"&$D43&"-"&I$2&"-"&$E43,INDEX(DB!$A$3:$A$65423&"-"&DB!$C$3:$C$65423&"-"&DB!$D$3:$D$65423&"-"&DB!$E$3:$E$65423,),0)),0) -> 0 | J43: =IF(ISERROR(I43/K43),0,I43/K43) -> 0 | K43: =IFERROR(INDEX(DB!$F$3:$F$65423,MATCH($C43&"-"&$D43&"-"&I$2&"-"&$E43,INDEX(DB!$A$3:$A$65423&"-"&DB!$C$3:$C$65423&"-"&DB!$D$3:$D$65423&"-"&DB!$E$3:$E$65423,),0)),0) -> 0
B44: 在庫 | D44: 2401 | E44: 20 | F44: =SUMIF(I$3:N$3,$F$3,I44:N44) -> 0 | G44: ⇔ | H44: =SUMIF(I$3:N$3,$H$3,I44:N44) -> 0 | I44: =IFERROR(INDEX(DB!$AB$3:$AB$65423,MATCH($D44&"-"&I$2,INDEX(DB!$Y$3:$Y$65423&"-"&DB!$Z$3:$Z$65423,),0)),0) -> 0 | J44: ⇔ | K44: =IFERROR(INDEX(DB!$AA$3:$AA$65423,MATCH($D44&"-"&I$2,INDEX(DB!$Y$3:$Y$65423&"-"&DB!$Z$3:$Z$65423,),0)),0) -> 0
A45: B | B45: 原/売 | D45: 6601 | F45: =SUMIF(I$3:N$3,$F$3,I45:N45) -> 0 | G45: =IF(ISERROR(F45/H45),0,F45/H45) -> 0 | H45: =SUMIF(I$3:N$3,$H$3,I45:N45) -> 0 | I45: =SUMIF($D46:$D51,$D45,I46:I51) -> 0 | J45: =IF(ISERROR(I45/K45),0,I45/K45) -> 0 | K45: =SUM(K46:K51) -> 0
B46: 営業 | C46: 0 | D46: 6601 | E46: 0 | F46: =SUMIF(I$3:N$3,$F$3,I46:N46) -> 0 | G46: =IF(ISERROR(F46/H46),0,F46/H46) -> 0 | H46: =SUMIF(I$3:N$3,$H$3,I46:N46) -> 0 | I46: =IFERROR(INDEX(DB!$G$3:$G$65423,MATCH($C46&"-"&$D46&"-"&I$2&"-"&$E46,INDEX(DB!$A$3:$A$65423&"-"&DB!$C$3:$C$65423&"-"&DB!$D$3:$D$65423&"-"&DB!$E$3:$E$65423,),0)),0) -> 0 | J46: =IF(ISERROR(I46/K46),0,I46/K46) -> 0 | K46: =IFERROR(INDEX(DB!$F$3:$F$65423,MATCH($C46&"-"&$D46&"-"&I$2&"-"&$E46,INDEX(DB!$A$3:$A$65423&"-"&DB!$C$3:$C$65423&"-"&DB!$D$3:$D$65423&"-"&DB!$E$3:$E$65423,),0)),0) -> 0
B47: 工事 | C47: 0 | D47: 6601 | E47: 1 | F47: =SUMIF(I$3:N$3,$F$3,I47:N47) -> 0 | G47: =IF(ISERROR(F47/H47),0,F47/H47) -> 0 | H47: =SUMIF(I$3:N$3,$H$3,I47:N47) -> 0 | I47: =IFERROR(INDEX(DB!$G$3:$G$65423,MATCH($C47&"-"&$D47&"-"&I$2&"-"&$E47,INDEX(DB!$A$3:$A$65423&"-"&DB!$C$3:$C$65423&"-"&DB!$D$3:$D$65423&"-"&DB!$E$3:$E$65423,),0)),0) -> 0 | J47: =IF(ISERROR(I47/K47),0,I47/K47) -> 0 | K47: =IFERROR(INDEX(DB!$F$3:$F$65423,MATCH($C47&"-"&$D47&"-"&I$2&"-"&$E47,INDEX(DB!$A$3:$A$65423&"-"&DB!$C$3:$C$65423&"-"&DB!$D$3:$D$65423&"-"&DB!$E$3:$E$65423,),0)),0) -> 0
B48: コール | C48: 0 | D48: 6601 | E48: 2 | F48: =SUMIF(I$3:N$3,$F$3,I48:N48) -> 0 | G48: =IF(ISERROR(F48/H48),0,F48/H48) -> 0 | H48: =SUMIF(I$3:N$3,$H$3,I48:N48) -> 0 | I48: =IFERROR(INDEX(DB!$G$3:$G$65423,MATCH($C48&"-"&$D48&"-"&I$2&"-"&$E48,INDEX(DB!$A$3:$A$65423&"-"&DB!$C$3:$C$65423&"-"&DB!$D$3:$D$65423&"-"&DB!$E$3:$E$65423,),0)),0) -> 0 | J48: =IF(ISERROR(I48/K48),0,I48/K48) -> 0 | K48: =IFERROR(INDEX(DB!$F$3:$F$65423,MATCH($C48&"-"&$D48&"-"&I$2&"-"&$E48,INDEX(DB!$A$3:$A$65423&"-"&DB!$C$3:$C$65423&"-"&DB!$D$3:$D$65423&"-"&DB!$E$3:$E$65423,),0)),0) -> 0
B49: 店装 | C49: 0 | D49: 6601 | E49: 3 | F49: =SUMIF(I$3:N$3,$F$3,I49:N49) -> 0 | G49: =IF(ISERROR(F49/H49),0,F49/H49) -> 0 | H49: =SUMIF(I$3:N$3,$H$3,I49:N49) -> 0 | I49: =IFERROR(INDEX(DB!$G$3:$G$65423,MATCH($C49&"-"&$D49&"-"&I$2&"-"&$E49,INDEX(DB!$A$3:$A$65423&"-"&DB!$C$3:$C$65423&"-"&DB!$D$3:$D$65423&"-"&DB!$E$3:$E$65423,),0)),0) -> 0 | J49: =IF(ISERROR(I49/K49),0,I49/K49) -> 0 | K49: =IFERROR(INDEX(DB!$F$3:$F$65423,MATCH($C49&"-"&$D49&"-"&I$2&"-"&$E49,INDEX(DB!$A$3:$A$65423&"-"&DB!$C$3:$C$65423&"-"&DB!$D$3:$D$65423&"-"&DB!$E$3:$E$65423,),0)),0) -> 0
B50: 委託 | C50: 0 | D50: 6601 | E50: 106 | F50: =SUMIF(I$3:N$3,$F$3,I50:N50) -> 0 | G50: =IF(ISERROR(F50/H50),0,F50/H50) -> 0 | H50: =SUMIF(I$3:N$3,$H$3,I50:N50) -> 0 | I50: =IFERROR(INDEX(DB!$G$3:$G$65423,MATCH($C50&"-"&$D50&"-"&I$2&"-"&$E50,INDEX(DB!$A$3:$A$65423&"-"&DB!$C$3:$C$65423&"-"&DB!$D$3:$D$65423&"-"&DB!$E$3:$E$65423,),0)),0) -> 0 | J50: =IF(ISERROR(I50/K50),0,I50/K50) -> 0 | K50: =IFERROR(INDEX(DB!$F$3:$F$65423,MATCH($C50&"-"&$D50&"-"&I$2&"-"&$E50,INDEX(DB!$A$3:$A$65423&"-"&DB!$C$3:$C$65423&"-"&DB!$D$3:$D$65423&"-"&DB!$E$3:$E$65423,),0)),0) -> 0
B51: クレーム | C51: 0 | D51: 6601 | E51: 4 | F51: =SUMIF(I$3:N$3,$F$3,I51:N51) -> 0 | G51: =IF(ISERROR(F51/H51),0,F51/H51) -> 0 | H51: =SUMIF(I$3:N$3,$H$3,I51:N51) -> 0 | I51: =IFERROR(INDEX(DB!$G$3:$G$65423,MATCH($C51&"-"&$D51&"-"&I$2&"-"&$E51,INDEX(DB!$A$3:$A$65423&"-"&DB!$C$3:$C$65423&"-"&DB!$D$3:$D$65423&"-"&DB!$E$3:$E$65423,),0)),0) -> 0 | J51: =IF(ISERROR(I51/K51),0,I51/K51) -> 0 | K51: =IFERROR(INDEX(DB!$F$3:$F$65423,MATCH($C51&"-"&$D51&"-"&I$2&"-"&$E51,INDEX(DB!$A$3:$A$65423&"-"&DB!$C$3:$C$65423&"-"&DB!$D$3:$D$65423&"-"&DB!$E$3:$E$65423,),0)),0) -> 0
B52: 在庫 | D52: 6601 | E52: 20 | F52: =SUMIF(I$3:N$3,$F$3,I52:N52) -> 0 | G52: ⇔ | H52: =SUMIF(I$3:N$3,$H$3,I52:N52) -> 0 | I52: =IFERROR(INDEX(DB!$AB$3:$AB$65423,MATCH($D52&"-"&I$2,INDEX(DB!$Y$3:$Y$65423&"-"&DB!$Z$3:$Z$65423,),0)),0) -> 0 | J52: ⇔ | K52: =IFERROR(INDEX(DB!$AA$3:$AA$65423,MATCH($D52&"-"&I$2,INDEX(DB!$Y$3:$Y$65423&"-"&DB!$Z$3:$Z$65423,),0)),0) -> 0
A53: BX | B53: 原/売 | D53: 3001 | F53: =SUMIF(I$3:N$3,$F$3,I53:N53) -> 0 | G53: =IF(ISERROR(F53/H53),0,F53/H53) -> 0 | H53: =SUMIF(I$3:N$3,$H$3,I53:N53) -> 0 | I53: =SUMIF($D54:$D59,$D53,I54:I59) -> 0 | J53: =IF(ISERROR(I53/K53),0,I53/K53) -> 0 | K53: =SUM(K54:K59) -> 0
B54: 営業 | C54: 0 | D54: 3001 | E54: 0 | F54: =SUMIF(I$3:N$3,$F$3,I54:N54) -> 0 | G54: =IF(ISERROR(F54/H54),0,F54/H54) -> 0 | H54: =SUMIF(I$3:N$3,$H$3,I54:N54) -> 0 | I54: =IFERROR(INDEX(DB!$G$3:$G$65423,MATCH($C54&"-"&$D54&"-"&I$2&"-"&$E54,INDEX(DB!$A$3:$A$65423&"-"&DB!$C$3:$C$65423&"-"&DB!$D$3:$D$65423&"-"&DB!$E$3:$E$65423,),0)),0) -> 0 | J54: =IF(ISERROR(I54/K54),0,I54/K54) -> 0 | K54: =IFERROR(INDEX(DB!$F$3:$F$65423,MATCH($C54&"-"&$D54&"-"&I$2&"-"&$E54,INDEX(DB!$A$3:$A$65423&"-"&DB!$C$3:$C$65423&"-"&DB!$D$3:$D$65423&"-"&DB!$E$3:$E$65423,),0)),0) -> 0
B55: 工事 | C55: 0 | D55: 3001 | E55: 1 | F55: =SUMIF(I$3:N$3,$F$3,I55:N55) -> 0 | G55: =IF(ISERROR(F55/H55),0,F55/H55) -> 0 | H55: =SUMIF(I$3:N$3,$H$3,I55:N55) -> 0 | I55: =IFERROR(INDEX(DB!$G$3:$G$65423,MATCH($C55&"-"&$D55&"-"&I$2&"-"&$E55,INDEX(DB!$A$3:$A$65423&"-"&DB!$C$3:$C$65423&"-"&DB!$D$3:$D$65423&"-"&DB!$E$3:$E$65423,),0)),0) -> 0 | J55: =IF(ISERROR(I55/K55),0,I55/K55) -> 0 | K55: =IFERROR(INDEX(DB!$F$3:$F$65423,MATCH($C55&"-"&$D55&"-"&I$2&"-"&$E55,INDEX(DB!$A$3:$A$65423&"-"&DB!$C$3:$C$65423&"-"&DB!$D$3:$D$65423&"-"&DB!$E$3:$E$65423,),0)),0) -> 0
B56: コール | C56: 0 | D56: 3001 | E56: 2 | F56: =SUMIF(I$3:N$3,$F$3,I56:N56) -> 0 | G56: =IF(ISERROR(F56/H56),0,F56/H56) -> 0 | H56: =SUMIF(I$3:N$3,$H$3,I56:N56) -> 0 | I56: =IFERROR(INDEX(DB!$G$3:$G$65423,MATCH($C56&"-"&$D56&"-"&I$2&"-"&$E56,INDEX(DB!$A$3:$A$65423&"-"&DB!$C$3:$C$65423&"-"&DB!$D$3:$D$65423&"-"&DB!$E$3:$E$65423,),0)),0) -> 0 | J56: =IF(ISERROR(I56/K56),0,I56/K56) -> 0 | K56: =IFERROR(INDEX(DB!$F$3:$F$65423,MATCH($C56&"-"&$D56&"-"&I$2&"-"&$E56,INDEX(DB!$A$3:$A$65423&"-"&DB!$C$3:$C$65423&"-"&DB!$D$3:$D$65423&"-"&DB!$E$3:$E$65423,),0)),0) -> 0
B57: 店装 | C57: 0 | D57: 3001 | E57: 3 | F57: =SUMIF(I$3:N$3,$F$3,I57:N57) -> 0 | G57: =IF(ISERROR(F57/H57),0,F57/H57) -> 0 | H57: =SUMIF(I$3:N$3,$H$3,I57:N57) -> 0 | I57: =IFERROR(INDEX(DB!$G$3:$G$65423,MATCH($C57&"-"&$D57&"-"&I$2&"-"&$E57,INDEX(DB!$A$3:$A$65423&"-"&DB!$C$3:$C$65423&"-"&DB!$D$3:$D$65423&"-"&DB!$E$3:$E$65423,),0)),0) -> 0 | J57: =IF(ISERROR(I57/K57),0,I57/K57) -> 0 | K57: =IFERROR(INDEX(DB!$F$3:$F$65423,MATCH($C57&"-"&$D57&"-"&I$2&"-"&$E57,INDEX(DB!$A$3:$A$65423&"-"&DB!$C$3:$C$65423&"-"&DB!$D$3:$D$65423&"-"&DB!$E$3:$E$65423,),0)),0) -> 0
B58: 委託 | C58: 0 | D58: 3001 | E58: 106 | F58: =SUMIF(I$3:N$3,$F$3,I58:N58) -> 0 | G58: =IF(ISERROR(F58/H58),0,F58/H58) -> 0 | H58: =SUMIF(I$3:N$3,$H$3,I58:N58) -> 0 | I58: =IFERROR(INDEX(DB!$G$3:$G$65423,MATCH($C58&"-"&$D58&"-"&I$2&"-"&$E58,INDEX(DB!$A$3:$A$65423&"-"&DB!$C$3:$C$65423&"-"&DB!$D$3:$D$65423&"-"&DB!$E$3:$E$65423,),0)),0) -> 0 | J58: =IF(ISERROR(I58/K58),0,I58/K58) -> 0 | K58: =IFERROR(INDEX(DB!$F$3:$F$65423,MATCH($C58&"-"&$D58&"-"&I$2&"-"&$E58,INDEX(DB!$A$3:$A$65423&"-"&DB!$C$3:$C$65423&"-"&DB!$D$3:$D$65423&"-"&DB!$E$3:$E$65423,),0)),0) -> 0
B59: クレーム | C59: 0 | D59: 3001 | E59: 4 | F59: =SUMIF(I$3:N$3,$F$3,I59:N59) -> 0 | G59: =IF(ISERROR(F59/H59),0,F59/H59) -> 0 | H59: =SUMIF(I$3:N$3,$H$3,I59:N59) -> 0 | I59: =IFERROR(INDEX(DB!$G$3:$G$65423,MATCH($C59&"-"&$D59&"-"&I$2&"-"&$E59,INDEX(DB!$A$3:$A$65423&"-"&DB!$C$3:$C$65423&"-"&DB!$D$3:$D$65423&"-"&DB!$E$3:$E$65423,),0)),0) -> 0 | J59: =IF(ISERROR(I59/K59),0,I59/K59) -> 0 | K59: =IFERROR(INDEX(DB!$F$3:$F$65423,MATCH($C59&"-"&$D59&"-"&I$2&"-"&$E59,INDEX(DB!$A$3:$A$65423&"-"&DB!$C$3:$C$65423&"-"&DB!$D$3:$D$65423&"-"&DB!$E$3:$E$65423,),0)),0) -> 0
B60: 在庫 | D60: 3001 | E60: 20 | F60: =SUMIF(I$3:N$3,$F$3,I60:N60) -> 0 | G60: ⇔ | H60: =SUMIF(I$3:N$3,$H$3,I60:N60) -> 0 | I60: =IFERROR(INDEX(DB!$AB$3:$AB$65423,MATCH($D60&"-"&I$2,INDEX(DB!$Y$3:$Y$65423&"-"&DB!$Z$3:$Z$65423,),0)),0) -> 0 | J60: ⇔ | K60: =IFERROR(INDEX(DB!$AA$3:$AA$65423,MATCH($D60&"-"&I$2,INDEX(DB!$Y$3:$Y$65423&"-"&DB!$Z$3:$Z$65423,),0)),0) -> 0
A61: LP | B61: 原/売 | D61: 9803 | F61: =SUMIF(I$3:N$3,$F$3,I61:N61) -> 0 | G61: =IF(ISERROR(F61/H61),0,F61/H61) -> 0 | H61: =SUMIF(I$3:N$3,$H$3,I61:N61) -> 0 | I61: =SUMIF($D62:$D67,$D61,I62:I67) -> 0 | J61: =IF(ISERROR(I61/K61),0,I61/K61) -> 0 | K61: =SUM(K62:K67) -> 0
B62: 営業 | C62: 0 | D62: 9803 | E62: 0 | F62: =SUMIF(I$3:N$3,$F$3,I62:N62) -> 0 | G62: =IF(ISERROR(F62/H62),0,F62/H62) -> 0 | H62: =SUMIF(I$3:N$3,$H$3,I62:N62) -> 0 | I62: =IFERROR(INDEX(DB!$G$3:$G$65423,MATCH($C62&"-"&$D62&"-"&I$2&"-"&$E62,INDEX(DB!$A$3:$A$65423&"-"&DB!$C$3:$C$65423&"-"&DB!$D$3:$D$65423&"-"&DB!$E$3:$E$65423,),0)),0) -> 0 | J62: =IF(ISERROR(I62/K62),0,I62/K62) -> 0 | K62: =IFERROR(INDEX(DB!$F$3:$F$65423,MATCH($C62&"-"&$D62&"-"&I$2&"-"&$E62,INDEX(DB!$A$3:$A$65423&"-"&DB!$C$3:$C$65423&"-"&DB!$D$3:$D$65423&"-"&DB!$E$3:$E$65423,),0)),0) -> 0
B63: 工事 | C63: 0 | D63: 9803 | E63: 1 | F63: =SUMIF(I$3:N$3,$F$3,I63:N63) -> 0 | G63: =IF(ISERROR(F63/H63),0,F63/H63) -> 0 | H63: =SUMIF(I$3:N$3,$H$3,I63:N63) -> 0 | I63: =IFERROR(INDEX(DB!$G$3:$G$65423,MATCH($C63&"-"&$D63&"-"&I$2&"-"&$E63,INDEX(DB!$A$3:$A$65423&"-"&DB!$C$3:$C$65423&"-"&DB!$D$3:$D$65423&"-"&DB!$E$3:$E$65423,),0)),0) -> 0 | J63: =IF(ISERROR(I63/K63),0,I63/K63) -> 0 | K63: =IFERROR(INDEX(DB!$F$3:$F$65423,MATCH($C63&"-"&$D63&"-"&I$2&"-"&$E63,INDEX(DB!$A$3:$A$65423&"-"&DB!$C$3:$C$65423&"-"&DB!$D$3:$D$65423&"-"&DB!$E$3:$E$65423,),0)),0) -> 0
B64: コール | C64: 0 | D64: 9803 | E64: 2 | F64: =SUMIF(I$3:N$3,$F$3,I64:N64) -> 0 | G64: =IF(ISERROR(F64/H64),0,F64/H64) -> 0 | H64: =SUMIF(I$3:N$3,$H$3,I64:N64) -> 0 | I64: =IFERROR(INDEX(DB!$G$3:$G$65423,MATCH($C64&"-"&$D64&"-"&I$2&"-"&$E64,INDEX(DB!$A$3:$A$65423&"-"&DB!$C$3:$C$65423&"-"&DB!$D$3:$D$65423&"-"&DB!$E$3:$E$65423,),0)),0) -> 0 | J64: =IF(ISERROR(I64/K64),0,I64/K64) -> 0 | K64: =IFERROR(INDEX(DB!$F$3:$F$65423,MATCH($C64&"-"&$D64&"-"&I$2&"-"&$E64,INDEX(DB!$A$3:$A$65423&"-"&DB!$C$3:$C$65423&"-"&DB!$D$3:$D$65423&"-"&DB!$E$3:$E$65423,),0)),0) -> 0
B65: 店装 | C65: 0 | D65: 9803 | E65: 3 | F65: =SUMIF(I$3:N$3,$F$3,I65:N65) -> 0 | G65: =IF(ISERROR(F65/H65),0,F65/H65) -> 0 | H65: =SUMIF(I$3:N$3,$H$3,I65:N65) -> 0 | I65: =IFERROR(INDEX(DB!$G$3:$G$65423,MATCH($C65&"-"&$D65&"-"&I$2&"-"&$E65,INDEX(DB!$A$3:$A$65423&"-"&DB!$C$3:$C$65423&"-"&DB!$D$3:$D$65423&"-"&DB!$E$3:$E$65423,),0)),0) -> 0 | J65: =IF(ISERROR(I65/K65),0,I65/K65) -> 0 | K65: =IFERROR(INDEX(DB!$F$3:$F$65423,MATCH($C65&"-"&$D65&"-"&I$2&"-"&$E65,INDEX(DB!$A$3:$A$65423&"-"&DB!$C$3:$C$65423&"-"&DB!$D$3:$D$65423&"-"&DB!$E$3:$E$65423,),0)),0) -> 0
B66: 委託 | C66: 0 | D66: 9803 | E66: 106 | F66: =SUMIF(I$3:N$3,$F$3,I66:N66) -> 0 | G66: =IF(ISERROR(F66/H66),0,F66/H66) -> 0 | H66: =SUMIF(I$3:N$3,$H$3,I66:N66) -> 0 | I66: =IFERROR(INDEX(DB!$G$3:$G$65423,MATCH($C66&"-"&$D66&"-"&I$2&"-"&$E66,INDEX(DB!$A$3:$A$65423&"-"&DB!$C$3:$C$65423&"-"&DB!$D$3:$D$65423&"-"&DB!$E$3:$E$65423,),0)),0) -> 0 | J66: =IF(ISERROR(I66/K66),0,I66/K66) -> 0 | K66: =IFERROR(INDEX(DB!$F$3:$F$65423,MATCH($C66&"-"&$D66&"-"&I$2&"-"&$E66,INDEX(DB!$A$3:$A$65423&"-"&DB!$C$3:$C$65423&"-"&DB!$D$3:$D$65423&"-"&DB!$E$3:$E$65423,),0)),0) -> 0
B67: クレーム | C67: 0 | D67: 9803 | E67: 4 | F67: =SUMIF(I$3:N$3,$F$3,I67:N67) -> 0 | G67: =IF(ISERROR(F67/H67),0,F67/H67) -> 0 | H67: =SUMIF(I$3:N$3,$H$3,I67:N67) -> 0 | I67: =IFERROR(INDEX(DB!$G$3:$G$65423,MATCH($C67&"-"&$D67&"-"&I$2&"-"&$E67,INDEX(DB!$A$3:$A$65423&"-"&DB!$C$3:$C$65423&"-"&DB!$D$3:$D$65423&"-"&DB!$E$3:$E$65423,),0)),0) -> 0 | J67: =IF(ISERROR(I67/K67),0,I67/K67) -> 0 | K67: =IFERROR(INDEX(DB!$F$3:$F$65423,MATCH($C67&"-"&$D67&"-"&I$2&"-"&$E67,INDEX(DB!$A$3:$A$65423&"-"&DB!$C$3:$C$65423&"-"&DB!$D$3:$D$65423&"-"&DB!$E$3:$E$65423,),0)),0) -> 0
B68: 在庫 | D68: 9803 | E68: 20 | F68: =SUMIF(I$3:N$3,$F$3,I68:N68) -> 0 | G68: ⇔ | H68: =SUMIF(I$3:N$3,$H$3,I68:N68) -> 0 | I68: =IFERROR(INDEX(DB!$AB$3:$AB$65423,MATCH($D68&"-"&I$2,INDEX(DB!$Y$3:$Y$65423&"-"&DB!$Z$3:$Z$65423,),0)),0) -> 0 | J68: ⇔ | K68: =IFERROR(INDEX(DB!$AA$3:$AA$65423,MATCH($D68&"-"&I$2,INDEX(DB!$Y$3:$Y$65423&"-"&DB!$Z$3:$Z$65423,),0)),0) -> 0
A69: AL | B69: 原/売 | D69: 4801 | F69: =SUMIF(I$3:N$3,$F$3,I69:N69) -> 0 | G69: =IF(ISERROR(F69/H69),0,F69/H69) -> 0 | H69: =SUMIF(I$3:N$3,$H$3,I69:N69) -> 0 | I69: =SUMIF($D70:$D75,$D69,I70:I75) -> 0 | J69: =IF(ISERROR(I69/K69),0,I69/K69) -> 0 | K69: =SUM(K70:K75) -> 0
B70: 営業 | C70: 0 | D70: 4801 | E70: 0 | F70: =SUMIF(I$3:N$3,$F$3,I70:N70) -> 0 | G70: =IF(ISERROR(F70/H70),0,F70/H70) -> 0 | H70: =SUMIF(I$3:N$3,$H$3,I70:N70) -> 0 | I70: =IFERROR(INDEX(DB!$G$3:$G$65423,MATCH($C70&"-"&$D70&"-"&I$2&"-"&$E70,INDEX(DB!$A$3:$A$65423&"-"&DB!$C$3:$C$65423&"-"&DB!$D$3:$D$65423&"-"&DB!$E$3:$E$65423,),0)),0) -> 0 | J70: =IF(ISERROR(I70/K70),0,I70/K70) -> 0 | K70: =IFERROR(INDEX(DB!$F$3:$F$65423,MATCH($C70&"-"&$D70&"-"&I$2&"-"&$E70,INDEX(DB!$A$3:$A$65423&"-"&DB!$C$3:$C$65423&"-"&DB!$D$3:$D$65423&"-"&DB!$E$3:$E$65423,),0)),0) -> 0
B71: 工事 | C71: 0 | D71: 4801 | E71: 1 | F71: =SUMIF(I$3:N$3,$F$3,I71:N71) -> 0 | G71: =IF(ISERROR(F71/H71),0,F71/H71) -> 0 | H71: =SUMIF(I$3:N$3,$H$3,I71:N71) -> 0 | I71: =IFERROR(INDEX(DB!$G$3:$G$65423,MATCH($C71&"-"&$D71&"-"&I$2&"-"&$E71,INDEX(DB!$A$3:$A$65423&"-"&DB!$C$3:$C$65423&"-"&DB!$D$3:$D$65423&"-"&DB!$E$3:$E$65423,),0)),0) -> 0 | J71: =IF(ISERROR(I71/K71),0,I71/K71) -> 0 | K71: =IFERROR(INDEX(DB!$F$3:$F$65423,MATCH($C71&"-"&$D71&"-"&I$2&"-"&$E71,INDEX(DB!$A$3:$A$65423&"-"&DB!$C$3:$C$65423&"-"&DB!$D$3:$D$65423&"-"&DB!$E$3:$E$65423,),0)),0) -> 0
B72: コール | C72: 0 | D72: 4801 | E72: 2 | F72: =SUMIF(I$3:N$3,$F$3,I72:N72) -> 0 | G72: =IF(ISERROR(F72/H72),0,F72/H72) -> 0 | H72: =SUMIF(I$3:N$3,$H$3,I72:N72) -> 0 | I72: =IFERROR(INDEX(DB!$G$3:$G$65423,MATCH($C72&"-"&$D72&"-"&I$2&"-"&$E72,INDEX(DB!$A$3:$A$65423&"-"&DB!$C$3:$C$65423&"-"&DB!$D$3:$D$65423&"-"&DB!$E$3:$E$65423,),0)),0) -> 0 | J72: =IF(ISERROR(I72/K72),0,I72/K72) -> 0 | K72: =IFERROR(INDEX(DB!$F$3:$F$65423,MATCH($C72&"-"&$D72&"-"&I$2&"-"&$E72,INDEX(DB!$A$3:$A$65423&"-"&DB!$C$3:$C$65423&"-"&DB!$D$3:$D$65423&"-"&DB!$E$3:$E$65423,),0)),0) -> 0
B73: 店装 | C73: 0 | D73: 4801 | E73: 3 | F73: =SUMIF(I$3:N$3,$F$3,I73:N73) -> 0 | G73: =IF(ISERROR(F73/H73),0,F73/H73) -> 0 | H73: =SUMIF(I$3:N$3,$H$3,I73:N73) -> 0 | I73: =IFERROR(INDEX(DB!$G$3:$G$65423,MATCH($C73&"-"&$D73&"-"&I$2&"-"&$E73,INDEX(DB!$A$3:$A$65423&"-"&DB!$C$3:$C$65423&"-"&DB!$D$3:$D$65423&"-"&DB!$E$3:$E$65423,),0)),0) -> 0 | J73: =IF(ISERROR(I73/K73),0,I73/K73) -> 0 | K73: =IFERROR(INDEX(DB!$F$3:$F$65423,MATCH($C73&"-"&$D73&"-"&I$2&"-"&$E73,INDEX(DB!$A$3:$A$65423&"-"&DB!$C$3:$C$65423&"-"&DB!$D$3:$D$65423&"-"&DB!$E$3:$E$65423,),0)),0) -> 0
B74: 委託 | C74: 0 | D74: 4801 | E74: 106 | F74: =SUMIF(I$3:N$3,$F$3,I74:N74) -> 0 | G74: =IF(ISERROR(F74/H74),0,F74/H74) -> 0 | H74: =SUMIF(I$3:N$3,$H$3,I74:N74) -> 0 | I74: =IFERROR(INDEX(DB!$G$3:$G$65423,MATCH($C74&"-"&$D74&"-"&I$2&"-"&$E74,INDEX(DB!$A$3:$A$65423&"-"&DB!$C$3:$C$65423&"-"&DB!$D$3:$D$65423&"-"&DB!$E$3:$E$65423,),0)),0) -> 0 | J74: =IF(ISERROR(I74/K74),0,I74/K74) -> 0 | K74: =IFERROR(INDEX(DB!$F$3:$F$65423,MATCH($C74&"-"&$D74&"-"&I$2&"-"&$E74,INDEX(DB!$A$3:$A$65423&"-"&DB!$C$3:$C$65423&"-"&DB!$D$3:$D$65423&"-"&DB!$E$3:$E$65423,),0)),0) -> 0
B75: クレーム | C75: 0 | D75: 4801 | E75: 4 | F75: =SUMIF(I$3:N$3,$F$3,I75:N75) -> 0 | G75: =IF(ISERROR(F75/H75),0,F75/H75) -> 0 | H75: =SUMIF(I$3:N$3,$H$3,I75:N75) -> 0 | I75: =IFERROR(INDEX(DB!$G$3:$G$65423,MATCH($C75&"-"&$D75&"-"&I$2&"-"&$E75,INDEX(DB!$A$3:$A$65423&"-"&DB!$C$3:$C$65423&"-"&DB!$D$3:$D$65423&"-"&DB!$E$3:$E$65423,),0)),0) -> 0 | J75: =IF(ISERROR(I75/K75),0,I75/K75) -> 0 | K75: =IFERROR(INDEX(DB!$F$3:$F$65423,MATCH($C75&"-"&$D75&"-"&I$2&"-"&$E75,INDEX(DB!$A$3:$A$65423&"-"&DB!$C$3:$C$65423&"-"&DB!$D$3:$D$65423&"-"&DB!$E$3:$E$65423,),0)),0) -> 0
B76: 在庫 | D76: 4801 | E76: 20 | F76: =SUMIF(I$3:N$3,$F$3,I76:N76) -> 0 | G76: ⇔ | H76: =SUMIF(I$3:N$3,$H$3,I76:N76) -> 0 | I76: =IFERROR(INDEX(DB!$AB$3:$AB$65423,MATCH($D76&"-"&I$2,INDEX(DB!$Y$3:$Y$65423&"-"&DB!$Z$3:$Z$65423,),0)),0) -> 0 | J76: ⇔ | K76: =IFERROR(INDEX(DB!$AA$3:$AA$65423,MATCH($D76&"-"&I$2,INDEX(DB!$Y$3:$Y$65423&"-"&DB!$Z$3:$Z$65423,),0)),0) -> 0
A77: Y | B77: 原/売 | D77: 8001 | F77: =SUMIF(I$3:N$3,$F$3,I77:N77) -> 0 | G77: =IF(ISERROR(F77/H77),0,F77/H77) -> 0 | H77: =SUMIF(I$3:N$3,$H$3,I77:N77) -> 0 | I77: =SUMIF($D78:$D83,$D77,I78:I83) -> 0 | J77: =IF(ISERROR(I77/K77),0,I77/K77) -> 0 | K77: =SUM(K78:K83) -> 0
B78: 営業 | C78: 0 | D78: 8001 | E78: 0 | F78: =SUMIF(I$3:N$3,$F$3,I78:N78) -> 0 | G78: =IF(ISERROR(F78/H78),0,F78/H78) -> 0 | H78: =SUMIF(I$3:N$3,$H$3,I78:N78) -> 0 | I78: =IFERROR(INDEX(DB!$G$3:$G$65423,MATCH($C78&"-"&$D78&"-"&I$2&"-"&$E78,INDEX(DB!$A$3:$A$65423&"-"&DB!$C$3:$C$65423&"-"&DB!$D$3:$D$65423&"-"&DB!$E$3:$E$65423,),0)),0) -> 0 | J78: =IF(ISERROR(I78/K78),0,I78/K78) -> 0 | K78: =IFERROR(INDEX(DB!$F$3:$F$65423,MATCH($C78&"-"&$D78&"-"&I$2&"-"&$E78,INDEX(DB!$A$3:$A$65423&"-"&DB!$C$3:$C$65423&"-"&DB!$D$3:$D$65423&"-"&DB!$E$3:$E$65423,),0)),0) -> 0
B79: 工事 | C79: 0 | D79: 8001 | E79: 1 | F79: =SUMIF(I$3:N$3,$F$3,I79:N79) -> 0 | G79: =IF(ISERROR(F79/H79),0,F79/H79) -> 0 | H79: =SUMIF(I$3:N$3,$H$3,I79:N79) -> 0 | I79: =IFERROR(INDEX(DB!$G$3:$G$65423,MATCH($C79&"-"&$D79&"-"&I$2&"-"&$E79,INDEX(DB!$A$3:$A$65423&"-"&DB!$C$3:$C$65423&"-"&DB!$D$3:$D$65423&"-"&DB!$E$3:$E$65423,),0)),0) -> 0 | J79: =IF(ISERROR(I79/K79),0,I79/K79) -> 0 | K79: =IFERROR(INDEX(DB!$F$3:$F$65423,MATCH($C79&"-"&$D79&"-"&I$2&"-"&$E79,INDEX(DB!$A$3:$A$65423&"-"&DB!$C$3:$C$65423&"-"&DB!$D$3:$D$65423&"-"&DB!$E$3:$E$65423,),0)),0) -> 0
B80: コール | C80: 0 | D80: 8001 | E80: 2 | F80: =SUMIF(I$3:N$3,$F$3,I80:N80) -> 0 | G80: =IF(ISERROR(F80/H80),0,F80/H80) -> 0 | H80: =SUMIF(I$3:N$3,$H$3,I80:N80) -> 0 | I80: =IFERROR(INDEX(DB!$G$3:$G$65423,MATCH($C80&"-"&$D80&"-"&I$2&"-"&$E80,INDEX(DB!$A$3:$A$65423&"-"&DB!$C$3:$C$65423&"-"&DB!$D$3:$D$65423&"-"&DB!$E$3:$E$65423,),0)),0) -> 0 | J80: =IF(ISERROR(I80/K80),0,I80/K80) -> 0 | K80: =IFERROR(INDEX(DB!$F$3:$F$65423,MATCH($C80&"-"&$D80&"-"&I$2&"-"&$E80,INDEX(DB!$A$3:$A$65423&"-"&DB!$C$3:$C$65423&"-"&DB!$D$3:$D$65423&"-"&DB!$E$3:$E$65423,),0)),0) -> 0
B81: 店装 | C81: 0 | D81: 8001 | E81: 3 | F81: =SUMIF(I$3:N$3,$F$3,I81:N81) -> 0 | G81: =IF(ISERROR(F81/H81),0,F81/H81) -> 0 | H81: =SUMIF(I$3:N$3,$H$3,I81:N81) -> 0 | I81: =IFERROR(INDEX(DB!$G$3:$G$65423,MATCH($C81&"-"&$D81&"-"&I$2&"-"&$E81,INDEX(DB!$A$3:$A$65423&"-"&DB!$C$3:$C$65423&"-"&DB!$D$3:$D$65423&"-"&DB!$E$3:$E$65423,),0)),0) -> 0 | J81: =IF(ISERROR(I81/K81),0,I81/K81) -> 0 | K81: =IFERROR(INDEX(DB!$F$3:$F$65423,MATCH($C81&"-"&$D81&"-"&I$2&"-"&$E81,INDEX(DB!$A$3:$A$65423&"-"&DB!$C$3:$C$65423&"-"&DB!$D$3:$D$65423&"-"&DB!$E$3:$E$65423,),0)),0) -> 0
B82: 委託 | C82: 0 | D82: 8001 | E82: 106 | F82: =SUMIF(I$3:N$3,$F$3,I82:N82) -> 0 | G82: =IF(ISERROR(F82/H82),0,F82/H82) -> 0 | H82: =SUMIF(I$3:N$3,$H$3,I82:N82) -> 0 | I82: =IFERROR(INDEX(DB!$G$3:$G$65423,MATCH($C82&"-"&$D82&"-"&I$2&"-"&$E82,INDEX(DB!$A$3:$A$65423&"-"&DB!$C$3:$C$65423&"-"&DB!$D$3:$D$65423&"-"&DB!$E$3:$E$65423,),0)),0) -> 0 | J82: =IF(ISERROR(I82/K82),0,I82/K82) -> 0 | K82: =IFERROR(INDEX(DB!$F$3:$F$65423,MATCH($C82&"-"&$D82&"-"&I$2&"-"&$E82,INDEX(DB!$A$3:$A$65423&"-"&DB!$C$3:$C$65423&"-"&DB!$D$3:$D$65423&"-"&DB!$E$3:$E$65423,),0)),0) -> 0
B83: クレーム | C83: 0 | D83: 8001 | E83: 4 | F83: =SUMIF(I$3:N$3,$F$3,I83:N83) -> 0 | G83: =IF(ISERROR(F83/H83),0,F83/H83) -> 0 | H83: =SUMIF(I$3:N$3,$H$3,I83:N83) -> 0 | I83: =IFERROR(INDEX(DB!$G$3:$G$65423,MATCH($C83&"-"&$D83&"-"&I$2&"-"&$E83,INDEX(DB!$A$3:$A$65423&"-"&DB!$C$3:$C$65423&"-"&DB!$D$3:$D$65423&"-"&DB!$E$3:$E$65423,),0)),0) -> 0 | J83: =IF(ISERROR(I83/K83),0,I83/K83) -> 0 | K83: =IFERROR(INDEX(DB!$F$3:$F$65423,MATCH($C83&"-"&$D83&"-"&I$2&"-"&$E83,INDEX(DB!$A$3:$A$65423&"-"&DB!$C$3:$C$65423&"-"&DB!$D$3:$D$65423&"-"&DB!$E$3:$E$65423,),0)),0) -> 0
B84: 在庫 | D84: 8001 | E84: 20 | F84: =SUMIF(I$3:N$3,$F$3,I84:N84) -> 0 | G84: ⇔ | H84: =SUMIF(I$3:N$3,$H$3,I84:N84) -> 0 | I84: =IFERROR(INDEX(DB!$AB$3:$AB$65423,MATCH($D84&"-"&I$2,INDEX(DB!$Y$3:$Y$65423&"-"&DB!$Z$3:$Z$65423,),0)),0) -> 0 | J84: ⇔ | K84: =IFERROR(INDEX(DB!$AA$3:$AA$65423,MATCH($D84&"-"&I$2,INDEX(DB!$Y$3:$Y$65423&"-"&DB!$Z$3:$Z$65423,),0)),0) -> 0
A85: その他 | B85: 原/売 | D85: 99999 | F85: =SUMIF(I$3:N$3,$F$3,I85:N85) -> 0 | G85: =IF(ISERROR(F85/H85),0,F85/H85) -> 0 | H85: =SUMIF(I$3:N$3,$H$3,I85:N85) -> 0 | I85: =SUMIF($D86:$D91,$D85,I86:I91) -> 0 | J85: =IF(ISERROR(I85/K85),0,I85/K85) -> 0 | K85: =SUM(K86:K91) -> 0
B86: 営業 | C86: 0 | D86: 99999 | E86: 0 | F86: =SUMIF(I$3:N$3,$F$3,I86:N86) -> 0 | G86: =IF(ISERROR(F86/H86),0,F86/H86) -> 0 | H86: =SUMIF(I$3:N$3,$H$3,I86:N86) -> 0 | I86: =IFERROR(INDEX(DB!$G$3:$G$65423,MATCH($C86&"-"&$D86&"-"&I$2&"-"&$E86,INDEX(DB!$A$3:$A$65423&"-"&DB!$C$3:$C$65423&"-"&DB!$D$3:$D$65423&"-"&DB!$E$3:$E$65423,),0)),0) -> 0 | J86: =IF(ISERROR(I86/K86),0,I86/K86) -> 0 | K86: =IFERROR(INDEX(DB!$F$3:$F$65423,MATCH($C86&"-"&$D86&"-"&I$2&"-"&$E86,INDEX(DB!$A$3:$A$65423&"-"&DB!$C$3:$C$65423&"-"&DB!$D$3:$D$65423&"-"&DB!$E$3:$E$65423,),0)),0) -> 0
B87: 工事 | C87: 0 | D87: 99999 | E87: 1 | F87: =SUMIF(I$3:N$3,$F$3,I87:N87) -> 0 | G87: =IF(ISERROR(F87/H87),0,F87/H87) -> 0 | H87: =SUMIF(I$3:N$3,$H$3,I87:N87) -> 0 | I87: =IFERROR(INDEX(DB!$G$3:$G$65423,MATCH($C87&"-"&$D87&"-"&I$2&"-"&$E87,INDEX(DB!$A$3:$A$65423&"-"&DB!$C$3:$C$65423&"-"&DB!$D$3:$D$65423&"-"&DB!$E$3:$E$65423,),0)),0) -> 0 | J87: =IF(ISERROR(I87/K87),0,I87/K87) -> 0 | K87: =IFERROR(INDEX(DB!$F$3:$F$65423,MATCH($C87&"-"&$D87&"-"&I$2&"-"&$E87,INDEX(DB!$A$3:$A$65423&"-"&DB!$C$3:$C$65423&"-"&DB!$D$3:$D$65423&"-"&DB!$E$3:$E$65423,),0)),0) -> 0
B88: コール | C88: 0 | D88: 99999 | E88: 2 | F88: =SUMIF(I$3:N$3,$F$3,I88:N88) -> 0 | G88: =IF(ISERROR(F88/H88),0,F88/H88) -> 0 | H88: =SUMIF(I$3:N$3,$H$3,I88:N88) -> 0 | I88: =IFERROR(INDEX(DB!$G$3:$G$65423,MATCH($C88&"-"&$D88&"-"&I$2&"-"&$E88,INDEX(DB!$A$3:$A$65423&"-"&DB!$C$3:$C$65423&"-"&DB!$D$3:$D$65423&"-"&DB!$E$3:$E$65423,),0)),0) -> 0 | J88: =IF(ISERROR(I88/K88),0,I88/K88) -> 0 | K88: =IFERROR(INDEX(DB!$F$3:$F$65423,MATCH($C88&"-"&$D88&"-"&I$2&"-"&$E88,INDEX(DB!$A$3:$A$65423&"-"&DB!$C$3:$C$65423&"-"&DB!$D$3:$D$65423&"-"&DB!$E$3:$E$65423,),0)),0) -> 0
B89: 店装 | C89: 0 | D89: 99999 | E89: 3 | F89: =SUMIF(I$3:N$3,$F$3,I89:N89) -> 0 | G89: =IF(ISERROR(F89/H89),0,F89/H89) -> 0 | H89: =SUMIF(I$3:N$3,$H$3,I89:N89) -> 0 | I89: =IFERROR(INDEX(DB!$G$3:$G$65423,MATCH($C89&"-"&$D89&"-"&I$2&"-"&$E89,INDEX(DB!$A$3:$A$65423&"-"&DB!$C$3:$C$65423&"-"&DB!$D$3:$D$65423&"-"&DB!$E$3:$E$65423,),0)),0) -> 0 | J89: =IF(ISERROR(I89/K89),0,I89/K89) -> 0 | K89: =IFERROR(INDEX(DB!$F$3:$F$65423,MATCH($C89&"-"&$D89&"-"&I$2&"-"&$E89,INDEX(DB!$A$3:$A$65423&"-"&DB!$C$3:$C$65423&"-"&DB!$D$3:$D$65423&"-"&DB!$E$3:$E$65423,),0)),0) -> 0
B90: 委託 | C90: 0 | D90: 99999 | E90: 106 | F90: =SUMIF(I$3:N$3,$F$3,I90:N90) -> 0 | G90: =IF(ISERROR(F90/H90),0,F90/H90) -> 0 | H90: =SUMIF(I$3:N$3,$H$3,I90:N90) -> 0 | I90: =IFERROR(INDEX(DB!$G$3:$G$65423,MATCH($C90&"-"&$D90&"-"&I$2&"-"&$E90,INDEX(DB!$A$3:$A$65423&"-"&DB!$C$3:$C$65423&"-"&DB!$D$3:$D$65423&"-"&DB!$E$3:$E$65423,),0)),0) -> 0 | J90: =IF(ISERROR(I90/K90),0,I90/K90) -> 0 | K90: =IFERROR(INDEX(DB!$F$3:$F$65423,MATCH($C90&"-"&$D90&"-"&I$2&"-"&$E90,INDEX(DB!$A$3:$A$65423&"-"&DB!$C$3:$C$65423&"-"&DB!$D$3:$D$65423&"-"&DB!$E$3:$E$65423,),0)),0) -> 0
B91: クレーム | C91: 0 | D91: 99999 | E91: 4 | F91: =SUMIF(I$3:N$3,$F$3,I91:N91) -> 0 | G91: =IF(ISERROR(F91/H91),0,F91/H91) -> 0 | H91: =SUMIF(I$3:N$3,$H$3,I91:N91) -> 0 | I91: =IFERROR(INDEX(DB!$G$3:$G$65423,MATCH($C91&"-"&$D91&"-"&I$2&"-"&$E91,INDEX(DB!$A$3:$A$65423&"-"&DB!$C$3:$C$65423&"-"&DB!$D$3:$D$65423&"-"&DB!$E$3:$E$65423,),0)),0) -> 0 | J91: =IF(ISERROR(I91/K91),0,I91/K91) -> 0 | K91: =IFERROR(INDEX(DB!$F$3:$F$65423,MATCH($C91&"-"&$D91&"-"&I$2&"-"&$E91,INDEX(DB!$A$3:$A$65423&"-"&DB!$C$3:$C$65423&"-"&DB!$D$3:$D$65423&"-"&DB!$E$3:$E$65423,),0)),0) -> 0
B92: 在庫 | D92: 0 | E92: 20 | F92: =SUMIF(I$3:N$3,$F$3,I92:N92) -> 0 | G92: ⇔ | H92: =SUMIF(I$3:N$3,$H$3,I92:N92) -> 0 | I92: =IFERROR(INDEX(DB!$AB$3:$AB$65423,MATCH($D92&"-"&I$2,INDEX(DB!$Y$3:$Y$65423&"-"&DB!$Z$3:$Z$65423,),0)),0) -> 0 | J92: ⇔ | K92: =IFERROR(INDEX(DB!$AA$3:$AA$65423,MATCH($D92&"-"&I$2,INDEX(DB!$Y$3:$Y$65423&"-"&DB!$Z$3:$Z$65423,),0)),0) -> 0
A93: EC | B93: 原/売 | C93: 0 | D93: 9 | F93: =SUMIF(I$3:N$3,$F$3,I93:N93) -> 0 | G93: =IF(ISERROR(F93/H93),0,F93/H93) -> 0 | H93: =SUMIF(I$3:N$3,$H$3,I93:N93) -> 0 | I93: =SUMIF($D94:$D99,$D93,I94:I99) -> 0 | J93: =IF(ISERROR(I93/K93),0,I93/K93) -> 0 | K93: =SUM(K94:K99) -> 0
B94: 営業 | D94: 9 | E94: 0 | F94: =SUMIF(I$3:N$3,$F$3,I94:N94) -> 0 | G94: =IF(ISERROR(F94/H94),0,F94/H94) -> 0 | H94: =SUMIF(I$3:N$3,$H$3,I94:N94) -> 0 | I94: =SUMIF($B$102:$B$116,$B94,I$102:I$116) -> 0 | J94: =IF(ISERROR(I94/K94),0,I94/K94) -> 0 | K94: =SUMIF($B$102:$B$116,$B94,K$102:K$116) -> 0
B95: 工事 | D95: 9 | E95: 1 | F95: =SUMIF(I$3:N$3,$F$3,I95:N95) -> 0 | G95: =IF(ISERROR(F95/H95),0,F95/H95) -> 0 | H95: =SUMIF(I$3:N$3,$H$3,I95:N95) -> 0 | I95: =SUMIF($B$102:$B$116,$B95,I$102:I$116) -> 0 | J95: =IF(ISERROR(I95/K95),0,I95/K95) -> 0 | K95: =SUMIF($B$102:$B$116,$B95,K$102:K$116) -> 0
B96: コール | D96: 9 | E96: 2 | F96: =SUMIF(I$3:N$3,$F$3,I96:N96) -> 0 | G96: =IF(ISERROR(F96/H96),0,F96/H96) -> 0 | H96: =SUMIF(I$3:N$3,$H$3,I96:N96) -> 0 | I96: =SUMIF($B$102:$B$116,$B96,I$102:I$116) -> 0 | J96: =IF(ISERROR(I96/K96),0,I96/K96) -> 0 | K96: =SUMIF($B$102:$B$116,$B96,K$102:K$116) -> 0
B97: 店装 | D97: 9 | E97: 3 | F97: =SUMIF(I$3:N$3,$F$3,I97:N97) -> 0 | G97: =IF(ISERROR(F97/H97),0,F97/H97) -> 0 | H97: =SUMIF(I$3:N$3,$H$3,I97:N97) -> 0 | I97: =SUMIF($B$102:$B$116,$B97,I$102:I$116) -> 0 | J97: =IF(ISERROR(I97/K97),0,I97/K97) -> 0 | K97: =SUMIF($B$102:$B$116,$B97,K$102:K$116) -> 0
B98: 委託 | D98: 9 | E98: 106 | F98: =SUMIF(I$3:N$3,$F$3,I98:N98) -> 0 | G98: =IF(ISERROR(F98/H98),0,F98/H98) -> 0 | H98: =SUMIF(I$3:N$3,$H$3,I98:N98) -> 0 | I98: =SUMIF($B$102:$B$116,$B98,I$102:I$116) -> 0 | J98: =IF(ISERROR(I98/K98),0,I98/K98) -> 0 | K98: =SUMIF($B$102:$B$116,$B98,K$102:K$116) -> 0
B99: クレーム | D99: 9 | E99: 4 | F99: =SUMIF(I$3:N$3,$F$3,I99:N99) -> 0 | G99: =IF(ISERROR(F99/H99),0,F99/H99) -> 0 | H99: =SUMIF(I$3:N$3,$H$3,I99:N99) -> 0 | I99: =SUMIF($B$102:$B$116,$B99,I$102:I$116) -> 0 | J99: =IF(ISERROR(I99/K99),0,I99/K99) -> 0 | K99: =SUMIF($B$102:$B$116,$B99,K$102:K$116) -> 0
B100: 在庫 | E100: 20 | F100: =SUMIF(I$3:N$3,$F$3,I100:N100) -> 0 | G100: ⇔ | H100: =SUMIF(I$3:N$3,$H$3,I100:N100) -> 0 | I100: =SUMIF($B$102:$B$116,$B100,I$102:I$116) -> 0 | J100: ⇔ | K100: =SUMIF($B$102:$B$116,$B100,K$102:K$116) -> 0
...
