Workbook

Sheet 変更履歴
B2: システム名 | H2: 画面ID | L2: 業務分類 | R2: ドキュメント種別 | X2: ドキュメント名 | AK2: 帳票名 | AX2: 作成日 | BB2: 作成者 | BF2: 更新日 | BJ2: 更新者
B3: 受発注システム | H3: =LEFT($X$3,FIND("_",$X$3)-1) -> KH0500 | L3: 受発注 | R3: =MID($X$3,FIND("_",$X$3,FIND("_",$X$3)+1)+1,LEN($X$3)-FIND("_",$X$3,FIND("_",$X$3)+1)) -> インポート_帳票設計書 | X3: =REPLACE(LEFT(CELL("filename",$B$2),FIND(".x",CELL("filename",$B$2))-1),1,FIND("[",CELL("filename",$B$2)),) -> KH0500_EXCEL仕訳TXT_インポート_帳票設計書 | AK3: =MID($X$3,FIND("_",$X$3)+1,FIND("_",$X$3,FIND("_",$X$3)+1)-FIND("_",$X$3)-1) -> EXCEL仕訳TXT | AX3: 45539 | BB3: 大谷 | BF3: 45539 | BJ3: 大谷
C7: 変更履歴
C8: 日付 | G8: 版数 | K8: 担当 | O8: 変更箇所 | Y8: 内容
C9: 45539 | G9: 1.0.0 | K9: 大谷 | O9: - | Y9: 新規作成

Sheet 概要
B2: システム名 | H2: 画面ID | L2: 業務分類 | R2: ドキュメント種別 | X2: ドキュメント名 | AK2: 帳票名 | AX2: 作成日 | BB2: 作成者 | BF2: 更新日 | BJ2: 更新者
B3: =変更履歴!B3 -> 受発注システム | H3: =変更履歴!H3 -> KH0500 | L3: =変更履歴!L3 -> 受発注 | R3: =変更履歴!R3 -> インポート_帳票設計書 | X3: =変更履歴!X3 -> KH0500_EXCEL仕訳TXT_インポート_帳票設計書 | AK3: =変更履歴!AK3 -> EXCEL仕訳TXT | AX3: =変更履歴!AX3 -> 45539 | BB3: =変更履歴!BB3 -> 大谷 | BF3: =変更履歴!BF3 -> 45539 | BJ3: =変更履歴!BJ3 -> 大谷
D7: 帳票の名称 | H7: =AK3 -> EXCEL仕訳TXT
D8: 帳票テンプレート名 | H8: -
D9: ファイル種類 | H9: Excel
D10: ファイル拡張子 | H10: xlsx
D11: 文字コード | H11: -
D12: コーテーション | H12: -
D13: 固定長/可変長 | H13: -
D14: 区切り文字 | H14: -
D15: 用紙サイズ
D16: 概要 | H16: 振替伝票シートのみインポート対象とする

Sheet 帳票レイアウト_借方勘定科目
B2: システム名 | H2: 画面ID | L2: 業務分類 | R2: ドキュメント種別 | X2: ドキュメント名 | AK2: 帳票名 | AX2: 作成日 | BB2: 作成者 | BF2: 更新日 | BJ2: 更新者
B3: =変更履歴!B3 -> 受発注システム | H3: =変更履歴!H3 -> KH0500 | L3: =変更履歴!L3 -> 受発注 | R3: =変更履歴!R3 -> インポート_帳票設計書 | X3: =変更履歴!X3 -> KH0500_EXCEL仕訳TXT_インポート_帳票設計書 | AK3: =変更履歴!AK3 -> EXCEL仕訳TXT | AX3: =変更履歴!AX3 -> 45539 | BB3: =変更履歴!BB3 -> 大谷 | BF3: =変更履歴!BF3 -> 45539 | BJ3: =変更履歴!BJ3 -> 大谷
B6: ページ１

Sheet 帳票レイアウト_貸方勘定科目
B2: システム名 | H2: 画面ID | L2: 業務分類 | R2: ドキュメント種別 | X2: ドキュメント名 | AK2: 帳票名 | AX2: 作成日 | BB2: 作成者 | BF2: 更新日 | BJ2: 更新者
B3: =変更履歴!B3 -> 受発注システム | H3: =変更履歴!H3 -> KH0500 | L3: =変更履歴!L3 -> 受発注 | R3: =変更履歴!R3 -> インポート_帳票設計書 | X3: =変更履歴!X3 -> KH0500_EXCEL仕訳TXT_インポート_帳票設計書 | AK3: =変更履歴!AK3 -> EXCEL仕訳TXT | AX3: =変更履歴!AX3 -> 45539 | BB3: =変更履歴!BB3 -> 大谷 | BF3: =変更履歴!BF3 -> 45539 | BJ3: =変更履歴!BJ3 -> 大谷
B6: ページ１

Sheet 帳票レイアウト_振替伝票
B2: システム名 | H2: 画面ID | L2: 業務分類 | R2: ドキュメント種別 | X2: ドキュメント名 | AK2: 帳票名 | AX2: 作成日 | BB2: 作成者 | BF2: 更新日 | BJ2: 更新者
B3: =変更履歴!B3 -> 受発注システム | H3: =変更履歴!H3 -> KH0500 | L3: =変更履歴!L3 -> 受発注 | R3: =変更履歴!R3 -> インポート_帳票設計書 | X3: =変更履歴!X3 -> KH0500_EXCEL仕訳TXT_インポート_帳票設計書 | AK3: =変更履歴!AK3 -> EXCEL仕訳TXT | AX3: =変更履歴!AX3 -> 45539 | BB3: =変更履歴!BB3 -> 大谷 | BF3: =変更履歴!BF3 -> 45539 | BJ3: =変更履歴!BJ3 -> 大谷
B6: ページ１

Sheet 項目一覧
B2: システム名 | H2: 画面ID | L2: 業務分類 | R2: ドキュメント種別 | X2: ドキュメント名 | AK2: 帳票名 | AX2: 作成日 | BB2: 作成者 | BF2: 更新日 | BJ2: 更新者
B3: =[1]変更履歴!B3 -> XXXXXXXX | H3: =[1]変更履歴!H3 -> KH0300 | L3: =[1]変更履歴!L3 -> 運用自動化 | R3: =[1]変更履歴!R3 -> インポート_帳票設計書 | X3: =[1]変更履歴!X3 -> KH0300_経費データ仕訳TXT_インポート_帳票設計書 | AK3: =[1]変更履歴!AK3 -> 経費データ仕訳TXT | AX3: =[1]変更履歴!AX3 -> 0 | BB3: =[1]変更履歴!BB3 -> 0 | BF3: =[1]変更履歴!BF3 -> 0 | BJ3: =[1]変更履歴!BJ3 -> 0
B7: 項目一覧
C9: 項目 | F9: フォントや文字サイズ、セル条件などは「別紙_テンプレート」準拠
D10: No. | E10: 項目名 | M10: データ型 | P10: 全角/半角 | S10: 文字数/桁数 | V10: データ取得元 | AB10: データ更新場所 | AH10: データ整形方法 | AX10: 整形後フォーマット | BD10: 備考
D11: 1 | E11: 年 | M11: 数値 | P11: 半角 | V11: 振替伝票.年 | AB11: レコードセット.年 | AH11: trimする
D12: 2 | E12: 月 | M12: 数値 | P12: 半角 | V12: 振替伝票.月 | AB12: レコードセット.月 | AH12: trimする
D13: 3 | E13: 日 | M13: 数値 | P13: 半角 | V13: 振替伝票.日 | AB13: レコードセット.日 | AH13: trimする
D14: 4 | E14: 伝票番号 | M14: 数値 | P14: 半角 | V14: null | AB14: レコードセット.伝票番号
D15: 5 | E15: 借方金額 | M15: 数値 | P15: 半角 | V15: 振替伝票.借方金額 | AB15: レコードセット.借方金額 | AH15: trimする
D16: 6 | E16: 借方勘定科目CD | M16: 数値 | P16: 半角 | V16: 振替伝票.借方勘定科目CD | AB16: レコードセット.借方勘定科目CD | AH16: trimする
D17: 7 | E17: 借方勘定科目名 | M17: 文字列 | P17: 全角 | S17: 24 | V17: 振替伝票.借方勘定科目名 | AB17: レコードセット.借方勘定科目名 | AH17: trimする
D18: 8 | E18: 借方消費税CD | M18: 数値 | P18: 半角 | V18: 振替伝票.借方消費税CD | AB18: レコードセット.借方消費税CD | AH18: スペースのみならnullとする、それ以外の場合はtrimする
D19: 9 | E19: 借方消費税率 | M19: 数値 | P19: 半角 | V19: 振替伝票.借方消費税率 | AB19: レコードセット.借方消費税率 | AH19: スペースのみならnullとする、それ以外の場合はtrimする
D20: 10 | E20: 借方業種 | M20: 数値 | P20: 半角 | V20: null | AB20: レコードセット.借方業種
D21: 11 | E21: 借方補助科目CD | M21: 数値 | P21: 半角 | V21: 振替伝票.借方補助科目CD | AB21: レコードセット.借方補助科目CD | AH21: スペースのみならnullとする、それ以外の場合はtrimする
D22: 12 | E22: 借方補助科目名 | M22: 文字列 | P22: 全角 | S22: 24 | V22: 振替伝票.借方補助科目名 | AB22: レコードセット.借方補助科目名 | AH22: スペースのみならnullとする、それ以外の場合はtrimする
D23: 13 | E23: 借方部門CD | M23: 数値 | P23: 半角 | V23: null | AB23: レコードセット.借方部門CD
D24: 14 | E24: 借方部門名 | M24: 文字列 | P24: 全角 | S24: 30 | V24: null | AB24: レコードセット.借方部門名
D25: 15 | E25: 貸方勘定科目CD | M25: 数値 | P25: 半角 | V25: 振替伝票.貸方勘定科目CD | AB25: レコードセット.貸方勘定科目CD | AH25: trimする
D26: 16 | E26: 貸方勘定科目名 | M26: 文字列 | P26: 全角 | S26: 24 | V26: 振替伝票.貸方勘定科目名 | AB26: レコードセット.貸方勘定科目名 | AH26: trimする
D27: 17 | E27: 貸方消費税CD | M27: 数値 | P27: 半角 | V27: 振替伝票.貸方消費税CD | AB27: レコードセット.貸方消費税CD | AH27: スペースのみならnullとする、それ以外の場合はtrimする
D28: 18 | E28: 貸方消費税率 | M28: 数値 | P28: 半角 | V28: 振替伝票.貸方消費税率 | AB28: レコードセット.貸方消費税率 | AH28: スペースのみならnullとする、それ以外の場合はtrimする
D29: 19 | E29: 貸方業種 | M29: 数値 | P29: 半角 | V29: null | AB29: レコードセット.貸方業種
D30: 20 | E30: 貸方補助科目CD | M30: 数値 | P30: 半角 | V30: 振替伝票.貸方補助科目CD | AB30: レコードセット.貸方補助科目CD | AH30: スペースのみならnullとする、それ以外の場合はtrimする
D31: 21 | E31: 貸方補助科目名 | M31: 文字列 | P31: 全角 | S31: 24 | V31: 振替伝票.貸方補助科目名 | AB31: レコードセット.貸方補助科目名 | AH31: trimする
D32: 22 | E32: 貸方部門CD | M32: 数値 | P32: 半角 | V32: null | AB32: レコードセット.貸方部門CD
D33: 23 | E33: 貸方部門名 | M33: 文字列 | P33: 全角 | S33: 30 | V33: null | AB33: レコードセット.貸方部門名
D34: 24 | E34: 貸方金額 | M34: 数値 | P34: 半角 | V34: 振替伝票.貸方金額 | AB34: レコードセット.貸方金額 | AH34: trimする
D35: 25 | E35: 摘要 | M35: 文字列 | P35: 全角 | S35: 96 | V35: 振替伝票.摘要 | AB35: レコードセット.摘要 | AH35: trimする
D36: 26 | E36: 期日_年 | M36: 数値 | P36: 半角 | V36: null | AB36: レコードセット.期日_年
D37: 27 | E37: 期日_月 | M37: 数値 | P37: 半角 | V37: null | AB37: レコードセット.期日_月
D38: 28 | E38: 期日_日 | M38: 数値 | P38: 半角 | V38: null | AB38: レコードセット.期日_日
D39: 29 | E39: 手形番号 | M39: 数値 | P39: 半角 | V39: null | AB39: レコードセット.手形番号
D40: 30

Sheet 処理詳細
B2: システム名 | H2: 画面ID | L2: 業務分類 | R2: ドキュメント種別 | X2: ドキュメント名 | AK2: 帳票名 | AX2: 作成日 | BB2: 作成者 | BF2: 更新日 | BJ2: 更新者
B3: =変更履歴!B3 -> 受発注システム | H3: =変更履歴!H3 -> KH0500 | L3: =変更履歴!L3 -> 受発注 | R3: =変更履歴!R3 -> インポート_帳票設計書 | X3: =変更履歴!X3 -> KH0500_EXCEL仕訳TXT_インポート_帳票設計書 | AK3: =変更履歴!AK3 -> EXCEL仕訳TXT | AX3: =変更履歴!AX3 -> 45539 | BB3: =変更履歴!BB3 -> 大谷 | BF3: =変更履歴!BF3 -> 45539 | BJ3: =変更履歴!BJ3 -> 大谷
B6: 1 | H6: select
H14: from
H19: join
H25: where

Sheet 処理詳細_書き方
B2: システム名 | H2: 画面ID | L2: 業務分類 | R2: ドキュメント種別 | X2: ドキュメント名 | AK2: 帳票名 | AX2: 作成日 | BB2: 作成者 | BF2: 更新日 | BJ2: 更新者
B3: =変更履歴!B3 -> 受発注システム | H3: =変更履歴!H3 -> KH0500 | L3: =変更履歴!L3 -> 受発注 | R3: =変更履歴!R3 -> インポート_帳票設計書 | X3: =変更履歴!X3 -> KH0500_EXCEL仕訳TXT_インポート_帳票設計書 | AK3: =変更履歴!AK3 -> EXCEL仕訳TXT | AX3: =変更履歴!AX3 -> 45539 | BB3: =変更履歴!BB3 -> 大谷 | BF3: =変更履歴!BF3 -> 45539 | BJ3: =変更履歴!BJ3 -> 大谷
B7: 1.タイトルを記載 | H7: select | J7: 項目名 | R7: 格納テーブル
J8: 仕入先CD | R8: VM支払予定情報.仕入先CD
J9: 仕入先名1 | R9: VM支払予定情報.仕入先名1
H10: from | J10: 使用するテーブル名を記載
J11: TD売上請求H
J12: TD見積
J13: TM納入先
H14: join | J14: 結合方式
K15: 結合テーブル名
M16: 結合条件
L17: and | M17: 結合条件
L18: or | M18: 結合条件
J19: INNER JOIN
K20: TM納入先
M21: [TD見積.納入得意先CD] = [TM納入先.得意先CD]
L22: and | M22: [TD見積.納入先CD] = [TM納入先.納入先CD]
H23: where | K23: 取得条件 | AK23: パラメータの意味が分かる場合は記載する
J24: and | K24: 取得条件
J25: or | K25: 取得条件
J26: ※可能な限り日本語化する
K27: [TD見積.得意先CD] = '8001' | AK27: 8001'はヤオコーの得意先CD
J28: and | K28: [TD売上請求H.請求日付]が[画面.請求期間From]以降
H32: order by | J32: ソート条件を記載
J33: [画面.iYK物件区分]が1の場合は[TD見積.納入得意先CD],[TD見積.納入先CD],[TD売上請求H.見積番号]を昇順でソート
H36: group byなどほかの条件がある場合は行を追加して記載

Sheet 確認事項
B2: 確認事項
B3: No. | C3: シート名 | D3: タイトル | E3: 概要 | F3: 確認済
B4: 1
B5: 2
B6: 3
B7: 4
B8: 5
B9: 6
B10: 7
B11: 8
B12: 9
B13: 10
B14: 11
B15: 12
... B54: 51

Sheet 別紙_テンプレート_借方勘定科目
A1: 借方勘定科目CD | B1: 借方勘定科目名 | C1: 借方消費税CD | D1: 借方消費税率 | E1: 借方補助科目CD | F1: 検索値 | G1: 借方補助科目名
A2: 100 | B2: 現金 | E2: 1 | F2: =A2&E2 -> 1001 | G2: 現金
A3: 100 | B3: 現金 | E3: 2 | F3: =A3&E3 -> 1002 | G3: RMB
A4: 110 | B4: 当座預金 | E4: 1 | F4: =A4&E4 -> 1101 | G4: 埼玉りそな
A5: 110 | B5: 当座預金 | E5: 2 | F5: =A5&E5 -> 1102 | G5: 埼信
A6: 110 | B6: 当座預金 | E6: 10 | F6: =A6&E6 -> 11010 | G6: 武蔵野
A7: 114 | B7: 普通預金 | E7: 1 | F7: =A7&E7 -> 1141 | G7: 埼玉りそな
A8: 114 | B8: 普通預金 | E8: 2 | F8: =A8&E8 -> 1142 | G8: 埼信
A9: 114 | B9: 普通預金 | E9: 3 | F9: =A9&E9 -> 1143 | G9: 三井住友
A10: 114 | B10: 普通預金 | E10: 4 | F10: =A10&E10 -> 1144 | G10: 住友USD
A11: 114 | B11: 普通預金 | E11: 5 | F11: =A11&E11 -> 1145 | G11: 住友CNY
A12: 114 | B12: 普通預金 | E12: 6 | F12: =A12&E12 -> 1146 | G12: 群馬
A13: 114 | B13: 普通預金 | E13: 7 | F13: =A13&E13 -> 1147 | G13: みずほ
... A20: 125 | B20: 定期積金 | E20: 2 | F20: =A20&E20 -> 1252 | G20: 埼信
A21: 130 | B21: 受取手形 | F21: =A21&E21 -> 130
A22: 131 | B22: 売掛金 | E22: 1001 | F22: =A22&E22 -> 1311001 | G22: アベイル
A23: 131 | B23: 売掛金 | E23: 1036 | F23: =A23&E23 -> 1311036 | G23: ｱｲﾘｽｵｰﾔﾏ㈱角田ITP
A24: 131 | B24: 売掛金 | E24: 1201 | F24: =A24&E24 -> 1311201 | G24: 石川建設㈱(松﨑由)
A25: 131 | B25: 売掛金 | E25: 1243 | F25: =A25&E25 -> 1311243 | G25: ㈱イマイ建築設計事務
A26: 131 | B26: 売掛金 | E26: 1608 | F26: =A26&E26 -> 1311608 | G26: エルテック㈱
A27: 131 | B27: 売掛金 | E27: 1617 | F27: =A27&E27 -> 1311617 | G27: ㈱江田組
A28: 131 | B28: 売掛金 | E28: 1803 | F28: =A28&E28 -> 1311803 | G28: ㈱岡村製作所 商環境
A29: 131 | B29: 売掛金 | E29: 1816 | F29: =A29&E29 -> 1311816 | G29: おかべ物産観光㈱
A30: 131 | B30: 売掛金 | E30: 1855 | F30: =A30&E30 -> 1311855 | G30: 株式会社織田
A31: 131 | B31: 売掛金 | E31: 2010 | F31: =A31&E31 -> 1312010 | G31: ｶﾈﾎﾞｳ化粧品群馬支社
A32: 131 | B32: 売掛金 | E32: 2011 | F32: =A32&E32 -> 1312011 | G32: ｶﾈﾎﾞｳ化粧品関越支社
A33: 131 | B33: 売掛金 | E33: 2012 | F33: =A33&E33 -> 1312012 | G33: ｶﾈﾎﾞｳ化粧品千葉支社
... A77: 131 | B77: 売掛金 | E77: 8805 | F77: =A77&E77 -> 1318805 | G77: ㈱ワームス 本社
A78: 132 | B78: 有価証券 | C78: 30 | E78: 2401 | F78: =A78&E78 -> 1322401 | G78: ウエルシア
A79: 132 | B79: 有価証券 | E79: 3028 | F79: =A79&E79 -> 1323028 | G79: サンプラ
A80: 132 | B80: 有価証券 | E80: 3201 | F80: =A80&E80 -> 1323201 | G80: しまむら
A81: 132 | B81: 有価証券 | E81: 4801 | F81: =A81&E81 -> 1324801 | G81: LIXILグループ
A82: 132 | B82: 有価証券 | E82: 6601 | F82: =A82&E82 -> 1326601 | G82: ベルク
A83: 132 | B83: 有価証券 | E83: 7001 | F83: =A83&E83 -> 1327001 | G83: マミー
A84: 132 | B84: 有価証券 | E84: 8001 | F84: =A84&E84 -> 1328001 | G84: ヤオコー
A85: 132 | B85: 有価証券 | E85: 9997 | F85: =A85&E85 -> 1329997 | G85: アクシアル
A86: 132 | B86: 有価証券 | E86: 9998 | F86: =A86&E86 -> 1329998 | G86: セキチュー
A87: 132 | B87: 有価証券 | E87: 9999 | F87: =A87&E87 -> 1329999 | G87: その他
A88: 140 | B88: 商品 | F88: =A88&E88 -> 140
A89: 150 | B89: 前渡金 | E89: 1 | F89: =A89&E89 -> 1501 | G89: 三研商貿有限公司
A90: 150 | B90: 前渡金 | E90: 2 | F90: =A90&E90 -> 1502 | G90: 異業種交流会
A91: 151 | B91: 短期貸付金 | E91: 1 | F91: =A91&E91 -> 1511 | G91: ㈱三和商研
A92: 151 | B92: 短期貸付金 | E92: 4 | F92: =A92&E92 -> 1514 | G92: 三研商貿有限公司
A93: 152 | B93: 立替金 | E93: 1 | F93: =A93&E93 -> 1521 | G93: ㈱三和商研
A94: 152 | B94: 立替金 | E94: 4 | F94: =A94&E94 -> 1524 | G94: 中国
A95: 152 | B95: 立替金 | E95: 100 | F95: =A95&E95 -> 152100 | G95: 一時的
A96: 152 | B96: 立替金 | E96: 101 | F96: =A96&E96 -> 152101 | G96: 従業員立替
A97: 152 | B97: 立替金 | E97: 102 | F97: =A97&E97 -> 152102 | G97: ｻﾝﾜﾌﾟﾗﾝﾆﾝｸﾞ
A98: 152 | B98: 立替金 | E98: 103 | F98: =A98&E98 -> 152103 | G98: 得意先
A99: 152 | B99: 立替金 | E99: 104 | F99: =A99&E99 -> 152104 | G99: 永見
A100: 152 | B100: 立替金 | E100: 105 | F100: =A100&E100 -> 152105 | G100: 三和会
... A116: 155 | B116: 前払費用 | E116: 102 | F116: =A116&E116 -> 155102 | G116: セコム
A117: 156 | B117: 預け金 | F117: =A117&E117 -> 156
A118: 158 | B118: 仮払消費税 | F118: =A118&E118 -> 158
A119: 161 | B119: 建物付属設備 | C119: 32 | D119: 5 | F119: =A119&E119 -> 161
A120: 162 | B120: 構築物 | C120: 32 | D120: 5 | F120: =A120&E120 -> 162
A121: 164 | B121: 車両運搬具 | C121: 32 | D121: 8 | F121: =A121&E121 -> 164
A122: 165 | B122: 器具備品 | C122: 32 | D122: 5 | F122: =A122&E122 -> 165
A123: 171 | B123: 差入保証金 | E123: 1 | F123: =A123&E123 -> 1711 | G123: ㈱岡村製作所
A124: 171 | B124: 差入保証金 | E124: 2 | F124: =A124&E124 -> 1712 | G124: 富士火災海上保険㈱
A125: 171 | B125: 差入保証金 | E125: 3 | F125: =A125&E125 -> 1713 | G125: 電気通信共済会
A126: 171 | B126: 差入保証金 | E126: 4 | F126: =A126&E126 -> 1714 | G126: ﾘｿﾞｰﾄﾄﾗｽﾄ㈱
A127: 173 | B127: ソフトウェア | C127: 32 | D127: 5 | F127: =A127&E127 -> 173
A128: 173 | B128: ソフトウェア | C128: 81 | F128: =A128&E128 -> 173
A129: 181 | B129: 出資金 | E129: 1 | F129: =A129&E129 -> 1811 | G129: 埼玉縣信金
A130: 181 | B130: 出資金 | E130: 2 | F130: =A130&E130 -> 1812 | G130: 熊谷異業種交流会
A131: 181 | B131: 出資金 | E131: 3 | F131: =A131&E131 -> 1813 | G131: エルテック㈱
A132: 181 | B132: 出資金 | E132: 4 | F132: =A132&E132 -> 1814 | G132: 三研商貿有限公司
A133: 185 | B133: 保険積立金 | F133: =A133&E133 -> 185
A134: 188 | B134: その他の投資 | F134: =A134&E134 -> 188
A135: 201 | B135: 買掛金 | E135: 1005 | F135: =A135&E135 -> 2011005 | G135: アイリスオーヤマ㈱
A136: 201 | B136: 買掛金 | E136: 1011 | F136: =A136&E136 -> 2011011 | G136: ㈱ｱｸﾃｨｰ.ｽﾀｯﾌ
A137: 201 | B137: 買掛金 | E137: 1023 | F137: =A137&E137 -> 2011023 | G137: ㈱アドシア
A138: 201 | B138: 買掛金 | E138: 1024 | F138: =A138&E138 -> 2011024 | G138: アドバンスサービス
A139: 201 | B139: 買掛金 | E139: 1027 | F139: =A139&E139 -> 2011027 | G139: アイエイト
A140: 201 | B140: 買掛金 | E140: 1028 | F140: =A140&E140 -> 2011028 | G140: 安西総合(有)
A141: 201 | B141: 買掛金 | E141: 1203 | F141: =A141&E141 -> 2011203 | G141: 石山商工
A142: 201 | B142: 買掛金 | E142: 1209 | F142: =A142&E142 -> 2011209 | G142: 井上金庫販売㈱
A143: 201 | B143: 買掛金 | E143: 1224 | F143: =A143&E143 -> 2011224 | G143: ㈲ｲﾝﾃﾘｱ ﾌﾟﾗｽﾃｨﾝｸﾞ
A144: 201 | B144: 買掛金 | E144: 1226 | F144: =A144&E144 -> 2011226 | G144: ㈱井上運送
A145: 201 | B145: 買掛金 | E145: 1227 | F145: =A145&E145 -> 2011227 | G145: ㈱井出木工
A146: 201 | B146: 買掛金 | E146: 1407 | F146: =A146&E146 -> 2011407 | G146: ｳｴﾙｼｱ薬局 各店
... A320: 201 | B320: 買掛金 | E320: 9999 | F320: =A320&E320 -> 2019999 | G320: ㈱三和商研
A321: 202 | B321: 短期借入金 | F321: =A321&E321 -> 202
A322: 204 | B322: 未払金 | E322: 1 | F322: =A322&E322 -> 2041 | G322: 三和商研 経費
A323: 204 | B323: 未払金 | E323: 4 | F323: =A323&E323 -> 2044 | G323: 中国
A324: 204 | B324: 未払金 | E324: 10 | F324: =A324&E324 -> 20410 | G324: 浅沼
A325: 204 | B325: 未払金 | E325: 11 | F325: =A325&E325 -> 20411 | G325: ｱｯﾌﾟﾙ
A326: 204 | B326: 未払金 | E326: 40 | F326: =A326&E326 -> 20440 | G326: Ｍクラフト
A327: 204 | B327: 未払金 | E327: 41 | F327: =A327&E327 -> 20441 | G327: エルテック
A328: 204 | B328: 未払金 | E328: 42 | F328: =A328&E328 -> 20442 | G328: エルム室内㈱
A329: 204 | B329: 未払金 | E329: 50 | F329: =A329&E329 -> 20450 | G329: 大石社労士
A330: 204 | B330: 未払金 | E330: 51 | F330: =A330&E330 -> 20451 | G330: 大里
A331: 204 | B331: 未払金 | E331: 52 | F331: =A331&E331 -> 20452 | G331: 大塚商会
A332: 204 | B332: 未払金 | E332: 53 | F332: =A332&E332 -> 20453 | G332: 岡村製作所
A333: 204 | B333: 未払金 | E333: 120 | F333: =A333&E333 -> 204120 | G333: 北本グリーンセンター
... A399: 208 | B399: 預り金 | E399: 44 | F399: =A399&E399 -> 20844 | G399: 中国
A400: 2117 | B400: 研修教育費 | C400: 32 | D400: 8 | F400: =A400&E400 -> 2117
A401: 212 | B401: 未払法人税等 | F401: =A401&E401 -> 212
A402: 220 | B402: 長期借入金 | F402: =A402&E402 -> 220
...

Sheet 別紙_テンプレート_貸方勘定科目
A1: 貸方勘定科目CD | B1: 貸方勘定科目名 | C1: 貸方消費税CD | D1: 貸方消費税率 | E1: 貸方補助科目CD | F1: 検索値 | G1: 貸方補助科目名
A2: 100 | B2: 現金 | E2: 1 | F2: =A2&E2 -> 1001 | G2: 現金
A3: 100 | B3: 現金 | E3: 2 | F3: =A3&E3 -> 1002 | G3: RMB
A4: 110 | B4: 当座預金 | E4: 1 | F4: =A4&E4 -> 1101 | G4: 埼玉りそな
A5: 110 | B5: 当座預金 | E5: 2 | F5: =A5&E5 -> 1102 | G5: 埼信
A6: 110 | B6: 当座預金 | E6: 10 | F6: =A6&E6 -> 11010 | G6: 武蔵野
A7: 114 | B7: 普通預金 | E7: 1 | F7: =A7&E7 -> 1141 | G7: 埼玉りそな
A8: 114 | B8: 普通預金 | E8: 2 | F8: =A8&E8 -> 1142 | G8: 埼信
A9: 114 | B9: 普通預金 | E9: 3 | F9: =A9&E9 -> 1143 | G9: 三井住友
A10: 114 | B10: 普通預金 | E10: 4 | F10: =A10&E10 -> 1144 | G10: 住友USD
A11: 114 | B11: 普通預金 | E11: 5 | F11: =A11&E11 -> 1145 | G11: 住友CNY
A12: 114 | B12: 普通預金 | E12: 6 | F12: =A12&E12 -> 1146 | G12: 群馬
A13: 114 | B13: 普通預金 | E13: 7 | F13: =A13&E13 -> 1147 | G13: みずほ
... A19: 125 | B19: 定期積金 | E19: 2 | F19: =A19&E19 -> 1252 | G19: 埼信
A20: 130 | B20: 受取手形 | F20: =A20&E20 -> 130
A21: 131 | B21: 売掛金 | E21: 1001 | F21: =A21&E21 -> 1311001 | G21: アベイル
A22: 131 | B22: 売掛金 | E22: 1012 | F22: =A22&E22 -> 1311012 | G22: ㈱秋山製作所
A23: 131 | B23: 売掛金 | E23: 1036 | F23: =A23&E23 -> 1311036 | G23: ｱｲﾘｽｵｰﾔﾏ㈱角田ITP
A24: 131 | B24: 売掛金 | E24: 1037 | F24: =A24&E24 -> 1311037 | G24: アツギ㈱
A25: 131 | B25: 売掛金 | E25: 1039 | F25: =A25&E25 -> 1311039 | G25: ㈱天池
A26: 131 | B26: 売掛金 | E26: 1201 | F26: =A26&E26 -> 1311201 | G26: 石川建設㈱(松﨑由)
A27: 131 | B27: 売掛金 | E27: 1243 | F27: =A27&E27 -> 1311243 | G27: ㈱イマイ建築設計事務
A28: 131 | B28: 売掛金 | E28: 1244 | F28: =A28&E28 -> 1311244 | G28: いわて生活協同組合
A29: 131 | B29: 売掛金 | E29: 1608 | F29: =A29&E29 -> 1311608 | G29: エルテック㈱
A30: 131 | B30: 売掛金 | E30: 1617 | F30: =A30&E30 -> 1311617 | G30: ㈱江田組
A31: 131 | B31: 売掛金 | E31: 1803 | F31: =A31&E31 -> 1311803 | G31: ㈱岡村製作所 商環境
A32: 131 | B32: 売掛金 | E32: 1805 | F32: =A32&E32 -> 1311805 | G32: ㈱岡村製作所商環境
... A108: 131 | B108: 売掛金 | E108: 7217 | F108: =A108&E108 -> 1317217 | G108: 三米施工
A109: 131 | E109: 7601 | F109: =A109&E109 -> 1317601 | G109: メディカルサービス
A110: 131 | B110: 売掛金 | E110: 7811 | F110: =A110&E110 -> 1317811 | G110: 本町薬局
A111: 131 | B111: 売掛金 | E111: 8001 | F111: =A111&E111 -> 1318001 | G111: ㈱ヤオコー
A112: 131 | B112: 売掛金 | E112: 8006 | F112: =A112&E112 -> 1318006 | G112: ㈱やまかわ
A113: 131 | B113: 売掛金 | E113: 8026 | F113: =A113&E113 -> 1318026 | G113: ヤマト運輸㈱
A114: 131 | B114: 売掛金 | E114: 8805 | F114: =A114&E114 -> 1318805 | G114: ㈱ワームス 本社
A115: 131 | B115: 売掛金 | E115: 8810 | F115: =A115&E115 -> 1318810 | G115: わかば薬局㈱
A116: 131 | B116: 売掛金 | E116: 8811 | F116: =A116&E116 -> 1318811 | G116: Y-TEC
A117: 131 | B117: 売掛金 | E117: 9997 | F117: =A117&E117 -> 1319997 | G117: その他得意先ﾁｰﾑＹ
A118: 131 | B118: 売掛金 | E118: 9998 | F118: =A118&E118 -> 1319998 | G118: その他得意先
A119: 132 | B119: 有価証券 | C119: 30 | F119: =A119&E119 -> 132
A120: 140 | B120: 商品 | F120: =A120&E120 -> 140
A121: 150 | B121: 前渡金 | E121: 1 | F121: =A121&E121 -> 1501 | G121: 三研商貿有限公司
A122: 150 | B122: 前渡金 | E122: 2 | F122: =A122&E122 -> 1502 | G122: 異業種交流会
A123: 151 | B123: 短期貸付金 | E123: 1 | F123: =A123&E123 -> 1511 | G123: ㈱三和商研
A124: 151 | B124: 短期貸付金 | E124: 4 | F124: =A124&E124 -> 1514 | G124: 三研商貿有限公司
A125: 152 | B125: 立替金 | E125: 1 | F125: =A125&E125 -> 1521 | G125: ㈱三和商研
A126: 152 | B126: 立替金 | E126: 4 | F126: =A126&E126 -> 1524 | G126: 中国
A127: 152 | B127: 立替金 | E127: 100 | F127: =A127&E127 -> 152100 | G127: 一時的
A128: 152 | B128: 立替金 | E128: 101 | F128: =A128&E128 -> 152101 | G128: 従業員立替
A129: 152 | B129: 立替金 | E129: 102 | F129: =A129&E129 -> 152102 | G129: ｻﾝﾜﾌﾟﾗﾝﾆﾝｸﾞ
A130: 152 | B130: 立替金 | E130: 103 | F130: =A130&E130 -> 152103 | G130: 得意先
A131: 152 | B131: 立替金 | E131: 104 | F131: =A131&E131 -> 152104 | G131: 永見
A132: 152 | B132: 立替金 | E132: 105 | F132: =A132&E132 -> 152105 | G132: 三和会
A133: 153 | B133: 未収入金 | F133: =A133&E133 -> 153
A134: 154 | B134: 仮払金 | E134: 4 | F134: =A134&E134 -> 1544 | G134: 中国
A135: 154 | B135: 仮払金 | E135: 10 | F135: =A135&E135 -> 15410 | G135: 社長小口
A136: 154 | B136: 仮払金 | E136: 11 | F136: =A136&E136 -> 15411 | G136: 社長外貨
A137: 154 | B137: 仮払金 | E137: 100 | F137: =A137&E137 -> 154100 | G137: 一時的
A138: 154 | B138: 仮払金 | E138: 101 | F138: =A138&E138 -> 154101 | G138: 一時的
A139: 154 | B139: 仮払金 | E139: 999 | F139: =A139&E139 -> 154999 | G139: その他
A140: 154 | B140: 仮払金 | E140: 2401 | F140: =A140&E140 -> 1542401 | G140: ウエルシア
A141: 155 | B141: 前払費用 | E141: 1 | F141: =A141&E141 -> 1551 | G141: 保証料
A142: 155 | B142: 前払費用 | E142: 10 | F142: =A142&E142 -> 15510 | G142: 三井住友海上
A143: 155 | B143: 前払費用 | E143: 100 | F143: =A143&E143 -> 155100 | G143: 家賃地代
A144: 158 | B144: 仮払消費税 | F144: =A144&E144 -> 158
A145: 161 | B145: 建物付属設備 | C145: 32 | D145: 5 | F145: =A145&E145 -> 161
A146: 162 | B146: 構築物 | C146: 32 | D146: 5 | F146: =A146&E146 -> 162
A147: 164 | B147: 車両運搬具 | C147: 32 | D147: 8 | F147: =A147&E147 -> 164
A148: 165 | B148: 器具備品 | C148: 32 | D148: 5 | F148: =A148&E148 -> 165
A149: 169 | B149: 減価償却累計額 | F149: =A149&E149 -> 169
A150: 171 | B150: 差入保証金 | E150: 1 | F150: =A150&E150 -> 1711 | G150: ㈱岡村製作所
A151: 171 | B151: 差入保証金 | E151: 2 | F151: =A151&E151 -> 1712 | G151: 富士火災海上保険㈱
A152: 171 | B152: 差入保証金 | E152: 3 | F152: =A152&E152 -> 1713 | G152: 電気通信共済会
A153: 171 | B153: 差入保証金 | E153: 4 | F153: =A153&E153 -> 1714 | G153: ﾘｿﾞｰﾄﾄﾗｽﾄ㈱
A154: 173 | B154: ソフトウェア | C154: 32 | D154: 5 | F154: =A154&E154 -> 173
A155: 173 | B155: ソフトウェア | C155: 81 | F155: =A155&E155 -> 173
A156: 181 | B156: 出資金 | E156: 1 | F156: =A156&E156 -> 1811 | G156: 埼玉縣信金
A157: 181 | B157: 出資金 | E157: 2 | F157: =A157&E157 -> 1812 | G157: 熊谷異業種交流会
A158: 181 | B158: 出資金 | E158: 3 | F158: =A158&E158 -> 1813 | G158: エルテック㈱
A159: 181 | B159: 出資金 | E159: 4 | F159: =A159&E159 -> 1814 | G159: 三研商貿有限公司
A160: 185 | B160: 保険積立金 | F160: =A160&E160 -> 185
A161: 188 | B161: その他の投資 | F161: =A161&E161 -> 188
A162: 201 | B162: 買掛金 | E162: 1005 | F162: =A162&E162 -> 2011005 | G162: アイリスオーヤマ㈱
A163: 201 | B163: 買掛金 | E163: 1011 | F163: =A163&E163 -> 2011011 | G163: ㈱ｱｸﾃｨｰ.ｽﾀｯﾌ
A164: 201 | B164: 買掛金 | E164: 1023 | F164: =A164&E164 -> 2011023 | G164: ㈱アドシア
A165: 201 | B165: 買掛金 | E165: 1027 | F165: =A165&E165 -> 2011027 | G165: アイエイト
A166: 201 | B166: 買掛金 | E166: 1028 | F166: =A166&E166 -> 2011028 | G166: 安西総合㈲
A167: 201 | B167: 買掛金 | E167: 1203 | F167: =A167&E167 -> 2011203 | G167: 石山商工
A168: 201 | B168: 買掛金 | E168: 1209 | F168: =A168&E168 -> 2011209 | G168: 井上金庫販売㈱
A169: 201 | B169: 買掛金 | E169: 1407 | F169: =A169&E169 -> 2011407 | G169: ｳｴﾙｼｱ薬局 各店
A170: 201 | B170: 買掛金 | E170: 1408 | F170: =A170&E170 -> 2011408 | G170: 運送費
A171: 201 | B171: 買掛金 | E171: 1601 | F171: =A171&E171 -> 2011601 | G171: ｴﾙﾃｯｸ㈱ PF事業部
A172: 201 | B172: 買掛金 | E172: 1606 | F172: =A172&E172 -> 2011606 | G172: エルム室内㈱
A173: 201 | B173: 買掛金 | E173: 1615 | F173: =A173&E173 -> 2011615 | G173: エム木工
... A288: 201 | B288: 買掛金 | E288: 9801 | F288: =A288&E288 -> 2019801 | G288: ロイヤルﾎｰﾑｾﾝﾀｰ
A289: 202 | B289: 短期借入金 | F289: =A289&E289 -> 202
A290: 204 | B290: 未払金 | E290: 1 | F290: =A290&E290 -> 2041 | G290: 三和商研 経費
A291: 204 | B291: 未払金 | E291: 4 | F291: =A291&E291 -> 2044 | G291: 中国
A292: 204 | B292: 未払金 | E292: 10 | F292: =A292&E292 -> 20410 | G292: 浅沼
A293: 204 | B293: 未払金 | E293: 11 | F293: =A293&E293 -> 20411 | G293: ｱｯﾌﾟﾙ
A294: 204 | B294: 未払金 | E294: 40 | F294: =A294&E294 -> 20440 | G294: Ｍクラフト
...

Sheet 別紙_テンプレート_振替伝票
A1: 【JCB】 | Q1: 借方合計 | R1: 貸方合計 | S1: =SUMIF(E90:E91,116,Q90:Q91)-SUMIF(K90:K91,116,R90:R91) -> 0 | T1: 口座差額
Q2: =SUM(Q4:Q13) -> 59820 | R2: =SUM(R4:R13) -> 59820 | S2: =SUMIF(E90:E91,999,Q90:Q91)-SUMIF(K90:K91,999,R90:R91) -> 0 | T2: 諸口
A3: 伝票番号 | B3: 年 | C3: 月 | D3: 日 | E3: 借方勘定科目CD | F3: 借方補助科目CD | G3: 借方消費税CD | H3: 借方消費税率 | I3: 借方科目 | J3: 借方補助科目 | K3: 貸方勘定科目CD | L3: 貸方補助科目CD | M3: 貸方消費税CD | N3: 貸方消費税率 | O3: 貸方科目 | P3: 貸方補助科目 | Q3: 借方金額 | R3: 貸方金額 | S3: 摘要 | T3: 銀行
I4: =IF(ISERROR(VLOOKUP(E4,[2]借方勘定科目!$A$2:$G$1045,2,FALSE))=FALSE,VLOOKUP(E4,[2]借方勘定科目!$A$2:$G$1045,2,FALSE)&"","") | J4: =IF(ISERROR(VLOOKUP(E4&F4,[2]借方勘定科目!$F$2:$G$1045,2,FALSE))=FALSE,VLOOKUP(E4&F4,[2]借方勘定科目!$F$2:$G$1045,2,FALSE)&"","") | O4: =IF(ISERROR(VLOOKUP(K4,[2]貸方勘定科目!$A$2:$G$1025,2,FALSE))=FALSE,VLOOKUP(K4,[2]貸方勘定科目!$A$2:$G$1025,2,FALSE)&"","") | P4: =IF(ISERROR(VLOOKUP(K4&L4,[2]貸方勘定科目!$F$2:$G$1025,2,FALSE))=FALSE,VLOOKUP(K4&L4,[2]貸方勘定科目!$F$2:$G$1025,2,FALSE)&"","")
B5: 2022 | C5: 11 | D5: 30 | E5: 536 | G5: 41 | H5: 10 | I5: =IF(ISERROR(VLOOKUP(E5,[2]借方勘定科目!$A$2:$G$1045,2,FALSE))=FALSE,VLOOKUP(E5,[2]借方勘定科目!$A$2:$G$1045,2,FALSE)&"","") -> 新聞図書費 | J5: =IF(ISERROR(VLOOKUP(E5&F5,[2]借方勘定科目!$F$2:$G$1045,2,FALSE))=FALSE,VLOOKUP(E5&F5,[2]借方勘定科目!$F$2:$G$1045,2,FALSE)&"","") | K5: 204 | L5: 225 | O5: =IF(ISERROR(VLOOKUP(K5,[2]貸方勘定科目!$A$2:$G$1025,2,FALSE))=FALSE,VLOOKUP(K5,[2]貸方勘定科目!$A$2:$G$1025,2,FALSE)&"","") -> 未払金 | P5: =IF(ISERROR(VLOOKUP(K5&L5,[2]貸方勘定科目!$F$2:$G$1025,2,FALSE))=FALSE,VLOOKUP(K5&L5,[2]貸方勘定科目!$F$2:$G$1025,2,FALSE)&"","") -> JCB | Q5: 50000 | R5: 50000 | S5: JCB XXXXXXXX 12/12引 | V5: =Q5-R5 -> 0
B6: 2022 | C6: 11 | D6: 30 | E6: 158 | G6: 41 | H6: 10 | I6: =IF(ISERROR(VLOOKUP(E6,[2]借方勘定科目!$A$2:$G$1045,2,FALSE))=FALSE,VLOOKUP(E6,[2]借方勘定科目!$A$2:$G$1045,2,FALSE)&"","") -> 仮払消費税 | J6: =IF(ISERROR(VLOOKUP(E6&F6,[2]借方勘定科目!$F$2:$G$1045,2,FALSE))=FALSE,VLOOKUP(E6&F6,[2]借方勘定科目!$F$2:$G$1045,2,FALSE)&"","") | K6: 204 | L6: 225 | O6: =IF(ISERROR(VLOOKUP(K6,[2]貸方勘定科目!$A$2:$G$1025,2,FALSE))=FALSE,VLOOKUP(K6,[2]貸方勘定科目!$A$2:$G$1025,2,FALSE)&"","") -> 未払金 | P6: =IF(ISERROR(VLOOKUP(K6&L6,[2]貸方勘定科目!$F$2:$G$1025,2,FALSE))=FALSE,VLOOKUP(K6&L6,[2]貸方勘定科目!$F$2:$G$1025,2,FALSE)&"","") -> JCB | Q6: 5000 | R6: 5000 | S6: JCB XXXXXXXX 12/12引 | V6: =Q6-R6 -> 0
B7: 2022 | C7: 11 | D7: 30 | E7: 536 | G7: 41 | H7: 10 | I7: =IF(ISERROR(VLOOKUP(E7,[2]借方勘定科目!$A$2:$G$1045,2,FALSE))=FALSE,VLOOKUP(E7,[2]借方勘定科目!$A$2:$G$1045,2,FALSE)&"","") -> 新聞図書費 | J7: =IF(ISERROR(VLOOKUP(E7&F7,[2]借方勘定科目!$F$2:$G$1045,2,FALSE))=FALSE,VLOOKUP(E7&F7,[2]借方勘定科目!$F$2:$G$1045,2,FALSE)&"","") | K7: 204 | L7: 225 | O7: =IF(ISERROR(VLOOKUP(K7,[2]貸方勘定科目!$A$2:$G$1025,2,FALSE))=FALSE,VLOOKUP(K7,[2]貸方勘定科目!$A$2:$G$1025,2,FALSE)&"","") -> 未払金 | P7: =IF(ISERROR(VLOOKUP(K7&L7,[2]貸方勘定科目!$F$2:$G$1025,2,FALSE))=FALSE,VLOOKUP(K7&L7,[2]貸方勘定科目!$F$2:$G$1025,2,FALSE)&"","") -> JCB | Q7: 1800 | R7: 1800 | S7: JCB XXXXXXXXXXXXXXX 12/12引 | V7: =Q7-R7 -> 0
B8: 2022 | C8: 11 | D8: 30 | E8: 158 | G8: 41 | H8: 10 | I8: =IF(ISERROR(VLOOKUP(E8,[2]借方勘定科目!$A$2:$G$1045,2,FALSE))=FALSE,VLOOKUP(E8,[2]借方勘定科目!$A$2:$G$1045,2,FALSE)&"","") -> 仮払消費税 | J8: =IF(ISERROR(VLOOKUP(E8&F8,[2]借方勘定科目!$F$2:$G$1045,2,FALSE))=FALSE,VLOOKUP(E8&F8,[2]借方勘定科目!$F$2:$G$1045,2,FALSE)&"","") | K8: 204 | L8: 225 | O8: =IF(ISERROR(VLOOKUP(K8,[2]貸方勘定科目!$A$2:$G$1025,2,FALSE))=FALSE,VLOOKUP(K8,[2]貸方勘定科目!$A$2:$G$1025,2,FALSE)&"","") -> 未払金 | P8: =IF(ISERROR(VLOOKUP(K8&L8,[2]貸方勘定科目!$F$2:$G$1025,2,FALSE))=FALSE,VLOOKUP(K8&L8,[2]貸方勘定科目!$F$2:$G$1025,2,FALSE)&"","") -> JCB | Q8: 200 | R8: 200 | S8: JCB XXXXXXXXXXXXXXX 12/12引 | V8: =Q8-R8 -> 0
V9: =Q9-R9 -> 0
B10: 2022 | C10: 11 | D10: 30 | E10: 529 | F10: 9998 | G10: 81 | I10: =IF(ISERROR(VLOOKUP(E10,[2]借方勘定科目!$A$2:$G$1045,2,FALSE))=FALSE,VLOOKUP(E10,[2]借方勘定科目!$A$2:$G$1045,2,FALSE)&"","") -> 交際接待費 | J10: =IF(ISERROR(VLOOKUP(E10&F10,[2]借方勘定科目!$F$2:$G$1045,2,FALSE))=FALSE,VLOOKUP(E10&F10,[2]借方勘定科目!$F$2:$G$1045,2,FALSE)&"","") -> その他 | K10: 204 | L10: 225 | O10: =IF(ISERROR(VLOOKUP(K10,[2]貸方勘定科目!$A$2:$G$1025,2,FALSE))=FALSE,VLOOKUP(K10,[2]貸方勘定科目!$A$2:$G$1025,2,FALSE)&"","") -> 未払金 | P10: =IF(ISERROR(VLOOKUP(K10&L10,[2]貸方勘定科目!$F$2:$G$1025,2,FALSE))=FALSE,VLOOKUP(K10&L10,[2]貸方勘定科目!$F$2:$G$1025,2,FALSE)&"","") -> JCB | Q10: 500 | R10: 500 | S10: JCB XXXXXXXXXXXXXX 社 12/12引 | V10: =Q10-R10 -> 0
B11: 2022 | C11: 11 | D11: 30 | E11: 158 | G11: 41 | H11: 10 | I11: =IF(ISERROR(VLOOKUP(E11,[2]借方勘定科目!$A$2:$G$1045,2,FALSE))=FALSE,VLOOKUP(E11,[2]借方勘定科目!$A$2:$G$1045,2,FALSE)&"","") -> 仮払消費税 | J11: =IF(ISERROR(VLOOKUP(E11&F11,[2]借方勘定科目!$F$2:$G$1045,2,FALSE))=FALSE,VLOOKUP(E11&F11,[2]借方勘定科目!$F$2:$G$1045,2,FALSE)&"","") | K11: 204 | L11: 225 | O11: =IF(ISERROR(VLOOKUP(K11,[2]貸方勘定科目!$A$2:$G$1025,2,FALSE))=FALSE,VLOOKUP(K11,[2]貸方勘定科目!$A$2:$G$1025,2,FALSE)&"","") -> 未払金 | P11: =IF(ISERROR(VLOOKUP(K11&L11,[2]貸方勘定科目!$F$2:$G$1025,2,FALSE))=FALSE,VLOOKUP(K11&L11,[2]貸方勘定科目!$F$2:$G$1025,2,FALSE)&"","") -> JCB | Q11: 2000 | R11: 2000 | S11: JCB XXXXXXXXXXXXXX 社 12/12引 | V11: =Q11-R11 -> 0
B12: 2022 | C12: 11 | D12: 30 | E12: 529 | F12: 9998 | G12: 41 | H12: 81 | I12: =IF(ISERROR(VLOOKUP(E12,[2]借方勘定科目!$A$2:$G$1045,2,FALSE))=FALSE,VLOOKUP(E12,[2]借方勘定科目!$A$2:$G$1045,2,FALSE)&"","") -> 交際接待費 | J12: =IF(ISERROR(VLOOKUP(E12&F12,[2]借方勘定科目!$F$2:$G$1045,2,FALSE))=FALSE,VLOOKUP(E12&F12,[2]借方勘定科目!$F$2:$G$1045,2,FALSE)&"","") -> その他 | K12: 204 | L12: 225 | O12: =IF(ISERROR(VLOOKUP(K12,[2]貸方勘定科目!$A$2:$G$1025,2,FALSE))=FALSE,VLOOKUP(K12,[2]貸方勘定科目!$A$2:$G$1025,2,FALSE)&"","") -> 未払金 | P12: =IF(ISERROR(VLOOKUP(K12&L12,[2]貸方勘定科目!$F$2:$G$1025,2,FALSE))=FALSE,VLOOKUP(K12&L12,[2]貸方勘定科目!$F$2:$G$1025,2,FALSE)&"","") -> JCB | Q12: 300 | R12: 300 | S12: JCB XXXXXXXXXXXXXX 社 12/12引 | V12: =Q12-R12 -> 0
B13: 2022 | C13: 11 | D13: 30 | E13: 158 | G13: 41 | H13: 81 | I13: =IF(ISERROR(VLOOKUP(E13,[2]借方勘定科目!$A$2:$G$1045,2,FALSE))=FALSE,VLOOKUP(E13,[2]借方勘定科目!$A$2:$G$1045,2,FALSE)&"","") -> 仮払消費税 | J13: =IF(ISERROR(VLOOKUP(E13&F13,[2]借方勘定科目!$F$2:$G$1045,2,FALSE))=FALSE,VLOOKUP(E13&F13,[2]借方勘定科目!$F$2:$G$1045,2,FALSE)&"","") | K13: 204 | L13: 225 | O13: =IF(ISERROR(VLOOKUP(K13,[2]貸方勘定科目!$A$2:$G$1025,2,FALSE))=FALSE,VLOOKUP(K13,[2]貸方勘定科目!$A$2:$G$1025,2,FALSE)&"","") -> 未払金 | P13: =IF(ISERROR(VLOOKUP(K13&L13,[2]貸方勘定科目!$F$2:$G$1025,2,FALSE))=FALSE,VLOOKUP(K13&L13,[2]貸方勘定科目!$F$2:$G$1025,2,FALSE)&"","") -> JCB | Q13: 20 | R13: 20 | S13: JCB XXXXXXXXXXXXXX 社 12/12引 | V13: =Q13-R13 -> 0
B15: 2022 | C15: 10 | D15: 31 | E15: 530 | F15: 4209 | G15: 41 | H15: 10 | I15: =IF(ISERROR(VLOOKUP(E15,[2]借方勘定科目!$A$2:$G$1045,2,FALSE))=FALSE,VLOOKUP(E15,[2]借方勘定科目!$A$2:$G$1045,2,FALSE)&"","") -> 旅費交通費 | J15: =IF(ISERROR(VLOOKUP(E15&F15,[2]借方勘定科目!$F$2:$G$1045,2,FALSE))=FALSE,VLOOKUP(E15&F15,[2]借方勘定科目!$F$2:$G$1045,2,FALSE)&"","") | K15: 204 | L15: 225 | O15: =IF(ISERROR(VLOOKUP(K15,[2]貸方勘定科目!$A$2:$G$1025,2,FALSE))=FALSE,VLOOKUP(K15,[2]貸方勘定科目!$A$2:$G$1025,2,FALSE)&"","") -> 未払金 | P15: =IF(ISERROR(VLOOKUP(K15&L15,[2]貸方勘定科目!$F$2:$G$1025,2,FALSE))=FALSE,VLOOKUP(K15&L15,[2]貸方勘定科目!$F$2:$G$1025,2,FALSE)&"","") -> JCB | Q15: 8000 | R15: 8000 | S15: JCB XXXXXXXXXXXXXX 社 11/10引 | V15: =Q15-R15 -> 0
B16: 2022 | C16: 10 | D16: 31 | E16: 158 | G16: 41 | H16: 10 | I16: =IF(ISERROR(VLOOKUP(E16,[2]借方勘定科目!$A$2:$G$1045,2,FALSE))=FALSE,VLOOKUP(E16,[2]借方勘定科目!$A$2:$G$1045,2,FALSE)&"","") -> 仮払消費税 | J16: =IF(ISERROR(VLOOKUP(E16&F16,[2]借方勘定科目!$F$2:$G$1045,2,FALSE))=FALSE,VLOOKUP(E16&F16,[2]借方勘定科目!$F$2:$G$1045,2,FALSE)&"","") | K16: 204 | L16: 225 | O16: =IF(ISERROR(VLOOKUP(K16,[2]貸方勘定科目!$A$2:$G$1025,2,FALSE))=FALSE,VLOOKUP(K16,[2]貸方勘定科目!$A$2:$G$1025,2,FALSE)&"","") -> 未払金 | P16: =IF(ISERROR(VLOOKUP(K16&L16,[2]貸方勘定科目!$F$2:$G$1025,2,FALSE))=FALSE,VLOOKUP(K16&L16,[2]貸方勘定科目!$F$2:$G$1025,2,FALSE)&"","") -> JCB | Q16: 750 | R16: 750 | S16: JCB XXXXXXXXXXXXXX 社 11/10引 | V16: =Q16-R16 -> 0
V17: =Q17-R17 -> 0
B18: 2022 | C18: 10 | D18: 31 | E18: 530 | F18: 9998 | G18: 41 | H18: 10 | I18: =IF(ISERROR(VLOOKUP(E18,[2]借方勘定科目!$A$2:$G$1045,2,FALSE))=FALSE,VLOOKUP(E18,[2]借方勘定科目!$A$2:$G$1045,2,FALSE)&"","") -> 旅費交通費 | J18: =IF(ISERROR(VLOOKUP(E18&F18,[2]借方勘定科目!$F$2:$G$1045,2,FALSE))=FALSE,VLOOKUP(E18&F18,[2]借方勘定科目!$F$2:$G$1045,2,FALSE)&"","") | K18: 204 | L18: 225 | O18: =IF(ISERROR(VLOOKUP(K18,[2]貸方勘定科目!$A$2:$G$1025,2,FALSE))=FALSE,VLOOKUP(K18,[2]貸方勘定科目!$A$2:$G$1025,2,FALSE)&"","") -> 未払金 | P18: =IF(ISERROR(VLOOKUP(K18&L18,[2]貸方勘定科目!$F$2:$G$1025,2,FALSE))=FALSE,VLOOKUP(K18&L18,[2]貸方勘定科目!$F$2:$G$1025,2,FALSE)&"","") -> JCB | Q18: 2500 | R18: 2500 | S18: JCB XXXXXXXXXXXXXXXXXXXXXXXXXXXXXXXXX 11/10引 | V18: =Q18-R18 -> 0
B19: 2022 | C19: 10 | D19: 31 | E19: 158 | G19: 41 | H19: 10 | I19: =IF(ISERROR(VLOOKUP(E19,[2]借方勘定科目!$A$2:$G$1045,2,FALSE))=FALSE,VLOOKUP(E19,[2]借方勘定科目!$A$2:$G$1045,2,FALSE)&"","") -> 仮払消費税 | J19: =IF(ISERROR(VLOOKUP(E19&F19,[2]借方勘定科目!$F$2:$G$1045,2,FALSE))=FALSE,VLOOKUP(E19&F19,[2]借方勘定科目!$F$2:$G$1045,2,FALSE)&"","") | K19: 204 | L19: 225 | O19: =IF(ISERROR(VLOOKUP(K19,[2]貸方勘定科目!$A$2:$G$1025,2,FALSE))=FALSE,VLOOKUP(K19,[2]貸方勘定科目!$A$2:$G$1025,2,FALSE)&"","") -> 未払金 | P19: =IF(ISERROR(VLOOKUP(K19&L19,[2]貸方勘定科目!$F$2:$G$1025,2,FALSE))=FALSE,VLOOKUP(K19&L19,[2]貸方勘定科目!$F$2:$G$1025,2,FALSE)&"","") -> JCB | Q19: 250 | R19: 250 | S19: JCB XXXXXXXXXXXXXXXXXXXXXXXXXXXXXXXXX 11/10引 | V19: =Q19-R19 -> 0
I20: =IF(ISERROR(VLOOKUP(E20,[2]借方勘定科目!$A$2:$G$1045,2,FALSE))=FALSE,VLOOKUP(E20,[2]借方勘定科目!$A$2:$G$1045,2,FALSE)&"","") | V20: =Q20-R20 -> 0

Sheet 参照
A1: 数値
A2: ブール値
A3: 文字列
A4: 日付
A5: リスト
A6: 辞書配列
