Workbook
Name CoreCells: 別紙_テンプレート!$A$43:$AC$43
Name CoreCellsRow: 別紙_テンプレート!$39:$73
Name クレーム区分: 別紙_テンプレート!$AB$12
Name 会社担当者: 別紙_テンプレート!$K$16
Name 会社担当者E_mail: 別紙_テンプレート!$K$17
Name 見積金額: 別紙_テンプレート!$D$8
Name 見積件名: 別紙_テンプレート!$D$12
Name 見積日: 別紙_テンプレート!$U$14
Name 見積番号: 別紙_テンプレート!$A$1
Name 見積有効期限: 別紙_テンプレート!$D$16
Name 現場名: 別紙_テンプレート!$U$17
Name 合計金額: 別紙_テンプレート!$D$10
Name 作成日: 別紙_テンプレート!$O$1
Name 支払条件: 別紙_テンプレート!$D$15
Name 受注区分: 別紙_テンプレート!$AB$11
Name 受注先1: 別紙_テンプレート!$U$11
Name 受渡地: 別紙_テンプレート!$D$14
Name 消費税額: 別紙_テンプレート!$D$9
Name 消費税等: 別紙_テンプレート!$A$9
Name 担当者: 別紙_テンプレート!$U$12
Name 担当者名: 別紙_テンプレート!$K$16
Name 店番: 別紙_テンプレート!$G$14
Name 得意先名1: 別紙_テンプレート!$A$3
Name 得意先名2: 別紙_テンプレート!$A$4
Name 納期: 別紙_テンプレート!$D$13
Name 納入先1: 別紙_テンプレート!$U$15
Name 納入先住所1: 別紙_テンプレート!$U$16
Name 備考: 別紙_テンプレート!$D$17

Sheet 変更履歴
B2: システム名 | H2: 画面ID | L2: システム分類 | R2: ドキュメント種別 | X2: ドキュメント名 | AK2: 帳票名 | AX2: 作成日 | BB2: 作成者 | BF2: 更新日 | BJ2: 更新者
B3: 受発注システム | H3: =LEFT($X$3,FIND("_",$X$3)-1) -> MH1100 | L3: 受発注 | R3: =MID($X$3,FIND("_",$X$3,FIND("_",$X$3)+1)+1,LEN($X$3)-FIND("_",$X$3,FIND("_",$X$3)+1)) -> 帳票設計書 | X3: =REPLACE(LEFT(CELL("filename",$B$2),FIND(".x",CELL("filename",$B$2))-1),1,FIND("[",CELL("filename",$B$2)),) -> MH1100_見積書(コーセー専用)_帳票設計書 | AK3: =MID($X$3,FIND("_",$X$3)+1,FIND("_",$X$3,FIND("_",$X$3)+1)-FIND("_",$X$3)-1) -> 見積書(コーセー専用) | AX3: 45581 | BB3: 大谷 | BF3: 45581 | BJ3: 大谷
C7: 変更履歴
C8: 日付 | G8: 版数 | K8: 担当 | O8: 変更箇所 | Y8: 内容
C9: 45581 | G9: 1.0.0 | K9: 大谷 | O9: - | Y9: 新規作成

Sheet 概要
B2: システム名 | H2: 画面ID | L2: システム分類 | R2: ドキュメント種別 | X2: ドキュメント名 | AK2: 帳票名 | AX2: 作成日 | BB2: 作成者 | BF2: 更新日 | BJ2: 更新者
B3: =変更履歴!B3 -> 受発注システム | H3: =変更履歴!H3 -> MH1100 | L3: =変更履歴!L3 -> 受発注 | R3: =変更履歴!R3 -> 帳票設計書 | X3: =変更履歴!X3 -> MH1100_見積書(コーセー専用)_帳票設計書 | AK3: =変更履歴!AK3 -> 見積書(コーセー専用) | AX3: =変更履歴!AX3 -> 45581 | BB3: =変更履歴!BB3 -> 大谷 | BF3: =変更履歴!BF3 -> 45581 | BJ3: =変更履歴!BJ3 -> 大谷
D7: 帳票の名称 | H7: =AK3 -> 見積書(コーセー専用)
D8: 帳票テンプレート名 | H8: Template_見積積算書.xlsx
D9: ファイル種類 | H9: Excel,PDF
D10: ファイル拡張子 | H10: xlsx,pdf
D11: 文字コード | H11: -
D12: コーテーション | H12: -
D13: 固定長/可変長 | H13: -
D14: 区切り文字 | H14: -
D15: 用紙サイズ | H15: A4横
D16: 概要

Sheet 帳票レイアウト
B2: システム名 | H2: 画面ID | L2: システム分類 | R2: ドキュメント種別 | X2: ドキュメント名 | AK2: 帳票名 | AX2: 作成日 | BB2: 作成者 | BF2: 更新日 | BJ2: 更新者
B3: =変更履歴!B3 -> 受発注システム | H3: =変更履歴!H3 -> MH1100 | L3: =変更履歴!L3 -> 受発注 | R3: =変更履歴!R3 -> 帳票設計書 | X3: =変更履歴!X3 -> MH1100_見積書(コーセー専用)_帳票設計書 | AK3: =変更履歴!AK3 -> 見積書(コーセー専用) | AX3: =変更履歴!AX3 -> 45581 | BB3: =変更履歴!BB3 -> 大谷 | BF3: =変更履歴!BF3 -> 45581 | BJ3: =変更履歴!BJ3 -> 大谷
B6: ページ１

Sheet 項目一覧
B2: システム名 | H2: 画面ID | L2: システム分類 | R2: ドキュメント種別 | X2: ドキュメント名 | AK2: 帳票名 | AX2: 作成日 | BB2: 作成者 | BF2: 更新日 | BJ2: 更新者
B3: =変更履歴!B3 -> 受発注システム | H3: =変更履歴!H3 -> MH1100 | L3: =変更履歴!L3 -> 受発注 | R3: =変更履歴!R3 -> 帳票設計書 | X3: =変更履歴!X3 -> MH1100_見積書(コーセー専用)_帳票設計書 | AK3: =変更履歴!AK3 -> 見積書(コーセー専用) | AX3: =変更履歴!AX3 -> 45581 | BB3: =変更履歴!BB3 -> 大谷 | BF3: =変更履歴!BF3 -> 45581 | BJ3: =変更履歴!BJ3 -> 大谷
B7: 項目一覧
C9: 項目 | F9: フォントや文字サイズ、セル条件などは「別紙_テンプレート」準拠
D10: No. | E10: 項目名 | M10: データ型 | P10: 全角/半角 | S10: 文字数/桁数 | V10: データ取得元 | AB10: データ整形方法 | AR10: 整形後フォーマット | AX10: 備考
D11: 1 | E11: 見積番号_見出し | M11: 文字列 | P11: 半角 | S11: 4 | V11: [SQL45.見積番号] | AB11: "No." + [SQL45.見積番号]
D12: 2 | E12: 作成日 | M12: 日付 | P12: 半角 | S12: 8 | V12: [SQL45.見積日出力],[SQL45.見積日付] | AB12: [SQL45.見積日出力]が1の場合[SQL45.見積日付]を表示 | AR12: 9999年99月99日
D13: 3 | E13: 得意先名1 | M13: 文字列 | P13: 全角 | S13: 17 | V13: [SQL45.得意先名1],[SQL45.得意先名2] | AB13: [SQL45.得意先名2]が空の場合は何も表示しない、空でない場合は[SQL45.得意先名1]を表示。
D14: 4 | E14: 得意先名2 | M14: 文字列 | P14: 全角 | S14: 縮小して全体表示 | V14: [SQL45.得意先名1],[SQL45.得意先名2] | AB14: [SQL45.得意先名2]が空の場合は[SQL45.得意先名1]、空でない場合は[SQL45.得意先名2]を表示。
D15: 5 | E15: 御見積金額 | M15: 数値 | P15: 半角 | S15: 13 | V15: [SQL45.合計金額],[SQL45.出精値引] | AB15: [SQL45.合計金額]と[SQL45.出精値引]の合計。 | AR15: \9,999-
D16: 6 | E16: 消費税等 | M16: 文字列 | P16: 全角 | S16: 8 | V16: [SQL45.見積日付],[TM税率.切替日付],[TM税率.税率],[TM税率.旧税率] | AB16: [SQL45.見積日付] >= [TM税率.切替日付]の場合は[TM税率.税率]、 [SQL45.見積日付] < [TM税率.切替日付]の場合は[TM税率.旧税率]を[税率]とする。 "消費税等(" + [税率] + "%)"で表示。
D17: 7 | E17: 消費税額 | M17: 数値 | P17: 半角 | S17: 13 | V17: [SQL45.外税額] | AR17: \9,999-
D18: 8 | E18: 合計 | M18: 数値 | P18: 半角 | S18: 13 | V18: [5.御見積金額],[7.消費税額] | AB18: [5.御見積金額]と[7.消費税額]の合計。 | AR18: \9,999-
D19: 9 | E19: 件名 | M19: 文字列 | P19: 全角 | S19: 縮小して全体表示 | V19: [SQL45.見積件名]
D20: 10 | E20: 納期_見出し | M20: 文字列 | P20: 全角 | S20: 縮小して全体表示 | V20: [SQL45.納期表示],[SQL45.納期S],[SQL45.納期E],[SQL45.納期その他] | AB20: [SQL45.納期表示]が0のとき[SQL45.納期S]と[SQL45.納期E]がどちらもnullでない場合は[SQL45.納期S] + "～" + [SQL45.納期E]を表示、どちらか片方がnullでない場合はnullでないものを表示、どちらもnullの場合は何も表示しない。 [SQL45.納期表示]が1の場合は"別途御打ち合せによる"、2の場合は[SQL45.納期その他]を表示。
D21: 11 | E21: 受渡地 | M21: 文字列 | P21: 全角 | S21: 縮小して全体表示 | V21: [SQL45.納入得意先CD],[SQL45.現場名],[SQL45.納入先CD] | AB21: [SQL45.納入得意先CD]が"2401","8001"の場合は[SQL45.現場名]に対して[SQL45.納入先CD]文字を""に置き換えた値、そうでない場合は[SQL45.現場名]を表示。
D22: 12 | E22: 店番 | M22: 文字列 | P22: 半角 | S22: 縮小して全体表示 | V22: [SQL45.納入得意先CD],[SQL45.納入先CD] | AB22: [SQL45.納入得意先CD]が"2401","8001"の場合は[SQL45.納入先CD]、そうでない場合は何も表示しない。
D23: 13 | E23: 御支払条件 | M23: 文字列 | P23: 全角 | S23: 縮小して全体表示 | V23: [SQL45.支払条件],[SQL45.支払条件その他] | AB23: [SQL45.支払条件]が0の場合は"別途御打ち合せによる"、1の場合は[SQL45.支払条件その他]
D24: 14 | E24: 見積有効期限 | M24: 文字列 | P24: 全角 | S24: 縮小して全体表示 | V24: SQL45.有効期限] | AB24: [SQL45.有効期限]が0でない場合は[SQL45.有効期限] + "日"で表示。
D25: 15 | E25: 備考 | M25: 文字列 | P25: 全角 | S25: 縮小して全体表示 | V25: [SQL45.備考]
D26: 16 | E26: 売場面積 | M26: 文字列 | P26: 全角 | S26: 9 | V26: [SQL45.ウエルシア売場面積] | AB26: [SQL45.ウエルシア売場面積]が0でない場合は"売 場 面 積 ："を表示。
D27: 17 | E27: ウエルシア売場面積 | M27: 文字列 | P27: 全角 | S27: 10 | V27: [SQL45.ウエルシア売場面積] | AB27: [SQL45.ウエルシア売場面積]が0でない場合は[SQL45.ウエルシ売場面積] + "坪"を表示。
D28: 18 | E28: 郵便番号 | M28: 数値 | P28: 半角 | S28: 7 | V28: [TM会社.郵便番号]
D29: 19 | E29: 住所 | M29: 文字列 | P29: 全角 | S29: 41 | V29: [TM会社.住所1]
D30: 20 | E30: TEL | M30: 数値 | P30: 半角 | S30: 11 | V30: [TM会社.電話番号]
D31: 21 | E31: FAX | M31: 数値 | P31: 半角 | S31: 11 | V31: [TM会社.FAX番号]
D32: 21 | E32: コールセンター | M32: 数値 | P32: 半角 | S32: 11 | V32: [TM会社.コールセンター番号]
D33: 23 | E33: 会社担当者 | M33: 文字列 | P33: 全角 | S33: 20 | V33: [SQL45.問い合わせ先] | AB33: [SQL45.問い合わせ先]が空の場合は何も表示しない | AR33: 問い合わせ先：[TM担当者.問い合わせ先] | AX33: cTanto.GetbyID
D34: 24 | E34: 会社担当者E-mail | M34: 文字列 | P34: 半角 | S34: 41 | V34: 空
D35: 25 | E35: (単位：円) | M35: 文字列 | P35: 全角 | S35: 6 | V35: "(単位：円)"
D36: 26 | E36: SEC | M36: 文字列 | P36: 半角 | S36: 4 | V36: [SQL46.仕分番号] | AB36: [TD見積シート内訳.仕分番号]のデータ型をVARCHAR(2)に変換し、"0"と結合した後に末尾2文字を取得する
D37: 27 | E37: 項目 | M37: 文字列 | P37: 半角 | S37: 4 | V37: [SQL48.見積区分],[SQL48.行番号] | AB37: [SQL48.見積区分]が"C"か"A"か"S"の場合は""、それ以外の場合は[SQL48.行番号]を表示
D38: 28 | E38: 品名_1 | M38: 文字列 | P38: 全角 | S38: 縮小して全体表示 | V38: [SQL48.見積区分],[SQL48.漢字名称] | AB38: [SQL48.見積区分]が"C"か"A"か"S"の場合は半角スペース2つ + [SQL48.漢字名称]、それ以外の場合は[SQL48.漢字名称]のみ表示
D39: 29 | E39: 製品 | M39: 文字列 | P39: 半角 | S39: 10 | V39: [SQL48.PC区分],[SQL48.製品NO] | AB39: [SQL48.PC区分] + [SQL48.製品NO]で表示
D40: 30 | E40: 仕様 | M40: 文字列 | P40: 半角 | S40: 10 | V40: [SQL48.仕様NO]
D41: 31 | E41: W | M41: 文字列 | P41: 半角 | S41: 9 | V41: [SQL48.W]
D42: 32 | E42: D | M42: 文字列 | P42: 半角 | S42: 9 | V42: [SQL48.D],[SQL48.D1],[SQL48.D2] | AB42: [SQL48.D]が0でない場合は[SQL48.D]を表示。 [SQL48.D]が0で[SQL48.D1]と[SQL48.D2]が0でない場合は[SQL48.D1] + "/" [SQL48.D2]を表示。すべて0の場合は何も表示しない。
D43: 33 | E43: H | M43: 文字列 | P43: 半角 | S43: 9 | V43: [SQL48.H],[SQL48.H1],[SQL48.H2] | AB43: [SQL48.H]が0でない場合は[SQL48.H]を表示。 [SQL48.H]が0で[SQL48.H1]と[SQL48.H2]が0でない場合は[SQL48.H1] + "/" [SQL48.H2]を表示。すべて0の場合は何も表示しない。
D44: 34 | E44: 数量_元 | M44: 数値 | P44: 半角 | S44: 6 | V44: [SQL48.数量]
D45: 35 | E45: 数量 | M45: 数値 | P45: 半角 | S45: 9 | V45: [33.数量_元] | AB45: [33.数量_元]が整数の場合は1の位まで表示、小数の場合は小数点第2位まで表示 | AR45: 9,999 or 9,999.99
D46: 36 | E46: 単位 | M46: 文字列 | P46: 全角 | S46: 3 | V46: [SQL48.単位名]
D47: 37 | E47: 単価_元 | M47: 数値 | P47: 半角 | S47: 6 | V47: [画面.書式区分],[SQL48.売上単価] | AB47: [画面.書式区分]が1以外の場合は[SQL48.売上単価]を表示、それ以外の場合は何も表示しない。
D48: 38 | E48: 単価 | M48: 数値 | P48: 半角 | S48: 12 | V48: [36.単価_元] | AB48: [32.単価_元]が整数の場合は1の位まで表示、小数の場合は小数点第2位まで表示 | AR48: 9,999 or 9,999.99
D49: 39 | E49: 金額 | M49: 数値 | P49: 半角 | S49: 12 | V49: [TD見積.売上端数],[TD見積シート内訳.数量],[TD見積シートM.売上単価][画面.書式区分],[TD見積シートM.見積区分],[SQL48.売上金額] | AB49: [TD見積シート内訳.数量]と[TD見積シートM.売上単価]をかけ、[TD見積.売上端数]が0の場合は四捨五入、1の場合は切り上げ、2の場合は切り捨てを行ったものを[売上金額]とする。 [画面.書式区分]が1以外かつ[TD見積シートM.見積区分]が"A","C","S"のいずれにも該当しない場合は[売上金額]を表示。 [画面.書式区分]が1以外かつ[TD見積シートM.見積区分]が"A","C","S"のいずれかに該当する場合は[売上金額]が0であれば何も表示しない、0でなければ[売上金額]を表示。 上記以外の場合は何も表示しない。 | AR49: 9999 | AX49: マイナスの値の場合は赤字で表示
D50: 40 | E50: 【合計】_1 | M50: 文字列 | P50: 全角 | S50: 縮小して全体表示 | V50: [SQL48仕分名称] | AB50: 17行目でまだデータが存在する場合、"次ページへ"を表示、 データ最終行の場合は"【合 計】"を表示、 最終行ではなくページの終わりの場合は"【" & [SQL48仕分名称] & "小計】"を表示。 | AR50: 1行空けて表示
D51: 41 | E51: 金額合計 | P51: 半角 | S51: 12 | V51: [34.金額] | AB51: [34.金額]の合計

Sheet 処理詳細
B2: システム名 | H2: 画面ID | L2: システム分類 | R2: ドキュメント種別 | X2: ドキュメント名 | AK2: 帳票名 | AX2: 作成日 | BB2: 作成者 | BF2: 更新日 | BJ2: 更新者
B3: =変更履歴!B3 -> 受発注システム | H3: =変更履歴!H3 -> MH1100 | L3: =変更履歴!L3 -> 受発注 | R3: =変更履歴!R3 -> 帳票設計書 | X3: =変更履歴!X3 -> MH1100_見積書(コーセー専用)_帳票設計書 | AK3: =変更履歴!AK3 -> 見積書(コーセー専用) | AX3: =変更履歴!AX3 -> 45581 | BB3: =変更履歴!BB3 -> 大谷 | BF3: =変更履歴!BF3 -> 45581 | BJ3: =変更履歴!BJ3 -> 大谷
B6: SQL1 | H6: select | J6: 見積番号 | R6: TD見積.見積番号
J7: 見積件名 | R7: TD見積.見積件名
J8: 得意先名1 | R8: TD見積.得意先名1
J9: 得意先名2 | R9: TD見積.得意先名2
J10: 現場名 | R10: TD見積.現場名
J11: 納期S | R11: TD見積.納期S
J12: 納期E | R12: TD見積.納期E
J13: 原価率 | R13: TD見積.原価率
J14: 担当者CD | R14: TD見積.担当者CD
H15: from | J15: From TD見積
H16: where | J16: WHERE 見積番号 = 画面.見積番号
B17: SQL2 | H17: select | J17: CreateDate | R17: TW見積出力履歴.CreateDate
J18: PCName | R18: TW見積出力履歴.PCName
H19: from | J19: From TW見積出力履歴
H20: where | J20: WHERE ListName = 見積書
J21: AND Number = 画面.見積番号
B22: SQL3 | H22: select | J22: @decimalPoint | R22: CASE WHEN COUNTRY_CODE = 'CN' THEN 2 ELSE 0 END
H23: from | J23: FROM AppCountry
B24: SQL4 | H24: select | J24: 番号 | AK24: 見積出力用データ作成 | AP24: SELECT * INTO #WK見積明細
J25: 見積番号
J26: 仕分番号
J27: 仕分名称
J28: 行番号
J29: SP区分
J30: PC区分
J31: 製品NO
J32: 仕様NO
J33: 漢字名称
J34: W
J35: D
J36: H
... J58: 見積区分
H59: from | J59: FROM (
J60: SQL5
J61: UNION ALL
J62: SQL6
J63: UNION ALL
J64: SQL8
J65: UNION ALL
J66: SQL10
J67: UNION ALL
J68: SQL11
J69: UNION ALL
J70: SQL14
J71: UNION ALL
... J73: ) AS 見積明細
B74: SQL5 | H74: select | J74: 番号 | R74: 1 | AK74: コメントでないもの
J75: 見積番号 | R75: TD見積.見積番号
J76: 仕分番号 | R76: RIGHT('0'+CONVERT(VARCHAR(2),TD見積シート内訳.仕分番号),2) AS 仕分番号
J77: 仕分名称 | R77: ISNULL(TD見積シート内訳名称.名称,'') AS 仕分名称
J78: 行番号 | R78: TD見積シートM.行番号
J79: SP区分 | R79: TD見積シートM.SP区分
J80: PC区分 | R80: TD見積シートM.PC区分
J81: 製品NO | R81: TD見積シートM.製品NO
J82: 仕様NO | R82: TD見積シートM.仕様NO
J83: 漢字名称 | R83: TD見積シートM.漢字名称
J84: W | R84: TD見積シートM.W
J85: D | R85: TD見積シートM.D
J86: H | R86: TD見積シートM.H
... J93: 売上単価 | R93: TD見積シートM.売上単価
J94: 売上金額 | R94: TD見積.売上端数が0の場合TD見積シート内訳.数量 * TD見積シートM.売上単価の結果をSQL3.@decimalPointの桁数に四捨五入、1の場合切り上げ、2の場合切り捨て | AK94: dbo.fn_CutFraction(TD見積.売上端数,TD見積シート内訳.数量 * TD見積シートM.売上単価,@decimalPoint) AS 売上金額
J95: 仕入先CD | R95: TD見積シートM.仕入先CD
J96: 仕入先略称 | R96: TD見積シートM.仕入先名 AS 仕入先略称
J97: 仕入単価 | R97: TD見積シートM.仕入単価
J98: 仕入金額 | R98: TD見積.売上端数が0の場合TD見積シート内訳.数量 * TD見積シートM.仕入単価の結果をSQL3.@decimalPointの桁数に四捨五入、1の場合切り上げ、2の場合切り捨て | AK98: dbo.fn_CutFraction(TD見積.売上端数,TD見積シート内訳.数量 * TD見積シートM.仕入単価,@decimalPoint) AS 仕入金額
J99: 原価率 | R99: 0 AS 原価率
J100: 粗利益 | R100: 0 AS 粗利益
J101: 配送先CD | R101: TD見積シートM.配送先CD
J102: 配送先略称 | R102: TD見積シートM.配送先名 AS 配送先略称
J103: 社内在庫数 | R103: TD見積シートM.社内在庫数
J104: 客先在庫数 | R104: TD見積シートM.客先在庫数
J105: 転用数 | R105: TD見積シートM.転用数
J106: 発注数 | R106: TD見積シートM.発注数
J107: 製品区分 | R107: TD見積シートM.製品区分
J108: 見積区分 | R108: TD見積シートM.見積区分
H109: from | J109: FROM TD見積 AS MH
H110: join | J110: INNER JOIN TD見積シートM AS MSM ON MSM.見積番号 = MH.見積番号
J111: INNER JOIN TD見積シート内訳 AS MSU ON MSM.見積明細連番 = MSU.見積明細連番
J112: LEFT JOIN TD見積シート内訳名称 MSUN ON MSU.見積番号 = MSUN.見積番号
K113: AND MSU.仕分番号 = MSUN.仕分番号
H114: where | J114: WHERE MH.見積番号 = 画面.見積番号
J115: AND MSM.見積区分 IN ('','1','2','3','4','5','6','7','8','9')
J116: AND MSU.数量 <> 0
B117: SQL6 | H117: select | J117: 番号 | R117: 1 | AK117: コメントAのもの
J118: 見積番号 | R118: TD見積.見積番号
J119: 仕分番号 | R119: RIGHT('0'+CONVERT(VARCHAR(2),TD見積シート内訳.仕分番号),2) AS 仕分番号
J120: 仕分名称 | R120: ISNULL(TD見積シート内訳名称.名称,'') AS 仕分名称
J121: 行番号 | R121: TD見積シートM.行番号
J122: SP区分 | R122: TD見積シートM.SP区分
J123: PC区分 | R123: TD見積シートM.PC区分
J124: 製品NO | R124: TD見積シートM.製品NO
J125: 仕様NO | R125: TD見積シートM.仕様NO
J126: 漢字名称 | R126: TD見積シートM.漢字名称
J127: W | R127: TD見積シートM.W
J128: D | R128: TD見積シートM.D
J129: H | R129: TD見積シートM.H
... J136: 売上単価 | R136: TD見積シートM.売上単価
J137: 売上金額 | R137: TD見積.売上端数が0の場合TD見積シート内訳.数量 * TD見積シートM.売上単価の結果をSQL3.@decimalPointの桁数に四捨五入、1の場合切り上げ、2の場合切り捨て | AK137: dbo.fn_CutFraction(TD見積.売上端数,TD見積シート内訳.数量 * TD見積シートM.売上単価,@decimalPoint) AS 売上金額
...

Sheet 確認事項
B2: 確認事項
B3: No. | C3: シート名 | D3: タイトル | E3: 概要 | F3: 回答 | G3: 確認済
B4: 1 | E4: 通常の見積書とテンプレートは同じでDBから取得するデータ条件のみ異なる認識で合っているか。 | F4: 合っている | G4: 〇 | H4: 左記のとおり。
B5: 2
B6: 3
B7: 4
B8: 5
B9: 6
B10: 7
B11: 8
B12: 9
B13: 10
B14: 11
B15: 12
B16: 13
... B54: 51

Sheet 別紙_テンプレート
E1: 御 見 積 書
A6: 下記の通り御見積り申し上げます。
A8: 御見積金額
A9: 消費税等(10%)
A10: 合計 | D10: =SUM(D8+D9) -> 0 | K10: 〒360-0012
K11: 埼玉県熊谷市上之2919-5
A12: 件 名 ： | K12: TEL 048-525-1171㈹
A13: 納 期 ： | K13: FAX 048-525-0008
A14: 受 渡 地 ：
A15: 御支払条件 ： | K15: コールセンター：048-507-1130
A16: 見積有効期限： | K16: 問い合わせ先：蓮見 明
A17: 備 考 ： | K17: E-mail:xxxxx@sanwashouken.co.jp
O19: (単位：円)
A20: SEC | B20: 項目 | C20: 品名 | E20: 製品 | F20: 仕様 | G20: Ｗ | H20: Ｄ | I20: Ｈ | K20: 数量 | L20: 単位 | N20: 単価 | O20: 金額
K21: =IF(MOD(J21,1)=0,TEXT(J21,"#,###"),TEXT(J21,"#,##0.##")) | N21: =IF(MOD(M21,1)=0,TEXT(M21,"#,###"),TEXT(M21,"#,##0.##"))
K22: =IF(MOD(J22,1)=0,TEXT(J22,"#,###"),TEXT(J22,"#,##0.##")) | N22: =IF(MOD(M22,1)=0,TEXT(M22,"#,###"),TEXT(M22,"#,##0.##"))
K23: =IF(MOD(J23,1)=0,TEXT(J23,"#,###"),TEXT(J23,"#,##0.##")) | N23: =IF(MOD(M23,1)=0,TEXT(M23,"#,###"),TEXT(M23,"#,##0.##"))
K24: =IF(MOD(J24,1)=0,TEXT(J24,"#,###"),TEXT(J24,"#,##0.##")) | N24: =IF(MOD(M24,1)=0,TEXT(M24,"#,###"),TEXT(M24,"#,##0.##"))
K25: =IF(MOD(J25,1)=0,TEXT(J25,"#,###"),TEXT(J25,"#,##0.##")) | N25: =IF(MOD(M25,1)=0,TEXT(M25,"#,###"),TEXT(M25,"#,##0.##"))
K26: =IF(MOD(J26,1)=0,TEXT(J26,"#,###"),TEXT(J26,"#,##0.##")) | N26: =IF(MOD(M26,1)=0,TEXT(M26,"#,###"),TEXT(M26,"#,##0.##"))
K27: =IF(MOD(J27,1)=0,TEXT(J27,"#,###"),TEXT(J27,"#,##0.##")) | N27: =IF(MOD(M27,1)=0,TEXT(M27,"#,###"),TEXT(M27,"#,##0.##"))
K28: =IF(MOD(J28,1)=0,TEXT(J28,"#,###"),TEXT(J28,"#,##0.##")) | N28: =IF(MOD(M28,1)=0,TEXT(M28,"#,###"),TEXT(M28,"#,##0.##"))
K29: =IF(MOD(J29,1)=0,TEXT(J29,"#,###"),TEXT(J29,"#,##0.##")) | N29: =IF(MOD(M29,1)=0,TEXT(M29,"#,###"),TEXT(M29,"#,##0.##"))
K30: =IF(MOD(J30,1)=0,TEXT(J30,"#,###"),TEXT(J30,"#,##0.##")) | N30: =IF(MOD(M30,1)=0,TEXT(M30,"#,###"),TEXT(M30,"#,##0.##"))
K31: =IF(MOD(J31,1)=0,TEXT(J31,"#,###"),TEXT(J31,"#,##0.##")) | N31: =IF(MOD(M31,1)=0,TEXT(M31,"#,###"),TEXT(M31,"#,##0.##"))
K32: =IF(MOD(J32,1)=0,TEXT(J32,"#,###"),TEXT(J32,"#,##0.##")) | N32: =IF(MOD(M32,1)=0,TEXT(M32,"#,###"),TEXT(M32,"#,##0.##"))
... K38: =IF(MOD(J38,1)=0,TEXT(J38,"#,###"),TEXT(J38,"#,##0.##")) | N38: =IF(MOD(M38,1)=0,TEXT(M38,"#,###"),TEXT(M38,"#,##0.##"))
O40: (単位：円)
A41: SEC | B41: 項目 | C41: 品名 | E41: 製品 | F41: 仕様 | G41: Ｗ | H41: Ｄ | I41: Ｈ | K41: 数量 | L41: 単位 | N41: 単価 | O41: 金額
K42: =IF(MOD(J42,1)=0,TEXT(J42,"#,###"),TEXT(J42,"#,##0.##")) | N42: =IF(MOD(M42,1)=0,TEXT(M42,"#,###"),TEXT(M42,"#,##0.##"))
K43: =IF(MOD(J43,1)=0,TEXT(J43,"#,###"),TEXT(J43,"#,##0.##")) | N43: =IF(MOD(M43,1)=0,TEXT(M43,"#,###"),TEXT(M43,"#,##0.##"))
K44: =IF(MOD(J44,1)=0,TEXT(J44,"#,###"),TEXT(J44,"#,##0.##")) | N44: =IF(MOD(M44,1)=0,TEXT(M44,"#,###"),TEXT(M44,"#,##0.##"))
K45: =IF(MOD(J45,1)=0,TEXT(J45,"#,###"),TEXT(J45,"#,##0.##")) | N45: =IF(MOD(M45,1)=0,TEXT(M45,"#,###"),TEXT(M45,"#,##0.##"))
K46: =IF(MOD(J46,1)=0,TEXT(J46,"#,###"),TEXT(J46,"#,##0.##")) | N46: =IF(MOD(M46,1)=0,TEXT(M46,"#,###"),TEXT(M46,"#,##0.##"))
K47: =IF(MOD(J47,1)=0,TEXT(J47,"#,###"),TEXT(J47,"#,##0.##")) | N47: =IF(MOD(M47,1)=0,TEXT(M47,"#,###"),TEXT(M47,"#,##0.##"))
K48: =IF(MOD(J48,1)=0,TEXT(J48,"#,###"),TEXT(J48,"#,##0.##")) | N48: =IF(MOD(M48,1)=0,TEXT(M48,"#,###"),TEXT(M48,"#,##0.##"))
K49: =IF(MOD(J49,1)=0,TEXT(J49,"#,###"),TEXT(J49,"#,##0.##")) | N49: =IF(MOD(M49,1)=0,TEXT(M49,"#,###"),TEXT(M49,"#,##0.##"))
K50: =IF(MOD(J50,1)=0,TEXT(J50,"#,###"),TEXT(J50,"#,##0.##")) | N50: =IF(MOD(M50,1)=0,TEXT(M50,"#,###"),TEXT(M50,"#,##0.##"))
K51: =IF(MOD(J51,1)=0,TEXT(J51,"#,###"),TEXT(J51,"#,##0.##")) | N51: =IF(MOD(M51,1)=0,TEXT(M51,"#,###"),TEXT(M51,"#,##0.##"))
K52: =IF(MOD(J52,1)=0,TEXT(J52,"#,###"),TEXT(J52,"#,##0.##")) | N52: =IF(MOD(M52,1)=0,TEXT(M52,"#,###"),TEXT(M52,"#,##0.##"))
K53: =IF(MOD(J53,1)=0,TEXT(J53,"#,###"),TEXT(J53,"#,##0.##")) | N53: =IF(MOD(M53,1)=0,TEXT(M53,"#,###"),TEXT(M53,"#,##0.##"))
... K73: =IF(MOD(J73,1)=0,TEXT(J73,"#,###"),TEXT(J73,"#,##0.##")) | N73: =IF(MOD(M73,1)=0,TEXT(M73,"#,###"),TEXT(M73,"#,##0.##"))

Sheet 別紙_印刷レイアウト

Sheet 参照
A1: 数値
A2: ブール値
A3: 文字列
A4: 日付
A5: リスト
A6: 辞書配列
