Workbook

Sheet 変更履歴
B2: システム名 | H2: 画面ID | L2: システム分類 | R2: ドキュメント種別 | X2: ドキュメント名 | AK2: 帳票名 | AX2: 作成日 | BB2: 作成者 | BF2: 更新日 | BJ2: 更新者
B3: 受発注システム | H3: =LEFT($X$3,FIND("_",$X$3)-1) -> SS0700 | L3: 受発注 | R3: =MID($X$3,FIND("_",$X$3,FIND("_",$X$3)+1)+1,LEN($X$3)-FIND("_",$X$3,FIND("_",$X$3)+1)) -> 帳票設計書 | X3: =REPLACE(LEFT(CELL("filename",$B$2),FIND(".x",CELL("filename",$B$2))-1),1,FIND("[",CELL("filename",$B$2)),) -> SS0700_支払取込エラーリスト_帳票設計書 | AK3: =MID($X$3,FIND("_",$X$3)+1,FIND("_",$X$3,FIND("_",$X$3)+1)-FIND("_",$X$3)-1) -> 支払取込エラーリスト | AX3: 45583 | BB3: 大谷 | BF3: 45583 | BJ3: 大谷
C7: 変更履歴
C8: 日付 | G8: 版数 | K8: 担当 | O8: 変更箇所 | Y8: 内容
C9: 45583 | G9: 1.0.0 | K9: 大谷 | O9: - | Y9: 新規作成

Sheet 概要
B2: システム名 | H2: 画面ID | L2: システム分類 | R2: ドキュメント種別 | X2: ドキュメント名 | AK2: 帳票名 | AX2: 作成日 | BB2: 作成者 | BF2: 更新日 | BJ2: 更新者
B3: =変更履歴!B3 -> 受発注システム | H3: =変更履歴!H3 -> SS0700 | L3: =変更履歴!L3 -> 受発注 | R3: =変更履歴!R3 -> 帳票設計書 | X3: =変更履歴!X3 -> SS0700_支払取込エラーリスト_帳票設計書 | AK3: =変更履歴!AK3 -> 支払取込エラーリスト | AX3: =変更履歴!AX3 -> 45583 | BB3: =変更履歴!BB3 -> 大谷 | BF3: =変更履歴!BF3 -> 45583 | BJ3: =変更履歴!BJ3 -> 大谷
D7: 帳票の名称 | H7: =AK3 -> 支払取込エラーリスト
D8: 帳票テンプレート名 | H8: -
D9: ファイル種類 | H9: PDF
D10: ファイル拡張子 | H10: pdf
D11: 文字コード | H11: -
D12: コーテーション | H12: -
D13: 固定長/可変長 | H13: -
D14: 区切り文字 | H14: -
D15: 用紙サイズ | H15: A4縦
D16: 概要

Sheet 帳票レイアウト
B2: システム名 | H2: 画面ID | L2: システム分類 | R2: ドキュメント種別 | X2: ドキュメント名 | AK2: 帳票名 | AX2: 作成日 | BB2: 作成者 | BF2: 更新日 | BJ2: 更新者
B3: =変更履歴!B3 -> 受発注システム | H3: =変更履歴!H3 -> SS0700 | L3: =変更履歴!L3 -> 受発注 | R3: =変更履歴!R3 -> 帳票設計書 | X3: =変更履歴!X3 -> SS0700_支払取込エラーリスト_帳票設計書 | AK3: =変更履歴!AK3 -> 支払取込エラーリスト | AX3: =変更履歴!AX3 -> 45583 | BB3: =変更履歴!BB3 -> 大谷 | BF3: =変更履歴!BF3 -> 45583 | BJ3: =変更履歴!BJ3 -> 大谷
B6: ページ１

Sheet 項目一覧
B2: システム名 | H2: 画面ID | L2: システム分類 | R2: ドキュメント種別 | X2: ドキュメント名 | AK2: 帳票名 | AX2: 作成日 | BB2: 作成者 | BF2: 更新日 | BJ2: 更新者
B3: =変更履歴!B3 -> 受発注システム | H3: =変更履歴!H3 -> SS0700 | L3: =変更履歴!L3 -> 受発注 | R3: =変更履歴!R3 -> 帳票設計書 | X3: =変更履歴!X3 -> SS0700_支払取込エラーリスト_帳票設計書 | AK3: =変更履歴!AK3 -> 支払取込エラーリスト | AX3: =変更履歴!AX3 -> 45583 | BB3: =変更履歴!BB3 -> 大谷 | BF3: =変更履歴!BF3 -> 45583 | BJ3: =変更履歴!BJ3 -> 大谷
B7: 項目一覧
C9: 項目 | F9: フォントや文字サイズ、セル条件などは「別紙_テンプレート」準拠
D10: No. | E10: 項目名 | M10: データ型 | P10: 全角/半角 | S10: 文字数/桁数 | V10: データ取得元 | AB10: データ整形方法 | AR10: 整形後フォーマット | AX10: 備考
D11: 1 | E11: tx_ope 作成日 | M11: 日付 | P11: 半角 | V11: 当日日付 | AR11: yyyy年mm月dd日
D12: 2 | E12: tx_経費日付 支払日付 | M12: 日付 | P12: 半角 | V12: 取込CSV.2列目 | AR12: yyyy/mm/dd
D13: 3 | E13: tx_科目CD 仕入先CD | M13: 数値 | P13: 半角 | V13: 取込CSV.1列目
D14: 4 | E14: tx_金額 支払金額 | M14: 数値 | P14: 半角 | V14: 取込CSV.3列目
D15: 5 | E15: tx_摘要 摘要名 | M15: 文字列 | P15: 全角 | V15: SQL1.略称

Sheet 処理詳細
B2: システム名 | H2: 画面ID | L2: システム分類 | R2: ドキュメント種別 | X2: ドキュメント名 | AK2: 帳票名 | AX2: 作成日 | BB2: 作成者 | BF2: 更新日 | BJ2: 更新者
B3: =変更履歴!B3 -> 受発注システム | H3: =変更履歴!H3 -> SS0700 | L3: =変更履歴!L3 -> 受発注 | R3: =変更履歴!R3 -> 帳票設計書 | X3: =変更履歴!X3 -> SS0700_支払取込エラーリスト_帳票設計書 | AK3: =変更履歴!AK3 -> 支払取込エラーリスト | AX3: =変更履歴!AX3 -> 45583 | BB3: =変更履歴!BB3 -> 大谷 | BF3: =変更履歴!BF3 -> 45583 | BJ3: =変更履歴!BJ3 -> 大谷
B6: SQL1 | H6: select | J6: 仕入先CD | R6: TM仕入先.仕入先CD | AK6: select * from TM仕入先
J7: 初期登録日 | R7: TM仕入先.初期登録日
J8: 仕入先名1 | R8: TM仕入先.仕入先名1
J9: 仕入先名2 | R9: TM仕入先.仕入先名2
J10: 略称 | R10: TM仕入先.略称
J11: フリガナ | R11: TM仕入先.フリガナ
J12: 郵便番号 | R12: TM仕入先.郵便番号
J13: 住所1 | R13: TM仕入先.住所1
J14: 住所2 | R14: TM仕入先.住所2
J15: 電話番号 | R15: TM仕入先.電話番号
J16: FAX番号 | R16: TM仕入先.FAX番号
J17: 仕入先担当者名 | R17: TM仕入先.仕入先担当者名
J18: 担当者CD | R18: TM仕入先.担当者CD
... J34: 登録変更日 | R34: TM仕入先.登録変更日
H35: from | J35: FROM TM仕入先
H36: where | J36: WHERE 仕入先CD = [取込CSV.1列目]

Sheet 処理詳細_書き方
B2: システム名 | H2: 画面ID | L2: 業務分類 | R2: ドキュメント種別 | X2: ドキュメント名 | AK2: 帳票名 | AX2: 作成日 | BB2: 作成者 | BF2: 更新日 | BJ2: 更新者
B3: =変更履歴!B3 -> 受発注システム | H3: =変更履歴!H3 -> SS0700 | L3: =変更履歴!L3 -> 受発注 | R3: =変更履歴!R3 -> 帳票設計書 | X3: =変更履歴!X3 -> SS0700_支払取込エラーリスト_帳票設計書 | AK3: =変更履歴!AK3 -> 支払取込エラーリスト | AX3: =変更履歴!AX3 -> 45583 | BB3: =変更履歴!BB3 -> 大谷 | BF3: =変更履歴!BF3 -> 45583 | BJ3: =変更履歴!BJ3 -> 大谷
B7: 1.タイトルを記載 | H7: select | J7: 項目名 | R7: 格納テーブル
J8: 仕入先CD | R8: VM支払予定情報.仕入先CD
J9: 仕入先名1 | R9: VM支払予定情報.仕入先名1
H10: from | J10: 使用するテーブル名を記載
J11: TD売上請求H
J12: TD見積
J13: TM納入先
H14: join | J14: 結合方式
K15: 結合テーブル名
M16: 結合条件
L17: and | M17: 結合条件
L18: or | M18: 結合条件
J19: INNER JOIN
K20: TM納入先
M21: [TD見積.納入得意先CD] = [TM納入先.得意先CD]
L22: and | M22: [TD見積.納入先CD] = [TM納入先.納入先CD]
H23: where | K23: 取得条件 | AK23: パラメータの意味が分かる場合は記載する
J24: and | K24: 取得条件
J25: or | K25: 取得条件
J26: ※可能な限り日本語化する
K27: [TD見積.得意先CD] = '8001' | AK27: 8001'はヤオコーの得意先CD
J28: and | K28: [TD売上請求H.請求日付]が[画面.請求期間From]以降
H32: order by | J32: ソート条件を記載
J33: [画面.iYK物件区分]が1の場合は[TD見積.納入得意先CD],[TD見積.納入先CD],[TD売上請求H.見積番号]を昇順でソート
H36: group byなどほかの条件がある場合は行を追加して記載

Sheet 確認事項
B2: 確認事項
B3: No. | C3: シート名 | D3: 概要 | E3: 確認済
B4: 1 | C4: エラー条件 | D4: エラー条件の認識合わせ | E4: 〇
B5: 2
B6: 3
B7: 4
B8: 5
B9: 6
B10: 7
B11: 8
B12: 9
B13: 10
B14: 11
B15: 12
B16: 13
... B54: 51

Sheet 新規レイアウト
A1: 取込エラーリスト | C1: 作成日: | D1: Page: /
A3: 日付 | B3: 仕入先CD | C3: 金額 | D3: 摘要
A4: 9999/99/99 | B4: 9999 | C4: 12345678901 | D4: WWWWWWWWWWWWWWWWWW

Sheet 旧レイアウト

Sheet エラー条件
A1: 支払取込エラー条件
F2: 仕入先CD | G2: 支払日付 | I2: 支払金額
B3: No. | C3: 項目 | D3: エラー条件
B4: 1 | C4: 仕入先CD | D4: 空
B5: 2 | C5: 仕入先CD | D5: TM仕入先.仕入先CDに存在しないCD
B6: 3 | C6: 支払日付 | D6: 空
B7: 4 | C7: 支払日付 | D7: 実在しない日付
B8: 5 | C8: 支払金額 | D8: 空 or 0未満(マイナスの値)

Sheet 別紙_印刷レイアウト

Sheet 参照
A1: 数値
A2: ブール値
A3: 文字列
A4: 日付
A5: リスト
A6: 辞書配列
