Workbook

Sheet 変更履歴
B2: システム名 | H2: 画面ID | L2: システム分類 | R2: ドキュメント種別 | X2: ドキュメント名 | AK2: 帳票名 | AX2: 作成日 | BB2: 作成者 | BF2: 更新日 | BJ2: 更新者
B3: 受発注システム | H3: =LEFT($X$3,FIND("_",$X$3)-1) -> SU0400 | L3: 受発注 | R3: =MID($X$3,FIND("_",$X$3,FIND("_",$X$3)+1)+1,LEN($X$3)-FIND("_",$X$3,FIND("_",$X$3)+1)) -> 帳票設計書 | X3: =REPLACE(LEFT(CELL("filename",$B$2),FIND(".x",CELL("filename",$B$2))-1),1,FIND("[",CELL("filename",$B$2)),) -> SU0400_請求一覧表_帳票設計書 | AK3: =MID($X$3,FIND("_",$X$3)+1,FIND("_",$X$3,FIND("_",$X$3)+1)-FIND("_",$X$3)-1) -> 請求一覧表 | AX3: 45583 | BB3: 大谷 | BF3: 45583 | BJ3: 大谷
C7: 変更履歴
C8: 日付 | G8: 版数 | K8: 担当 | O8: 変更箇所 | Y8: 内容
C9: 45583 | G9: 1.0.0 | K9: 大谷 | O9: - | Y9: 新規作成

Sheet 概要
B2: システム名 | H2: 画面ID | L2: システム分類 | R2: ドキュメント種別 | X2: ドキュメント名 | AK2: 帳票名 | AX2: 作成日 | BB2: 作成者 | BF2: 更新日 | BJ2: 更新者
B3: =変更履歴!B3 -> 受発注システム | H3: =変更履歴!H3 -> SU0400 | L3: =変更履歴!L3 -> 受発注 | R3: =変更履歴!R3 -> 帳票設計書 | X3: =変更履歴!X3 -> SU0400_請求一覧表_帳票設計書 | AK3: =変更履歴!AK3 -> 請求一覧表 | AX3: =変更履歴!AX3 -> 45583 | BB3: =変更履歴!BB3 -> 大谷 | BF3: =変更履歴!BF3 -> 45583 | BJ3: =変更履歴!BJ3 -> 大谷
D7: 帳票の名称 | H7: =AK3 -> 請求一覧表
D8: 帳票テンプレート名 | H8: -
D9: ファイル種類 | H9: PDF
D10: ファイル拡張子 | H10: pdf
D11: 文字コード | H11: -
D12: コーテーション | H12: -
D13: 固定長/可変長 | H13: -
D14: 区切り文字 | H14: -
D15: 用紙サイズ | H15: A3横
D16: 概要

Sheet 帳票レイアウト
B2: システム名 | H2: 画面ID | L2: システム分類 | R2: ドキュメント種別 | X2: ドキュメント名 | AK2: 帳票名 | AX2: 作成日 | BB2: 作成者 | BF2: 更新日 | BJ2: 更新者
B3: =変更履歴!B3 -> 受発注システム | H3: =変更履歴!H3 -> SU0400 | L3: =変更履歴!L3 -> 受発注 | R3: =変更履歴!R3 -> 帳票設計書 | X3: =変更履歴!X3 -> SU0400_請求一覧表_帳票設計書 | AK3: =変更履歴!AK3 -> 請求一覧表 | AX3: =変更履歴!AX3 -> 45583 | BB3: =変更履歴!BB3 -> 大谷 | BF3: =変更履歴!BF3 -> 45583 | BJ3: =変更履歴!BJ3 -> 大谷
B6: ページ１

Sheet 項目一覧
B2: システム名 | H2: 画面ID | L2: システム分類 | R2: ドキュメント種別 | X2: ドキュメント名 | AK2: 帳票名 | AX2: 作成日 | BB2: 作成者 | BF2: 更新日 | BJ2: 更新者
B3: =変更履歴!B3 -> 受発注システム | H3: =変更履歴!H3 -> SU0400 | L3: =変更履歴!L3 -> 受発注 | R3: =変更履歴!R3 -> 帳票設計書 | X3: =変更履歴!X3 -> SU0400_請求一覧表_帳票設計書 | AK3: =変更履歴!AK3 -> 請求一覧表 | AX3: =変更履歴!AX3 -> 45583 | BB3: =変更履歴!BB3 -> 大谷 | BF3: =変更履歴!BF3 -> 45583 | BJ3: =変更履歴!BJ3 -> 大谷
B7: 項目一覧
C9: 項目 | F9: フォントや文字サイズ、セル条件などは「別紙_テンプレート」準拠
D10: No. | E10: 項目名 | M10: データ型 | P10: 全角/半角 | S10: 文字数/桁数 | V10: データ取得元 | AB10: データ整形方法 | AR10: 整形後フォーマット | AX10: 備考
D11: 1 | E11: 作成日 | M11: 日付 | P11: 全角 | V11: 現在日付 | AR11: yyyy年mm月dd日
D12: 2 | E12: 請求日付 | M12: 日付 | P12: 半角 | V12: 画面.請求日付 | AR12: yyyy年mm月dd日締
D13: 3 | E13: 開始CD | M13: 数値 | P13: 半角 | V13: 画面.開始CD | AB13: 開始得意先が空の場合は[最初]を表示 空でない場合は[開始CD]を表示
D14: 4 | E14: 終了CD | M14: 数値 | P14: 半角 | V14: 画面.終了CD | AB14: 開始得意先が空の場合は[最初]を表示 空でない場合は[開始CD]を表示
D15: 5 | E15: 得意先CD | M15: 数値 | P15: 半角 | V15: SQL1.得意先CD
D16: 6 | E16: 得意先名1 | M16: 文字列 | P16: 全角 | V16: SQL1.得意先名1
D17: 7 | E17: 得意先名2 | M17: 文字列 | P17: 全角 | V17: SQL1.得意先名2
D18: 8 | E18: 前月残高 | M18: 数値 | P18: 半角 | V18: SQL1.前月残高 | AR18: 9999
D19: 9 | E19: 入金金額 | M19: 数値 | P19: 半角 | V19: SQL1.入金金額 | AR19: 9999
D20: 10 | E20: 調整金額 | M20: 数値 | P20: 半角 | V20: SQL1.調整金額 | AR20: 9999
D21: 11 | E21: 差引繰越額 | M21: 数値 | P21: 半角 | V21: SQL1.差引繰越額 | AR21: 9999
D22: 12 | E22: 売上金額 | M22: 数値 | P22: 半角 | V22: SQL1.売上金額 | AR22: 9999
D23: 13 | E23: 返品金額 | M23: 数値 | P23: 半角 | V23: SQL1.返品金額 | AR23: 9999
D24: 14 | E24: 訂正金額 | M24: 数値 | P24: 半角 | V24: SQL1.訂正金額 | AR24: 9999
D25: 15 | E25: 差引売上額 | M25: 数値 | P25: 半角 | V25: SQL1.差引売上額 | AR25: 9999
D26: 16 | E26: 消費税額 | M26: 数値 | P26: 半角 | V26: SQL1.消費税額 | AR26: 9999
D27: 17 | E27: 当月残高 | M27: 数値 | P27: 半角 | V27: SQL1.当月残高 | AR27: 9999
D28: 18 | E28: 入金予定日 | M28: 日付 | P28: 半角 | V28: SQL1.入金予定日 | AR28: yyyy年mm月dd日
D29: 19 | E29: 請求様式名 | M29: 文字列 | P29: 全角 | V29: SQL1.請求様式名
D30: 20 | E30: 担当者名 | M30: 文字列 | P30: 全角 | V30: SQL1.担当者名
D31: 21 | E31: 前月残高計 | M31: 数値 | P31: 半角 | V31: SQL1.前月残高 | AB31: [SQL1.前月残高]の合計 | AR31: 9999
D32: 22 | E32: 入金金額計 | M32: 数値 | P32: 半角 | V32: SQL1.入金金額 | AB32: [SQL1.入金金額]の合計 | AR32: 9999
D33: 23 | E33: 調整金額計 | M33: 数値 | P33: 半角 | V33: SQL1.調整金額 | AB33: [SQL1.調整金額]の合計 | AR33: 9999
D34: 24 | E34: 差引繰越額計 | M34: 数値 | P34: 半角 | V34: SQL1.差引繰越額 | AB34: [SQL1.差引繰越額]の合計 | AR34: 9999
D35: 25 | E35: 売上金額計 | M35: 数値 | P35: 半角 | V35: SQL1.売上金額 | AB35: [SQL1.売上金額]の合計 | AR35: 9999
D36: 26 | E36: 返品金額計 | M36: 数値 | P36: 半角 | V36: SQL1.返品金額 | AB36: [SQL1.返品金額]の合計 | AR36: 9999
D37: 27 | E37: 訂正金額計 | M37: 数値 | P37: 半角 | V37: SQL1.訂正金額 | AB37: [SQL1.訂正金額]の合計 | AR37: 9999
D38: 28 | E38: 差引売上額計 | M38: 数値 | P38: 半角 | V38: SQL1.差引売上額 | AB38: [SQL1.差引売上額]の合計 | AR38: 9999
D39: 29 | E39: 消費税額計 | M39: 数値 | P39: 半角 | V39: SQL1.消費税額 | AB39: [SQL1.消費税額]の合計 | AR39: 9999
D40: 30 | E40: 当月請求額計 | M40: 数値 | P40: 半角 | V40: SQL1.当月残高 | AB40: [SQL1.当月残高]の合計 | AR40: 9999

Sheet 処理詳細
B2: システム名 | H2: 画面ID | L2: システム分類 | R2: ドキュメント種別 | X2: ドキュメント名 | AK2: 帳票名 | AX2: 作成日 | BB2: 作成者 | BF2: 更新日 | BJ2: 更新者
B3: =変更履歴!B3 -> 受発注システム | H3: =変更履歴!H3 -> SU0400 | L3: =変更履歴!L3 -> 受発注 | R3: =変更履歴!R3 -> 帳票設計書 | X3: =変更履歴!X3 -> SU0400_請求一覧表_帳票設計書 | AK3: =変更履歴!AK3 -> 請求一覧表 | AX3: =変更履歴!AX3 -> 45583 | BB3: =変更履歴!BB3 -> 大谷 | BF3: =変更履歴!BF3 -> 45583 | BJ3: =変更履歴!BJ3 -> 大谷
B6: SQL1 | H6: select | J6: 得意先CD | R6: TM請求金額.得意先CD
J7: 得意先名1 | R7: TM得意先.得意先名1
J8: 得意先名2 | R8: TM得意先.得意先名2
J9: 請求日付 | R9: TM請求金額.請求日付
J10: 前月残高 | R10: TM請求金額.前月残高
J11: 入金金額 | R11: SK.入金金額
J12: 調整金額 | R12: TM請求金額.調整金額
J13: 差引繰越額 | R13: ISNULL(TM請求金額.前月残高,0)-ISNULL(TM請求金額.入金金額,0)-ISNULL(TM請求金額.調整金額,0) AS 差引繰越額
J14: 売上金額 | R14: TM請求金額.売上金額
J15: 返品金額 | R15: TM請求金額.返品金額
J16: 訂正金額 | R16: TM請求金額.訂正金額
J17: 差引売上額 | R17: ISNULL(TM請求金額.売上金額,0)+ISNULL(TM請求金額.返品金額,0)+ISNULL(TM請求金額.訂正金額,0) AS 差引売上額
J18: 消費税額 | R18: TM請求金額.消費税額
... J22: 担当者名 | R22: TM担当者.担当者名
H23: from | J23: TM請求金額 AS SK
H24: join | J24: LEFT JOIN TM得意先 AS TK ON SK.得意先CD = TK.得意先CD
J25: LEFT JOIN TM担当者 AS TN ON TK.担当者CD = TN.担当者CD
H26: where | J26: SK.請求日付 = CONVERT(VARCHAR(10),画面.請求日付,111)
J27: AND SK.締日 = 締日 | AK27: 締日は画面.請求日付が翌月末日だった場合99、それ以外の場合は画面.請求日付
J28: AND SK.得意先CD >= COALESCE(CONVERT(VARCHAR(4),画面.開始得意先),SK.得意先CD)
J29: AND SK.得意先CD <= COALESCE(CONVERT(VARCHAR(4),画面.終了得意先),SK.得意先CD)
J30: AND NOT( SK.前月残高 = 0
K31: AND SK.入金金額 = 0
K32: AND SK.売上金額 = 0
K33: AND SK.返品金額 = 0
K34: AND SK.消費税額 = 0
K35: AND SK.当月残高 = 0)
H36: order by | J36: ORDER BY SK.得意先CD の昇順でソート

Sheet 処理詳細_書き方
B2: システム名 | H2: 画面ID | L2: 業務分類 | R2: ドキュメント種別 | X2: ドキュメント名 | AK2: 帳票名 | AX2: 作成日 | BB2: 作成者 | BF2: 更新日 | BJ2: 更新者
B3: =変更履歴!B3 -> 受発注システム | H3: =変更履歴!H3 -> SU0400 | L3: =変更履歴!L3 -> 受発注 | R3: =変更履歴!R3 -> 帳票設計書 | X3: =変更履歴!X3 -> SU0400_請求一覧表_帳票設計書 | AK3: =変更履歴!AK3 -> 請求一覧表 | AX3: =変更履歴!AX3 -> 45583 | BB3: =変更履歴!BB3 -> 大谷 | BF3: =変更履歴!BF3 -> 45583 | BJ3: =変更履歴!BJ3 -> 大谷
B7: 1.タイトルを記載 | H7: select | J7: 項目名 | R7: 格納テーブル
J8: 仕入先CD | R8: VM支払予定情報.仕入先CD
J9: 仕入先名1 | R9: VM支払予定情報.仕入先名1
H10: from | J10: 使用するテーブル名を記載
J11: TD売上請求H
J12: TD見積
J13: TM納入先
H14: join | J14: 結合方式
K15: 結合テーブル名
M16: 結合条件
L17: and | M17: 結合条件
L18: or | M18: 結合条件
J19: INNER JOIN
K20: TM納入先
M21: [TD見積.納入得意先CD] = [TM納入先.得意先CD]
L22: and | M22: [TD見積.納入先CD] = [TM納入先.納入先CD]
H23: where | K23: 取得条件 | AK23: パラメータの意味が分かる場合は記載する
J24: and | K24: 取得条件
J25: or | K25: 取得条件
J26: ※可能な限り日本語化する
K27: [TD見積.得意先CD] = '8001' | AK27: 8001'はヤオコーの得意先CD
J28: and | K28: [TD売上請求H.請求日付]が[画面.請求期間From]以降
H32: order by | J32: ソート条件を記載
J33: [画面.iYK物件区分]が1の場合は[TD見積.納入得意先CD],[TD見積.納入先CD],[TD売上請求H.見積番号]を昇順でソート
H36: group byなどほかの条件がある場合は行を追加して記載

Sheet 確認事項
B2: 確認事項
B3: No. | C3: シート名 | D3: タイトル | E3: 概要 | F3: 確認済
B4: 1
B5: 2
B6: 3
B7: 4
B8: 5
B9: 6
B10: 7
B11: 8
B12: 9
B13: 10
B14: 11
B15: 12
... B54: 51

Sheet 別紙_印刷レイアウト

Sheet 参照
A1: 数値
A2: ブール値
A3: 文字列
A4: 日付
A5: リスト
A6: 辞書配列
