Workbook
Name TukiNamePos: #REF!
Name TukiNamePos_SS: #REF!
Name TukiRetu_SS: #REF!
Name TukiRetu_zen: #REF!
Name TukiRetu_顧客: #REF!
Name TukiRetu_工事: #REF!
Name サービス_営業外費_貨物: 別紙_テンプレート_DB!$DA$3:$DA$65423
Name サービス_営業外費_物流: 別紙_テンプレート_DB!$DC$3:$DC$65423
Name サービス_原額_貨物自_サンプラ: 別紙_テンプレート_DB!$BU$3:$BU$65423
Name サービス_原額_貨物自_その他: 別紙_テンプレート_DB!$CA$3:$CA$65423
Name サービス_原額_貨物自_トラン: 別紙_テンプレート_DB!$BY$3:$BY$65423
Name サービス_原額_貨物自_三シャ: 別紙_テンプレート_DB!$BW$3:$BW$65423
Name サービス_原額_貨物自_三商: 別紙_テンプレート_DB!$BQ$3:$BQ$65423
Name サービス_原額_貨物自_事故: 別紙_テンプレート_DB!$CC$3:$CC$65423
Name サービス_原額_貨物自_店装: 別紙_テンプレート_DB!$BS$3:$BS$65423
Name サービス_原額_貨物庸_サンプラ: 別紙_テンプレート_DB!$CI$3:$CI$65423
Name サービス_原額_貨物庸_その他: 別紙_テンプレート_DB!$CO$3:$CO$65423
Name サービス_原額_貨物庸_トラン: 別紙_テンプレート_DB!$CM$3:$CM$65423
Name サービス_原額_貨物庸_三シャ: 別紙_テンプレート_DB!$CK$3:$CK$65423
Name サービス_原額_貨物庸_三商: 別紙_テンプレート_DB!$CE$3:$CE$65423
Name サービス_原額_貨物庸_事故: 別紙_テンプレート_DB!$CQ$3:$CQ$65423
Name サービス_原額_貨物庸_店装: 別紙_テンプレート_DB!$CG$3:$CG$65423
Name サービス_原額_物流_その他: 別紙_テンプレート_DB!$CW$3:$CW$65423
Name サービス_原額_物流_ルート: 別紙_テンプレート_DB!$CS$3:$CS$65423
Name サービス_原額_物流_丸和: 別紙_テンプレート_DB!$CU$3:$CU$65423
Name サービス_原額_物流_事故: 別紙_テンプレート_DB!$CY$3:$CY$65423
Name サービス_人件一般費_貨物: 別紙_テンプレート_DB!$CZ$3:$CZ$65423
Name サービス_人件一般費_物流: 別紙_テンプレート_DB!$DB$3:$DB$65423
Name サービス_年月: 別紙_テンプレート_DB!$BO$3:$BO$65423
Name サービス_売額_貨物自_サンプラ: 別紙_テンプレート_DB!$BT$3:$BT$65423
Name サービス_売額_貨物自_その他: 別紙_テンプレート_DB!$BZ$3:$BZ$65423
Name サービス_売額_貨物自_トラン: 別紙_テンプレート_DB!$BX$3:$BX$65423
Name サービス_売額_貨物自_三シャ: 別紙_テンプレート_DB!$BV$3:$BV$65423
Name サービス_売額_貨物自_三商: 別紙_テンプレート_DB!$BP$3:$BP$65423
Name サービス_売額_貨物自_事故: 別紙_テンプレート_DB!$CB$3:$CB$65423
Name サービス_売額_貨物自_店装: 別紙_テンプレート_DB!$BR$3:$BR$65423
Name サービス_売額_貨物庸_サンプラ: 別紙_テンプレート_DB!$CH$3:$CH$65423
Name サービス_売額_貨物庸_その他: 別紙_テンプレート_DB!$CN$3:$CN$65423
Name サービス_売額_貨物庸_トラン: 別紙_テンプレート_DB!$CL$3:$CL$65423
Name サービス_売額_貨物庸_三シャ: 別紙_テンプレート_DB!$CJ$3:$CJ$65423
Name サービス_売額_貨物庸_三商: 別紙_テンプレート_DB!$CD$3:$CD$65423
Name サービス_売額_貨物庸_事故: 別紙_テンプレート_DB!$CP$3:$CP$65423
Name サービス_売額_貨物庸_店装: 別紙_テンプレート_DB!$CF$3:$CF$65423
Name サービス_売額_物流_その他: 別紙_テンプレート_DB!$CV$3:$CV$65423
Name サービス_売額_物流_ルート: 別紙_テンプレート_DB!$CR$3:$CR$65423
Name サービス_売額_物流_丸和: 別紙_テンプレート_DB!$CT$3:$CT$65423
Name サービス_売額_物流_事故: 別紙_テンプレート_DB!$CX$3:$CX$65423
Name サービス予測_年月: 別紙_テンプレート_DB!$BA$3:$BA$65423
Name サービス予測_予測原価金額_貨物: 別紙_テンプレート_DB!$BC$3:$BC$65423
Name サービス予測_予測原価金額_物流: 別紙_テンプレート_DB!$BE$3:$BE$65423
Name サービス予測_予測売上金額_貨物: 別紙_テンプレート_DB!$BB$3:$BB$65423
Name サービス予測_予測売上金額_物流: 別紙_テンプレート_DB!$BD$3:$BD$65423
Name フロント_営業外費: 別紙_テンプレート_DB!$BL$3:$BL$65423
Name フロント_原価税抜金額: 別紙_テンプレート_DB!$BJ$3:$BJ$65423
Name フロント_人件一般費: 別紙_テンプレート_DB!$BK$3:$BK$65423
Name フロント_年月: 別紙_テンプレート_DB!$BH$3:$BH$65423
Name フロント_売上税抜金額: 別紙_テンプレート_DB!$BI$3:$BI$65423
Name フロント予測_年月: 別紙_テンプレート_DB!$AV$3:$AV$65423
Name フロント予測_予測原価金額: 別紙_テンプレート_DB!$AX$3:$AX$65423
Name フロント予測_予測売上金額: 別紙_テンプレート_DB!$AW$3:$AW$65423

Sheet 変更履歴
B2: システム名 | H2: 画面ID | L2: システム分類 | R2: ドキュメント種別 | X2: ドキュメント名 | AK2: 帳票名 | AX2: 作成日 | BB2: 作成者 | BF2: 更新日 | BJ2: 更新者
B3: 受発注システム | H3: =LEFT($X$3,FIND("_",$X$3)-1) -> TK0300 | L3: 受発注 | R3: =MID($X$3,FIND("_",$X$3,FIND("_",$X$3)+1)+1,LEN($X$3)-FIND("_",$X$3,FIND("_",$X$3)+1)) -> 帳票設計書 | X3: =REPLACE(LEFT(CELL("filename",$B$2),FIND(".x",CELL("filename",$B$2))-1),1,FIND("[",CELL("filename",$B$2)),) -> TK0300_統計推移表(日単位)_帳票設計書 | AK3: =MID($X$3,FIND("_",$X$3)+1,FIND("_",$X$3,FIND("_",$X$3)+1)-FIND("_",$X$3)-1) -> 統計推移表(日単位) | AX3: 45581 | BB3: 大谷 | BF3: 45581 | BJ3: 大谷
C7: 変更履歴
C8: 日付 | G8: 版数 | K8: 担当 | O8: 変更箇所 | Y8: 内容
C9: 45581 | G9: 1.0.0 | K9: 大谷 | O9: - | Y9: 新規作成

Sheet 概要
B2: システム名 | H2: 画面ID | L2: システム分類 | R2: ドキュメント種別 | X2: ドキュメント名 | AK2: 帳票名 | AX2: 作成日 | BB2: 作成者 | BF2: 更新日 | BJ2: 更新者
B3: =変更履歴!B3 -> 受発注システム | H3: =変更履歴!H3 -> TK0300 | L3: =変更履歴!L3 -> 受発注 | R3: =変更履歴!R3 -> 帳票設計書 | X3: =変更履歴!X3 -> TK0300_統計推移表(日単位)_帳票設計書 | AK3: =変更履歴!AK3 -> 統計推移表(日単位) | AX3: =変更履歴!AX3 -> 45581 | BB3: =変更履歴!BB3 -> 大谷 | BF3: =変更履歴!BF3 -> 45581 | BJ3: =変更履歴!BJ3 -> 大谷
D7: 帳票の名称 | H7: =AK3 -> 統計推移表(日単位)
D8: 帳票テンプレート名 | H8: Temp統計推移表v13
D9: ファイル種類 | H9: Excel
D10: ファイル拡張子 | H10: xlsx
D11: 文字コード | H11: -
D12: コーテーション | H12: -
D13: 固定長/可変長 | H13: -
D14: 区切り文字 | H14: -
D15: 用紙サイズ | H15: A4横
D16: 概要

Sheet 帳票レイアウト(グループ)
B2: システム名 | H2: 画面ID | L2: 業務分類 | R2: ドキュメント種別 | X2: ドキュメント名 | AK2: 帳票名 | AX2: 作成日 | BB2: 作成者 | BF2: 更新日 | BJ2: 更新者
B3: =変更履歴!B3 -> 受発注システム | H3: =変更履歴!H3 -> TK0300 | L3: =変更履歴!L3 -> 受発注 | R3: =変更履歴!R3 -> 帳票設計書 | X3: =変更履歴!X3 -> TK0300_統計推移表(日単位)_帳票設計書 | AK3: =変更履歴!AK3 -> 統計推移表(日単位) | AX3: =変更履歴!AX3 -> 45581 | BB3: =変更履歴!BB3 -> 大谷 | BF3: =変更履歴!BF3 -> 45581 | BJ3: =変更履歴!BJ3 -> 大谷
B6: ページ１

Sheet 帳票レイアウト(商研)
B2: システム名 | H2: 画面ID | L2: システム分類 | R2: ドキュメント種別 | X2: ドキュメント名 | AK2: 帳票名 | AX2: 作成日 | BB2: 作成者 | BF2: 更新日 | BJ2: 更新者
B3: =変更履歴!B3 -> 受発注システム | H3: =変更履歴!H3 -> TK0300 | L3: =変更履歴!L3 -> 受発注 | R3: =変更履歴!R3 -> 帳票設計書 | X3: =変更履歴!X3 -> TK0300_統計推移表(日単位)_帳票設計書 | AK3: =変更履歴!AK3 -> 統計推移表(日単位) | AX3: =変更履歴!AX3 -> 45581 | BB3: =変更履歴!BB3 -> 大谷 | BF3: =変更履歴!BF3 -> 45581 | BJ3: =変更履歴!BJ3 -> 大谷
B6: ページ１
B49: ページ２
B92: ページ３

Sheet 帳票レイアウト(工事)
B2: システム名 | H2: 画面ID | L2: 業務分類 | R2: ドキュメント種別 | X2: ドキュメント名 | AK2: 帳票名 | AX2: 作成日 | BB2: 作成者 | BF2: 更新日 | BJ2: 更新者
B3: =変更履歴!B3 -> 受発注システム | H3: =変更履歴!H3 -> TK0300 | L3: =変更履歴!L3 -> 受発注 | R3: =変更履歴!R3 -> 帳票設計書 | X3: =変更履歴!X3 -> TK0300_統計推移表(日単位)_帳票設計書 | AK3: =変更履歴!AK3 -> 統計推移表(日単位) | AX3: =変更履歴!AX3 -> 45581 | BB3: =変更履歴!BB3 -> 大谷 | BF3: =変更履歴!BF3 -> 45581 | BJ3: =変更履歴!BJ3 -> 大谷
B6: ページ１

Sheet 帳票レイアウト(三和サービス)
B2: システム名 | H2: 画面ID | L2: 業務分類 | R2: ドキュメント種別 | X2: ドキュメント名 | AK2: 帳票名 | AX2: 作成日 | BB2: 作成者 | BF2: 更新日 | BJ2: 更新者
B3: =変更履歴!B3 -> 受発注システム | H3: =変更履歴!H3 -> TK0300 | L3: =変更履歴!L3 -> 受発注 | R3: =変更履歴!R3 -> 帳票設計書 | X3: =変更履歴!X3 -> TK0300_統計推移表(日単位)_帳票設計書 | AK3: =変更履歴!AK3 -> 統計推移表(日単位) | AX3: =変更履歴!AX3 -> 45581 | BB3: =変更履歴!BB3 -> 大谷 | BF3: =変更履歴!BF3 -> 45581 | BJ3: =変更履歴!BJ3 -> 大谷
B6: ページ１

Sheet 項目一覧
B2: システム名 | H2: 画面ID | L2: システム分類 | R2: ドキュメント種別 | X2: ドキュメント名 | AK2: 帳票名 | AX2: 作成日 | BB2: 作成者 | BF2: 更新日 | BJ2: 更新者
B3: =変更履歴!B3 -> 受発注システム | H3: =変更履歴!H3 -> TK0300 | L3: =変更履歴!L3 -> 受発注 | R3: =変更履歴!R3 -> 帳票設計書 | X3: =変更履歴!X3 -> TK0300_統計推移表(日単位)_帳票設計書 | AK3: =変更履歴!AK3 -> 統計推移表(日単位) | AX3: =変更履歴!AX3 -> 45581 | BB3: =変更履歴!BB3 -> 大谷 | BF3: =変更履歴!BF3 -> 45581 | BJ3: =変更履歴!BJ3 -> 大谷
B7: 項目一覧
C9: 項目 | F9: フォントや文字サイズ、セル条件などは「別紙_テンプレート」準拠
D10: No. | E10: 項目名 | M10: データ型 | P10: 全角/半角 | S10: 文字数/桁数 | V10: データ取得元 | AB10: データ整形方法 | AR10: 整形後フォーマット | AX10: 備考
D11: 1 | E11: 売上・原価_営業担当CD | M11: 数値 | P11: 半角 | S11: 7 | V11: - | AX11: 固定値で0
D12: 2 | E12: 売上・原価_番号 | M12: 数値 | P12: 半角 | S12: 4 | V12: - | AX12: 固定値で0
D13: 3 | E13: 売上・原価_集計CD | M13: 文字列 | P13: 半角 | S13: 8 | V13: TD見積.集計CD
D14: 4 | E14: 売上・原価_年月日 | M14: 日付 | P14: 半角 | S14: 10 | V14: TD売上v2.売上日付 | AB14: [TD売上v2.売上日付]の月初（例：2024/12/31 → 2024/12/1） | AR14: yyyy/m/d
D15: 5 | E15: 売上・原価_作業区分CD | M15: 数値 | P15: 半角 | S15: 7 | V15: TD見積.物件種別,TD見積.業種区分,TD見積シートM.作業区分CD | AB15: [TD見積.物件種別]が6の場合は106, 106以外かつ[TD見積.業種区分]が1の場合は3, 106以外かつ[TD見積.業種区分]が1以外の場合は[TD見積.業種区分]の値（Nullは0に置換）
D16: 6 | E16: 売上・原価_売上税抜金額 | M16: 数値 | P16: 半角 | S16: 9 | V16: TD売上明細V2.売上税区分,TD売上明細V2.売上金額,TD売上明細V2.消費税額 | AB16: [TD売上明細V2.売上税区分]が1の場合は[TD売上明細V2.売上金額]から[TD売上明細V2.消費税額]を引いた値、 それ以外の場合は[TD売上明細V2.売上金額] | AR16: 999999
D17: 7 | E17: 売上・原価_原価税抜金額 | M17: 数値 | P17: 半角 | S17: 9 | V17: TD仕入明細内訳.仕入税区分,TD仕入明細内訳.仕入金額,TD仕入明細内訳.消費税額 | AB17: [TD仕入明細内訳.売上税区分]が1の場合は[TD仕入明細内訳.仕入金額]から[TD仕入明細内訳.消費税額]を引いた値、 それ以外の場合は[TD仕入明細内訳.売上金額][TD仕入明細内訳.売上税区分]が1の場合は[TD仕入明細内訳.売上金額]から[TD仕入明細内訳.消費税額]を引いた値、 それ以外の場合は[TD仕入明細内訳.売上金額] | AR17: 999999
D18: 8 | E18: 工事・売上・原価_工事担当CD | M18: 数値 | P18: 半角 | S18: 8 | V18: TD見積.工事担当CD
D19: 9 | E19: 工事・売上・原価_番号 | M19: 数値 | P19: 半角 | S19: 4 | V19: - | AX19: 固定値で0
D20: 10 | E20: 工事・売上・原価_集計CD（未使用） | M20: 数値 | P20: 半角 | S20: 6 | V20: - | AX20: 固定値で0
D21: 11 | E21: 工事・売上・原価_年月日 | M21: 日付 | P21: 半角 | S21: 10 | V21: TD売上v2.売上日付 | AB21: [TD売上v2.売上日付]の月初（例：2024/12/31 → 2024/12/1） | AR21: yyyy/m/d
D22: 12 | E22: 工事・売上・原価_作業区分CD | M22: 数値 | P22: 半角 | S22: 9 | V22: TD見積.物件種別,TD見積もり.業種区分,TD見積シートM.作業区分CD | AB22: [TD見積.物件種別]が6の場合は106, 106以外かつ[TD見積.業種区分]が1の場合は3, 106以外かつ[TD見積.業種区分]が1以外の場合は[TD見積.業種区分]の値（Nullは0に置換）
D23: 13 | E23: 工事・売上・原価_売上税抜金額 | M23: 数値 | P23: 半角 | S23: 10 | V23: TD売上明細V2.売上税区分,TD売上明細V2.売上金額,TD売上明細V2.消費税額 | AB23: [TD売上明細V2.売上税区分]が1の場合は[TD売上明細V2.売上金額]から[TD売上明細V2.消費税額]を引いた値、 それ以外の場合は[TD売上明細V2.売上金額] | AR23: 999999
D24: 14 | E24: 工事・売上・原価_原価税抜金額 | M24: 数値 | P24: 半角 | S24: 10 | V24: TD仕入明細内訳.仕入税区分,TD仕入明細内訳.仕入金額,TD仕入明細内訳.消費税額 | AB24: [TD仕入明細内訳.売上税区分]が1の場合は[TD仕入明細内訳.仕入金額]から[TD仕入明細内訳.消費税額]を引いた値、 それ以外の場合は[TD仕入明細内訳.売上金額][TD仕入明細内訳.売上税区分]が1の場合は[TD仕入明細内訳.売上金額]から[TD仕入明細内訳.消費税額]を引いた値、 それ以外の場合は[TD仕入明細内訳.売上金額] | AR24: 999999
D25: 15 | E25: 入出庫_集計CD | M25: 文字列 | P25: 半角 | S25: 7 | V25: TD見積.集計CD
D26: 16 | E26: 入出庫_年月日 | M26: 日付 | P26: 半角 | S26: 10 | V26: TD仕入明細.仕入日付 | AB26: [TD仕入明細.仕入日付]の月初（例：2024/12/31 → 2024/12/1） | AR26: yyyy/m/d
D27: 17 | E27: 入出庫_出庫金額 | M27: 数値 | P27: 半角 | S27: 7 | V27: TD仕入明細内訳.仕入税区分,TD仕入明細内訳.消費税額,TD在庫調整明細.仕入税区分,TD在庫調整明細.調整金額,TD在庫調整明細.消費税額 | AB27: 出庫合計金額 = [TD仕入明細内訳.仕入税区分]が1の場合は[TD仕入明細内訳.仕入金額] - [TD仕入明細内訳.消費税額]、1以外の場合は[TD仕入明細内訳.仕入金額]の合計 調整出庫合計金額 = [TD在庫調整明細.仕入税区分]が1の場合は[TD在庫調整明細.調整金額]-[TD在庫調整明細.消費税額]、1以外の場合は[TD在庫調整明細.調整金額]の合計 出庫合計金額 + 調整出庫合計金額の合計 | AR27: 999999
D28: 18 | E28: 入出庫_入庫金額 | M28: 数値 | P28: 半角 | S28: 7 | V28: TD仕入明細内訳.仕入税区分,TD仕入明細内訳.消費税額,TD在庫調整明細.仕入税区分,TD在庫調整明細.調整金額,TD在庫調整明細.消費税額 | AB28: 入庫合計金額 = [TD仕入明細内訳.仕入税区分]が1の場合は[TD仕入明細内訳.仕入金額] - [TD仕入明細内訳.消費税額]、1以外の場合は[TD仕入明細内訳.仕入金額]の合計 調整入庫合計金額 = [TD在庫調整明細.仕入税区分]が1の場合は[TD在庫調整明細.調整金額]-[TD在庫調整明細.消費税額]、1以外の場合は[TD在庫調整明細.調整金額]の合計 入庫合計金額 + 調整入庫合計金額の合計 | AR28: 999999
D29: 19 | E29: 三研 売上（円）_年月日 | M29: 日付 | P29: 半角 | S29: 10 | V29: TM三研情報.年月 | AR29: yyyy/m/d
D30: 20 | E30: 三研 売上（円）_売上税抜金額 | M30: 数値 | P30: 半角 | S30: 7 | V30: TM三研情報.売上税抜金額_円
D31: 21 | E31: 三研 売上（円）_原価税抜金額 | M31: 数値 | P31: 半角 | S31: 7 | V31: TM三研情報.原価税抜金額_円
D32: 22 | E32: 三研 売上（円）_人件一般費 | M32: 数値 | P32: 半角 | S32: 7 | V32: TM三研情報.人件一般費_円
D33: 23 | E33: 三研 売上（円）_営業外費 | M33: 数値 | P33: 半角 | S33: 7 | V33: TM三研情報.営業外費_円
D34: 24 | E34: サービス 売上（円）_年月日 | M34: 日付 | P34: 半角 | S34: 10 | V34: TMサービス実績情報.年月 | AR34: yyyy/m/d
D35: 25 | E35: サービス 売上（円）_売額_貨物自_三商 | M35: 数値 | P35: 半角 | S35: 15 | V35: TMサービス実績情報.売額_貨物自_三商
D36: 26 | E36: サービス 売上（円）_原額_貨物自_三商 | M36: 数値 | P36: 半角 | S36: 15 | V36: TMサービス実績情報.原額_貨物自_三商
D37: 27 | E37: サービス 売上（円）_売額_貨物自_店装 | M37: 数値 | P37: 半角 | S37: 15 | V37: TMサービス実績情報.売額_貨物自_店装
D38: 28 | E38: サービス 売上（円）_原額_貨物自_店装 | M38: 数値 | P38: 半角 | S38: 15 | V38: TMサービス実績情報.原額_貨物自_店装
D39: 29 | E39: サービス 売上（円）_売額_貨物自_サンプラ | M39: 数値 | P39: 半角 | S39: 15 | V39: TMサービス実績情報.売額_貨物自_サンプラ
D40: 30 | E40: サービス 売上（円）_原額_貨物自_サンプラ | M40: 数値 | P40: 半角 | S40: 15 | V40: TMサービス実績情報.原額_貨物自_サンプラ
D41: 31 | E41: サービス 売上（円）_売額_貨物自_三シャ | M41: 数値 | P41: 半角 | S41: 15 | V41: TMサービス実績情報.売額_貨物自_三シャ
D42: 32 | E42: サービス 売上（円）_原額_貨物自_三シャ | M42: 数値 | P42: 半角 | S42: 15 | V42: TMサービス実績情報.原額_貨物自_三シャ
D43: 33 | E43: サービス 売上（円）_売額_貨物自_トラン | M43: 数値 | P43: 半角 | S43: 15 | V43: TMサービス実績情報.売額_貨物自_トラン
D44: 34 | E44: サービス 売上（円）_原額_貨物自_トラン | M44: 数値 | P44: 半角 | S44: 15 | V44: TMサービス実績情報.原額_貨物自_トラン
D45: 35 | E45: サービス 売上（円）_売額_貨物自_その他 | M45: 数値 | P45: 半角 | S45: 15 | V45: TMサービス実績情報.売額_貨物自_その他
D46: 36 | E46: サービス 売上（円）_原額_貨物自_その他 | M46: 数値 | P46: 半角 | S46: 15 | V46: TMサービス実績情報.原額_貨物自_その他
... D74: 64 | E74: サービス 売上（円）_営業外費_物流 | M74: 数値 | P74: 半角 | S74: 15 | V74: TMサービス実績情報.営業外費_物流
D75: 64 | E75: 営業担当別経費_業種区分
D76: 64 | E76: 営業担当別経費_部CD（未使用）
D77: 64 | E77: 営業担当別経費_年月日
D78: 64 | E78: 営業担当別経費_人件費一般費
D79: 64 | E79: 部署別 売上・原価_部署
D80: 64 | E80: 部署別 売上・原価_年月日
D81: 64 | E81: 部署別 売上・原価_作業区分CD
D82: 64 | E82: 部署別 売上・原価_売上税抜金額
D83: 64 | E83: 部署別 売上・原価_原価税抜金額

Sheet 処理詳細_書き方
B2: システム名 | H2: 画面ID | L2: 業務分類 | R2: ドキュメント種別 | X2: ドキュメント名 | AK2: 帳票名 | AX2: 作成日 | BB2: 作成者 | BF2: 更新日 | BJ2: 更新者
B3: =変更履歴!B3 -> 受発注システム | H3: =変更履歴!H3 -> TK0300 | L3: =変更履歴!L3 -> 受発注 | R3: =変更履歴!R3 -> 帳票設計書 | X3: =変更履歴!X3 -> TK0300_統計推移表(日単位)_帳票設計書 | AK3: =変更履歴!AK3 -> 統計推移表(日単位) | AX3: =変更履歴!AX3 -> 45581 | BB3: =変更履歴!BB3 -> 大谷 | BF3: =変更履歴!BF3 -> 45581 | BJ3: =変更履歴!BJ3 -> 大谷
B7: 1.タイトルを記載 | H7: select | J7: 項目名 | R7: 格納テーブル
J8: 仕入先CD | R8: VM支払予定情報.仕入先CD
J9: 仕入先名1 | R9: VM支払予定情報.仕入先名1
H10: from | J10: 使用するテーブル名を記載
J11: TD売上請求H
J12: TD見積
J13: TM納入先
H14: join | J14: 結合方式
K15: 結合テーブル名
M16: 結合条件
L17: and | M17: 結合条件
L18: or | M18: 結合条件
J19: INNER JOIN
K20: TM納入先
M21: [TD見積.納入得意先CD] = [TM納入先.得意先CD]
L22: and | M22: [TD見積.納入先CD] = [TM納入先.納入先CD]
H23: where | K23: 取得条件 | AK23: パラメータの意味が分かる場合は記載する
J24: and | K24: 取得条件
J25: or | K25: 取得条件
J26: ※可能な限り日本語化する
K27: [TD見積.得意先CD] = '8001' | AK27: 8001'はヤオコーの得意先CD
J28: and | K28: [TD売上請求H.請求日付]が[画面.請求期間From]以降
H32: order by | J32: ソート条件を記載
J33: [画面.iYK物件区分]が1の場合は[TD見積.納入得意先CD],[TD見積.納入先CD],[TD売上請求H.見積番号]を昇順でソート
H36: group byなどほかの条件がある場合は行を追加して記載

Sheet 処理詳細
B2: システム名 | H2: 画面ID | L2: システム分類 | R2: ドキュメント種別 | X2: ドキュメント名 | AK2: 帳票名 | AX2: 作成日 | BB2: 作成者 | BF2: 更新日 | BJ2: 更新者
B3: =[1]変更履歴!B3 -> XXXXXXXX | H3: =[1]変更履歴!H3 -> TK0300 | L3: =[1]変更履歴!L3 -> 運用自動化 | R3: =[1]変更履歴!R3 -> 帳票設計書 | X3: =[1]変更履歴!X3 -> TK0300_統計推移表_帳票設計書 | AK3: =[1]変更履歴!AK3 -> 統計推移表 | AX3: =[1]変更履歴!AX3 -> 45474 | BB3: =[1]変更履歴!BB3 -> 丹羽 | BF3: =[1]変更履歴!BF3 -> 0 | BJ3: =[1]変更履歴!BJ3 -> 0
B6: SQL1 MERGE INTO | H6: merge into | J6: #TMP_TOTAL AS A
H7: using | J7: SQL2 AS B
H8: on | K8: A.部署CD = B.部署CD
J9: AND | K9: A.工事担当CD = B.工事担当CD
J10: AND | K10: A.番号 = B.番号
J11: AND | K11: A.集計CD = B.集計CD
J12: AND | K12: A.年月日 = B.年月日
J13: AND | K13: A.作業区分CD = B.作業区分CD
H14: matched | J14: WHEN MATCHED THEN
K15: UPDATE
L16: SET A.売上税抜金額 = A.売上税抜金額 + B.税抜金額
J17: WHEN NOT MATCHED THEN
K18: INSERT
J19: 部署CD | R19: B.部署CD
J20: 工事担当CD | R20: B.工事担当CD
J21: 番号 | R21: B.番号
J22: 集計CD | R22: B.集計CD
J23: 年月日 | R23: B.年月日
J24: 作業区分CD | R24: B.作業区分CD
J25: 売上税抜金額 | R25: B.税抜金額
B26: SQL2 | H26: select | J26: 部署CD | R26: MH.部署CD
J27: 工事担当CD | R27: MH.工事担当CD
J28: 番号 | R28: 0
J29: 集計CD | R29: MH.集計CD
J30: 年月日 | R30: CONVERT(DATETIME, CONVERT(CHAR (7), UH.売上日付, 111) + '/1')
J31: 作業区分CD | R31: CASE WHEN MH.物件種別 = 6 THEN 106 ELSE CASE WHEN (MH.業種区分 = 1) THEN 3 ELSE ISNULL(MSM.作業区分CD, 0) END END
J32: 税抜金額 | R32: SUM(CASE WHEN UM.売上税区分 = 1 THEN (UM.売上金額 - UM.消費税額) ELSE UM.売上金額 END)
H33: from | J33: TD売上v2 AS UH
J34: TD見積 AS MH
J35: TD売上明細V2 AS UM
J36: TD見積シートM AS MSM
J37: TM得意先 AS TM
J38: TD物件情報 AS BK
J39: TM製品 AS SE
H40: join | J40: INNER JOIN
K41: TD見積
M42: UH.見積番号 = MH.見積番号
J43: INNER JOIN
K44: TD売上明細V2
M45: UH.売上番号 = UM.売上番号
J46: LEFT JOIN
K47: TD見積シートM
M48: UM.見積明細連番 = MSM.見積明細連番
J49: INNER JOIN
K50: TM得意先
M51: MH.販売先得意先CD = TM.得意先CD
J52: LEFT JOIN
K53: TD物件情報
M54: MH.物件番号 = BK.物件番号
J55: LEFT JOIN
K56: TM製品
M57: MSM.製品NO = SE.製品NO
L58: AND | M58: MSM.仕様NO = SE.仕様NO
H59: where | K59: (
M60: (
O61: UH.売上日付 >= [画面.集計期間from]
N62: AND | O62: UH.売上日付 <= [画面.集計期間to])
M63: )
L64: AND | M64: (
O65: MH.集計CD IN (@wヤオコー, @wロピア, @wベルク, @wサンベルクス, @wアマゾン, @wメルカリ, @wウエルシア, @wビバ) | AK65: @wヤオコー = '8001' @wマミー = '7001' @wロピア = '9803' @wベルク = '6601' @wサンベルクス = '3001' @wウエルシア = '2401' @wビバ = '4801' @wアマゾン = '1041' @wメルカリ = '7605'
M66: )
K67: )
H68: group by | J68: MH.部署CD
J69: MH.工事担当CD
J70: MH.集計CD
J71: CONVERT(DATETIME,CONVERT(CHAR(7),UH.売上日付,111)+'/1')
J72: CASE WHEN MH.物件種別 = 6 THEN 106 ELSE CASE WHEN (MH.業種区分=1) THEN 3 ELSE ISNULL(MSM.作業区分CD,0) END END
B73: SQL3 MERGE INTO | H73: merge into | J73: #TMP_TOTAL AS A
H74: using | J74: SQL4 AS B
H75: on | K75: A.部署CD = B.部署CD
J76: AND | K76: A.工事担当CD = B.工事担当CD
J77: AND | K77: A.番号 = B.番号
J78: AND | K78: A.集計CD = B.集計CD
J79: AND | K79: A.年月日 = B.年月日
J80: AND | K80: A.作業区分CD = B.作業区分CD
H81: matched | J81: WHEN MATCHED THEN
K82: UPDATE
L83: SET A.売上税抜金額 = A.売上税抜金額 + B.税抜金額
J84: WHEN NOT MATCHED THEN
K85: INSERT
J86: 部署CD | R86: B.部署CD
J87: 工事担当CD | R87: B.工事担当CD
J88: 番号 | R88: B.番号
J89: 集計CD | R89: B.集計CD
J90: 年月日 | R90: B.年月日
J91: 作業区分CD | R91: B.作業区分CD
J92: 売上税抜金額 | R92: B.税抜金額
B93: SQL4 | H93: select | J93: 部署CD | R93: MH.部署CD
J94: 工事担当CD | R94: MH.工事担当CD
J95: 番号 | R95: 99
J96: 集計CD | R96: 99999
J97: 年月日 | R97: CONVERT(DATETIME, CONVERT(CHAR (7), UH.売上日付, 111) + '/1')
J98: 作業区分CD | R98: CASE WHEN MH.物件種別 = 6 THEN 106 ELSE CASE WHEN (MH.業種区分 = 1) THEN 3 ELSE ISNULL(MSM.作業区分CD, 0) END END
J99: 税抜金額 | R99: SUM(CASE WHEN UM.売上税区分 = 1 THEN (UM.売上金額-UM.消費税額) ELSE UM.売上金額 END)
H100: from | J100: TD売上v2 AS UH
J101: TD見積 AS MH
J102: TD売上明細V2 AS UM
J103: TD見積シートM AS MSM
...

Sheet 確認事項
B2: 確認事項
B3: No. | C3: シート名 | D3: タイトル | E3: 概要 | F3: 確認済
B4: 1
B5: 2
B6: 3
B7: 4
B8: 5
B9: 6
B10: 7
B11: 8
B12: 9
B13: 10
B14: 11
B15: 12
... B54: 51

Sheet 別紙_テンプレート_DB
A1: 顧客別 売上・原価 | J1: 工事 売上・原価 | Y1: 入出庫 | AE1: 三研 売上（円） | AL1: 2016年 担当別原価埋込 | AQ1: 三研予測(円) | AV1: フロント予測(円) | BA1: サービス予測(円) | BH1: フロント 売上（円） | BO1: サービス 売上（円） | DF1: 営業担当別経費 | DM1: 部署別 売上・原価
A2: 営業担当CD | B2: 番号 | C2: 集計CD | D2: 年月日 | E2: 作業区分CD | F2: 売上税抜金額 | G2: 原価税抜金額 | J2: 工事担当CD | K2: 番号 | L2: 集計CD（未使用） | M2: 年月日 | N2: 作業区分CD | O2: 売上税抜金額 | P2: 原価税抜金額 | Y2: 集計CD | Z2: 年月日 | AA2: 出庫金額 | AB2: 入庫金額 | AE2: 年月日 | AF2: 売上税抜金額 | AG2: 原価税抜金額 | AH2: 人件一般費 | AI2: 営業外費 | AL2: チームCD | AM2: 年月 | AN2: 原価金額 | AQ2: 年月 | AR2: 予測売上金額 | AS2: 予測原価金額 | AV2: 年月 | AW2: 予測売上金額 | AX2: 予測原価金額 | BA2: 年月 | BB2: 予測売上額_貨物 | BC2: 予測原価額_貨物 | BD2: 予測売上額_物流 | BE2: 予測原価額_物流 | BH2: 年月 | BI2: 売上税抜金額 | BJ2: 原価税抜金額 | BK2: 人件一般費 | BL2: 営業外費 | BO2: 年月日 | BP2: 売額_貨物自_三商 | BQ2: 原額_貨物自_三商 | BR2: 売額_貨物自_店装 | BS2: 原額_貨物自_店装 | BT2: 売額_貨物自_サンプラ | BU2: 原額_貨物自_サンプラ | BV2: 売額_貨物自_三シャ | BW2: 原額_貨物自_三シャ | BX2: 売額_貨物自_トラン | BY2: 原額_貨物自_トラン | BZ2: 売額_貨物自_その他 | CA2: 原額_貨物自_その他 | CB2: 売額_貨物自_事故 | CC2: 原額_貨物自_事故 | CD2: 売額_貨物庸_三商 | CE2: 原額_貨物庸_三商 | CF2: 売額_貨物庸_店装 | CG2: 原額_貨物庸_店装 | CH2: 売額_貨物庸_サンプラ | CI2: 原額_貨物庸_サンプラ | CJ2: 売額_貨物庸_三シャ | CK2: 原額_貨物庸_三シャ | CL2: 売額_貨物庸_トラン | CM2: 原額_貨物庸_トラン | CN2: 売額_貨物庸_その他 | CO2: 原額_貨物庸_その他 | CP2: 売額_貨物庸_事故 | CQ2: 原額_貨物庸_事故 | CR2: 売額_物流_ルート | CS2: 原額_物流_ルート | CT2: 売額_物流_丸和 | CU2: 原額_物流_丸和 | CV2: 売額_物流_その他 | CW2: 原額_物流_その他 | CX2: 売額_物流_事故 | CY2: 原額_物流_事故 | CZ2: 人件一般費_貨物 | DA2: 営業外費_貨物 | DB2: 人件一般費_物流 | DC2: 営業外費_物流 | DF2: 業種区分 | DG2: 部CD（未使用） | DH2: 年月日 | DI2: 人件費一般費 | DM2: 部署 | DN2: 年月日 | DO2: 作業区分CD | DP2: 売上税抜金額 | DQ2: 原価税抜金額

Sheet 別紙_テンプレート_グループ
B1: 三和グループ統計
B2: 項目 | F2: =IF(MONTH(I2)<4,YEAR(I2)-1&"年度",YEAR(I2)&"年度") -> 2020年度 | I2: 44227 | L2: 44226
F3: 原価 | H3: 売上 | I3: 原価 | K3: 売上 | L3: 原価 | N3: 売上
B4: 原価 | F4: =SUMIF(I$3:N$3,$F$3,I4:N4) -> 0 | G4: =IF(ISERROR(F4/H4),0,F4/H4) -> 0 | H4: =SUMIF(I$3:N$3,$H$3,I4:N4) -> 0 | I4: =SUM(I10,I16,I22) -> 0 | J4: =IF(ISERROR(I4/K4),0,I4/K4) -> 0 | K4: =SUM(K10,K16,K22) -> 0 | L4: =SUM(L10,L16,L22) -> 0 | M4: =IF(ISERROR(L4/N4),0,L4/N4) -> 0 | N4: =SUM(N10,N16,N22) -> 0
B5: 営利 | F5: =SUMIF(I$3:N$3,$F$3,I5:N5) -> #REF! | G5: =IF(ISERROR(F5/H4),0,F5/H4) -> 0 | I5: =SUM(I11,I17,I23) -> #REF! | J5: =IF(ISERROR(I5/K4),0,I5/K4) -> 0 | L5: =SUM(L11,L17,L23) -> #REF! | M5: =IF(ISERROR(L5/N4),0,L5/N4) -> 0
B6: 債務 差引 | F6: =OFFSET(F6,,3) -> 0 | G6: 借入 | H6: =OFFSET(H6,,5) -> 0 | I6: =SUM(I12,I18,I24,I30) -> 0 | K6: =SUM(K12,K18,K24,K30) -> 0 | L6: =SUM(L12,L18,L24,L30) -> 0 | N6: =SUM(N12,N18,N24,N30) -> 0
F7: =OFFSET(F7,,3) -> 0 | G7: 現預金 | H7: =OFFSET(H7,,5) -> 0 | I7: =SUM(I13,I19,I25,I35) -> 0 | K7: =SUM(K13,K19,K25,K35) -> 0 | L7: =SUM(L13,L19,L25,L35) -> 0 | N7: =SUM(N13,N19,N25,N35) -> 0
B8: 株式会社 三和商研
B9: 項目 | F9: =YEAR(I9)-1978+1&"期" -> 44期 | I9: =I2 -> 44227 | L9: =L2 -> 44226
B10: 原価 | F10: =SUMIF(I$3:N$3,$F$3,I10:N10) -> 0 | G10: =IF(ISERROR(F10/H10),0,F10/H10) -> 0 | H10: =SUMIF(I$3:N$3,$H$3,I10:N10) -> 0 | I10: =別紙_テンプレート_商研!K5 -> 0 | J10: =IF(ISERROR(I10/K10),0,I10/K10) -> 0 | K10: =別紙_テンプレート_商研!I4 -> 0 | L10: =別紙_テンプレート_商研!N5 -> 0 | M10: =IF(ISERROR(L10/N10),0,L10/N10) -> 0 | N10: =別紙_テンプレート_商研!L4 -> 0
B11: 営利 | F11: =SUMIF(I$3:N$3,$F$3,I11:N11) -> #REF! | G11: =IF(ISERROR(F11/H10),0,F11/H10) -> 0 | I11: =別紙_テンプレート_商研!#REF! -> #REF! | J11: =IF(ISERROR(I11/K10),0,I11/K10) -> 0 | L11: =別紙_テンプレート_商研!#REF! -> #REF! | M11: =IF(ISERROR(L11/N10),0,L11/N10) -> 0
B12: 債務 差引 | F12: =OFFSET(F12,,3) -> 0 | G12: 借入 | H12: =OFFSET(H12,,5) -> 0 | I12: =K13-K12 -> 0 | L12: =N13-N12 -> 0
F13: =OFFSET(F13,,3) -> 0 | G13: 現預金 | H13: =OFFSET(H13,,5) -> 0 | I13: =SUM(I12-OFFSET(I12,,3)) -> 0 | L13: =SUM(L12-OFFSET(L12,,3)) -> 0
B14: 三研(上海)商貿有限公司
B15: 項目 | F15: =YEAR(I15)-2014+1&"期" -> 8期 | I15: =I2 -> 44227 | L15: =L2 -> 44226
B16: 原価 | F16: =SUMIF(I$3:N$3,$F$3,I16:N16) -> 0 | G16: =IF(ISERROR(F16/H16),0,F16/H16) -> 0 | H16: =SUMIF(I$3:N$3,$H$3,I16:N16) -> 0 | I16: =IFERROR(INDEX(別紙_テンプレート_DB!三研_原価税抜金額,MATCH(I$2,INDEX(別紙_テンプレート_DB!三研_年月,),0)),0) -> 0 | J16: =IF(ISERROR(I16/K16),0,I16/K16) -> 0 | K16: =IFERROR(INDEX(別紙_テンプレート_DB!三研_売上税抜金額,MATCH(I$2,INDEX(別紙_テンプレート_DB!三研_年月,),0)),0) -> 0 | L16: =IFERROR(INDEX(別紙_テンプレート_DB!三研_原価税抜金額,MATCH(L$2,INDEX(別紙_テンプレート_DB!三研_年月,),0)),0) -> 0 | M16: =IF(ISERROR(L16/N16),0,L16/N16) -> 0 | N16: =IFERROR(INDEX(別紙_テンプレート_DB!三研_売上税抜金額,MATCH(L$2,INDEX(別紙_テンプレート_DB!三研_年月,),0)),0) -> 0
B17: 営利 | F17: =SUMIF(I$3:N$3,$F$3,I17:N17) -> 0 | G17: =IF(ISERROR(F17/H16),0,F17/H16) -> 0 | I17: =K16-I16-(IFERROR(INDEX(別紙_テンプレート_DB!三研_人件一般費,MATCH(I$2,INDEX(別紙_テンプレート_DB!三研_年月,),0)),0)) -> 0 | J17: =IF(ISERROR(I17/K16),0,I17/K16) -> 0 | L17: =N16-L16-(IFERROR(INDEX(別紙_テンプレート_DB!三研_人件一般費,MATCH(L$2,INDEX(別紙_テンプレート_DB!三研_年月,),0)),0)) -> 0 | M17: =IF(ISERROR(L17/N16),0,L17/N16) -> 0
B18: 債務 差引 | F18: =OFFSET(F18,,3) -> 0 | G18: 借入 | H18: =OFFSET(H18,,5) -> 0 | I18: =K19-K18 -> 0 | L18: =N19-N18 -> 0
F19: =OFFSET(F19,,3) -> 0 | G19: 現預金 | H19: =OFFSET(H19,,5) -> 0 | I19: =SUM(I18-OFFSET(I18,,3)) -> 0 | L19: =SUM(L18-OFFSET(L18,,3)) -> 0
B20: 株式会社 三和サービス
B21: 項目 | F21: =YEAR(I21)-1980+1&"期" -> 42期 | I21: =I2 -> 44227 | L21: =L2 -> 44226
B22: 原価 | F22: =SUMIF(I$3:N$3,$F$3,I22:N22) -> 0 | G22: =IF(ISERROR(F22/H22),0,F22/H22) -> 0 | H22: =SUMIF(I$3:N$3,$H$3,I22:N22) -> 0 | I22: =別紙_テンプレート_三和サービス!H4 -> 0 | J22: =IF(ISERROR(I22/K22),0,I22/K22) -> 0 | K22: =別紙_テンプレート_三和サービス!J4 -> 0 | L22: =別紙_テンプレート_三和サービス!K4 -> 0 | M22: =IF(ISERROR(L22/N22),0,L22/N22) -> 0 | N22: =別紙_テンプレート_三和サービス!M4 -> 0
B23: 営利 | F23: =SUMIF(I$3:N$3,$F$3,I23:N23) -> 0 | G23: =IF(ISERROR(F23/H22),0,F23/H22) -> 0 | I23: =別紙_テンプレート_三和サービス!H6 -> 0 | J23: =IF(ISERROR(I23/K22),0,I23/K22) -> 0 | L23: =別紙_テンプレート_三和サービス!K6 -> 0 | M23: =IF(ISERROR(L23/N22),0,L23/N22) -> 0
B24: 債務 差引 | F24: =OFFSET(F24,,3) -> 0 | G24: 借入 | H24: =OFFSET(H24,,5) -> 0 | I24: =K25-K24 -> 0 | L24: =N25-N24 -> 0
F25: =OFFSET(F25,,3) -> 0 | G25: 現預金 | H25: =OFFSET(H25,,5) -> 0 | I25: =SUM(I24-OFFSET(I24,,3)) -> 0 | L25: =SUM(L24-OFFSET(L24,,3)) -> 0
B26: 株式会社 三和
B27: 項目 | F27: =YEAR(I27)-1985+1&"期" -> 37期 | I27: =I2 -> 44227 | L27: =L2 -> 44226
B28: 原価 | F28: =SUMIF(I$3:N$3,$F$3,I28:N28) -> 0 | G28: =IF(ISERROR(F28/H28),0,F28/H28) -> 0 | H28: =SUMIF(I$3:N$3,$H$3,I28:N28) -> 0 | J28: =IF(ISERROR(I28/K28),0,I28/K28) -> 0 | M28: =IF(ISERROR(L28/N28),0,L28/N28) -> 0
B29: 営利 | F29: =SUMIF(I$3:N$3,$F$3,I29:N29) -> 0 | G29: =IF(ISERROR(F29/H28),0,F29/H28) -> 0 | J29: =IF(ISERROR(I29/K28),0,I29/K28) -> 0 | M29: =IF(ISERROR(L29/N28),0,L29/N28) -> 0
B30: 債務 差引 | F30: =H35-SUM(H30:H34) -> 0 | G30: 長期借入 | I30: =K35-SUM(K30:K34) -> 0 | L30: =N35-SUM(N30:N34) -> 0
G31: Ｇｒ借入
G32: 役員借入
G33: 長期未払
G34: リース債務 | H34: =OFFSET(H34,,5) -> 0
F35: =OFFSET(F35,,3) -> 0 | G35: 現預金 | H35: =OFFSET(H35,,3) -> 0 | I35: =SUM(I30-OFFSET(I30,,3)) -> 0 | L35: =SUM(L30-OFFSET(L30,,3)) -> 0

Sheet 別紙_テンプレート_商研
A1: 営業チーム統計
A2: 項目 | F2: =YEAR(I2)-1978+1&"期" -> 46期 | I2: 45199 | L2: 45198
F3: 原価 | H3: 売上 | I3: 原価 | K3: 売上 | L3: 原価 | N3: 売上
A4: 売上 | C4: 0 | F4: =SUM(I4:N4) -> 0 | I4: =SUMIF($C8:$C34,$C4,I8:I34) -> 0 | J4: =SUMIF($C7:$C33,$C4,J7:J33) -> 0 | K4: =SUMIF($C7:$C33,$C4,K7:K33) -> 0 | L4: =SUMIF($C8:$C34,$C4,L8:L34) -> 0 | M4: =SUMIF($C7:$C33,$C4,M7:M33) -> 0 | N4: =SUMIF($C7:$C33,$C4,N7:N33) -> 0
A5: 原価 | C5: 1 | H5: =SUM(I5:N5) -> 0 | K5: =SUMIF($C8:$C34,$C5,K8:K34) -> 0 | N5: =SUMIF($C8:$C34,$C5,N8:N34) -> 0
A6: 売上総利益 | F6: =SUMIF(I$3:N$3,$F$3,I6:N6) -> 0 | H6: =IF(ISERROR(F6/F4),0,F6/F4) -> 0 | I6: =I4-K5 -> 0 | K6: =IF(ISERROR(I6/I4),0,I6/I4) -> 0 | L6: =L4-N5 -> 0 | N6: =IF(ISERROR(L6/L4),0,L6/L4) -> 0
B7: 在庫 | E7: 20 | F7: =SUMIF(I$3:N$3,$F$3,I7:N7) -> 0 | G7: ⇔ | H7: =SUMIF(I$3:N$3,$H$3,I7:N7) -> 0 | I7: =SUMIF($B$35:$B$98,$B7,I$35:I$98) -> 0 | J7: ⇔ | K7: =SUMIF($B$35:$B$98,$B7,K$35:K$98) -> 0 | L7: =SUMIF($B$35:$B$98,$B7,L$35:L$98) -> 0 | M7: ⇔ | N7: =SUMIF($B$35:$B$98,$B7,N$35:N$98) -> 0
A8: 売上 | C8: 0 | F8: =SUM(H11:H16) -> 0 | I8: =SUM(K11:K16) -> 0 | L8: =SUM(N11:N16) -> 0
A9: 原価 | C9: 1 | H9: =SUM(I9:N9) -> 0 | K9: =SUM(I11:I16) -> 0 | N9: =SUM(L11:L16) -> 0
A10: 売上総利益 | F10: =F8-H9 -> 0 | H10: =IF(ISERROR(F10/F8),0,F10/F8) -> 0 | I10: =I8-K9 -> 0 | K10: =IF(ISERROR(I10/I8),0,I10/I8) -> 0 | L10: =L8-N9 -> 0 | N10: =IF(ISERROR(L10/L8),0,L10/L8) -> 0
A11: 営業１部 | B11: 営業 | D11: 1 | E11: 0 | F11: =SUMIF(I$3:N$3,$F$3,I11:N11) -> 0 | G11: =IF(ISERROR(F11/H11),0,F11/H11) -> 0 | H11: =SUMIF(I$3:N$3,$H$3,I11:N11) -> 0 | I11: =IFERROR(INDEX(別紙_テンプレート_DB!$DQ$3:$DQ$65423,MATCH($D11&"-"&I$2&"-"&$E11,INDEX(別紙_テンプレート_DB!$DM$3:$DM$65423&"-"&別紙_テンプレート_DB!$DN$3:$DN$65423&"-"&別紙_テンプレート_DB!$DO$3:$DO$65423,),0)),0) -> 0 | J11: =IF(ISERROR(I11/K11),0,I11/K11) -> 0 | K11: =IFERROR(INDEX(別紙_テンプレート_DB!$DP$3:$DP$65423,MATCH($D11&"-"&I$2&"-"&$E11,INDEX(別紙_テンプレート_DB!$DM$3:$DM$65423&"-"&別紙_テンプレート_DB!$DN$3:$DN$65423&"-"&別紙_テンプレート_DB!$DO$3:$DO$65423,),0)),0) -> 0 | L11: =IFERROR(INDEX(別紙_テンプレート_DB!$DQ$3:$DQ$65423,MATCH($D11&"-"&L$2&"-"&$E11,INDEX(別紙_テンプレート_DB!$DM$3:$DM$65423&"-"&別紙_テンプレート_DB!$DN$3:$DN$65423&"-"&別紙_テンプレート_DB!$DO$3:$DO$65423,),0)),0) -> 0 | M11: =IF(ISERROR(L11/N11),0,L11/N11) -> 0 | N11: =IFERROR(INDEX(別紙_テンプレート_DB!$DP$3:$DP$65423,MATCH($D11&"-"&L$2&"-"&$E11,INDEX(別紙_テンプレート_DB!$DM$3:$DM$65423&"-"&別紙_テンプレート_DB!$DN$3:$DN$65423&"-"&別紙_テンプレート_DB!$DO$3:$DO$65423,),0)),0) -> 0
B12: 工事 | D12: 1 | E12: 1 | F12: =SUMIF(I$3:N$3,$F$3,I12:N12) -> 0 | G12: =IF(ISERROR(F12/H12),0,F12/H12) -> 0 | H12: =SUMIF(I$3:N$3,$H$3,I12:N12) -> 0 | I12: =IFERROR(INDEX(別紙_テンプレート_DB!$DQ$3:$DQ$65423,MATCH($D12&"-"&I$2&"-"&$E12,INDEX(別紙_テンプレート_DB!$DM$3:$DM$65423&"-"&別紙_テンプレート_DB!$DN$3:$DN$65423&"-"&別紙_テンプレート_DB!$DO$3:$DO$65423,),0)),0) -> 0 | J12: =IF(ISERROR(I12/K12),0,I12/K12) -> 0 | K12: =IFERROR(INDEX(別紙_テンプレート_DB!$DP$3:$DP$65423,MATCH($D12&"-"&I$2&"-"&$E12,INDEX(別紙_テンプレート_DB!$DM$3:$DM$65423&"-"&別紙_テンプレート_DB!$DN$3:$DN$65423&"-"&別紙_テンプレート_DB!$DO$3:$DO$65423,),0)),0) -> 0 | L12: =IFERROR(INDEX(別紙_テンプレート_DB!$DQ$3:$DQ$65423,MATCH($D12&"-"&L$2&"-"&$E12,INDEX(別紙_テンプレート_DB!$DM$3:$DM$65423&"-"&別紙_テンプレート_DB!$DN$3:$DN$65423&"-"&別紙_テンプレート_DB!$DO$3:$DO$65423,),0)),0) -> 0 | M12: =IF(ISERROR(L12/N12),0,L12/N12) -> 0 | N12: =IFERROR(INDEX(別紙_テンプレート_DB!$DP$3:$DP$65423,MATCH($D12&"-"&L$2&"-"&$E12,INDEX(別紙_テンプレート_DB!$DM$3:$DM$65423&"-"&別紙_テンプレート_DB!$DN$3:$DN$65423&"-"&別紙_テンプレート_DB!$DO$3:$DO$65423,),0)),0) -> 0
B13: コール | D13: 1 | E13: 2 | F13: =SUMIF(I$3:N$3,$F$3,I13:N13) -> 0 | G13: =IF(ISERROR(F13/H13),0,F13/H13) -> 0 | H13: =SUMIF(I$3:N$3,$H$3,I13:N13) -> 0 | I13: =IFERROR(INDEX(別紙_テンプレート_DB!$DQ$3:$DQ$65423,MATCH($D13&"-"&I$2&"-"&$E13,INDEX(別紙_テンプレート_DB!$DM$3:$DM$65423&"-"&別紙_テンプレート_DB!$DN$3:$DN$65423&"-"&別紙_テンプレート_DB!$DO$3:$DO$65423,),0)),0) -> 0 | J13: =IF(ISERROR(I13/K13),0,I13/K13) -> 0 | K13: =IFERROR(INDEX(別紙_テンプレート_DB!$DP$3:$DP$65423,MATCH($D13&"-"&I$2&"-"&$E13,INDEX(別紙_テンプレート_DB!$DM$3:$DM$65423&"-"&別紙_テンプレート_DB!$DN$3:$DN$65423&"-"&別紙_テンプレート_DB!$DO$3:$DO$65423,),0)),0) -> 0 | L13: =IFERROR(INDEX(別紙_テンプレート_DB!$DQ$3:$DQ$65423,MATCH($D13&"-"&L$2&"-"&$E13,INDEX(別紙_テンプレート_DB!$DM$3:$DM$65423&"-"&別紙_テンプレート_DB!$DN$3:$DN$65423&"-"&別紙_テンプレート_DB!$DO$3:$DO$65423,),0)),0) -> 0 | M13: =IF(ISERROR(L13/N13),0,L13/N13) -> 0 | N13: =IFERROR(INDEX(別紙_テンプレート_DB!$DP$3:$DP$65423,MATCH($D13&"-"&L$2&"-"&$E13,INDEX(別紙_テンプレート_DB!$DM$3:$DM$65423&"-"&別紙_テンプレート_DB!$DN$3:$DN$65423&"-"&別紙_テンプレート_DB!$DO$3:$DO$65423,),0)),0) -> 0
B14: 店装 | D14: 1 | E14: 3 | F14: =SUMIF(I$3:N$3,$F$3,I14:N14) -> 0 | G14: =IF(ISERROR(F14/H14),0,F14/H14) -> 0 | H14: =SUMIF(I$3:N$3,$H$3,I14:N14) -> 0 | I14: =IFERROR(INDEX(別紙_テンプレート_DB!$DQ$3:$DQ$65423,MATCH($D14&"-"&I$2&"-"&$E14,INDEX(別紙_テンプレート_DB!$DM$3:$DM$65423&"-"&別紙_テンプレート_DB!$DN$3:$DN$65423&"-"&別紙_テンプレート_DB!$DO$3:$DO$65423,),0)),0) -> 0 | J14: =IF(ISERROR(I14/K14),0,I14/K14) -> 0 | K14: =IFERROR(INDEX(別紙_テンプレート_DB!$DP$3:$DP$65423,MATCH($D14&"-"&I$2&"-"&$E14,INDEX(別紙_テンプレート_DB!$DM$3:$DM$65423&"-"&別紙_テンプレート_DB!$DN$3:$DN$65423&"-"&別紙_テンプレート_DB!$DO$3:$DO$65423,),0)),0) -> 0 | L14: =IFERROR(INDEX(別紙_テンプレート_DB!$DQ$3:$DQ$65423,MATCH($D14&"-"&L$2&"-"&$E14,INDEX(別紙_テンプレート_DB!$DM$3:$DM$65423&"-"&別紙_テンプレート_DB!$DN$3:$DN$65423&"-"&別紙_テンプレート_DB!$DO$3:$DO$65423,),0)),0) -> 0 | M14: =IF(ISERROR(L14/N14),0,L14/N14) -> 0 | N14: =IFERROR(INDEX(別紙_テンプレート_DB!$DP$3:$DP$65423,MATCH($D14&"-"&L$2&"-"&$E14,INDEX(別紙_テンプレート_DB!$DM$3:$DM$65423&"-"&別紙_テンプレート_DB!$DN$3:$DN$65423&"-"&別紙_テンプレート_DB!$DO$3:$DO$65423,),0)),0) -> 0
B15: 委託 | D15: 1 | E15: 106 | F15: =SUMIF(I$3:N$3,$F$3,I15:N15) -> 0 | G15: =IF(ISERROR(F15/H15),0,F15/H15) -> 0 | H15: =SUMIF(I$3:N$3,$H$3,I15:N15) -> 0 | I15: =IFERROR(INDEX(別紙_テンプレート_DB!$DQ$3:$DQ$65423,MATCH($D15&"-"&I$2&"-"&$E15,INDEX(別紙_テンプレート_DB!$DM$3:$DM$65423&"-"&別紙_テンプレート_DB!$DN$3:$DN$65423&"-"&別紙_テンプレート_DB!$DO$3:$DO$65423,),0)),0) -> 0 | J15: =IF(ISERROR(I15/K15),0,I15/K15) -> 0 | K15: =IFERROR(INDEX(別紙_テンプレート_DB!$DP$3:$DP$65423,MATCH($D15&"-"&I$2&"-"&$E15,INDEX(別紙_テンプレート_DB!$DM$3:$DM$65423&"-"&別紙_テンプレート_DB!$DN$3:$DN$65423&"-"&別紙_テンプレート_DB!$DO$3:$DO$65423,),0)),0) -> 0 | L15: =IFERROR(INDEX(別紙_テンプレート_DB!$DQ$3:$DQ$65423,MATCH($D15&"-"&L$2&"-"&$E15,INDEX(別紙_テンプレート_DB!$DM$3:$DM$65423&"-"&別紙_テンプレート_DB!$DN$3:$DN$65423&"-"&別紙_テンプレート_DB!$DO$3:$DO$65423,),0)),0) -> 0 | M15: =IF(ISERROR(L15/N15),0,L15/N15) -> 0 | N15: =IFERROR(INDEX(別紙_テンプレート_DB!$DP$3:$DP$65423,MATCH($D15&"-"&L$2&"-"&$E15,INDEX(別紙_テンプレート_DB!$DM$3:$DM$65423&"-"&別紙_テンプレート_DB!$DN$3:$DN$65423&"-"&別紙_テンプレート_DB!$DO$3:$DO$65423,),0)),0) -> 0
B16: クレーム | D16: 1 | E16: 4 | F16: =SUMIF(I$3:N$3,$F$3,I16:N16) -> 0 | G16: =IF(ISERROR(F16/H16),0,F16/H16) -> 0 | H16: =SUMIF(I$3:N$3,$H$3,I16:N16) -> 0 | I16: =IFERROR(INDEX(別紙_テンプレート_DB!$DQ$3:$DQ$65423,MATCH($D16&"-"&I$2&"-"&$E16,INDEX(別紙_テンプレート_DB!$DM$3:$DM$65423&"-"&別紙_テンプレート_DB!$DN$3:$DN$65423&"-"&別紙_テンプレート_DB!$DO$3:$DO$65423,),0)),0) -> 0 | J16: =IF(ISERROR(I16/K16),0,I16/K16) -> 0 | K16: =IFERROR(INDEX(別紙_テンプレート_DB!$DP$3:$DP$65423,MATCH($D16&"-"&I$2&"-"&$E16,INDEX(別紙_テンプレート_DB!$DM$3:$DM$65423&"-"&別紙_テンプレート_DB!$DN$3:$DN$65423&"-"&別紙_テンプレート_DB!$DO$3:$DO$65423,),0)),0) -> 0 | L16: =IFERROR(INDEX(別紙_テンプレート_DB!$DQ$3:$DQ$65423,MATCH($D16&"-"&L$2&"-"&$E16,INDEX(別紙_テンプレート_DB!$DM$3:$DM$65423&"-"&別紙_テンプレート_DB!$DN$3:$DN$65423&"-"&別紙_テンプレート_DB!$DO$3:$DO$65423,),0)),0) -> 0 | M16: =IF(ISERROR(L16/N16),0,L16/N16) -> 0 | N16: =IFERROR(INDEX(別紙_テンプレート_DB!$DP$3:$DP$65423,MATCH($D16&"-"&L$2&"-"&$E16,INDEX(別紙_テンプレート_DB!$DM$3:$DM$65423&"-"&別紙_テンプレート_DB!$DN$3:$DN$65423&"-"&別紙_テンプレート_DB!$DO$3:$DO$65423,),0)),0) -> 0
A17: 売上 | C17: 0 | F17: =SUM(H20:H25) -> 0 | I17: =SUM(K20:K25) -> 0 | L17: =SUM(N20:N25) -> 0
A18: 原価 | C18: 1 | H18: =SUM(I18:N18) -> 0 | K18: =SUM(I20:I25) -> 0 | N18: =SUM(L20:L25) -> 0
A19: 売上総利益 | F19: =F17-H18 -> 0 | H19: =IF(ISERROR(F19/F17),0,F19/F17) -> 0 | I19: =I17-K18 -> 0 | K19: =IF(ISERROR(I19/I17),0,I19/I17) -> 0 | L19: =L17-N18 -> 0 | N19: =IF(ISERROR(L19/L17),0,L19/L17) -> 0
A20: 営業２部 | B20: 営業 | D20: 2 | E20: 0 | F20: =SUMIF(I$3:N$3,$F$3,I20:N20) -> 0 | G20: =IF(ISERROR(F20/H20),0,F20/H20) -> 0 | H20: =SUMIF(I$3:N$3,$H$3,I20:N20) -> 0 | I20: =IFERROR(INDEX(別紙_テンプレート_DB!$DQ$3:$DQ$65423,MATCH($D20&"-"&I$2&"-"&$E20,INDEX(別紙_テンプレート_DB!$DM$3:$DM$65423&"-"&別紙_テンプレート_DB!$DN$3:$DN$65423&"-"&別紙_テンプレート_DB!$DO$3:$DO$65423,),0)),0) -> 0 | J20: =IF(ISERROR(I20/K20),0,I20/K20) -> 0 | K20: =IFERROR(INDEX(別紙_テンプレート_DB!$DP$3:$DP$65423,MATCH($D20&"-"&I$2&"-"&$E20,INDEX(別紙_テンプレート_DB!$DM$3:$DM$65423&"-"&別紙_テンプレート_DB!$DN$3:$DN$65423&"-"&別紙_テンプレート_DB!$DO$3:$DO$65423,),0)),0) -> 0 | L20: =IFERROR(INDEX(別紙_テンプレート_DB!$DQ$3:$DQ$65423,MATCH($D20&"-"&L$2&"-"&$E20,INDEX(別紙_テンプレート_DB!$DM$3:$DM$65423&"-"&別紙_テンプレート_DB!$DN$3:$DN$65423&"-"&別紙_テンプレート_DB!$DO$3:$DO$65423,),0)),0) -> 0 | M20: =IF(ISERROR(L20/N20),0,L20/N20) -> 0 | N20: =IFERROR(INDEX(別紙_テンプレート_DB!$DP$3:$DP$65423,MATCH($D20&"-"&L$2&"-"&$E20,INDEX(別紙_テンプレート_DB!$DM$3:$DM$65423&"-"&別紙_テンプレート_DB!$DN$3:$DN$65423&"-"&別紙_テンプレート_DB!$DO$3:$DO$65423,),0)),0) -> 0
B21: 工事 | D21: 2 | E21: 1 | F21: =SUMIF(I$3:N$3,$F$3,I21:N21) -> 0 | G21: =IF(ISERROR(F21/H21),0,F21/H21) -> 0 | H21: =SUMIF(I$3:N$3,$H$3,I21:N21) -> 0 | I21: =IFERROR(INDEX(別紙_テンプレート_DB!$DQ$3:$DQ$65423,MATCH($D21&"-"&I$2&"-"&$E21,INDEX(別紙_テンプレート_DB!$DM$3:$DM$65423&"-"&別紙_テンプレート_DB!$DN$3:$DN$65423&"-"&別紙_テンプレート_DB!$DO$3:$DO$65423,),0)),0) -> 0 | J21: =IF(ISERROR(I21/K21),0,I21/K21) -> 0 | K21: =IFERROR(INDEX(別紙_テンプレート_DB!$DP$3:$DP$65423,MATCH($D21&"-"&I$2&"-"&$E21,INDEX(別紙_テンプレート_DB!$DM$3:$DM$65423&"-"&別紙_テンプレート_DB!$DN$3:$DN$65423&"-"&別紙_テンプレート_DB!$DO$3:$DO$65423,),0)),0) -> 0 | L21: =IFERROR(INDEX(別紙_テンプレート_DB!$DQ$3:$DQ$65423,MATCH($D21&"-"&L$2&"-"&$E21,INDEX(別紙_テンプレート_DB!$DM$3:$DM$65423&"-"&別紙_テンプレート_DB!$DN$3:$DN$65423&"-"&別紙_テンプレート_DB!$DO$3:$DO$65423,),0)),0) -> 0 | M21: =IF(ISERROR(L21/N21),0,L21/N21) -> 0 | N21: =IFERROR(INDEX(別紙_テンプレート_DB!$DP$3:$DP$65423,MATCH($D21&"-"&L$2&"-"&$E21,INDEX(別紙_テンプレート_DB!$DM$3:$DM$65423&"-"&別紙_テンプレート_DB!$DN$3:$DN$65423&"-"&別紙_テンプレート_DB!$DO$3:$DO$65423,),0)),0) -> 0
B22: コール | D22: 2 | E22: 2 | F22: =SUMIF(I$3:N$3,$F$3,I22:N22) -> 0 | G22: =IF(ISERROR(F22/H22),0,F22/H22) -> 0 | H22: =SUMIF(I$3:N$3,$H$3,I22:N22) -> 0 | I22: =IFERROR(INDEX(別紙_テンプレート_DB!$DQ$3:$DQ$65423,MATCH($D22&"-"&I$2&"-"&$E22,INDEX(別紙_テンプレート_DB!$DM$3:$DM$65423&"-"&別紙_テンプレート_DB!$DN$3:$DN$65423&"-"&別紙_テンプレート_DB!$DO$3:$DO$65423,),0)),0) -> 0 | J22: =IF(ISERROR(I22/K22),0,I22/K22) -> 0 | K22: =IFERROR(INDEX(別紙_テンプレート_DB!$DP$3:$DP$65423,MATCH($D22&"-"&I$2&"-"&$E22,INDEX(別紙_テンプレート_DB!$DM$3:$DM$65423&"-"&別紙_テンプレート_DB!$DN$3:$DN$65423&"-"&別紙_テンプレート_DB!$DO$3:$DO$65423,),0)),0) -> 0 | L22: =IFERROR(INDEX(別紙_テンプレート_DB!$DQ$3:$DQ$65423,MATCH($D22&"-"&L$2&"-"&$E22,INDEX(別紙_テンプレート_DB!$DM$3:$DM$65423&"-"&別紙_テンプレート_DB!$DN$3:$DN$65423&"-"&別紙_テンプレート_DB!$DO$3:$DO$65423,),0)),0) -> 0 | M22: =IF(ISERROR(L22/N22),0,L22/N22) -> 0 | N22: =IFERROR(INDEX(別紙_テンプレート_DB!$DP$3:$DP$65423,MATCH($D22&"-"&L$2&"-"&$E22,INDEX(別紙_テンプレート_DB!$DM$3:$DM$65423&"-"&別紙_テンプレート_DB!$DN$3:$DN$65423&"-"&別紙_テンプレート_DB!$DO$3:$DO$65423,),0)),0) -> 0
B23: 店装 | D23: 2 | E23: 3 | F23: =SUMIF(I$3:N$3,$F$3,I23:N23) -> 0 | G23: =IF(ISERROR(F23/H23),0,F23/H23) -> 0 | H23: =SUMIF(I$3:N$3,$H$3,I23:N23) -> 0 | I23: =IFERROR(INDEX(別紙_テンプレート_DB!$DQ$3:$DQ$65423,MATCH($D23&"-"&I$2&"-"&$E23,INDEX(別紙_テンプレート_DB!$DM$3:$DM$65423&"-"&別紙_テンプレート_DB!$DN$3:$DN$65423&"-"&別紙_テンプレート_DB!$DO$3:$DO$65423,),0)),0) -> 0 | J23: =IF(ISERROR(I23/K23),0,I23/K23) -> 0 | K23: =IFERROR(INDEX(別紙_テンプレート_DB!$DP$3:$DP$65423,MATCH($D23&"-"&I$2&"-"&$E23,INDEX(別紙_テンプレート_DB!$DM$3:$DM$65423&"-"&別紙_テンプレート_DB!$DN$3:$DN$65423&"-"&別紙_テンプレート_DB!$DO$3:$DO$65423,),0)),0) -> 0 | L23: =IFERROR(INDEX(別紙_テンプレート_DB!$DQ$3:$DQ$65423,MATCH($D23&"-"&L$2&"-"&$E23,INDEX(別紙_テンプレート_DB!$DM$3:$DM$65423&"-"&別紙_テンプレート_DB!$DN$3:$DN$65423&"-"&別紙_テンプレート_DB!$DO$3:$DO$65423,),0)),0) -> 0 | M23: =IF(ISERROR(L23/N23),0,L23/N23) -> 0 | N23: =IFERROR(INDEX(別紙_テンプレート_DB!$DP$3:$DP$65423,MATCH($D23&"-"&L$2&"-"&$E23,INDEX(別紙_テンプレート_DB!$DM$3:$DM$65423&"-"&別紙_テンプレート_DB!$DN$3:$DN$65423&"-"&別紙_テンプレート_DB!$DO$3:$DO$65423,),0)),0) -> 0
B24: 委託 | D24: 2 | E24: 106 | F24: =SUMIF(I$3:N$3,$F$3,I24:N24) -> 0 | G24: =IF(ISERROR(F24/H24),0,F24/H24) -> 0 | H24: =SUMIF(I$3:N$3,$H$3,I24:N24) -> 0 | I24: =IFERROR(INDEX(別紙_テンプレート_DB!$DQ$3:$DQ$65423,MATCH($D24&"-"&I$2&"-"&$E24,INDEX(別紙_テンプレート_DB!$DM$3:$DM$65423&"-"&別紙_テンプレート_DB!$DN$3:$DN$65423&"-"&別紙_テンプレート_DB!$DO$3:$DO$65423,),0)),0) -> 0 | J24: =IF(ISERROR(I24/K24),0,I24/K24) -> 0 | K24: =IFERROR(INDEX(別紙_テンプレート_DB!$DP$3:$DP$65423,MATCH($D24&"-"&I$2&"-"&$E24,INDEX(別紙_テンプレート_DB!$DM$3:$DM$65423&"-"&別紙_テンプレート_DB!$DN$3:$DN$65423&"-"&別紙_テンプレート_DB!$DO$3:$DO$65423,),0)),0) -> 0 | L24: =IFERROR(INDEX(別紙_テンプレート_DB!$DQ$3:$DQ$65423,MATCH($D24&"-"&L$2&"-"&$E24,INDEX(別紙_テンプレート_DB!$DM$3:$DM$65423&"-"&別紙_テンプレート_DB!$DN$3:$DN$65423&"-"&別紙_テンプレート_DB!$DO$3:$DO$65423,),0)),0) -> 0 | M24: =IF(ISERROR(L24/N24),0,L24/N24) -> 0 | N24: =IFERROR(INDEX(別紙_テンプレート_DB!$DP$3:$DP$65423,MATCH($D24&"-"&L$2&"-"&$E24,INDEX(別紙_テンプレート_DB!$DM$3:$DM$65423&"-"&別紙_テンプレート_DB!$DN$3:$DN$65423&"-"&別紙_テンプレート_DB!$DO$3:$DO$65423,),0)),0) -> 0
B25: クレーム | D25: 2 | E25: 4 | F25: =SUMIF(I$3:N$3,$F$3,I25:N25) -> 0 | G25: =IF(ISERROR(F25/H25),0,F25/H25) -> 0 | H25: =SUMIF(I$3:N$3,$H$3,I25:N25) -> 0 | I25: =IFERROR(INDEX(別紙_テンプレート_DB!$DQ$3:$DQ$65423,MATCH($D25&"-"&I$2&"-"&$E25,INDEX(別紙_テンプレート_DB!$DM$3:$DM$65423&"-"&別紙_テンプレート_DB!$DN$3:$DN$65423&"-"&別紙_テンプレート_DB!$DO$3:$DO$65423,),0)),0) -> 0 | J25: =IF(ISERROR(I25/K25),0,I25/K25) -> 0 | K25: =IFERROR(INDEX(別紙_テンプレート_DB!$DP$3:$DP$65423,MATCH($D25&"-"&I$2&"-"&$E25,INDEX(別紙_テンプレート_DB!$DM$3:$DM$65423&"-"&別紙_テンプレート_DB!$DN$3:$DN$65423&"-"&別紙_テンプレート_DB!$DO$3:$DO$65423,),0)),0) -> 0 | L25: =IFERROR(INDEX(別紙_テンプレート_DB!$DQ$3:$DQ$65423,MATCH($D25&"-"&L$2&"-"&$E25,INDEX(別紙_テンプレート_DB!$DM$3:$DM$65423&"-"&別紙_テンプレート_DB!$DN$3:$DN$65423&"-"&別紙_テンプレート_DB!$DO$3:$DO$65423,),0)),0) -> 0 | M25: =IF(ISERROR(L25/N25),0,L25/N25) -> 0 | N25: =IFERROR(INDEX(別紙_テンプレート_DB!$DP$3:$DP$65423,MATCH($D25&"-"&L$2&"-"&$E25,INDEX(別紙_テンプレート_DB!$DM$3:$DM$65423&"-"&別紙_テンプレート_DB!$DN$3:$DN$65423&"-"&別紙_テンプレート_DB!$DO$3:$DO$65423,),0)),0) -> 0
A26: 売上 | C26: 0 | F26: =SUM(H29:H34) -> 0 | I26: =SUM(K29:K34) -> 0 | L26: =SUM(N29:N34) -> 0
A27: 原価 | C27: 1 | H27: =SUM(I27:N27) -> 0 | K27: =SUM(I29:I34) -> 0 | N27: =SUM(L29:L34) -> 0
A28: 売上総利益 | F28: =F26-H27 -> 0 | H28: =IF(ISERROR(F28/F26),0,F28/F26) -> 0 | I28: =I26-K27 -> 0 | K28: =IF(ISERROR(I28/I26),0,I28/I26) -> 0 | L28: =L26-N27 -> 0 | N28: =IF(ISERROR(L28/L26),0,L28/L26) -> 0
A29: 営業３部 | B29: 営業 | D29: 3 | E29: 0 | F29: =SUMIF(I$3:N$3,$F$3,I29:N29) -> 0 | G29: =IF(ISERROR(F29/H29),0,F29/H29) -> 0 | H29: =SUMIF(I$3:N$3,$H$3,I29:N29) -> 0 | I29: =IFERROR(INDEX(別紙_テンプレート_DB!$DQ$3:$DQ$65423,MATCH($D29&"-"&I$2&"-"&$E29,INDEX(別紙_テンプレート_DB!$DM$3:$DM$65423&"-"&別紙_テンプレート_DB!$DN$3:$DN$65423&"-"&別紙_テンプレート_DB!$DO$3:$DO$65423,),0)),0) -> 0 | J29: =IF(ISERROR(I29/K29),0,I29/K29) -> 0 | K29: =IFERROR(INDEX(別紙_テンプレート_DB!$DP$3:$DP$65423,MATCH($D29&"-"&I$2&"-"&$E29,INDEX(別紙_テンプレート_DB!$DM$3:$DM$65423&"-"&別紙_テンプレート_DB!$DN$3:$DN$65423&"-"&別紙_テンプレート_DB!$DO$3:$DO$65423,),0)),0) -> 0 | L29: =IFERROR(INDEX(別紙_テンプレート_DB!$DQ$3:$DQ$65423,MATCH($D29&"-"&L$2&"-"&$E29,INDEX(別紙_テンプレート_DB!$DM$3:$DM$65423&"-"&別紙_テンプレート_DB!$DN$3:$DN$65423&"-"&別紙_テンプレート_DB!$DO$3:$DO$65423,),0)),0) -> 0 | M29: =IF(ISERROR(L29/N29),0,L29/N29) -> 0 | N29: =IFERROR(INDEX(別紙_テンプレート_DB!$DP$3:$DP$65423,MATCH($D29&"-"&L$2&"-"&$E29,INDEX(別紙_テンプレート_DB!$DM$3:$DM$65423&"-"&別紙_テンプレート_DB!$DN$3:$DN$65423&"-"&別紙_テンプレート_DB!$DO$3:$DO$65423,),0)),0) -> 0
B30: 工事 | D30: 3 | E30: 1 | F30: =SUMIF(I$3:N$3,$F$3,I30:N30) -> 0 | G30: =IF(ISERROR(F30/H30),0,F30/H30) -> 0 | H30: =SUMIF(I$3:N$3,$H$3,I30:N30) -> 0 | I30: =IFERROR(INDEX(別紙_テンプレート_DB!$DQ$3:$DQ$65423,MATCH($D30&"-"&I$2&"-"&$E30,INDEX(別紙_テンプレート_DB!$DM$3:$DM$65423&"-"&別紙_テンプレート_DB!$DN$3:$DN$65423&"-"&別紙_テンプレート_DB!$DO$3:$DO$65423,),0)),0) -> 0 | J30: =IF(ISERROR(I30/K30),0,I30/K30) -> 0 | K30: =IFERROR(INDEX(別紙_テンプレート_DB!$DP$3:$DP$65423,MATCH($D30&"-"&I$2&"-"&$E30,INDEX(別紙_テンプレート_DB!$DM$3:$DM$65423&"-"&別紙_テンプレート_DB!$DN$3:$DN$65423&"-"&別紙_テンプレート_DB!$DO$3:$DO$65423,),0)),0) -> 0 | L30: =IFERROR(INDEX(別紙_テンプレート_DB!$DQ$3:$DQ$65423,MATCH($D30&"-"&L$2&"-"&$E30,INDEX(別紙_テンプレート_DB!$DM$3:$DM$65423&"-"&別紙_テンプレート_DB!$DN$3:$DN$65423&"-"&別紙_テンプレート_DB!$DO$3:$DO$65423,),0)),0) -> 0 | M30: =IF(ISERROR(L30/N30),0,L30/N30) -> 0 | N30: =IFERROR(INDEX(別紙_テンプレート_DB!$DP$3:$DP$65423,MATCH($D30&"-"&L$2&"-"&$E30,INDEX(別紙_テンプレート_DB!$DM$3:$DM$65423&"-"&別紙_テンプレート_DB!$DN$3:$DN$65423&"-"&別紙_テンプレート_DB!$DO$3:$DO$65423,),0)),0) -> 0
B31: コール | D31: 3 | E31: 2 | F31: =SUMIF(I$3:N$3,$F$3,I31:N31) -> 0 | G31: =IF(ISERROR(F31/H31),0,F31/H31) -> 0 | H31: =SUMIF(I$3:N$3,$H$3,I31:N31) -> 0 | I31: =IFERROR(INDEX(別紙_テンプレート_DB!$DQ$3:$DQ$65423,MATCH($D31&"-"&I$2&"-"&$E31,INDEX(別紙_テンプレート_DB!$DM$3:$DM$65423&"-"&別紙_テンプレート_DB!$DN$3:$DN$65423&"-"&別紙_テンプレート_DB!$DO$3:$DO$65423,),0)),0) -> 0 | J31: =IF(ISERROR(I31/K31),0,I31/K31) -> 0 | K31: =IFERROR(INDEX(別紙_テンプレート_DB!$DP$3:$DP$65423,MATCH($D31&"-"&I$2&"-"&$E31,INDEX(別紙_テンプレート_DB!$DM$3:$DM$65423&"-"&別紙_テンプレート_DB!$DN$3:$DN$65423&"-"&別紙_テンプレート_DB!$DO$3:$DO$65423,),0)),0) -> 0 | L31: =IFERROR(INDEX(別紙_テンプレート_DB!$DQ$3:$DQ$65423,MATCH($D31&"-"&L$2&"-"&$E31,INDEX(別紙_テンプレート_DB!$DM$3:$DM$65423&"-"&別紙_テンプレート_DB!$DN$3:$DN$65423&"-"&別紙_テンプレート_DB!$DO$3:$DO$65423,),0)),0) -> 0 | M31: =IF(ISERROR(L31/N31),0,L31/N31) -> 0 | N31: =IFERROR(INDEX(別紙_テンプレート_DB!$DP$3:$DP$65423,MATCH($D31&"-"&L$2&"-"&$E31,INDEX(別紙_テンプレート_DB!$DM$3:$DM$65423&"-"&別紙_テンプレート_DB!$DN$3:$DN$65423&"-"&別紙_テンプレート_DB!$DO$3:$DO$65423,),0)),0) -> 0
B32: 店装 | D32: 3 | E32: 3 | F32: =SUMIF(I$3:N$3,$F$3,I32:N32) -> 0 | G32: =IF(ISERROR(F32/H32),0,F32/H32) -> 0 | H32: =SUMIF(I$3:N$3,$H$3,I32:N32) -> 0 | I32: =IFERROR(INDEX(別紙_テンプレート_DB!$DQ$3:$DQ$65423,MATCH($D32&"-"&I$2&"-"&$E32,INDEX(別紙_テンプレート_DB!$DM$3:$DM$65423&"-"&別紙_テンプレート_DB!$DN$3:$DN$65423&"-"&別紙_テンプレート_DB!$DO$3:$DO$65423,),0)),0) -> 0 | J32: =IF(ISERROR(I32/K32),0,I32/K32) -> 0 | K32: =IFERROR(INDEX(別紙_テンプレート_DB!$DP$3:$DP$65423,MATCH($D32&"-"&I$2&"-"&$E32,INDEX(別紙_テンプレート_DB!$DM$3:$DM$65423&"-"&別紙_テンプレート_DB!$DN$3:$DN$65423&"-"&別紙_テンプレート_DB!$DO$3:$DO$65423,),0)),0) -> 0 | L32: =IFERROR(INDEX(別紙_テンプレート_DB!$DQ$3:$DQ$65423,MATCH($D32&"-"&L$2&"-"&$E32,INDEX(別紙_テンプレート_DB!$DM$3:$DM$65423&"-"&別紙_テンプレート_DB!$DN$3:$DN$65423&"-"&別紙_テンプレート_DB!$DO$3:$DO$65423,),0)),0) -> 0 | M32: =IF(ISERROR(L32/N32),0,L32/N32) -> 0 | N32: =IFERROR(INDEX(別紙_テンプレート_DB!$DP$3:$DP$65423,MATCH($D32&"-"&L$2&"-"&$E32,INDEX(別紙_テンプレート_DB!$DM$3:$DM$65423&"-"&別紙_テンプレート_DB!$DN$3:$DN$65423&"-"&別紙_テンプレート_DB!$DO$3:$DO$65423,),0)),0) -> 0
B33: 委託 | D33: 3 | E33: 106 | F33: =SUMIF(I$3:N$3,$F$3,I33:N33) -> 0 | G33: =IF(ISERROR(F33/H33),0,F33/H33) -> 0 | H33: =SUMIF(I$3:N$3,$H$3,I33:N33) -> 0 | I33: =IFERROR(INDEX(別紙_テンプレート_DB!$DQ$3:$DQ$65423,MATCH($D33&"-"&I$2&"-"&$E33,INDEX(別紙_テンプレート_DB!$DM$3:$DM$65423&"-"&別紙_テンプレート_DB!$DN$3:$DN$65423&"-"&別紙_テンプレート_DB!$DO$3:$DO$65423,),0)),0) -> 0 | J33: =IF(ISERROR(I33/K33),0,I33/K33) -> 0 | K33: =IFERROR(INDEX(別紙_テンプレート_DB!$DP$3:$DP$65423,MATCH($D33&"-"&I$2&"-"&$E33,INDEX(別紙_テンプレート_DB!$DM$3:$DM$65423&"-"&別紙_テンプレート_DB!$DN$3:$DN$65423&"-"&別紙_テンプレート_DB!$DO$3:$DO$65423,),0)),0) -> 0 | L33: =IFERROR(INDEX(別紙_テンプレート_DB!$DQ$3:$DQ$65423,MATCH($D33&"-"&L$2&"-"&$E33,INDEX(別紙_テンプレート_DB!$DM$3:$DM$65423&"-"&別紙_テンプレート_DB!$DN$3:$DN$65423&"-"&別紙_テンプレート_DB!$DO$3:$DO$65423,),0)),0) -> 0 | M33: =IF(ISERROR(L33/N33),0,L33/N33) -> 0 | N33: =IFERROR(INDEX(別紙_テンプレート_DB!$DP$3:$DP$65423,MATCH($D33&"-"&L$2&"-"&$E33,INDEX(別紙_テンプレート_DB!$DM$3:$DM$65423&"-"&別紙_テンプレート_DB!$DN$3:$DN$65423&"-"&別紙_テンプレート_DB!$DO$3:$DO$65423,),0)),0) -> 0
B34: クレーム | D34: 3 | E34: 4 | F34: =SUMIF(I$3:N$3,$F$3,I34:N34) -> 0 | G34: =IF(ISERROR(F34/H34),0,F34/H34) -> 0 | H34: =SUMIF(I$3:N$3,$H$3,I34:N34) -> 0 | I34: =IFERROR(INDEX(別紙_テンプレート_DB!$DQ$3:$DQ$65423,MATCH($D34&"-"&I$2&"-"&$E34,INDEX(別紙_テンプレート_DB!$DM$3:$DM$65423&"-"&別紙_テンプレート_DB!$DN$3:$DN$65423&"-"&別紙_テンプレート_DB!$DO$3:$DO$65423,),0)),0) -> 0 | J34: =IF(ISERROR(I34/K34),0,I34/K34) -> 0 | K34: =IFERROR(INDEX(別紙_テンプレート_DB!$DP$3:$DP$65423,MATCH($D34&"-"&I$2&"-"&$E34,INDEX(別紙_テンプレート_DB!$DM$3:$DM$65423&"-"&別紙_テンプレート_DB!$DN$3:$DN$65423&"-"&別紙_テンプレート_DB!$DO$3:$DO$65423,),0)),0) -> 0 | L34: =IFERROR(INDEX(別紙_テンプレート_DB!$DQ$3:$DQ$65423,MATCH($D34&"-"&L$2&"-"&$E34,INDEX(別紙_テンプレート_DB!$DM$3:$DM$65423&"-"&別紙_テンプレート_DB!$DN$3:$DN$65423&"-"&別紙_テンプレート_DB!$DO$3:$DO$65423,),0)),0) -> 0 | M34: =IF(ISERROR(L34/N34),0,L34/N34) -> 0 | N34: =IFERROR(INDEX(別紙_テンプレート_DB!$DP$3:$DP$65423,MATCH($D34&"-"&L$2&"-"&$E34,INDEX(別紙_テンプレート_DB!$DM$3:$DM$65423&"-"&別紙_テンプレート_DB!$DN$3:$DN$65423&"-"&別紙_テンプレート_DB!$DO$3:$DO$65423,),0)),0) -> 0
A35: W | B35: 原/売 | D35: 2401 | F35: =SUMIF(I$3:N$3,$F$3,I35:N35) -> 0 | G35: =IF(ISERROR(F35/H35),0,F35/H35) -> 0 | H35: =SUMIF(I$3:N$3,$H$3,I35:N35) -> 0 | I35: =SUMIF($D36:$D41,$D35,I36:I41) -> 0 | J35: =IF(ISERROR(I35/K35),0,I35/K35) -> 0 | K35: =SUM(K36:K41) -> 0 | L35: =SUMIF($D36:$D41,$D35,L36:L41) -> 0 | M35: =IF(ISERROR(L35/N35),0,L35/N35) -> 0 | N35: =SUM(N36:N41) -> 0
B36: 営業 | C36: 0 | D36: 2401 | E36: 0 | F36: =SUMIF(I$3:N$3,$F$3,I36:N36) -> 0 | G36: =IF(ISERROR(F36/H36),0,F36/H36) -> 0 | H36: =SUMIF(I$3:N$3,$H$3,I36:N36) -> 0 | I36: =IFERROR(INDEX(別紙_テンプレート_DB!$G$3:$G$65423,MATCH($C36&"-"&$D36&"-"&I$2&"-"&$E36,INDEX(別紙_テンプレート_DB!$A$3:$A$65423&"-"&別紙_テンプレート_DB!$C$3:$C$65423&"-"&別紙_テンプレート_DB!$D$3:$D$65423&"-"&別紙_テンプレート_DB!$E$3:$E$65423,),0)),0) -> 0 | J36: =IF(ISERROR(I36/K36),0,I36/K36) -> 0 | K36: =IFERROR(INDEX(別紙_テンプレート_DB!$F$3:$F$65423,MATCH($C36&"-"&$D36&"-"&I$2&"-"&$E36,INDEX(別紙_テンプレート_DB!$A$3:$A$65423&"-"&別紙_テンプレート_DB!$C$3:$C$65423&"-"&別紙_テンプレート_DB!$D$3:$D$65423&"-"&別紙_テンプレート_DB!$E$3:$E$65423,),0)),0) -> 0 | L36: =IFERROR(INDEX(別紙_テンプレート_DB!$G$3:$G$65423,MATCH($C36&"-"&$D36&"-"&L$2&"-"&$E36,INDEX(別紙_テンプレート_DB!$A$3:$A$65423&"-"&別紙_テンプレート_DB!$C$3:$C$65423&"-"&別紙_テンプレート_DB!$D$3:$D$65423&"-"&別紙_テンプレート_DB!$E$3:$E$65423,),0)),0) -> 0 | M36: =IF(ISERROR(L36/N36),0,L36/N36) -> 0 | N36: =IFERROR(INDEX(別紙_テンプレート_DB!$F$3:$F$65423,MATCH($C36&"-"&$D36&"-"&L$2&"-"&$E36,INDEX(別紙_テンプレート_DB!$A$3:$A$65423&"-"&別紙_テンプレート_DB!$C$3:$C$65423&"-"&別紙_テンプレート_DB!$D$3:$D$65423&"-"&別紙_テンプレート_DB!$E$3:$E$65423,),0)),0) -> 0
B37: 工事 | C37: 0 | D37: 2401 | E37: 1 | F37: =SUMIF(I$3:N$3,$F$3,I37:N37) -> 0 | G37: =IF(ISERROR(F37/H37),0,F37/H37) -> 0 | H37: =SUMIF(I$3:N$3,$H$3,I37:N37) -> 0 | I37: =IFERROR(INDEX(別紙_テンプレート_DB!$G$3:$G$65423,MATCH($C37&"-"&$D37&"-"&I$2&"-"&$E37,INDEX(別紙_テンプレート_DB!$A$3:$A$65423&"-"&別紙_テンプレート_DB!$C$3:$C$65423&"-"&別紙_テンプレート_DB!$D$3:$D$65423&"-"&別紙_テンプレート_DB!$E$3:$E$65423,),0)),0) -> 0 | J37: =IF(ISERROR(I37/K37),0,I37/K37) -> 0 | K37: =IFERROR(INDEX(別紙_テンプレート_DB!$F$3:$F$65423,MATCH($C37&"-"&$D37&"-"&I$2&"-"&$E37,INDEX(別紙_テンプレート_DB!$A$3:$A$65423&"-"&別紙_テンプレート_DB!$C$3:$C$65423&"-"&別紙_テンプレート_DB!$D$3:$D$65423&"-"&別紙_テンプレート_DB!$E$3:$E$65423,),0)),0) -> 0 | L37: =IFERROR(INDEX(別紙_テンプレート_DB!$G$3:$G$65423,MATCH($C37&"-"&$D37&"-"&L$2&"-"&$E37,INDEX(別紙_テンプレート_DB!$A$3:$A$65423&"-"&別紙_テンプレート_DB!$C$3:$C$65423&"-"&別紙_テンプレート_DB!$D$3:$D$65423&"-"&別紙_テンプレート_DB!$E$3:$E$65423,),0)),0) -> 0 | M37: =IF(ISERROR(L37/N37),0,L37/N37) -> 0 | N37: =IFERROR(INDEX(別紙_テンプレート_DB!$F$3:$F$65423,MATCH($C37&"-"&$D37&"-"&L$2&"-"&$E37,INDEX(別紙_テンプレート_DB!$A$3:$A$65423&"-"&別紙_テンプレート_DB!$C$3:$C$65423&"-"&別紙_テンプレート_DB!$D$3:$D$65423&"-"&別紙_テンプレート_DB!$E$3:$E$65423,),0)),0) -> 0
B38: コール | C38: 0 | D38: 2401 | E38: 2 | F38: =SUMIF(I$3:N$3,$F$3,I38:N38) -> 0 | G38: =IF(ISERROR(F38/H38),0,F38/H38) -> 0 | H38: =SUMIF(I$3:N$3,$H$3,I38:N38) -> 0 | I38: =IFERROR(INDEX(別紙_テンプレート_DB!$G$3:$G$65423,MATCH($C38&"-"&$D38&"-"&I$2&"-"&$E38,INDEX(別紙_テンプレート_DB!$A$3:$A$65423&"-"&別紙_テンプレート_DB!$C$3:$C$65423&"-"&別紙_テンプレート_DB!$D$3:$D$65423&"-"&別紙_テンプレート_DB!$E$3:$E$65423,),0)),0) -> 0 | J38: =IF(ISERROR(I38/K38),0,I38/K38) -> 0 | K38: =IFERROR(INDEX(別紙_テンプレート_DB!$F$3:$F$65423,MATCH($C38&"-"&$D38&"-"&I$2&"-"&$E38,INDEX(別紙_テンプレート_DB!$A$3:$A$65423&"-"&別紙_テンプレート_DB!$C$3:$C$65423&"-"&別紙_テンプレート_DB!$D$3:$D$65423&"-"&別紙_テンプレート_DB!$E$3:$E$65423,),0)),0) -> 0 | L38: =IFERROR(INDEX(別紙_テンプレート_DB!$G$3:$G$65423,MATCH($C38&"-"&$D38&"-"&L$2&"-"&$E38,INDEX(別紙_テンプレート_DB!$A$3:$A$65423&"-"&別紙_テンプレート_DB!$C$3:$C$65423&"-"&別紙_テンプレート_DB!$D$3:$D$65423&"-"&別紙_テンプレート_DB!$E$3:$E$65423,),0)),0) -> 0 | M38: =IF(ISERROR(L38/N38),0,L38/N38) -> 0 | N38: =IFERROR(INDEX(別紙_テンプレート_DB!$F$3:$F$65423,MATCH($C38&"-"&$D38&"-"&L$2&"-"&$E38,INDEX(別紙_テンプレート_DB!$A$3:$A$65423&"-"&別紙_テンプレート_DB!$C$3:$C$65423&"-"&別紙_テンプレート_DB!$D$3:$D$65423&"-"&別紙_テンプレート_DB!$E$3:$E$65423,),0)),0) -> 0
B39: 店装 | C39: 0 | D39: 2401 | E39: 3 | F39: =SUMIF(I$3:N$3,$F$3,I39:N39) -> 0 | G39: =IF(ISERROR(F39/H39),0,F39/H39) -> 0 | H39: =SUMIF(I$3:N$3,$H$3,I39:N39) -> 0 | I39: =IFERROR(INDEX(別紙_テンプレート_DB!$G$3:$G$65423,MATCH($C39&"-"&$D39&"-"&I$2&"-"&$E39,INDEX(別紙_テンプレート_DB!$A$3:$A$65423&"-"&別紙_テンプレート_DB!$C$3:$C$65423&"-"&別紙_テンプレート_DB!$D$3:$D$65423&"-"&別紙_テンプレート_DB!$E$3:$E$65423,),0)),0) -> 0 | J39: =IF(ISERROR(I39/K39),0,I39/K39) -> 0 | K39: =IFERROR(INDEX(別紙_テンプレート_DB!$F$3:$F$65423,MATCH($C39&"-"&$D39&"-"&I$2&"-"&$E39,INDEX(別紙_テンプレート_DB!$A$3:$A$65423&"-"&別紙_テンプレート_DB!$C$3:$C$65423&"-"&別紙_テンプレート_DB!$D$3:$D$65423&"-"&別紙_テンプレート_DB!$E$3:$E$65423,),0)),0) -> 0 | L39: =IFERROR(INDEX(別紙_テンプレート_DB!$G$3:$G$65423,MATCH($C39&"-"&$D39&"-"&L$2&"-"&$E39,INDEX(別紙_テンプレート_DB!$A$3:$A$65423&"-"&別紙_テンプレート_DB!$C$3:$C$65423&"-"&別紙_テンプレート_DB!$D$3:$D$65423&"-"&別紙_テンプレート_DB!$E$3:$E$65423,),0)),0) -> 0 | M39: =IF(ISERROR(L39/N39),0,L39/N39) -> 0 | N39: =IFERROR(INDEX(別紙_テンプレート_DB!$F$3:$F$65423,MATCH($C39&"-"&$D39&"-"&L$2&"-"&$E39,INDEX(別紙_テンプレート_DB!$A$3:$A$65423&"-"&別紙_テンプレート_DB!$C$3:$C$65423&"-"&別紙_テンプレート_DB!$D$3:$D$65423&"-"&別紙_テンプレート_DB!$E$3:$E$65423,),0)),0) -> 0
B40: 委託 | C40: 0 | D40: 2401 | E40: 106 | F40: =SUMIF(I$3:N$3,$F$3,I40:N40) -> 0 | G40: =IF(ISERROR(F40/H40),0,F40/H40) -> 0 | H40: =SUMIF(I$3:N$3,$H$3,I40:N40) -> 0 | I40: =IFERROR(INDEX(別紙_テンプレート_DB!$G$3:$G$65423,MATCH($C40&"-"&$D40&"-"&I$2&"-"&$E40,INDEX(別紙_テンプレート_DB!$A$3:$A$65423&"-"&別紙_テンプレート_DB!$C$3:$C$65423&"-"&別紙_テンプレート_DB!$D$3:$D$65423&"-"&別紙_テンプレート_DB!$E$3:$E$65423,),0)),0) -> 0 | J40: =IF(ISERROR(I40/K40),0,I40/K40) -> 0 | K40: =IFERROR(INDEX(別紙_テンプレート_DB!$F$3:$F$65423,MATCH($C40&"-"&$D40&"-"&I$2&"-"&$E40,INDEX(別紙_テンプレート_DB!$A$3:$A$65423&"-"&別紙_テンプレート_DB!$C$3:$C$65423&"-"&別紙_テンプレート_DB!$D$3:$D$65423&"-"&別紙_テンプレート_DB!$E$3:$E$65423,),0)),0) -> 0 | L40: =IFERROR(INDEX(別紙_テンプレート_DB!$G$3:$G$65423,MATCH($C40&"-"&$D40&"-"&L$2&"-"&$E40,INDEX(別紙_テンプレート_DB!$A$3:$A$65423&"-"&別紙_テンプレート_DB!$C$3:$C$65423&"-"&別紙_テンプレート_DB!$D$3:$D$65423&"-"&別紙_テンプレート_DB!$E$3:$E$65423,),0)),0) -> 0 | M40: =IF(ISERROR(L40/N40),0,L40/N40) -> 0 | N40: =IFERROR(INDEX(別紙_テンプレート_DB!$F$3:$F$65423,MATCH($C40&"-"&$D40&"-"&L$2&"-"&$E40,INDEX(別紙_テンプレート_DB!$A$3:$A$65423&"-"&別紙_テンプレート_DB!$C$3:$C$65423&"-"&別紙_テンプレート_DB!$D$3:$D$65423&"-"&別紙_テンプレート_DB!$E$3:$E$65423,),0)),0) -> 0
B41: クレーム | C41: 0 | D41: 2401 | E41: 4 | F41: =SUMIF(I$3:N$3,$F$3,I41:N41) -> 0 | G41: =IF(ISERROR(F41/H41),0,F41/H41) -> 0 | H41: =SUMIF(I$3:N$3,$H$3,I41:N41) -> 0 | I41: =IFERROR(INDEX(別紙_テンプレート_DB!$G$3:$G$65423,MATCH($C41&"-"&$D41&"-"&I$2&"-"&$E41,INDEX(別紙_テンプレート_DB!$A$3:$A$65423&"-"&別紙_テンプレート_DB!$C$3:$C$65423&"-"&別紙_テンプレート_DB!$D$3:$D$65423&"-"&別紙_テンプレート_DB!$E$3:$E$65423,),0)),0) -> 0 | J41: =IF(ISERROR(I41/K41),0,I41/K41) -> 0 | K41: =IFERROR(INDEX(別紙_テンプレート_DB!$F$3:$F$65423,MATCH($C41&"-"&$D41&"-"&I$2&"-"&$E41,INDEX(別紙_テンプレート_DB!$A$3:$A$65423&"-"&別紙_テンプレート_DB!$C$3:$C$65423&"-"&別紙_テンプレート_DB!$D$3:$D$65423&"-"&別紙_テンプレート_DB!$E$3:$E$65423,),0)),0) -> 0 | L41: =IFERROR(INDEX(別紙_テンプレート_DB!$G$3:$G$65423,MATCH($C41&"-"&$D41&"-"&L$2&"-"&$E41,INDEX(別紙_テンプレート_DB!$A$3:$A$65423&"-"&別紙_テンプレート_DB!$C$3:$C$65423&"-"&別紙_テンプレート_DB!$D$3:$D$65423&"-"&別紙_テンプレート_DB!$E$3:$E$65423,),0)),0) -> 0 | M41: =IF(ISERROR(L41/N41),0,L41/N41) -> 0 | N41: =IFERROR(INDEX(別紙_テンプレート_DB!$F$3:$F$65423,MATCH($C41&"-"&$D41&"-"&L$2&"-"&$E41,INDEX(別紙_テンプレート_DB!$A$3:$A$65423&"-"&別紙_テンプレート_DB!$C$3:$C$65423&"-"&別紙_テンプレート_DB!$D$3:$D$65423&"-"&別紙_テンプレート_DB!$E$3:$E$65423,),0)),0) -> 0
B42: 在庫 | D42: 2401 | E42: 20 | F42: =SUMIF(I$3:N$3,$F$3,I42:N42) -> 0 | G42: ⇔ | H42: =SUMIF(I$3:N$3,$H$3,I42:N42) -> 0 | I42: =IFERROR(INDEX(別紙_テンプレート_DB!$AB$3:$AB$65423,MATCH($D42&"-"&I$2,INDEX(別紙_テンプレート_DB!$Y$3:$Y$65423&"-"&別紙_テンプレート_DB!$Z$3:$Z$65423,),0)),0) -> 0 | J42: ⇔ | K42: =IFERROR(INDEX(別紙_テンプレート_DB!$AA$3:$AA$65423,MATCH($D42&"-"&I$2,INDEX(別紙_テンプレート_DB!$Y$3:$Y$65423&"-"&別紙_テンプレート_DB!$Z$3:$Z$65423,),0)),0) -> 0 | L42: =IFERROR(INDEX(別紙_テンプレート_DB!$AB$3:$AB$65423,MATCH($D42&"-"&L$2,INDEX(別紙_テンプレート_DB!$Y$3:$Y$65423&"-"&別紙_テンプレート_DB!$Z$3:$Z$65423,),0)),0) -> 0 | M42: ⇔ | N42: =IFERROR(INDEX(別紙_テンプレート_DB!$AA$3:$AA$65423,MATCH($D42&"-"&L$2,INDEX(別紙_テンプレート_DB!$Y$3:$Y$65423&"-"&別紙_テンプレート_DB!$Z$3:$Z$65423,),0)),0) -> 0
A43: B | B43: 原/売 | D43: 6601 | F43: =SUMIF(I$3:N$3,$F$3,I43:N43) -> 0 | G43: =IF(ISERROR(F43/H43),0,F43/H43) -> 0 | H43: =SUMIF(I$3:N$3,$H$3,I43:N43) -> 0 | I43: =SUMIF($D44:$D49,$D43,I44:I49) -> 0 | J43: =IF(ISERROR(I43/K43),0,I43/K43) -> 0 | K43: =SUM(K44:K49) -> 0 | L43: =SUMIF($D44:$D49,$D43,L44:L49) -> 0 | M43: =IF(ISERROR(L43/N43),0,L43/N43) -> 0 | N43: =SUM(N44:N49) -> 0
B44: 営業 | C44: 0 | D44: 6601 | E44: 0 | F44: =SUMIF(I$3:N$3,$F$3,I44:N44) -> 0 | G44: =IF(ISERROR(F44/H44),0,F44/H44) -> 0 | H44: =SUMIF(I$3:N$3,$H$3,I44:N44) -> 0 | I44: =IFERROR(INDEX(別紙_テンプレート_DB!$G$3:$G$65423,MATCH($C44&"-"&$D44&"-"&I$2&"-"&$E44,INDEX(別紙_テンプレート_DB!$A$3:$A$65423&"-"&別紙_テンプレート_DB!$C$3:$C$65423&"-"&別紙_テンプレート_DB!$D$3:$D$65423&"-"&別紙_テンプレート_DB!$E$3:$E$65423,),0)),0) -> 0 | J44: =IF(ISERROR(I44/K44),0,I44/K44) -> 0 | K44: =IFERROR(INDEX(別紙_テンプレート_DB!$F$3:$F$65423,MATCH($C44&"-"&$D44&"-"&I$2&"-"&$E44,INDEX(別紙_テンプレート_DB!$A$3:$A$65423&"-"&別紙_テンプレート_DB!$C$3:$C$65423&"-"&別紙_テンプレート_DB!$D$3:$D$65423&"-"&別紙_テンプレート_DB!$E$3:$E$65423,),0)),0) -> 0 | L44: =IFERROR(INDEX(別紙_テンプレート_DB!$G$3:$G$65423,MATCH($C44&"-"&$D44&"-"&L$2&"-"&$E44,INDEX(別紙_テンプレート_DB!$A$3:$A$65423&"-"&別紙_テンプレート_DB!$C$3:$C$65423&"-"&別紙_テンプレート_DB!$D$3:$D$65423&"-"&別紙_テンプレート_DB!$E$3:$E$65423,),0)),0) -> 0 | M44: =IF(ISERROR(L44/N44),0,L44/N44) -> 0 | N44: =IFERROR(INDEX(別紙_テンプレート_DB!$F$3:$F$65423,MATCH($C44&"-"&$D44&"-"&L$2&"-"&$E44,INDEX(別紙_テンプレート_DB!$A$3:$A$65423&"-"&別紙_テンプレート_DB!$C$3:$C$65423&"-"&別紙_テンプレート_DB!$D$3:$D$65423&"-"&別紙_テンプレート_DB!$E$3:$E$65423,),0)),0) -> 0
B45: 工事 | C45: 0 | D45: 6601 | E45: 1 | F45: =SUMIF(I$3:N$3,$F$3,I45:N45) -> 0 | G45: =IF(ISERROR(F45/H45),0,F45/H45) -> 0 | H45: =SUMIF(I$3:N$3,$H$3,I45:N45) -> 0 | I45: =IFERROR(INDEX(別紙_テンプレート_DB!$G$3:$G$65423,MATCH($C45&"-"&$D45&"-"&I$2&"-"&$E45,INDEX(別紙_テンプレート_DB!$A$3:$A$65423&"-"&別紙_テンプレート_DB!$C$3:$C$65423&"-"&別紙_テンプレート_DB!$D$3:$D$65423&"-"&別紙_テンプレート_DB!$E$3:$E$65423,),0)),0) -> 0 | J45: =IF(ISERROR(I45/K45),0,I45/K45) -> 0 | K45: =IFERROR(INDEX(別紙_テンプレート_DB!$F$3:$F$65423,MATCH($C45&"-"&$D45&"-"&I$2&"-"&$E45,INDEX(別紙_テンプレート_DB!$A$3:$A$65423&"-"&別紙_テンプレート_DB!$C$3:$C$65423&"-"&別紙_テンプレート_DB!$D$3:$D$65423&"-"&別紙_テンプレート_DB!$E$3:$E$65423,),0)),0) -> 0 | L45: =IFERROR(INDEX(別紙_テンプレート_DB!$G$3:$G$65423,MATCH($C45&"-"&$D45&"-"&L$2&"-"&$E45,INDEX(別紙_テンプレート_DB!$A$3:$A$65423&"-"&別紙_テンプレート_DB!$C$3:$C$65423&"-"&別紙_テンプレート_DB!$D$3:$D$65423&"-"&別紙_テンプレート_DB!$E$3:$E$65423,),0)),0) -> 0 | M45: =IF(ISERROR(L45/N45),0,L45/N45) -> 0 | N45: =IFERROR(INDEX(別紙_テンプレート_DB!$F$3:$F$65423,MATCH($C45&"-"&$D45&"-"&L$2&"-"&$E45,INDEX(別紙_テンプレート_DB!$A$3:$A$65423&"-"&別紙_テンプレート_DB!$C$3:$C$65423&"-"&別紙_テンプレート_DB!$D$3:$D$65423&"-"&別紙_テンプレート_DB!$E$3:$E$65423,),0)),0) -> 0
B46: コール | C46: 0 | D46: 6601 | E46: 2 | F46: =SUMIF(I$3:N$3,$F$3,I46:N46) -> 0 | G46: =IF(ISERROR(F46/H46),0,F46/H46) -> 0 | H46: =SUMIF(I$3:N$3,$H$3,I46:N46) -> 0 | I46: =IFERROR(INDEX(別紙_テンプレート_DB!$G$3:$G$65423,MATCH($C46&"-"&$D46&"-"&I$2&"-"&$E46,INDEX(別紙_テンプレート_DB!$A$3:$A$65423&"-"&別紙_テンプレート_DB!$C$3:$C$65423&"-"&別紙_テンプレート_DB!$D$3:$D$65423&"-"&別紙_テンプレート_DB!$E$3:$E$65423,),0)),0) -> 0 | J46: =IF(ISERROR(I46/K46),0,I46/K46) -> 0 | K46: =IFERROR(INDEX(別紙_テンプレート_DB!$F$3:$F$65423,MATCH($C46&"-"&$D46&"-"&I$2&"-"&$E46,INDEX(別紙_テンプレート_DB!$A$3:$A$65423&"-"&別紙_テンプレート_DB!$C$3:$C$65423&"-"&別紙_テンプレート_DB!$D$3:$D$65423&"-"&別紙_テンプレート_DB!$E$3:$E$65423,),0)),0) -> 0 | L46: =IFERROR(INDEX(別紙_テンプレート_DB!$G$3:$G$65423,MATCH($C46&"-"&$D46&"-"&L$2&"-"&$E46,INDEX(別紙_テンプレート_DB!$A$3:$A$65423&"-"&別紙_テンプレート_DB!$C$3:$C$65423&"-"&別紙_テンプレート_DB!$D$3:$D$65423&"-"&別紙_テンプレート_DB!$E$3:$E$65423,),0)),0) -> 0 | M46: =IF(ISERROR(L46/N46),0,L46/N46) -> 0 | N46: =IFERROR(INDEX(別紙_テンプレート_DB!$F$3:$F$65423,MATCH($C46&"-"&$D46&"-"&L$2&"-"&$E46,INDEX(別紙_テンプレート_DB!$A$3:$A$65423&"-"&別紙_テンプレート_DB!$C$3:$C$65423&"-"&別紙_テンプレート_DB!$D$3:$D$65423&"-"&別紙_テンプレート_DB!$E$3:$E$65423,),0)),0) -> 0
B47: 店装 | C47: 0 | D47: 6601 | E47: 3 | F47: =SUMIF(I$3:N$3,$F$3,I47:N47) -> 0 | G47: =IF(ISERROR(F47/H47),0,F47/H47) -> 0 | H47: =SUMIF(I$3:N$3,$H$3,I47:N47) -> 0 | I47: =IFERROR(INDEX(別紙_テンプレート_DB!$G$3:$G$65423,MATCH($C47&"-"&$D47&"-"&I$2&"-"&$E47,INDEX(別紙_テンプレート_DB!$A$3:$A$65423&"-"&別紙_テンプレート_DB!$C$3:$C$65423&"-"&別紙_テンプレート_DB!$D$3:$D$65423&"-"&別紙_テンプレート_DB!$E$3:$E$65423,),0)),0) -> 0 | J47: =IF(ISERROR(I47/K47),0,I47/K47) -> 0 | K47: =IFERROR(INDEX(別紙_テンプレート_DB!$F$3:$F$65423,MATCH($C47&"-"&$D47&"-"&I$2&"-"&$E47,INDEX(別紙_テンプレート_DB!$A$3:$A$65423&"-"&別紙_テンプレート_DB!$C$3:$C$65423&"-"&別紙_テンプレート_DB!$D$3:$D$65423&"-"&別紙_テンプレート_DB!$E$3:$E$65423,),0)),0) -> 0 | L47: =IFERROR(INDEX(別紙_テンプレート_DB!$G$3:$G$65423,MATCH($C47&"-"&$D47&"-"&L$2&"-"&$E47,INDEX(別紙_テンプレート_DB!$A$3:$A$65423&"-"&別紙_テンプレート_DB!$C$3:$C$65423&"-"&別紙_テンプレート_DB!$D$3:$D$65423&"-"&別紙_テンプレート_DB!$E$3:$E$65423,),0)),0) -> 0 | M47: =IF(ISERROR(L47/N47),0,L47/N47) -> 0 | N47: =IFERROR(INDEX(別紙_テンプレート_DB!$F$3:$F$65423,MATCH($C47&"-"&$D47&"-"&L$2&"-"&$E47,INDEX(別紙_テンプレート_DB!$A$3:$A$65423&"-"&別紙_テンプレート_DB!$C$3:$C$65423&"-"&別紙_テンプレート_DB!$D$3:$D$65423&"-"&別紙_テンプレート_DB!$E$3:$E$65423,),0)),0) -> 0
B48: 委託 | C48: 0 | D48: 6601 | E48: 106 | F48: =SUMIF(I$3:N$3,$F$3,I48:N48) -> 0 | G48: =IF(ISERROR(F48/H48),0,F48/H48) -> 0 | H48: =SUMIF(I$3:N$3,$H$3,I48:N48) -> 0 | I48: =IFERROR(INDEX(別紙_テンプレート_DB!$G$3:$G$65423,MATCH($C48&"-"&$D48&"-"&I$2&"-"&$E48,INDEX(別紙_テンプレート_DB!$A$3:$A$65423&"-"&別紙_テンプレート_DB!$C$3:$C$65423&"-"&別紙_テンプレート_DB!$D$3:$D$65423&"-"&別紙_テンプレート_DB!$E$3:$E$65423,),0)),0) -> 0 | J48: =IF(ISERROR(I48/K48),0,I48/K48) -> 0 | K48: =IFERROR(INDEX(別紙_テンプレート_DB!$F$3:$F$65423,MATCH($C48&"-"&$D48&"-"&I$2&"-"&$E48,INDEX(別紙_テンプレート_DB!$A$3:$A$65423&"-"&別紙_テンプレート_DB!$C$3:$C$65423&"-"&別紙_テンプレート_DB!$D$3:$D$65423&"-"&別紙_テンプレート_DB!$E$3:$E$65423,),0)),0) -> 0 | L48: =IFERROR(INDEX(別紙_テンプレート_DB!$G$3:$G$65423,MATCH($C48&"-"&$D48&"-"&L$2&"-"&$E48,INDEX(別紙_テンプレート_DB!$A$3:$A$65423&"-"&別紙_テンプレート_DB!$C$3:$C$65423&"-"&別紙_テンプレート_DB!$D$3:$D$65423&"-"&別紙_テンプレート_DB!$E$3:$E$65423,),0)),0) -> 0 | M48: =IF(ISERROR(L48/N48),0,L48/N48) -> 0 | N48: =IFERROR(INDEX(別紙_テンプレート_DB!$F$3:$F$65423,MATCH($C48&"-"&$D48&"-"&L$2&"-"&$E48,INDEX(別紙_テンプレート_DB!$A$3:$A$65423&"-"&別紙_テンプレート_DB!$C$3:$C$65423&"-"&別紙_テンプレート_DB!$D$3:$D$65423&"-"&別紙_テンプレート_DB!$E$3:$E$65423,),0)),0) -> 0
B49: クレーム | C49: 0 | D49: 6601 | E49: 4 | F49: =SUMIF(I$3:N$3,$F$3,I49:N49) -> 0 | G49: =IF(ISERROR(F49/H49),0,F49/H49) -> 0 | H49: =SUMIF(I$3:N$3,$H$3,I49:N49) -> 0 | I49: =IFERROR(INDEX(別紙_テンプレート_DB!$G$3:$G$65423,MATCH($C49&"-"&$D49&"-"&I$2&"-"&$E49,INDEX(別紙_テンプレート_DB!$A$3:$A$65423&"-"&別紙_テンプレート_DB!$C$3:$C$65423&"-"&別紙_テンプレート_DB!$D$3:$D$65423&"-"&別紙_テンプレート_DB!$E$3:$E$65423,),0)),0) -> 0 | J49: =IF(ISERROR(I49/K49),0,I49/K49) -> 0 | K49: =IFERROR(INDEX(別紙_テンプレート_DB!$F$3:$F$65423,MATCH($C49&"-"&$D49&"-"&I$2&"-"&$E49,INDEX(別紙_テンプレート_DB!$A$3:$A$65423&"-"&別紙_テンプレート_DB!$C$3:$C$65423&"-"&別紙_テンプレート_DB!$D$3:$D$65423&"-"&別紙_テンプレート_DB!$E$3:$E$65423,),0)),0) -> 0 | L49: =IFERROR(INDEX(別紙_テンプレート_DB!$G$3:$G$65423,MATCH($C49&"-"&$D49&"-"&L$2&"-"&$E49,INDEX(別紙_テンプレート_DB!$A$3:$A$65423&"-"&別紙_テンプレート_DB!$C$3:$C$65423&"-"&別紙_テンプレート_DB!$D$3:$D$65423&"-"&別紙_テンプレート_DB!$E$3:$E$65423,),0)),0) -> 0 | M49: =IF(ISERROR(L49/N49),0,L49/N49) -> 0 | N49: =IFERROR(INDEX(別紙_テンプレート_DB!$F$3:$F$65423,MATCH($C49&"-"&$D49&"-"&L$2&"-"&$E49,INDEX(別紙_テンプレート_DB!$A$3:$A$65423&"-"&別紙_テンプレート_DB!$C$3:$C$65423&"-"&別紙_テンプレート_DB!$D$3:$D$65423&"-"&別紙_テンプレート_DB!$E$3:$E$65423,),0)),0) -> 0
B50: 在庫 | D50: 6601 | E50: 20 | F50: =SUMIF(I$3:N$3,$F$3,I50:N50) -> 0 | G50: ⇔ | H50: =SUMIF(I$3:N$3,$H$3,I50:N50) -> 0 | I50: =IFERROR(INDEX(別紙_テンプレート_DB!$AB$3:$AB$65423,MATCH($D50&"-"&I$2,INDEX(別紙_テンプレート_DB!$Y$3:$Y$65423&"-"&別紙_テンプレート_DB!$Z$3:$Z$65423,),0)),0) -> 0 | J50: ⇔ | K50: =IFERROR(INDEX(別紙_テンプレート_DB!$AA$3:$AA$65423,MATCH($D50&"-"&I$2,INDEX(別紙_テンプレート_DB!$Y$3:$Y$65423&"-"&別紙_テンプレート_DB!$Z$3:$Z$65423,),0)),0) -> 0 | L50: =IFERROR(INDEX(別紙_テンプレート_DB!$AB$3:$AB$65423,MATCH($D50&"-"&L$2,INDEX(別紙_テンプレート_DB!$Y$3:$Y$65423&"-"&別紙_テンプレート_DB!$Z$3:$Z$65423,),0)),0) -> 0 | M50: ⇔ | N50: =IFERROR(INDEX(別紙_テンプレート_DB!$AA$3:$AA$65423,MATCH($D50&"-"&L$2,INDEX(別紙_テンプレート_DB!$Y$3:$Y$65423&"-"&別紙_テンプレート_DB!$Z$3:$Z$65423,),0)),0) -> 0
A51: BX | B51: 原/売 | D51: 3001 | F51: =SUMIF(I$3:N$3,$F$3,I51:N51) -> 0 | G51: =IF(ISERROR(F51/H51),0,F51/H51) -> 0 | H51: =SUMIF(I$3:N$3,$H$3,I51:N51) -> 0 | I51: =SUMIF($D52:$D57,$D51,I52:I57) -> 0 | J51: =IF(ISERROR(I51/K51),0,I51/K51) -> 0 | K51: =SUM(K52:K57) -> 0 | L51: =SUMIF($D52:$D57,$D51,L52:L57) -> 0 | M51: =IF(ISERROR(L51/N51),0,L51/N51) -> 0 | N51: =SUM(N52:N57) -> 0
B52: 営業 | C52: 0 | D52: 3001 | E52: 0 | F52: =SUMIF(I$3:N$3,$F$3,I52:N52) -> 0 | G52: =IF(ISERROR(F52/H52),0,F52/H52) -> 0 | H52: =SUMIF(I$3:N$3,$H$3,I52:N52) -> 0 | I52: =IFERROR(INDEX(別紙_テンプレート_DB!$G$3:$G$65423,MATCH($C52&"-"&$D52&"-"&I$2&"-"&$E52,INDEX(別紙_テンプレート_DB!$A$3:$A$65423&"-"&別紙_テンプレート_DB!$C$3:$C$65423&"-"&別紙_テンプレート_DB!$D$3:$D$65423&"-"&別紙_テンプレート_DB!$E$3:$E$65423,),0)),0) -> 0 | J52: =IF(ISERROR(I52/K52),0,I52/K52) -> 0 | K52: =IFERROR(INDEX(別紙_テンプレート_DB!$F$3:$F$65423,MATCH($C52&"-"&$D52&"-"&I$2&"-"&$E52,INDEX(別紙_テンプレート_DB!$A$3:$A$65423&"-"&別紙_テンプレート_DB!$C$3:$C$65423&"-"&別紙_テンプレート_DB!$D$3:$D$65423&"-"&別紙_テンプレート_DB!$E$3:$E$65423,),0)),0) -> 0 | L52: =IFERROR(INDEX(別紙_テンプレート_DB!$G$3:$G$65423,MATCH($C52&"-"&$D52&"-"&L$2&"-"&$E52,INDEX(別紙_テンプレート_DB!$A$3:$A$65423&"-"&別紙_テンプレート_DB!$C$3:$C$65423&"-"&別紙_テンプレート_DB!$D$3:$D$65423&"-"&別紙_テンプレート_DB!$E$3:$E$65423,),0)),0) -> 0 | M52: =IF(ISERROR(L52/N52),0,L52/N52) -> 0 | N52: =IFERROR(INDEX(別紙_テンプレート_DB!$F$3:$F$65423,MATCH($C52&"-"&$D52&"-"&L$2&"-"&$E52,INDEX(別紙_テンプレート_DB!$A$3:$A$65423&"-"&別紙_テンプレート_DB!$C$3:$C$65423&"-"&別紙_テンプレート_DB!$D$3:$D$65423&"-"&別紙_テンプレート_DB!$E$3:$E$65423,),0)),0) -> 0
B53: 工事 | C53: 0 | D53: 3001 | E53: 1 | F53: =SUMIF(I$3:N$3,$F$3,I53:N53) -> 0 | G53: =IF(ISERROR(F53/H53),0,F53/H53) -> 0 | H53: =SUMIF(I$3:N$3,$H$3,I53:N53) -> 0 | I53: =IFERROR(INDEX(別紙_テンプレート_DB!$G$3:$G$65423,MATCH($C53&"-"&$D53&"-"&I$2&"-"&$E53,INDEX(別紙_テンプレート_DB!$A$3:$A$65423&"-"&別紙_テンプレート_DB!$C$3:$C$65423&"-"&別紙_テンプレート_DB!$D$3:$D$65423&"-"&別紙_テンプレート_DB!$E$3:$E$65423,),0)),0) -> 0 | J53: =IF(ISERROR(I53/K53),0,I53/K53) -> 0 | K53: =IFERROR(INDEX(別紙_テンプレート_DB!$F$3:$F$65423,MATCH($C53&"-"&$D53&"-"&I$2&"-"&$E53,INDEX(別紙_テンプレート_DB!$A$3:$A$65423&"-"&別紙_テンプレート_DB!$C$3:$C$65423&"-"&別紙_テンプレート_DB!$D$3:$D$65423&"-"&別紙_テンプレート_DB!$E$3:$E$65423,),0)),0) -> 0 | L53: =IFERROR(INDEX(別紙_テンプレート_DB!$G$3:$G$65423,MATCH($C53&"-"&$D53&"-"&L$2&"-"&$E53,INDEX(別紙_テンプレート_DB!$A$3:$A$65423&"-"&別紙_テンプレート_DB!$C$3:$C$65423&"-"&別紙_テンプレート_DB!$D$3:$D$65423&"-"&別紙_テンプレート_DB!$E$3:$E$65423,),0)),0) -> 0 | M53: =IF(ISERROR(L53/N53),0,L53/N53) -> 0 | N53: =IFERROR(INDEX(別紙_テンプレート_DB!$F$3:$F$65423,MATCH($C53&"-"&$D53&"-"&L$2&"-"&$E53,INDEX(別紙_テンプレート_DB!$A$3:$A$65423&"-"&別紙_テンプレート_DB!$C$3:$C$65423&"-"&別紙_テンプレート_DB!$D$3:$D$65423&"-"&別紙_テンプレート_DB!$E$3:$E$65423,),0)),0) -> 0
B54: コール | C54: 0 | D54: 3001 | E54: 2 | F54: =SUMIF(I$3:N$3,$F$3,I54:N54) -> 0 | G54: =IF(ISERROR(F54/H54),0,F54/H54) -> 0 | H54: =SUMIF(I$3:N$3,$H$3,I54:N54) -> 0 | I54: =IFERROR(INDEX(別紙_テンプレート_DB!$G$3:$G$65423,MATCH($C54&"-"&$D54&"-"&I$2&"-"&$E54,INDEX(別紙_テンプレート_DB!$A$3:$A$65423&"-"&別紙_テンプレート_DB!$C$3:$C$65423&"-"&別紙_テンプレート_DB!$D$3:$D$65423&"-"&別紙_テンプレート_DB!$E$3:$E$65423,),0)),0) -> 0 | J54: =IF(ISERROR(I54/K54),0,I54/K54) -> 0 | K54: =IFERROR(INDEX(別紙_テンプレート_DB!$F$3:$F$65423,MATCH($C54&"-"&$D54&"-"&I$2&"-"&$E54,INDEX(別紙_テンプレート_DB!$A$3:$A$65423&"-"&別紙_テンプレート_DB!$C$3:$C$65423&"-"&別紙_テンプレート_DB!$D$3:$D$65423&"-"&別紙_テンプレート_DB!$E$3:$E$65423,),0)),0) -> 0 | L54: =IFERROR(INDEX(別紙_テンプレート_DB!$G$3:$G$65423,MATCH($C54&"-"&$D54&"-"&L$2&"-"&$E54,INDEX(別紙_テンプレート_DB!$A$3:$A$65423&"-"&別紙_テンプレート_DB!$C$3:$C$65423&"-"&別紙_テンプレート_DB!$D$3:$D$65423&"-"&別紙_テンプレート_DB!$E$3:$E$65423,),0)),0) -> 0 | M54: =IF(ISERROR(L54/N54),0,L54/N54) -> 0 | N54: =IFERROR(INDEX(別紙_テンプレート_DB!$F$3:$F$65423,MATCH($C54&"-"&$D54&"-"&L$2&"-"&$E54,INDEX(別紙_テンプレート_DB!$A$3:$A$65423&"-"&別紙_テンプレート_DB!$C$3:$C$65423&"-"&別紙_テンプレート_DB!$D$3:$D$65423&"-"&別紙_テンプレート_DB!$E$3:$E$65423,),0)),0) -> 0
B55: 店装 | C55: 0 | D55: 3001 | E55: 3 | F55: =SUMIF(I$3:N$3,$F$3,I55:N55) -> 0 | G55: =IF(ISERROR(F55/H55),0,F55/H55) -> 0 | H55: =SUMIF(I$3:N$3,$H$3,I55:N55) -> 0 | I55: =IFERROR(INDEX(別紙_テンプレート_DB!$G$3:$G$65423,MATCH($C55&"-"&$D55&"-"&I$2&"-"&$E55,INDEX(別紙_テンプレート_DB!$A$3:$A$65423&"-"&別紙_テンプレート_DB!$C$3:$C$65423&"-"&別紙_テンプレート_DB!$D$3:$D$65423&"-"&別紙_テンプレート_DB!$E$3:$E$65423,),0)),0) -> 0 | J55: =IF(ISERROR(I55/K55),0,I55/K55) -> 0 | K55: =IFERROR(INDEX(別紙_テンプレート_DB!$F$3:$F$65423,MATCH($C55&"-"&$D55&"-"&I$2&"-"&$E55,INDEX(別紙_テンプレート_DB!$A$3:$A$65423&"-"&別紙_テンプレート_DB!$C$3:$C$65423&"-"&別紙_テンプレート_DB!$D$3:$D$65423&"-"&別紙_テンプレート_DB!$E$3:$E$65423,),0)),0) -> 0 | L55: =IFERROR(INDEX(別紙_テンプレート_DB!$G$3:$G$65423,MATCH($C55&"-"&$D55&"-"&L$2&"-"&$E55,INDEX(別紙_テンプレート_DB!$A$3:$A$65423&"-"&別紙_テンプレート_DB!$C$3:$C$65423&"-"&別紙_テンプレート_DB!$D$3:$D$65423&"-"&別紙_テンプレート_DB!$E$3:$E$65423,),0)),0) -> 0 | M55: =IF(ISERROR(L55/N55),0,L55/N55) -> 0 | N55: =IFERROR(INDEX(別紙_テンプレート_DB!$F$3:$F$65423,MATCH($C55&"-"&$D55&"-"&L$2&"-"&$E55,INDEX(別紙_テンプレート_DB!$A$3:$A$65423&"-"&別紙_テンプレート_DB!$C$3:$C$65423&"-"&別紙_テンプレート_DB!$D$3:$D$65423&"-"&別紙_テンプレート_DB!$E$3:$E$65423,),0)),0) -> 0
B56: 委託 | C56: 0 | D56: 3001 | E56: 106 | F56: =SUMIF(I$3:N$3,$F$3,I56:N56) -> 0 | G56: =IF(ISERROR(F56/H56),0,F56/H56) -> 0 | H56: =SUMIF(I$3:N$3,$H$3,I56:N56) -> 0 | I56: =IFERROR(INDEX(別紙_テンプレート_DB!$G$3:$G$65423,MATCH($C56&"-"&$D56&"-"&I$2&"-"&$E56,INDEX(別紙_テンプレート_DB!$A$3:$A$65423&"-"&別紙_テンプレート_DB!$C$3:$C$65423&"-"&別紙_テンプレート_DB!$D$3:$D$65423&"-"&別紙_テンプレート_DB!$E$3:$E$65423,),0)),0) -> 0 | J56: =IF(ISERROR(I56/K56),0,I56/K56) -> 0 | K56: =IFERROR(INDEX(別紙_テンプレート_DB!$F$3:$F$65423,MATCH($C56&"-"&$D56&"-"&I$2&"-"&$E56,INDEX(別紙_テンプレート_DB!$A$3:$A$65423&"-"&別紙_テンプレート_DB!$C$3:$C$65423&"-"&別紙_テンプレート_DB!$D$3:$D$65423&"-"&別紙_テンプレート_DB!$E$3:$E$65423,),0)),0) -> 0 | L56: =IFERROR(INDEX(別紙_テンプレート_DB!$G$3:$G$65423,MATCH($C56&"-"&$D56&"-"&L$2&"-"&$E56,INDEX(別紙_テンプレート_DB!$A$3:$A$65423&"-"&別紙_テンプレート_DB!$C$3:$C$65423&"-"&別紙_テンプレート_DB!$D$3:$D$65423&"-"&別紙_テンプレート_DB!$E$3:$E$65423,),0)),0) -> 0 | M56: =IF(ISERROR(L56/N56),0,L56/N56) -> 0 | N56: =IFERROR(INDEX(別紙_テンプレート_DB!$F$3:$F$65423,MATCH($C56&"-"&$D56&"-"&L$2&"-"&$E56,INDEX(別紙_テンプレート_DB!$A$3:$A$65423&"-"&別紙_テンプレート_DB!$C$3:$C$65423&"-"&別紙_テンプレート_DB!$D$3:$D$65423&"-"&別紙_テンプレート_DB!$E$3:$E$65423,),0)),0) -> 0
B57: クレーム | C57: 0 | D57: 3001 | E57: 4 | F57: =SUMIF(I$3:N$3,$F$3,I57:N57) -> 0 | G57: =IF(ISERROR(F57/H57),0,F57/H57) -> 0 | H57: =SUMIF(I$3:N$3,$H$3,I57:N57) -> 0 | I57: =IFERROR(INDEX(別紙_テンプレート_DB!$G$3:$G$65423,MATCH($C57&"-"&$D57&"-"&I$2&"-"&$E57,INDEX(別紙_テンプレート_DB!$A$3:$A$65423&"-"&別紙_テンプレート_DB!$C$3:$C$65423&"-"&別紙_テンプレート_DB!$D$3:$D$65423&"-"&別紙_テンプレート_DB!$E$3:$E$65423,),0)),0) -> 0 | J57: =IF(ISERROR(I57/K57),0,I57/K57) -> 0 | K57: =IFERROR(INDEX(別紙_テンプレート_DB!$F$3:$F$65423,MATCH($C57&"-"&$D57&"-"&I$2&"-"&$E57,INDEX(別紙_テンプレート_DB!$A$3:$A$65423&"-"&別紙_テンプレート_DB!$C$3:$C$65423&"-"&別紙_テンプレート_DB!$D$3:$D$65423&"-"&別紙_テンプレート_DB!$E$3:$E$65423,),0)),0) -> 0 | L57: =IFERROR(INDEX(別紙_テンプレート_DB!$G$3:$G$65423,MATCH($C57&"-"&$D57&"-"&L$2&"-"&$E57,INDEX(別紙_テンプレート_DB!$A$3:$A$65423&"-"&別紙_テンプレート_DB!$C$3:$C$65423&"-"&別紙_テンプレート_DB!$D$3:$D$65423&"-"&別紙_テンプレート_DB!$E$3:$E$65423,),0)),0) -> 0 | M57: =IF(ISERROR(L57/N57),0,L57/N57) -> 0 | N57: =IFERROR(INDEX(別紙_テンプレート_DB!$F$3:$F$65423,MATCH($C57&"-"&$D57&"-"&L$2&"-"&$E57,INDEX(別紙_テンプレート_DB!$A$3:$A$65423&"-"&別紙_テンプレート_DB!$C$3:$C$65423&"-"&別紙_テンプレート_DB!$D$3:$D$65423&"-"&別紙_テンプレート_DB!$E$3:$E$65423,),0)),0) -> 0
B58: 在庫 | D58: 3001 | E58: 20 | F58: =SUMIF(I$3:N$3,$F$3,I58:N58) -> 0 | G58: ⇔ | H58: =SUMIF(I$3:N$3,$H$3,I58:N58) -> 0 | I58: =IFERROR(INDEX(別紙_テンプレート_DB!$AB$3:$AB$65423,MATCH($D58&"-"&I$2,INDEX(別紙_テンプレート_DB!$Y$3:$Y$65423&"-"&別紙_テンプレート_DB!$Z$3:$Z$65423,),0)),0) -> 0 | J58: ⇔ | K58: =IFERROR(INDEX(別紙_テンプレート_DB!$AA$3:$AA$65423,MATCH($D58&"-"&I$2,INDEX(別紙_テンプレート_DB!$Y$3:$Y$65423&"-"&別紙_テンプレート_DB!$Z$3:$Z$65423,),0)),0) -> 0 | L58: =IFERROR(INDEX(別紙_テンプレート_DB!$AB$3:$AB$65423,MATCH($D58&"-"&L$2,INDEX(別紙_テンプレート_DB!$Y$3:$Y$65423&"-"&別紙_テンプレート_DB!$Z$3:$Z$65423,),0)),0) -> 0 | M58: ⇔ | N58: =IFERROR(INDEX(別紙_テンプレート_DB!$AA$3:$AA$65423,MATCH($D58&"-"&L$2,INDEX(別紙_テンプレート_DB!$Y$3:$Y$65423&"-"&別紙_テンプレート_DB!$Z$3:$Z$65423,),0)),0) -> 0
A59: LP | B59: 原/売 | D59: 9803 | F59: =SUMIF(I$3:N$3,$F$3,I59:N59) -> 0 | G59: =IF(ISERROR(F59/H59),0,F59/H59) -> 0 | H59: =SUMIF(I$3:N$3,$H$3,I59:N59) -> 0 | I59: =SUMIF($D60:$D65,$D59,I60:I65) -> 0 | J59: =IF(ISERROR(I59/K59),0,I59/K59) -> 0 | K59: =SUM(K60:K65) -> 0 | L59: =SUMIF($D60:$D65,$D59,L60:L65) -> 0 | M59: =IF(ISERROR(L59/N59),0,L59/N59) -> 0 | N59: =SUM(N60:N65) -> 0
B60: 営業 | C60: 0 | D60: 9803 | E60: 0 | F60: =SUMIF(I$3:N$3,$F$3,I60:N60) -> 0 | G60: =IF(ISERROR(F60/H60),0,F60/H60) -> 0 | H60: =SUMIF(I$3:N$3,$H$3,I60:N60) -> 0 | I60: =IFERROR(INDEX(別紙_テンプレート_DB!$G$3:$G$65423,MATCH($C60&"-"&$D60&"-"&I$2&"-"&$E60,INDEX(別紙_テンプレート_DB!$A$3:$A$65423&"-"&別紙_テンプレート_DB!$C$3:$C$65423&"-"&別紙_テンプレート_DB!$D$3:$D$65423&"-"&別紙_テンプレート_DB!$E$3:$E$65423,),0)),0) -> 0 | J60: =IF(ISERROR(I60/K60),0,I60/K60) -> 0 | K60: =IFERROR(INDEX(別紙_テンプレート_DB!$F$3:$F$65423,MATCH($C60&"-"&$D60&"-"&I$2&"-"&$E60,INDEX(別紙_テンプレート_DB!$A$3:$A$65423&"-"&別紙_テンプレート_DB!$C$3:$C$65423&"-"&別紙_テンプレート_DB!$D$3:$D$65423&"-"&別紙_テンプレート_DB!$E$3:$E$65423,),0)),0) -> 0 | L60: =IFERROR(INDEX(別紙_テンプレート_DB!$G$3:$G$65423,MATCH($C60&"-"&$D60&"-"&L$2&"-"&$E60,INDEX(別紙_テンプレート_DB!$A$3:$A$65423&"-"&別紙_テンプレート_DB!$C$3:$C$65423&"-"&別紙_テンプレート_DB!$D$3:$D$65423&"-"&別紙_テンプレート_DB!$E$3:$E$65423,),0)),0) -> 0 | M60: =IF(ISERROR(L60/N60),0,L60/N60) -> 0 | N60: =IFERROR(INDEX(別紙_テンプレート_DB!$F$3:$F$65423,MATCH($C60&"-"&$D60&"-"&L$2&"-"&$E60,INDEX(別紙_テンプレート_DB!$A$3:$A$65423&"-"&別紙_テンプレート_DB!$C$3:$C$65423&"-"&別紙_テンプレート_DB!$D$3:$D$65423&"-"&別紙_テンプレート_DB!$E$3:$E$65423,),0)),0) -> 0
B61: 工事 | C61: 0 | D61: 9803 | E61: 1 | F61: =SUMIF(I$3:N$3,$F$3,I61:N61) -> 0 | G61: =IF(ISERROR(F61/H61),0,F61/H61) -> 0 | H61: =SUMIF(I$3:N$3,$H$3,I61:N61) -> 0 | I61: =IFERROR(INDEX(別紙_テンプレート_DB!$G$3:$G$65423,MATCH($C61&"-"&$D61&"-"&I$2&"-"&$E61,INDEX(別紙_テンプレート_DB!$A$3:$A$65423&"-"&別紙_テンプレート_DB!$C$3:$C$65423&"-"&別紙_テンプレート_DB!$D$3:$D$65423&"-"&別紙_テンプレート_DB!$E$3:$E$65423,),0)),0) -> 0 | J61: =IF(ISERROR(I61/K61),0,I61/K61) -> 0 | K61: =IFERROR(INDEX(別紙_テンプレート_DB!$F$3:$F$65423,MATCH($C61&"-"&$D61&"-"&I$2&"-"&$E61,INDEX(別紙_テンプレート_DB!$A$3:$A$65423&"-"&別紙_テンプレート_DB!$C$3:$C$65423&"-"&別紙_テンプレート_DB!$D$3:$D$65423&"-"&別紙_テンプレート_DB!$E$3:$E$65423,),0)),0) -> 0 | L61: =IFERROR(INDEX(別紙_テンプレート_DB!$G$3:$G$65423,MATCH($C61&"-"&$D61&"-"&L$2&"-"&$E61,INDEX(別紙_テンプレート_DB!$A$3:$A$65423&"-"&別紙_テンプレート_DB!$C$3:$C$65423&"-"&別紙_テンプレート_DB!$D$3:$D$65423&"-"&別紙_テンプレート_DB!$E$3:$E$65423,),0)),0) -> 0 | M61: =IF(ISERROR(L61/N61),0,L61/N61) -> 0 | N61: =IFERROR(INDEX(別紙_テンプレート_DB!$F$3:$F$65423,MATCH($C61&"-"&$D61&"-"&L$2&"-"&$E61,INDEX(別紙_テンプレート_DB!$A$3:$A$65423&"-"&別紙_テンプレート_DB!$C$3:$C$65423&"-"&別紙_テンプレート_DB!$D$3:$D$65423&"-"&別紙_テンプレート_DB!$E$3:$E$65423,),0)),0) -> 0
B62: コール | C62: 0 | D62: 9803 | E62: 2 | F62: =SUMIF(I$3:N$3,$F$3,I62:N62) -> 0 | G62: =IF(ISERROR(F62/H62),0,F62/H62) -> 0 | H62: =SUMIF(I$3:N$3,$H$3,I62:N62) -> 0 | I62: =IFERROR(INDEX(別紙_テンプレート_DB!$G$3:$G$65423,MATCH($C62&"-"&$D62&"-"&I$2&"-"&$E62,INDEX(別紙_テンプレート_DB!$A$3:$A$65423&"-"&別紙_テンプレート_DB!$C$3:$C$65423&"-"&別紙_テンプレート_DB!$D$3:$D$65423&"-"&別紙_テンプレート_DB!$E$3:$E$65423,),0)),0) -> 0 | J62: =IF(ISERROR(I62/K62),0,I62/K62) -> 0 | K62: =IFERROR(INDEX(別紙_テンプレート_DB!$F$3:$F$65423,MATCH($C62&"-"&$D62&"-"&I$2&"-"&$E62,INDEX(別紙_テンプレート_DB!$A$3:$A$65423&"-"&別紙_テンプレート_DB!$C$3:$C$65423&"-"&別紙_テンプレート_DB!$D$3:$D$65423&"-"&別紙_テンプレート_DB!$E$3:$E$65423,),0)),0) -> 0 | L62: =IFERROR(INDEX(別紙_テンプレート_DB!$G$3:$G$65423,MATCH($C62&"-"&$D62&"-"&L$2&"-"&$E62,INDEX(別紙_テンプレート_DB!$A$3:$A$65423&"-"&別紙_テンプレート_DB!$C$3:$C$65423&"-"&別紙_テンプレート_DB!$D$3:$D$65423&"-"&別紙_テンプレート_DB!$E$3:$E$65423,),0)),0) -> 0 | M62: =IF(ISERROR(L62/N62),0,L62/N62) -> 0 | N62: =IFERROR(INDEX(別紙_テンプレート_DB!$F$3:$F$65423,MATCH($C62&"-"&$D62&"-"&L$2&"-"&$E62,INDEX(別紙_テンプレート_DB!$A$3:$A$65423&"-"&別紙_テンプレート_DB!$C$3:$C$65423&"-"&別紙_テンプレート_DB!$D$3:$D$65423&"-"&別紙_テンプレート_DB!$E$3:$E$65423,),0)),0) -> 0
B63: 店装 | C63: 0 | D63: 9803 | E63: 3 | F63: =SUMIF(I$3:N$3,$F$3,I63:N63) -> 0 | G63: =IF(ISERROR(F63/H63),0,F63/H63) -> 0 | H63: =SUMIF(I$3:N$3,$H$3,I63:N63) -> 0 | I63: =IFERROR(INDEX(別紙_テンプレート_DB!$G$3:$G$65423,MATCH($C63&"-"&$D63&"-"&I$2&"-"&$E63,INDEX(別紙_テンプレート_DB!$A$3:$A$65423&"-"&別紙_テンプレート_DB!$C$3:$C$65423&"-"&別紙_テンプレート_DB!$D$3:$D$65423&"-"&別紙_テンプレート_DB!$E$3:$E$65423,),0)),0) -> 0 | J63: =IF(ISERROR(I63/K63),0,I63/K63) -> 0 | K63: =IFERROR(INDEX(別紙_テンプレート_DB!$F$3:$F$65423,MATCH($C63&"-"&$D63&"-"&I$2&"-"&$E63,INDEX(別紙_テンプレート_DB!$A$3:$A$65423&"-"&別紙_テンプレート_DB!$C$3:$C$65423&"-"&別紙_テンプレート_DB!$D$3:$D$65423&"-"&別紙_テンプレート_DB!$E$3:$E$65423,),0)),0) -> 0 | L63: =IFERROR(INDEX(別紙_テンプレート_DB!$G$3:$G$65423,MATCH($C63&"-"&$D63&"-"&L$2&"-"&$E63,INDEX(別紙_テンプレート_DB!$A$3:$A$65423&"-"&別紙_テンプレート_DB!$C$3:$C$65423&"-"&別紙_テンプレート_DB!$D$3:$D$65423&"-"&別紙_テンプレート_DB!$E$3:$E$65423,),0)),0) -> 0 | M63: =IF(ISERROR(L63/N63),0,L63/N63) -> 0 | N63: =IFERROR(INDEX(別紙_テンプレート_DB!$F$3:$F$65423,MATCH($C63&"-"&$D63&"-"&L$2&"-"&$E63,INDEX(別紙_テンプレート_DB!$A$3:$A$65423&"-"&別紙_テンプレート_DB!$C$3:$C$65423&"-"&別紙_テンプレート_DB!$D$3:$D$65423&"-"&別紙_テンプレート_DB!$E$3:$E$65423,),0)),0) -> 0
B64: 委託 | C64: 0 | D64: 9803 | E64: 106 | F64: =SUMIF(I$3:N$3,$F$3,I64:N64) -> 0 | G64: =IF(ISERROR(F64/H64),0,F64/H64) -> 0 | H64: =SUMIF(I$3:N$3,$H$3,I64:N64) -> 0 | I64: =IFERROR(INDEX(別紙_テンプレート_DB!$G$3:$G$65423,MATCH($C64&"-"&$D64&"-"&I$2&"-"&$E64,INDEX(別紙_テンプレート_DB!$A$3:$A$65423&"-"&別紙_テンプレート_DB!$C$3:$C$65423&"-"&別紙_テンプレート_DB!$D$3:$D$65423&"-"&別紙_テンプレート_DB!$E$3:$E$65423,),0)),0) -> 0 | J64: =IF(ISERROR(I64/K64),0,I64/K64) -> 0 | K64: =IFERROR(INDEX(別紙_テンプレート_DB!$F$3:$F$65423,MATCH($C64&"-"&$D64&"-"&I$2&"-"&$E64,INDEX(別紙_テンプレート_DB!$A$3:$A$65423&"-"&別紙_テンプレート_DB!$C$3:$C$65423&"-"&別紙_テンプレート_DB!$D$3:$D$65423&"-"&別紙_テンプレート_DB!$E$3:$E$65423,),0)),0) -> 0 | L64: =IFERROR(INDEX(別紙_テンプレート_DB!$G$3:$G$65423,MATCH($C64&"-"&$D64&"-"&L$2&"-"&$E64,INDEX(別紙_テンプレート_DB!$A$3:$A$65423&"-"&別紙_テンプレート_DB!$C$3:$C$65423&"-"&別紙_テンプレート_DB!$D$3:$D$65423&"-"&別紙_テンプレート_DB!$E$3:$E$65423,),0)),0) -> 0 | M64: =IF(ISERROR(L64/N64),0,L64/N64) -> 0 | N64: =IFERROR(INDEX(別紙_テンプレート_DB!$F$3:$F$65423,MATCH($C64&"-"&$D64&"-"&L$2&"-"&$E64,INDEX(別紙_テンプレート_DB!$A$3:$A$65423&"-"&別紙_テンプレート_DB!$C$3:$C$65423&"-"&別紙_テンプレート_DB!$D$3:$D$65423&"-"&別紙_テンプレート_DB!$E$3:$E$65423,),0)),0) -> 0
B65: クレーム | C65: 0 | D65: 9803 | E65: 4 | F65: =SUMIF(I$3:N$3,$F$3,I65:N65) -> 0 | G65: =IF(ISERROR(F65/H65),0,F65/H65) -> 0 | H65: =SUMIF(I$3:N$3,$H$3,I65:N65) -> 0 | I65: =IFERROR(INDEX(別紙_テンプレート_DB!$G$3:$G$65423,MATCH($C65&"-"&$D65&"-"&I$2&"-"&$E65,INDEX(別紙_テンプレート_DB!$A$3:$A$65423&"-"&別紙_テンプレート_DB!$C$3:$C$65423&"-"&別紙_テンプレート_DB!$D$3:$D$65423&"-"&別紙_テンプレート_DB!$E$3:$E$65423,),0)),0) -> 0 | J65: =IF(ISERROR(I65/K65),0,I65/K65) -> 0 | K65: =IFERROR(INDEX(別紙_テンプレート_DB!$F$3:$F$65423,MATCH($C65&"-"&$D65&"-"&I$2&"-"&$E65,INDEX(別紙_テンプレート_DB!$A$3:$A$65423&"-"&別紙_テンプレート_DB!$C$3:$C$65423&"-"&別紙_テンプレート_DB!$D$3:$D$65423&"-"&別紙_テンプレート_DB!$E$3:$E$65423,),0)),0) -> 0 | L65: =IFERROR(INDEX(別紙_テンプレート_DB!$G$3:$G$65423,MATCH($C65&"-"&$D65&"-"&L$2&"-"&$E65,INDEX(別紙_テンプレート_DB!$A$3:$A$65423&"-"&別紙_テンプレート_DB!$C$3:$C$65423&"-"&別紙_テンプレート_DB!$D$3:$D$65423&"-"&別紙_テンプレート_DB!$E$3:$E$65423,),0)),0) -> 0 | M65: =IF(ISERROR(L65/N65),0,L65/N65) -> 0 | N65: =IFERROR(INDEX(別紙_テンプレート_DB!$F$3:$F$65423,MATCH($C65&"-"&$D65&"-"&L$2&"-"&$E65,INDEX(別紙_テンプレート_DB!$A$3:$A$65423&"-"&別紙_テンプレート_DB!$C$3:$C$65423&"-"&別紙_テンプレート_DB!$D$3:$D$65423&"-"&別紙_テンプレート_DB!$E$3:$E$65423,),0)),0) -> 0
B66: 在庫 | D66: 9803 | E66: 20 | F66: =SUMIF(I$3:N$3,$F$3,I66:N66) -> 0 | G66: ⇔ | H66: =SUMIF(I$3:N$3,$H$3,I66:N66) -> 0 | I66: =IFERROR(INDEX(別紙_テンプレート_DB!$AB$3:$AB$65423,MATCH($D66&"-"&I$2,INDEX(別紙_テンプレート_DB!$Y$3:$Y$65423&"-"&別紙_テンプレート_DB!$Z$3:$Z$65423,),0)),0) -> 0 | J66: ⇔ | K66: =IFERROR(INDEX(別紙_テンプレート_DB!$AA$3:$AA$65423,MATCH($D66&"-"&I$2,INDEX(別紙_テンプレート_DB!$Y$3:$Y$65423&"-"&別紙_テンプレート_DB!$Z$3:$Z$65423,),0)),0) -> 0 | L66: =IFERROR(INDEX(別紙_テンプレート_DB!$AB$3:$AB$65423,MATCH($D66&"-"&L$2,INDEX(別紙_テンプレート_DB!$Y$3:$Y$65423&"-"&別紙_テンプレート_DB!$Z$3:$Z$65423,),0)),0) -> 0 | M66: ⇔ | N66: =IFERROR(INDEX(別紙_テンプレート_DB!$AA$3:$AA$65423,MATCH($D66&"-"&L$2,INDEX(別紙_テンプレート_DB!$Y$3:$Y$65423&"-"&別紙_テンプレート_DB!$Z$3:$Z$65423,),0)),0) -> 0
A67: AL | B67: 原/売 | D67: 4801 | F67: =SUMIF(I$3:N$3,$F$3,I67:N67) -> 0 | G67: =IF(ISERROR(F67/H67),0,F67/H67) -> 0 | H67: =SUMIF(I$3:N$3,$H$3,I67:N67) -> 0 | I67: =SUMIF($D68:$D73,$D67,I68:I73) -> 0 | J67: =IF(ISERROR(I67/K67),0,I67/K67) -> 0 | K67: =SUM(K68:K73) -> 0 | L67: =SUMIF($D68:$D73,$D67,L68:L73) -> 0 | M67: =IF(ISERROR(L67/N67),0,L67/N67) -> 0 | N67: =SUM(N68:N73) -> 0
B68: 営業 | C68: 0 | D68: 4801 | E68: 0 | F68: =SUMIF(I$3:N$3,$F$3,I68:N68) -> 0 | G68: =IF(ISERROR(F68/H68),0,F68/H68) -> 0 | H68: =SUMIF(I$3:N$3,$H$3,I68:N68) -> 0 | I68: =IFERROR(INDEX(別紙_テンプレート_DB!$G$3:$G$65423,MATCH($C68&"-"&$D68&"-"&I$2&"-"&$E68,INDEX(別紙_テンプレート_DB!$A$3:$A$65423&"-"&別紙_テンプレート_DB!$C$3:$C$65423&"-"&別紙_テンプレート_DB!$D$3:$D$65423&"-"&別紙_テンプレート_DB!$E$3:$E$65423,),0)),0) -> 0 | J68: =IF(ISERROR(I68/K68),0,I68/K68) -> 0 | K68: =IFERROR(INDEX(別紙_テンプレート_DB!$F$3:$F$65423,MATCH($C68&"-"&$D68&"-"&I$2&"-"&$E68,INDEX(別紙_テンプレート_DB!$A$3:$A$65423&"-"&別紙_テンプレート_DB!$C$3:$C$65423&"-"&別紙_テンプレート_DB!$D$3:$D$65423&"-"&別紙_テンプレート_DB!$E$3:$E$65423,),0)),0) -> 0 | L68: =IFERROR(INDEX(別紙_テンプレート_DB!$G$3:$G$65423,MATCH($C68&"-"&$D68&"-"&L$2&"-"&$E68,INDEX(別紙_テンプレート_DB!$A$3:$A$65423&"-"&別紙_テンプレート_DB!$C$3:$C$65423&"-"&別紙_テンプレート_DB!$D$3:$D$65423&"-"&別紙_テンプレート_DB!$E$3:$E$65423,),0)),0) -> 0 | M68: =IF(ISERROR(L68/N68),0,L68/N68) -> 0 | N68: =IFERROR(INDEX(別紙_テンプレート_DB!$F$3:$F$65423,MATCH($C68&"-"&$D68&"-"&L$2&"-"&$E68,INDEX(別紙_テンプレート_DB!$A$3:$A$65423&"-"&別紙_テンプレート_DB!$C$3:$C$65423&"-"&別紙_テンプレート_DB!$D$3:$D$65423&"-"&別紙_テンプレート_DB!$E$3:$E$65423,),0)),0) -> 0
B69: 工事 | C69: 0 | D69: 4801 | E69: 1 | F69: =SUMIF(I$3:N$3,$F$3,I69:N69) -> 0 | G69: =IF(ISERROR(F69/H69),0,F69/H69) -> 0 | H69: =SUMIF(I$3:N$3,$H$3,I69:N69) -> 0 | I69: =IFERROR(INDEX(別紙_テンプレート_DB!$G$3:$G$65423,MATCH($C69&"-"&$D69&"-"&I$2&"-"&$E69,INDEX(別紙_テンプレート_DB!$A$3:$A$65423&"-"&別紙_テンプレート_DB!$C$3:$C$65423&"-"&別紙_テンプレート_DB!$D$3:$D$65423&"-"&別紙_テンプレート_DB!$E$3:$E$65423,),0)),0) -> 0 | J69: =IF(ISERROR(I69/K69),0,I69/K69) -> 0 | K69: =IFERROR(INDEX(別紙_テンプレート_DB!$F$3:$F$65423,MATCH($C69&"-"&$D69&"-"&I$2&"-"&$E69,INDEX(別紙_テンプレート_DB!$A$3:$A$65423&"-"&別紙_テンプレート_DB!$C$3:$C$65423&"-"&別紙_テンプレート_DB!$D$3:$D$65423&"-"&別紙_テンプレート_DB!$E$3:$E$65423,),0)),0) -> 0 | L69: =IFERROR(INDEX(別紙_テンプレート_DB!$G$3:$G$65423,MATCH($C69&"-"&$D69&"-"&L$2&"-"&$E69,INDEX(別紙_テンプレート_DB!$A$3:$A$65423&"-"&別紙_テンプレート_DB!$C$3:$C$65423&"-"&別紙_テンプレート_DB!$D$3:$D$65423&"-"&別紙_テンプレート_DB!$E$3:$E$65423,),0)),0) -> 0 | M69: =IF(ISERROR(L69/N69),0,L69/N69) -> 0 | N69: =IFERROR(INDEX(別紙_テンプレート_DB!$F$3:$F$65423,MATCH($C69&"-"&$D69&"-"&L$2&"-"&$E69,INDEX(別紙_テンプレート_DB!$A$3:$A$65423&"-"&別紙_テンプレート_DB!$C$3:$C$65423&"-"&別紙_テンプレート_DB!$D$3:$D$65423&"-"&別紙_テンプレート_DB!$E$3:$E$65423,),0)),0) -> 0
B70: コール | C70: 0 | D70: 4801 | E70: 2 | F70: =SUMIF(I$3:N$3,$F$3,I70:N70) -> 0 | G70: =IF(ISERROR(F70/H70),0,F70/H70) -> 0 | H70: =SUMIF(I$3:N$3,$H$3,I70:N70) -> 0 | I70: =IFERROR(INDEX(別紙_テンプレート_DB!$G$3:$G$65423,MATCH($C70&"-"&$D70&"-"&I$2&"-"&$E70,INDEX(別紙_テンプレート_DB!$A$3:$A$65423&"-"&別紙_テンプレート_DB!$C$3:$C$65423&"-"&別紙_テンプレート_DB!$D$3:$D$65423&"-"&別紙_テンプレート_DB!$E$3:$E$65423,),0)),0) -> 0 | J70: =IF(ISERROR(I70/K70),0,I70/K70) -> 0 | K70: =IFERROR(INDEX(別紙_テンプレート_DB!$F$3:$F$65423,MATCH($C70&"-"&$D70&"-"&I$2&"-"&$E70,INDEX(別紙_テンプレート_DB!$A$3:$A$65423&"-"&別紙_テンプレート_DB!$C$3:$C$65423&"-"&別紙_テンプレート_DB!$D$3:$D$65423&"-"&別紙_テンプレート_DB!$E$3:$E$65423,),0)),0) -> 0 | L70: =IFERROR(INDEX(別紙_テンプレート_DB!$G$3:$G$65423,MATCH($C70&"-"&$D70&"-"&L$2&"-"&$E70,INDEX(別紙_テンプレート_DB!$A$3:$A$65423&"-"&別紙_テンプレート_DB!$C$3:$C$65423&"-"&別紙_テンプレート_DB!$D$3:$D$65423&"-"&別紙_テンプレート_DB!$E$3:$E$65423,),0)),0) -> 0 | M70: =IF(ISERROR(L70/N70),0,L70/N70) -> 0 | N70: =IFERROR(INDEX(別紙_テンプレート_DB!$F$3:$F$65423,MATCH($C70&"-"&$D70&"-"&L$2&"-"&$E70,INDEX(別紙_テンプレート_DB!$A$3:$A$65423&"-"&別紙_テンプレート_DB!$C$3:$C$65423&"-"&別紙_テンプレート_DB!$D$3:$D$65423&"-"&別紙_テンプレート_DB!$E$3:$E$65423,),0)),0) -> 0
B71: 店装 | C71: 0 | D71: 4801 | E71: 3 | F71: =SUMIF(I$3:N$3,$F$3,I71:N71) -> 0 | G71: =IF(ISERROR(F71/H71),0,F71/H71) -> 0 | H71: =SUMIF(I$3:N$3,$H$3,I71:N71) -> 0 | I71: =IFERROR(INDEX(別紙_テンプレート_DB!$G$3:$G$65423,MATCH($C71&"-"&$D71&"-"&I$2&"-"&$E71,INDEX(別紙_テンプレート_DB!$A$3:$A$65423&"-"&別紙_テンプレート_DB!$C$3:$C$65423&"-"&別紙_テンプレート_DB!$D$3:$D$65423&"-"&別紙_テンプレート_DB!$E$3:$E$65423,),0)),0) -> 0 | J71: =IF(ISERROR(I71/K71),0,I71/K71) -> 0 | K71: =IFERROR(INDEX(別紙_テンプレート_DB!$F$3:$F$65423,MATCH($C71&"-"&$D71&"-"&I$2&"-"&$E71,INDEX(別紙_テンプレート_DB!$A$3:$A$65423&"-"&別紙_テンプレート_DB!$C$3:$C$65423&"-"&別紙_テンプレート_DB!$D$3:$D$65423&"-"&別紙_テンプレート_DB!$E$3:$E$65423,),0)),0) -> 0 | L71: =IFERROR(INDEX(別紙_テンプレート_DB!$G$3:$G$65423,MATCH($C71&"-"&$D71&"-"&L$2&"-"&$E71,INDEX(別紙_テンプレート_DB!$A$3:$A$65423&"-"&別紙_テンプレート_DB!$C$3:$C$65423&"-"&別紙_テンプレート_DB!$D$3:$D$65423&"-"&別紙_テンプレート_DB!$E$3:$E$65423,),0)),0) -> 0 | M71: =IF(ISERROR(L71/N71),0,L71/N71) -> 0 | N71: =IFERROR(INDEX(別紙_テンプレート_DB!$F$3:$F$65423,MATCH($C71&"-"&$D71&"-"&L$2&"-"&$E71,INDEX(別紙_テンプレート_DB!$A$3:$A$65423&"-"&別紙_テンプレート_DB!$C$3:$C$65423&"-"&別紙_テンプレート_DB!$D$3:$D$65423&"-"&別紙_テンプレート_DB!$E$3:$E$65423,),0)),0) -> 0
B72: 委託 | C72: 0 | D72: 4801 | E72: 106 | F72: =SUMIF(I$3:N$3,$F$3,I72:N72) -> 0 | G72: =IF(ISERROR(F72/H72),0,F72/H72) -> 0 | H72: =SUMIF(I$3:N$3,$H$3,I72:N72) -> 0 | I72: =IFERROR(INDEX(別紙_テンプレート_DB!$G$3:$G$65423,MATCH($C72&"-"&$D72&"-"&I$2&"-"&$E72,INDEX(別紙_テンプレート_DB!$A$3:$A$65423&"-"&別紙_テンプレート_DB!$C$3:$C$65423&"-"&別紙_テンプレート_DB!$D$3:$D$65423&"-"&別紙_テンプレート_DB!$E$3:$E$65423,),0)),0) -> 0 | J72: =IF(ISERROR(I72/K72),0,I72/K72) -> 0 | K72: =IFERROR(INDEX(別紙_テンプレート_DB!$F$3:$F$65423,MATCH($C72&"-"&$D72&"-"&I$2&"-"&$E72,INDEX(別紙_テンプレート_DB!$A$3:$A$65423&"-"&別紙_テンプレート_DB!$C$3:$C$65423&"-"&別紙_テンプレート_DB!$D$3:$D$65423&"-"&別紙_テンプレート_DB!$E$3:$E$65423,),0)),0) -> 0 | L72: =IFERROR(INDEX(別紙_テンプレート_DB!$G$3:$G$65423,MATCH($C72&"-"&$D72&"-"&L$2&"-"&$E72,INDEX(別紙_テンプレート_DB!$A$3:$A$65423&"-"&別紙_テンプレート_DB!$C$3:$C$65423&"-"&別紙_テンプレート_DB!$D$3:$D$65423&"-"&別紙_テンプレート_DB!$E$3:$E$65423,),0)),0) -> 0 | M72: =IF(ISERROR(L72/N72),0,L72/N72) -> 0 | N72: =IFERROR(INDEX(別紙_テンプレート_DB!$F$3:$F$65423,MATCH($C72&"-"&$D72&"-"&L$2&"-"&$E72,INDEX(別紙_テンプレート_DB!$A$3:$A$65423&"-"&別紙_テンプレート_DB!$C$3:$C$65423&"-"&別紙_テンプレート_DB!$D$3:$D$65423&"-"&別紙_テンプレート_DB!$E$3:$E$65423,),0)),0) -> 0
B73: クレーム | C73: 0 | D73: 4801 | E73: 4 | F73: =SUMIF(I$3:N$3,$F$3,I73:N73) -> 0 | G73: =IF(ISERROR(F73/H73),0,F73/H73) -> 0 | H73: =SUMIF(I$3:N$3,$H$3,I73:N73) -> 0 | I73: =IFERROR(INDEX(別紙_テンプレート_DB!$G$3:$G$65423,MATCH($C73&"-"&$D73&"-"&I$2&"-"&$E73,INDEX(別紙_テンプレート_DB!$A$3:$A$65423&"-"&別紙_テンプレート_DB!$C$3:$C$65423&"-"&別紙_テンプレート_DB!$D$3:$D$65423&"-"&別紙_テンプレート_DB!$E$3:$E$65423,),0)),0) -> 0 | J73: =IF(ISERROR(I73/K73),0,I73/K73) -> 0 | K73: =IFERROR(INDEX(別紙_テンプレート_DB!$F$3:$F$65423,MATCH($C73&"-"&$D73&"-"&I$2&"-"&$E73,INDEX(別紙_テンプレート_DB!$A$3:$A$65423&"-"&別紙_テンプレート_DB!$C$3:$C$65423&"-"&別紙_テンプレート_DB!$D$3:$D$65423&"-"&別紙_テンプレート_DB!$E$3:$E$65423,),0)),0) -> 0 | L73: =IFERROR(INDEX(別紙_テンプレート_DB!$G$3:$G$65423,MATCH($C73&"-"&$D73&"-"&L$2&"-"&$E73,INDEX(別紙_テンプレート_DB!$A$3:$A$65423&"-"&別紙_テンプレート_DB!$C$3:$C$65423&"-"&別紙_テンプレート_DB!$D$3:$D$65423&"-"&別紙_テンプレート_DB!$E$3:$E$65423,),0)),0) -> 0 | M73: =IF(ISERROR(L73/N73),0,L73/N73) -> 0 | N73: =IFERROR(INDEX(別紙_テンプレート_DB!$F$3:$F$65423,MATCH($C73&"-"&$D73&"-"&L$2&"-"&$E73,INDEX(別紙_テンプレート_DB!$A$3:$A$65423&"-"&別紙_テンプレート_DB!$C$3:$C$65423&"-"&別紙_テンプレート_DB!$D$3:$D$65423&"-"&別紙_テンプレート_DB!$E$3:$E$65423,),0)),0) -> 0
B74: 在庫 | D74: 4801 | E74: 20 | F74: =SUMIF(I$3:N$3,$F$3,I74:N74) -> 0 | G74: ⇔ | H74: =SUMIF(I$3:N$3,$H$3,I74:N74) -> 0 | I74: =IFERROR(INDEX(別紙_テンプレート_DB!$AB$3:$AB$65423,MATCH($D74&"-"&I$2,INDEX(別紙_テンプレート_DB!$Y$3:$Y$65423&"-"&別紙_テンプレート_DB!$Z$3:$Z$65423,),0)),0) -> 0 | J74: ⇔ | K74: =IFERROR(INDEX(別紙_テンプレート_DB!$AA$3:$AA$65423,MATCH($D74&"-"&I$2,INDEX(別紙_テンプレート_DB!$Y$3:$Y$65423&"-"&別紙_テンプレート_DB!$Z$3:$Z$65423,),0)),0) -> 0 | L74: =IFERROR(INDEX(別紙_テンプレート_DB!$AB$3:$AB$65423,MATCH($D74&"-"&L$2,INDEX(別紙_テンプレート_DB!$Y$3:$Y$65423&"-"&別紙_テンプレート_DB!$Z$3:$Z$65423,),0)),0) -> 0 | M74: ⇔ | N74: =IFERROR(INDEX(別紙_テンプレート_DB!$AA$3:$AA$65423,MATCH($D74&"-"&L$2,INDEX(別紙_テンプレート_DB!$Y$3:$Y$65423&"-"&別紙_テンプレート_DB!$Z$3:$Z$65423,),0)),0) -> 0
A75: Y | B75: 原/売 | D75: 8001 | F75: =SUMIF(I$3:N$3,$F$3,I75:N75) -> 0 | G75: =IF(ISERROR(F75/H75),0,F75/H75) -> 0 | H75: =SUMIF(I$3:N$3,$H$3,I75:N75) -> 0 | I75: =SUMIF($D76:$D81,$D75,I76:I81) -> 0 | J75: =IF(ISERROR(I75/K75),0,I75/K75) -> 0 | K75: =SUM(K76:K81) -> 0 | L75: =SUMIF($D76:$D81,$D75,L76:L81) -> 0 | M75: =IF(ISERROR(L75/N75),0,L75/N75) -> 0 | N75: =SUM(N76:N81) -> 0
B76: 営業 | C76: 0 | D76: 8001 | E76: 0 | F76: =SUMIF(I$3:N$3,$F$3,I76:N76) -> 0 | G76: =IF(ISERROR(F76/H76),0,F76/H76) -> 0 | H76: =SUMIF(I$3:N$3,$H$3,I76:N76) -> 0 | I76: =IFERROR(INDEX(別紙_テンプレート_DB!$G$3:$G$65423,MATCH($C76&"-"&$D76&"-"&I$2&"-"&$E76,INDEX(別紙_テンプレート_DB!$A$3:$A$65423&"-"&別紙_テンプレート_DB!$C$3:$C$65423&"-"&別紙_テンプレート_DB!$D$3:$D$65423&"-"&別紙_テンプレート_DB!$E$3:$E$65423,),0)),0) -> 0 | J76: =IF(ISERROR(I76/K76),0,I76/K76) -> 0 | K76: =IFERROR(INDEX(別紙_テンプレート_DB!$F$3:$F$65423,MATCH($C76&"-"&$D76&"-"&I$2&"-"&$E76,INDEX(別紙_テンプレート_DB!$A$3:$A$65423&"-"&別紙_テンプレート_DB!$C$3:$C$65423&"-"&別紙_テンプレート_DB!$D$3:$D$65423&"-"&別紙_テンプレート_DB!$E$3:$E$65423,),0)),0) -> 0 | L76: =IFERROR(INDEX(別紙_テンプレート_DB!$G$3:$G$65423,MATCH($C76&"-"&$D76&"-"&L$2&"-"&$E76,INDEX(別紙_テンプレート_DB!$A$3:$A$65423&"-"&別紙_テンプレート_DB!$C$3:$C$65423&"-"&別紙_テンプレート_DB!$D$3:$D$65423&"-"&別紙_テンプレート_DB!$E$3:$E$65423,),0)),0) -> 0 | M76: =IF(ISERROR(L76/N76),0,L76/N76) -> 0 | N76: =IFERROR(INDEX(別紙_テンプレート_DB!$F$3:$F$65423,MATCH($C76&"-"&$D76&"-"&L$2&"-"&$E76,INDEX(別紙_テンプレート_DB!$A$3:$A$65423&"-"&別紙_テンプレート_DB!$C$3:$C$65423&"-"&別紙_テンプレート_DB!$D$3:$D$65423&"-"&別紙_テンプレート_DB!$E$3:$E$65423,),0)),0) -> 0
B77: 工事 | C77: 0 | D77: 8001 | E77: 1 | F77: =SUMIF(I$3:N$3,$F$3,I77:N77) -> 0 | G77: =IF(ISERROR(F77/H77),0,F77/H77) -> 0 | H77: =SUMIF(I$3:N$3,$H$3,I77:N77) -> 0 | I77: =IFERROR(INDEX(別紙_テンプレート_DB!$G$3:$G$65423,MATCH($C77&"-"&$D77&"-"&I$2&"-"&$E77,INDEX(別紙_テンプレート_DB!$A$3:$A$65423&"-"&別紙_テンプレート_DB!$C$3:$C$65423&"-"&別紙_テンプレート_DB!$D$3:$D$65423&"-"&別紙_テンプレート_DB!$E$3:$E$65423,),0)),0) -> 0 | J77: =IF(ISERROR(I77/K77),0,I77/K77) -> 0 | K77: =IFERROR(INDEX(別紙_テンプレート_DB!$F$3:$F$65423,MATCH($C77&"-"&$D77&"-"&I$2&"-"&$E77,INDEX(別紙_テンプレート_DB!$A$3:$A$65423&"-"&別紙_テンプレート_DB!$C$3:$C$65423&"-"&別紙_テンプレート_DB!$D$3:$D$65423&"-"&別紙_テンプレート_DB!$E$3:$E$65423,),0)),0) -> 0 | L77: =IFERROR(INDEX(別紙_テンプレート_DB!$G$3:$G$65423,MATCH($C77&"-"&$D77&"-"&L$2&"-"&$E77,INDEX(別紙_テンプレート_DB!$A$3:$A$65423&"-"&別紙_テンプレート_DB!$C$3:$C$65423&"-"&別紙_テンプレート_DB!$D$3:$D$65423&"-"&別紙_テンプレート_DB!$E$3:$E$65423,),0)),0) -> 0 | M77: =IF(ISERROR(L77/N77),0,L77/N77) -> 0 | N77: =IFERROR(INDEX(別紙_テンプレート_DB!$F$3:$F$65423,MATCH($C77&"-"&$D77&"-"&L$2&"-"&$E77,INDEX(別紙_テンプレート_DB!$A$3:$A$65423&"-"&別紙_テンプレート_DB!$C$3:$C$65423&"-"&別紙_テンプレート_DB!$D$3:$D$65423&"-"&別紙_テンプレート_DB!$E$3:$E$65423,),0)),0) -> 0
B78: コール | C78: 0 | D78: 8001 | E78: 2 | F78: =SUMIF(I$3:N$3,$F$3,I78:N78) -> 0 | G78: =IF(ISERROR(F78/H78),0,F78/H78) -> 0 | H78: =SUMIF(I$3:N$3,$H$3,I78:N78) -> 0 | I78: =IFERROR(INDEX(別紙_テンプレート_DB!$G$3:$G$65423,MATCH($C78&"-"&$D78&"-"&I$2&"-"&$E78,INDEX(別紙_テンプレート_DB!$A$3:$A$65423&"-"&別紙_テンプレート_DB!$C$3:$C$65423&"-"&別紙_テンプレート_DB!$D$3:$D$65423&"-"&別紙_テンプレート_DB!$E$3:$E$65423,),0)),0) -> 0 | J78: =IF(ISERROR(I78/K78),0,I78/K78) -> 0 | K78: =IFERROR(INDEX(別紙_テンプレート_DB!$F$3:$F$65423,MATCH($C78&"-"&$D78&"-"&I$2&"-"&$E78,INDEX(別紙_テンプレート_DB!$A$3:$A$65423&"-"&別紙_テンプレート_DB!$C$3:$C$65423&"-"&別紙_テンプレート_DB!$D$3:$D$65423&"-"&別紙_テンプレート_DB!$E$3:$E$65423,),0)),0) -> 0 | L78: =IFERROR(INDEX(別紙_テンプレート_DB!$G$3:$G$65423,MATCH($C78&"-"&$D78&"-"&L$2&"-"&$E78,INDEX(別紙_テンプレート_DB!$A$3:$A$65423&"-"&別紙_テンプレート_DB!$C$3:$C$65423&"-"&別紙_テンプレート_DB!$D$3:$D$65423&"-"&別紙_テンプレート_DB!$E$3:$E$65423,),0)),0) -> 0 | M78: =IF(ISERROR(L78/N78),0,L78/N78) -> 0 | N78: =IFERROR(INDEX(別紙_テンプレート_DB!$F$3:$F$65423,MATCH($C78&"-"&$D78&"-"&L$2&"-"&$E78,INDEX(別紙_テンプレート_DB!$A$3:$A$65423&"-"&別紙_テンプレート_DB!$C$3:$C$65423&"-"&別紙_テンプレート_DB!$D$3:$D$65423&"-"&別紙_テンプレート_DB!$E$3:$E$65423,),0)),0) -> 0
B79: 店装 | C79: 0 | D79: 8001 | E79: 3 | F79: =SUMIF(I$3:N$3,$F$3,I79:N79) -> 0 | G79: =IF(ISERROR(F79/H79),0,F79/H79) -> 0 | H79: =SUMIF(I$3:N$3,$H$3,I79:N79) -> 0 | I79: =IFERROR(INDEX(別紙_テンプレート_DB!$G$3:$G$65423,MATCH($C79&"-"&$D79&"-"&I$2&"-"&$E79,INDEX(別紙_テンプレート_DB!$A$3:$A$65423&"-"&別紙_テンプレート_DB!$C$3:$C$65423&"-"&別紙_テンプレート_DB!$D$3:$D$65423&"-"&別紙_テンプレート_DB!$E$3:$E$65423,),0)),0) -> 0 | J79: =IF(ISERROR(I79/K79),0,I79/K79) -> 0 | K79: =IFERROR(INDEX(別紙_テンプレート_DB!$F$3:$F$65423,MATCH($C79&"-"&$D79&"-"&I$2&"-"&$E79,INDEX(別紙_テンプレート_DB!$A$3:$A$65423&"-"&別紙_テンプレート_DB!$C$3:$C$65423&"-"&別紙_テンプレート_DB!$D$3:$D$65423&"-"&別紙_テンプレート_DB!$E$3:$E$65423,),0)),0) -> 0 | L79: =IFERROR(INDEX(別紙_テンプレート_DB!$G$3:$G$65423,MATCH($C79&"-"&$D79&"-"&L$2&"-"&$E79,INDEX(別紙_テンプレート_DB!$A$3:$A$65423&"-"&別紙_テンプレート_DB!$C$3:$C$65423&"-"&別紙_テンプレート_DB!$D$3:$D$65423&"-"&別紙_テンプレート_DB!$E$3:$E$65423,),0)),0) -> 0 | M79: =IF(ISERROR(L79/N79),0,L79/N79) -> 0 | N79: =IFERROR(INDEX(別紙_テンプレート_DB!$F$3:$F$65423,MATCH($C79&"-"&$D79&"-"&L$2&"-"&$E79,INDEX(別紙_テンプレート_DB!$A$3:$A$65423&"-"&別紙_テンプレート_DB!$C$3:$C$65423&"-"&別紙_テンプレート_DB!$D$3:$D$65423&"-"&別紙_テンプレート_DB!$E$3:$E$65423,),0)),0) -> 0
B80: 委託 | C80: 0 | D80: 8001 | E80: 106 | F80: =SUMIF(I$3:N$3,$F$3,I80:N80) -> 0 | G80: =IF(ISERROR(F80/H80),0,F80/H80) -> 0 | H80: =SUMIF(I$3:N$3,$H$3,I80:N80) -> 0 | I80: =IFERROR(INDEX(別紙_テンプレート_DB!$G$3:$G$65423,MATCH($C80&"-"&$D80&"-"&I$2&"-"&$E80,INDEX(別紙_テンプレート_DB!$A$3:$A$65423&"-"&別紙_テンプレート_DB!$C$3:$C$65423&"-"&別紙_テンプレート_DB!$D$3:$D$65423&"-"&別紙_テンプレート_DB!$E$3:$E$65423,),0)),0) -> 0 | J80: =IF(ISERROR(I80/K80),0,I80/K80) -> 0 | K80: =IFERROR(INDEX(別紙_テンプレート_DB!$F$3:$F$65423,MATCH($C80&"-"&$D80&"-"&I$2&"-"&$E80,INDEX(別紙_テンプレート_DB!$A$3:$A$65423&"-"&別紙_テンプレート_DB!$C$3:$C$65423&"-"&別紙_テンプレート_DB!$D$3:$D$65423&"-"&別紙_テンプレート_DB!$E$3:$E$65423,),0)),0) -> 0 | L80: =IFERROR(INDEX(別紙_テンプレート_DB!$G$3:$G$65423,MATCH($C80&"-"&$D80&"-"&L$2&"-"&$E80,INDEX(別紙_テンプレート_DB!$A$3:$A$65423&"-"&別紙_テンプレート_DB!$C$3:$C$65423&"-"&別紙_テンプレート_DB!$D$3:$D$65423&"-"&別紙_テンプレート_DB!$E$3:$E$65423,),0)),0) -> 0 | M80: =IF(ISERROR(L80/N80),0,L80/N80) -> 0 | N80: =IFERROR(INDEX(別紙_テンプレート_DB!$F$3:$F$65423,MATCH($C80&"-"&$D80&"-"&L$2&"-"&$E80,INDEX(別紙_テンプレート_DB!$A$3:$A$65423&"-"&別紙_テンプレート_DB!$C$3:$C$65423&"-"&別紙_テンプレート_DB!$D$3:$D$65423&"-"&別紙_テンプレート_DB!$E$3:$E$65423,),0)),0) -> 0
B81: クレーム | C81: 0 | D81: 8001 | E81: 4 | F81: =SUMIF(I$3:N$3,$F$3,I81:N81) -> 0 | G81: =IF(ISERROR(F81/H81),0,F81/H81) -> 0 | H81: =SUMIF(I$3:N$3,$H$3,I81:N81) -> 0 | I81: =IFERROR(INDEX(別紙_テンプレート_DB!$G$3:$G$65423,MATCH($C81&"-"&$D81&"-"&I$2&"-"&$E81,INDEX(別紙_テンプレート_DB!$A$3:$A$65423&"-"&別紙_テンプレート_DB!$C$3:$C$65423&"-"&別紙_テンプレート_DB!$D$3:$D$65423&"-"&別紙_テンプレート_DB!$E$3:$E$65423,),0)),0) -> 0 | J81: =IF(ISERROR(I81/K81),0,I81/K81) -> 0 | K81: =IFERROR(INDEX(別紙_テンプレート_DB!$F$3:$F$65423,MATCH($C81&"-"&$D81&"-"&I$2&"-"&$E81,INDEX(別紙_テンプレート_DB!$A$3:$A$65423&"-"&別紙_テンプレート_DB!$C$3:$C$65423&"-"&別紙_テンプレート_DB!$D$3:$D$65423&"-"&別紙_テンプレート_DB!$E$3:$E$65423,),0)),0) -> 0 | L81: =IFERROR(INDEX(別紙_テンプレート_DB!$G$3:$G$65423,MATCH($C81&"-"&$D81&"-"&L$2&"-"&$E81,INDEX(別紙_テンプレート_DB!$A$3:$A$65423&"-"&別紙_テンプレート_DB!$C$3:$C$65423&"-"&別紙_テンプレート_DB!$D$3:$D$65423&"-"&別紙_テンプレート_DB!$E$3:$E$65423,),0)),0) -> 0 | M81: =IF(ISERROR(L81/N81),0,L81/N81) -> 0 | N81: =IFERROR(INDEX(別紙_テンプレート_DB!$F$3:$F$65423,MATCH($C81&"-"&$D81&"-"&L$2&"-"&$E81,INDEX(別紙_テンプレート_DB!$A$3:$A$65423&"-"&別紙_テンプレート_DB!$C$3:$C$65423&"-"&別紙_テンプレート_DB!$D$3:$D$65423&"-"&別紙_テンプレート_DB!$E$3:$E$65423,),0)),0) -> 0
B82: 在庫 | D82: 8001 | E82: 20 | F82: =SUMIF(I$3:N$3,$F$3,I82:N82) -> 0 | G82: ⇔ | H82: =SUMIF(I$3:N$3,$H$3,I82:N82) -> 0 | I82: =IFERROR(INDEX(別紙_テンプレート_DB!$AB$3:$AB$65423,MATCH($D82&"-"&I$2,INDEX(別紙_テンプレート_DB!$Y$3:$Y$65423&"-"&別紙_テンプレート_DB!$Z$3:$Z$65423,),0)),0) -> 0 | J82: ⇔ | K82: =IFERROR(INDEX(別紙_テンプレート_DB!$AA$3:$AA$65423,MATCH($D82&"-"&I$2,INDEX(別紙_テンプレート_DB!$Y$3:$Y$65423&"-"&別紙_テンプレート_DB!$Z$3:$Z$65423,),0)),0) -> 0 | L82: =IFERROR(INDEX(別紙_テンプレート_DB!$AB$3:$AB$65423,MATCH($D82&"-"&L$2,INDEX(別紙_テンプレート_DB!$Y$3:$Y$65423&"-"&別紙_テンプレート_DB!$Z$3:$Z$65423,),0)),0) -> 0 | M82: ⇔ | N82: =IFERROR(INDEX(別紙_テンプレート_DB!$AA$3:$AA$65423,MATCH($D82&"-"&L$2,INDEX(別紙_テンプレート_DB!$Y$3:$Y$65423&"-"&別紙_テンプレート_DB!$Z$3:$Z$65423,),0)),0) -> 0
A83: その他 | B83: 原/売 | D83: 99999 | F83: =SUMIF(I$3:N$3,$F$3,I83:N83) -> 0 | G83: =IF(ISERROR(F83/H83),0,F83/H83) -> 0 | H83: =SUMIF(I$3:N$3,$H$3,I83:N83) -> 0 | I83: =SUMIF($D84:$D89,$D83,I84:I89) -> 0 | J83: =IF(ISERROR(I83/K83),0,I83/K83) -> 0 | K83: =SUM(K84:K89) -> 0 | L83: =SUMIF($D84:$D89,$D83,L84:L89) -> 0 | M83: =IF(ISERROR(L83/N83),0,L83/N83) -> 0 | N83: =SUM(N84:N89) -> 0
B84: 営業 | C84: 0 | D84: 99999 | E84: 0 | F84: =SUMIF(I$3:N$3,$F$3,I84:N84) -> 0 | G84: =IF(ISERROR(F84/H84),0,F84/H84) -> 0 | H84: =SUMIF(I$3:N$3,$H$3,I84:N84) -> 0 | I84: =IFERROR(INDEX(別紙_テンプレート_DB!$G$3:$G$65423,MATCH($C84&"-"&$D84&"-"&I$2&"-"&$E84,INDEX(別紙_テンプレート_DB!$A$3:$A$65423&"-"&別紙_テンプレート_DB!$C$3:$C$65423&"-"&別紙_テンプレート_DB!$D$3:$D$65423&"-"&別紙_テンプレート_DB!$E$3:$E$65423,),0)),0) -> 0 | J84: =IF(ISERROR(I84/K84),0,I84/K84) -> 0 | K84: =IFERROR(INDEX(別紙_テンプレート_DB!$F$3:$F$65423,MATCH($C84&"-"&$D84&"-"&I$2&"-"&$E84,INDEX(別紙_テンプレート_DB!$A$3:$A$65423&"-"&別紙_テンプレート_DB!$C$3:$C$65423&"-"&別紙_テンプレート_DB!$D$3:$D$65423&"-"&別紙_テンプレート_DB!$E$3:$E$65423,),0)),0) -> 0 | L84: =IFERROR(INDEX(別紙_テンプレート_DB!$G$3:$G$65423,MATCH($C84&"-"&$D84&"-"&L$2&"-"&$E84,INDEX(別紙_テンプレート_DB!$A$3:$A$65423&"-"&別紙_テンプレート_DB!$C$3:$C$65423&"-"&別紙_テンプレート_DB!$D$3:$D$65423&"-"&別紙_テンプレート_DB!$E$3:$E$65423,),0)),0) -> 0 | M84: =IF(ISERROR(L84/N84),0,L84/N84) -> 0 | N84: =IFERROR(INDEX(別紙_テンプレート_DB!$F$3:$F$65423,MATCH($C84&"-"&$D84&"-"&L$2&"-"&$E84,INDEX(別紙_テンプレート_DB!$A$3:$A$65423&"-"&別紙_テンプレート_DB!$C$3:$C$65423&"-"&別紙_テンプレート_DB!$D$3:$D$65423&"-"&別紙_テンプレート_DB!$E$3:$E$65423,),0)),0) -> 0
B85: 工事 | C85: 0 | D85: 99999 | E85: 1 | F85: =SUMIF(I$3:N$3,$F$3,I85:N85) -> 0 | G85: =IF(ISERROR(F85/H85),0,F85/H85) -> 0 | H85: =SUMIF(I$3:N$3,$H$3,I85:N85) -> 0 | I85: =IFERROR(INDEX(別紙_テンプレート_DB!$G$3:$G$65423,MATCH($C85&"-"&$D85&"-"&I$2&"-"&$E85,INDEX(別紙_テンプレート_DB!$A$3:$A$65423&"-"&別紙_テンプレート_DB!$C$3:$C$65423&"-"&別紙_テンプレート_DB!$D$3:$D$65423&"-"&別紙_テンプレート_DB!$E$3:$E$65423,),0)),0) -> 0 | J85: =IF(ISERROR(I85/K85),0,I85/K85) -> 0 | K85: =IFERROR(INDEX(別紙_テンプレート_DB!$F$3:$F$65423,MATCH($C85&"-"&$D85&"-"&I$2&"-"&$E85,INDEX(別紙_テンプレート_DB!$A$3:$A$65423&"-"&別紙_テンプレート_DB!$C$3:$C$65423&"-"&別紙_テンプレート_DB!$D$3:$D$65423&"-"&別紙_テンプレート_DB!$E$3:$E$65423,),0)),0) -> 0 | L85: =IFERROR(INDEX(別紙_テンプレート_DB!$G$3:$G$65423,MATCH($C85&"-"&$D85&"-"&L$2&"-"&$E85,INDEX(別紙_テンプレート_DB!$A$3:$A$65423&"-"&別紙_テンプレート_DB!$C$3:$C$65423&"-"&別紙_テンプレート_DB!$D$3:$D$65423&"-"&別紙_テンプレート_DB!$E$3:$E$65423,),0)),0) -> 0 | M85: =IF(ISERROR(L85/N85),0,L85/N85) -> 0 | N85: =IFERROR(INDEX(別紙_テンプレート_DB!$F$3:$F$65423,MATCH($C85&"-"&$D85&"-"&L$2&"-"&$E85,INDEX(別紙_テンプレート_DB!$A$3:$A$65423&"-"&別紙_テンプレート_DB!$C$3:$C$65423&"-"&別紙_テンプレート_DB!$D$3:$D$65423&"-"&別紙_テンプレート_DB!$E$3:$E$65423,),0)),0) -> 0
B86: コール | C86: 0 | D86: 99999 | E86: 2 | F86: =SUMIF(I$3:N$3,$F$3,I86:N86) -> 0 | G86: =IF(ISERROR(F86/H86),0,F86/H86) -> 0 | H86: =SUMIF(I$3:N$3,$H$3,I86:N86) -> 0 | I86: =IFERROR(INDEX(別紙_テンプレート_DB!$G$3:$G$65423,MATCH($C86&"-"&$D86&"-"&I$2&"-"&$E86,INDEX(別紙_テンプレート_DB!$A$3:$A$65423&"-"&別紙_テンプレート_DB!$C$3:$C$65423&"-"&別紙_テンプレート_DB!$D$3:$D$65423&"-"&別紙_テンプレート_DB!$E$3:$E$65423,),0)),0) -> 0 | J86: =IF(ISERROR(I86/K86),0,I86/K86) -> 0 | K86: =IFERROR(INDEX(別紙_テンプレート_DB!$F$3:$F$65423,MATCH($C86&"-"&$D86&"-"&I$2&"-"&$E86,INDEX(別紙_テンプレート_DB!$A$3:$A$65423&"-"&別紙_テンプレート_DB!$C$3:$C$65423&"-"&別紙_テンプレート_DB!$D$3:$D$65423&"-"&別紙_テンプレート_DB!$E$3:$E$65423,),0)),0) -> 0 | L86: =IFERROR(INDEX(別紙_テンプレート_DB!$G$3:$G$65423,MATCH($C86&"-"&$D86&"-"&L$2&"-"&$E86,INDEX(別紙_テンプレート_DB!$A$3:$A$65423&"-"&別紙_テンプレート_DB!$C$3:$C$65423&"-"&別紙_テンプレート_DB!$D$3:$D$65423&"-"&別紙_テンプレート_DB!$E$3:$E$65423,),0)),0) -> 0 | M86: =IF(ISERROR(L86/N86),0,L86/N86) -> 0 | N86: =IFERROR(INDEX(別紙_テンプレート_DB!$F$3:$F$65423,MATCH($C86&"-"&$D86&"-"&L$2&"-"&$E86,INDEX(別紙_テンプレート_DB!$A$3:$A$65423&"-"&別紙_テンプレート_DB!$C$3:$C$65423&"-"&別紙_テンプレート_DB!$D$3:$D$65423&"-"&別紙_テンプレート_DB!$E$3:$E$65423,),0)),0) -> 0
B87: 店装 | C87: 0 | D87: 99999 | E87: 3 | F87: =SUMIF(I$3:N$3,$F$3,I87:N87) -> 0 | G87: =IF(ISERROR(F87/H87),0,F87/H87) -> 0 | H87: =SUMIF(I$3:N$3,$H$3,I87:N87) -> 0 | I87: =IFERROR(INDEX(別紙_テンプレート_DB!$G$3:$G$65423,MATCH($C87&"-"&$D87&"-"&I$2&"-"&$E87,INDEX(別紙_テンプレート_DB!$A$3:$A$65423&"-"&別紙_テンプレート_DB!$C$3:$C$65423&"-"&別紙_テンプレート_DB!$D$3:$D$65423&"-"&別紙_テンプレート_DB!$E$3:$E$65423,),0)),0) -> 0 | J87: =IF(ISERROR(I87/K87),0,I87/K87) -> 0 | K87: =IFERROR(INDEX(別紙_テンプレート_DB!$F$3:$F$65423,MATCH($C87&"-"&$D87&"-"&I$2&"-"&$E87,INDEX(別紙_テンプレート_DB!$A$3:$A$65423&"-"&別紙_テンプレート_DB!$C$3:$C$65423&"-"&別紙_テンプレート_DB!$D$3:$D$65423&"-"&別紙_テンプレート_DB!$E$3:$E$65423,),0)),0) -> 0 | L87: =IFERROR(INDEX(別紙_テンプレート_DB!$G$3:$G$65423,MATCH($C87&"-"&$D87&"-"&L$2&"-"&$E87,INDEX(別紙_テンプレート_DB!$A$3:$A$65423&"-"&別紙_テンプレート_DB!$C$3:$C$65423&"-"&別紙_テンプレート_DB!$D$3:$D$65423&"-"&別紙_テンプレート_DB!$E$3:$E$65423,),0)),0) -> 0 | M87: =IF(ISERROR(L87/N87),0,L87/N87) -> 0 | N87: =IFERROR(INDEX(別紙_テンプレート_DB!$F$3:$F$65423,MATCH($C87&"-"&$D87&"-"&L$2&"-"&$E87,INDEX(別紙_テンプレート_DB!$A$3:$A$65423&"-"&別紙_テンプレート_DB!$C$3:$C$65423&"-"&別紙_テンプレート_DB!$D$3:$D$65423&"-"&別紙_テンプレート_DB!$E$3:$E$65423,),0)),0) -> 0
B88: 委託 | C88: 0 | D88: 99999 | E88: 106 | F88: =SUMIF(I$3:N$3,$F$3,I88:N88) -> 0 | G88: =IF(ISERROR(F88/H88),0,F88/H88) -> 0 | H88: =SUMIF(I$3:N$3,$H$3,I88:N88) -> 0 | I88: =IFERROR(INDEX(別紙_テンプレート_DB!$G$3:$G$65423,MATCH($C88&"-"&$D88&"-"&I$2&"-"&$E88,INDEX(別紙_テンプレート_DB!$A$3:$A$65423&"-"&別紙_テンプレート_DB!$C$3:$C$65423&"-"&別紙_テンプレート_DB!$D$3:$D$65423&"-"&別紙_テンプレート_DB!$E$3:$E$65423,),0)),0) -> 0 | J88: =IF(ISERROR(I88/K88),0,I88/K88) -> 0 | K88: =IFERROR(INDEX(別紙_テンプレート_DB!$F$3:$F$65423,MATCH($C88&"-"&$D88&"-"&I$2&"-"&$E88,INDEX(別紙_テンプレート_DB!$A$3:$A$65423&"-"&別紙_テンプレート_DB!$C$3:$C$65423&"-"&別紙_テンプレート_DB!$D$3:$D$65423&"-"&別紙_テンプレート_DB!$E$3:$E$65423,),0)),0) -> 0 | L88: =IFERROR(INDEX(別紙_テンプレート_DB!$G$3:$G$65423,MATCH($C88&"-"&$D88&"-"&L$2&"-"&$E88,INDEX(別紙_テンプレート_DB!$A$3:$A$65423&"-"&別紙_テンプレート_DB!$C$3:$C$65423&"-"&別紙_テンプレート_DB!$D$3:$D$65423&"-"&別紙_テンプレート_DB!$E$3:$E$65423,),0)),0) -> 0 | M88: =IF(ISERROR(L88/N88),0,L88/N88) -> 0 | N88: =IFERROR(INDEX(別紙_テンプレート_DB!$F$3:$F$65423,MATCH($C88&"-"&$D88&"-"&L$2&"-"&$E88,INDEX(別紙_テンプレート_DB!$A$3:$A$65423&"-"&別紙_テンプレート_DB!$C$3:$C$65423&"-"&別紙_テンプレート_DB!$D$3:$D$65423&"-"&別紙_テンプレート_DB!$E$3:$E$65423,),0)),0) -> 0
B89: クレーム | C89: 0 | D89: 99999 | E89: 4 | F89: =SUMIF(I$3:N$3,$F$3,I89:N89) -> 0 | G89: =IF(ISERROR(F89/H89),0,F89/H89) -> 0 | H89: =SUMIF(I$3:N$3,$H$3,I89:N89) -> 0 | I89: =IFERROR(INDEX(別紙_テンプレート_DB!$G$3:$G$65423,MATCH($C89&"-"&$D89&"-"&I$2&"-"&$E89,INDEX(別紙_テンプレート_DB!$A$3:$A$65423&"-"&別紙_テンプレート_DB!$C$3:$C$65423&"-"&別紙_テンプレート_DB!$D$3:$D$65423&"-"&別紙_テンプレート_DB!$E$3:$E$65423,),0)),0) -> 0 | J89: =IF(ISERROR(I89/K89),0,I89/K89) -> 0 | K89: =IFERROR(INDEX(別紙_テンプレート_DB!$F$3:$F$65423,MATCH($C89&"-"&$D89&"-"&I$2&"-"&$E89,INDEX(別紙_テンプレート_DB!$A$3:$A$65423&"-"&別紙_テンプレート_DB!$C$3:$C$65423&"-"&別紙_テンプレート_DB!$D$3:$D$65423&"-"&別紙_テンプレート_DB!$E$3:$E$65423,),0)),0) -> 0 | L89: =IFERROR(INDEX(別紙_テンプレート_DB!$G$3:$G$65423,MATCH($C89&"-"&$D89&"-"&L$2&"-"&$E89,INDEX(別紙_テンプレート_DB!$A$3:$A$65423&"-"&別紙_テンプレート_DB!$C$3:$C$65423&"-"&別紙_テンプレート_DB!$D$3:$D$65423&"-"&別紙_テンプレート_DB!$E$3:$E$65423,),0)),0) -> 0 | M89: =IF(ISERROR(L89/N89),0,L89/N89) -> 0 | N89: =IFERROR(INDEX(別紙_テンプレート_DB!$F$3:$F$65423,MATCH($C89&"-"&$D89&"-"&L$2&"-"&$E89,INDEX(別紙_テンプレート_DB!$A$3:$A$65423&"-"&別紙_テンプレート_DB!$C$3:$C$65423&"-"&別紙_テンプレート_DB!$D$3:$D$65423&"-"&別紙_テンプレート_DB!$E$3:$E$65423,),0)),0) -> 0
B90: 在庫 | D90: 0 | E90: 20 | F90: =SUMIF(I$3:N$3,$F$3,I90:N90) -> 0 | G90: ⇔ | H90: =SUMIF(I$3:N$3,$H$3,I90:N90) -> 0 | I90: =IFERROR(INDEX(別紙_テンプレート_DB!$AB$3:$AB$65423,MATCH($D90&"-"&I$2,INDEX(別紙_テンプレート_DB!$Y$3:$Y$65423&"-"&別紙_テンプレート_DB!$Z$3:$Z$65423,),0)),0) -> 0 | J90: ⇔ | K90: =IFERROR(INDEX(別紙_テンプレート_DB!$AA$3:$AA$65423,MATCH($D90&"-"&I$2,INDEX(別紙_テンプレート_DB!$Y$3:$Y$65423&"-"&別紙_テンプレート_DB!$Z$3:$Z$65423,),0)),0) -> 0 | L90: =IFERROR(INDEX(別紙_テンプレート_DB!$AB$3:$AB$65423,MATCH($D90&"-"&L$2,INDEX(別紙_テンプレート_DB!$Y$3:$Y$65423&"-"&別紙_テンプレート_DB!$Z$3:$Z$65423,),0)),0) -> 0 | M90: ⇔ | N90: =IFERROR(INDEX(別紙_テンプレート_DB!$AA$3:$AA$65423,MATCH($D90&"-"&L$2,INDEX(別紙_テンプレート_DB!$Y$3:$Y$65423&"-"&別紙_テンプレート_DB!$Z$3:$Z$65423,),0)),0) -> 0
A91: EC | B91: 原/売 | C91: 0 | D91: 9 | F91: =SUMIF(I$3:N$3,$F$3,I91:N91) -> 0 | G91: =IF(ISERROR(F91/H91),0,F91/H91) -> 0 | H91: =SUMIF(I$3:N$3,$H$3,I91:N91) -> 0 | I91: =SUMIF($D92:$D97,$D91,I92:I97) -> 0 | J91: =IF(ISERROR(I91/K91),0,I91/K91) -> 0 | K91: =SUM(K92:K97) -> 0 | L91: =SUMIF($D92:$D97,$D91,L92:L97) -> 0 | M91: =IF(ISERROR(L91/N91),0,L91/N91) -> 0 | N91: =SUM(N92:N97) -> 0
B92: 営業 | D92: 9 | E92: 0 | F92: =SUMIF(I$3:N$3,$F$3,I92:N92) -> 0 | G92: =IF(ISERROR(F92/H92),0,F92/H92) -> 0 | H92: =SUMIF(I$3:N$3,$H$3,I92:N92) -> 0 | I92: =SUMIF($B$100:$B$114,$B92,I$100:I$114) -> 0 | J92: =IF(ISERROR(I92/K92),0,I92/K92) -> 0 | K92: =SUMIF($B$100:$B$114,$B92,K$100:K$114) -> 0 | L92: =SUMIF($B$100:$B$114,$B92,L$100:L$114) -> 0 | M92: =IF(ISERROR(L92/N92),0,L92/N92) -> 0 | N92: =SUMIF($B$100:$B$114,$B92,N$100:N$114) -> 0
B93: 工事 | D93: 9 | E93: 1 | F93: =SUMIF(I$3:N$3,$F$3,I93:N93) -> 0 | G93: =IF(ISERROR(F93/H93),0,F93/H93) -> 0 | H93: =SUMIF(I$3:N$3,$H$3,I93:N93) -> 0 | I93: =SUMIF($B$100:$B$114,$B93,I$100:I$114) -> 0 | J93: =IF(ISERROR(I93/K93),0,I93/K93) -> 0 | K93: =SUMIF($B$100:$B$114,$B93,K$100:K$114) -> 0 | L93: =SUMIF($B$100:$B$114,$B93,L$100:L$114) -> 0 | M93: =IF(ISERROR(L93/N93),0,L93/N93) -> 0 | N93: =SUMIF($B$100:$B$114,$B93,N$100:N$114) -> 0
B94: コール | D94: 9 | E94: 2 | F94: =SUMIF(I$3:N$3,$F$3,I94:N94) -> 0 | G94: =IF(ISERROR(F94/H94),0,F94/H94) -> 0 | H94: =SUMIF(I$3:N$3,$H$3,I94:N94) -> 0 | I94: =SUMIF($B$100:$B$114,$B94,I$100:I$114) -> 0 | J94: =IF(ISERROR(I94/K94),0,I94/K94) -> 0 | K94: =SUMIF($B$100:$B$114,$B94,K$100:K$114) -> 0 | L94: =SUMIF($B$100:$B$114,$B94,L$100:L$114) -> 0 | M94: =IF(ISERROR(L94/N94),0,L94/N94) -> 0 | N94: =SUMIF($B$100:$B$114,$B94,N$100:N$114) -> 0
B95: 店装 | D95: 9 | E95: 3 | F95: =SUMIF(I$3:N$3,$F$3,I95:N95) -> 0 | G95: =IF(ISERROR(F95/H95),0,F95/H95) -> 0 | H95: =SUMIF(I$3:N$3,$H$3,I95:N95) -> 0 | I95: =SUMIF($B$100:$B$114,$B95,I$100:I$114) -> 0 | J95: =IF(ISERROR(I95/K95),0,I95/K95) -> 0 | K95: =SUMIF($B$100:$B$114,$B95,K$100:K$114) -> 0 | L95: =SUMIF($B$100:$B$114,$B95,L$100:L$114) -> 0 | M95: =IF(ISERROR(L95/N95),0,L95/N95) -> 0 | N95: =SUMIF($B$100:$B$114,$B95,N$100:N$114) -> 0
B96: 委託 | D96: 9 | E96: 106 | F96: =SUMIF(I$3:N$3,$F$3,I96:N96) -> 0 | G96: =IF(ISERROR(F96/H96),0,F96/H96) -> 0 | H96: =SUMIF(I$3:N$3,$H$3,I96:N96) -> 0 | I96: =SUMIF($B$100:$B$114,$B96,I$100:I$114) -> 0 | J96: =IF(ISERROR(I96/K96),0,I96/K96) -> 0 | K96: =SUMIF($B$100:$B$114,$B96,K$100:K$114) -> 0 | L96: =SUMIF($B$100:$B$114,$B96,L$100:L$114) -> 0 | M96: =IF(ISERROR(L96/N96),0,L96/N96) -> 0 | N96: =SUMIF($B$100:$B$114,$B96,N$100:N$114) -> 0
B97: クレーム | D97: 9 | E97: 4 | F97: =SUMIF(I$3:N$3,$F$3,I97:N97) -> 0 | G97: =IF(ISERROR(F97/H97),0,F97/H97) -> 0 | H97: =SUMIF(I$3:N$3,$H$3,I97:N97) -> 0 | I97: =SUMIF($B$100:$B$114,$B97,I$100:I$114) -> 0 | J97: =IF(ISERROR(I97/K97),0,I97/K97) -> 0 | K97: =SUMIF($B$100:$B$114,$B97,K$100:K$114) -> 0 | L97: =SUMIF($B$100:$B$114,$B97,L$100:L$114) -> 0 | M97: =IF(ISERROR(L97/N97),0,L97/N97) -> 0 | N97: =SUMIF($B$100:$B$114,$B97,N$100:N$114) -> 0
B98: 在庫 | E98: 20 | F98: =SUMIF(I$3:N$3,$F$3,I98:N98) -> 0 | G98: ⇔ | H98: =SUMIF(I$3:N$3,$H$3,I98:N98) -> 0 | I98: =SUMIF($B$100:$B$114,$B98,I$100:I$114) -> 0 | J98: ⇔ | K98: =SUMIF($B$100:$B$114,$B98,K$100:K$114) -> 0 | L98: =SUMIF($B$100:$B$114,$B98,L$100:L$114) -> 0 | M98: ⇔ | N98: =SUMIF($B$100:$B$114,$B98,N$100:N$114) -> 0
A99: Amazon | B99: 原/売 | C99: 0 | D99: 1041 | F99: =SUMIF(I$3:N$3,$F$3,I99:N99) -> 0 | G99: =IF(ISERROR(F99/H99),0,F99/H99) -> 0 | H99: =SUMIF(I$3:N$3,$H$3,I99:N99) -> 0 | I99: =SUMIF($D100:$D105,$D99,I100:I105) -> 0 | J99: =IF(ISERROR(I99/K99),0,I99/K99) -> 0 | K99: =SUM(K100:K105) -> 0 | L99: =SUMIF($D100:$D105,$D99,L100:L105) -> 0 | M99: =IF(ISERROR(L99/N99),0,L99/N99) -> 0 | N99: =SUM(N100:N105) -> 0
B100: 営業 | C100: 0 | D100: 1041 | E100: 0 | F100: =SUMIF(I$3:N$3,$F$3,I100:N100) -> 0 | G100: =IF(ISERROR(F100/H100),0,F100/H100) -> 0 | H100: =SUMIF(I$3:N$3,$H$3,I100:N100) -> 0 | I100: =IFERROR(INDEX(別紙_テンプレート_DB!$G$3:$G$65423,MATCH($C100&"-"&$D100&"-"&I$2&"-"&$E100,INDEX(別紙_テンプレート_DB!$A$3:$A$65423&"-"&別紙_テンプレート_DB!$C$3:$C$65423&"-"&別紙_テンプレート_DB!$D$3:$D$65423&"-"&別紙_テンプレート_DB!$E$3:$E$65423,),0)),0) -> 0 | J100: =IF(ISERROR(I100/K100),0,I100/K100) -> 0 | K100: =IFERROR(INDEX(別紙_テンプレート_DB!$F$3:$F$65423,MATCH($C100&"-"&$D100&"-"&I$2&"-"&$E100,INDEX(別紙_テンプレート_DB!$A$3:$A$65423&"-"&別紙_テンプレート_DB!$C$3:$C$65423&"-"&別紙_テンプレート_DB!$D$3:$D$65423&"-"&別紙_テンプレート_DB!$E$3:$E$65423,),0)),0) -> 0 | L100: =IFERROR(INDEX(別紙_テンプレート_DB!$G$3:$G$65423,MATCH($C100&"-"&$D100&"-"&L$2&"-"&$E100,INDEX(別紙_テンプレート_DB!$A$3:$A$65423&"-"&別紙_テンプレート_DB!$C$3:$C$65423&"-"&別紙_テンプレート_DB!$D$3:$D$65423&"-"&別紙_テンプレート_DB!$E$3:$E$65423,),0)),0) -> 0 | M100: =IF(ISERROR(L100/N100),0,L100/N100) -> 0 | N100: =IFERROR(INDEX(別紙_テンプレート_DB!$F$3:$F$65423,MATCH($C100&"-"&$D100&"-"&L$2&"-"&$E100,INDEX(別紙_テンプレート_DB!$A$3:$A$65423&"-"&別紙_テンプレート_DB!$C$3:$C$65423&"-"&別紙_テンプレート_DB!$D$3:$D$65423&"-"&別紙_テンプレート_DB!$E$3:$E$65423,),0)),0) -> 0
...

Sheet 別紙_印刷レイアウト

Sheet 別紙_テンプレート_工事
A1: 工事チーム統計
A2: 項目 | F2: =IF(MONTH(I2)<4,YEAR(I2)-1&"年度",YEAR(I2)&"年度") -> 2022年度 | I2: 44773 | L2: 44772
F3: 原価 | H3: 売上 | I3: 原価 | K3: 売上 | L3: 原価 | N3: 売上
A4: 売上総利益 | D4: 0 | F4: =SUMIF(I$3:N$3,$F$3,I4:N4) -> 0 | G4: =IF(ISERROR(F4/H4),0,F4/H4) -> 0 | H4: =SUMIF(I$3:N$3,$H$3,I4:N4) -> 0 | I4: =SUMIF($D6:$D12,$D4,I6:I12) -> 0 | J4: =IF(ISERROR(I4/K4),0,I4/K4) -> 0 | K4: =SUM(K6:K12) -> 0 | L4: =SUMIF($D6:$D12,$D4,L6:L12) -> 0 | M4: =IF(ISERROR(L4/N4),0,L4/N4) -> 0 | N4: =SUM(N6:N12) -> 0
A5: 粗利益 | F5: =SUMIF(I$3:N$3,$F$3,I5:N5) -> 0 | G5: =IF(ISERROR(F5/H4),0,F5/H4) -> 0 | I5: =K4-I4-(I7) -> 0 | J5: =IF(ISERROR(I5/K4),0,I5/K4) -> 0 | L5: =N4-L4-(L7) -> 0 | M5: =IF(ISERROR(L5/N4),0,L5/N4) -> 0
A6: 科目計 | B6: 営業 | D6: 0 | E6: 0 | F6: =SUMIF(I$3:N$3,$F$3,I6:N6) -> 0 | G6: =IF(ISERROR(F6/H6),0,F6/H6) -> 0 | H6: =SUMIF(I$3:N$3,$H$3,I6:N6) -> 0 | I6: =SUMIF($B$13:$B$75,$B6,I$13:I$75) -> 0 | J6: =IF(ISERROR(I6/K6),0,I6/K6) -> 0 | K6: =SUMIF($B$13:$B$75,$B6,K$13:K$75) -> 0 | L6: =SUMIF($B$13:$B$75,$B6,L$13:L$75) -> 0 | M6: =IF(ISERROR(L6/N6),0,L6/N6) -> 0 | N6: =SUMIF($B$13:$B$75,$B6,N$13:N$75) -> 0
B7: 営業経費 | I7: =SUMIF($B$13:$B$75,$B7,I$13:I$75) -> 0 | L7: =SUMIF($B$13:$B$75,$B7,L$13:L$75) -> 0
B8: 工事 | D8: 0 | E8: 1 | F8: =SUMIF(I$3:N$3,$F$3,I8:N8) -> 0 | G8: =IF(ISERROR(F8/H8),0,F8/H8) -> 0 | H8: =SUMIF(I$3:N$3,$H$3,I8:N8) -> 0 | I8: =SUMIF($B$13:$B$75,$B8,I$13:I$75) -> 0 | J8: =IF(ISERROR(I8/K8),0,I8/K8) -> 0 | K8: =SUMIF($B$13:$B$75,$B8,K$13:K$75) -> 0 | L8: =SUMIF($B$13:$B$75,$B8,L$13:L$75) -> 0 | M8: =IF(ISERROR(L8/N8),0,L8/N8) -> 0 | N8: =SUMIF($B$13:$B$75,$B8,N$13:N$75) -> 0
B9: コール | D9: 0 | E9: 2 | F9: =SUMIF(I$3:N$3,$F$3,I9:N9) -> 0 | G9: =IF(ISERROR(F9/H9),0,F9/H9) -> 0 | H9: =SUMIF(I$3:N$3,$H$3,I9:N9) -> 0 | I9: =SUMIF($B$13:$B$75,$B9,I$13:I$75) -> 0 | J9: =IF(ISERROR(I9/K9),0,I9/K9) -> 0 | K9: =SUMIF($B$13:$B$75,$B9,K$13:K$75) -> 0 | L9: =SUMIF($B$13:$B$75,$B9,L$13:L$75) -> 0 | M9: =IF(ISERROR(L9/N9),0,L9/N9) -> 0 | N9: =SUMIF($B$13:$B$75,$B9,N$13:N$75) -> 0
B10: 内装 | D10: 0 | E10: 3 | F10: =SUMIF(I$3:N$3,$F$3,I10:N10) -> 0 | G10: =IF(ISERROR(F10/H10),0,F10/H10) -> 0 | H10: =SUMIF(I$3:N$3,$H$3,I10:N10) -> 0 | I10: =SUMIF($B$13:$B$75,$B10,I$13:I$75) -> 0 | J10: =IF(ISERROR(I10/K10),0,I10/K10) -> 0 | K10: =SUMIF($B$13:$B$75,$B10,K$13:K$75) -> 0 | L10: =SUMIF($B$13:$B$75,$B10,L$13:L$75) -> 0 | M10: =IF(ISERROR(L10/N10),0,L10/N10) -> 0 | N10: =SUMIF($B$13:$B$75,$B10,N$13:N$75) -> 0
B11: 委託 | D11: 0 | E11: 106 | F11: =SUMIF(I$3:N$3,$F$3,I11:N11) -> 0 | G11: =IF(ISERROR(F11/H11),0,F11/H11) -> 0 | H11: =SUMIF(I$3:N$3,$H$3,I11:N11) -> 0 | I11: =SUMIF($B$13:$B$75,$B11,I$13:I$75) -> 0 | J11: =IF(ISERROR(I11/K11),0,I11/K11) -> 0 | K11: =SUMIF($B$13:$B$75,$B11,K$13:K$75) -> 0 | L11: =SUMIF($B$13:$B$75,$B11,L$13:L$75) -> 0 | M11: =IF(ISERROR(L11/N11),0,L11/N11) -> 0 | N11: =SUMIF($B$13:$B$75,$B11,N$13:N$75) -> 0
B12: クレーム | D12: 0 | E12: 4 | F12: =SUMIF(I$3:N$3,$F$3,I12:N12) -> 0 | G12: =IF(ISERROR(F12/H12),0,F12/H12) -> 0 | H12: =SUMIF(I$3:N$3,$H$3,I12:N12) -> 0 | I12: =SUMIF($B$13:$B$75,$B12,I$13:I$75) -> 0 | J12: =IF(ISERROR(I12/K12),0,I12/K12) -> 0 | K12: =SUMIF($B$13:$B$75,$B12,K$13:K$75) -> 0 | L12: =SUMIF($B$13:$B$75,$B12,L$13:L$75) -> 0 | M12: =IF(ISERROR(L12/N12),0,L12/N12) -> 0 | N12: =SUMIF($B$13:$B$75,$B12,N$13:N$75) -> 0
A13: 原価 ／ 売価 | C13: 工事担当 | D13: 119 | F13: =SUMIF(I$3:N$3,$F$3,I13:N13) -> 0 | G13: =IF(ISERROR(F13/H13),0,F13/H13) -> 0 | H13: =SUMIF(I$3:N$3,$H$3,I13:N13) -> 0 | I13: =SUMIF($D15:$D21,$D13,I15:I21) -> 0 | J13: =IF(ISERROR(I13/K13),0,I13/K13) -> 0 | K13: =SUM(K15:K21) -> 0 | L13: =SUMIF($D15:$D21,$D13,L15:L21) -> 0 | M13: =IF(ISERROR(L13/N13),0,L13/N13) -> 0 | N13: =SUM(N15:N21) -> 0
A14: 粗利益 | F14: =SUMIF(I$3:N$3,$F$3,I14:N14) -> 0 | I14: =K13-I13-(I16) -> 0 | L14: =N13-L13-(L16) -> 0
A15: 高橋 | B15: 営業 | D15: 119 | E15: 0 | F15: =SUMIF(I$3:N$3,$F$3,I15:N15) -> 0 | G15: =IF(ISERROR(F15/H15),0,F15/H15) -> 0 | H15: =SUMIF(I$3:N$3,$H$3,I15:N15) -> 0 | I15: =IFERROR(INDEX(別紙_テンプレート_DB!$P$3:$P$65423,MATCH($D15&"-"&I$2&"-"&$E15,INDEX(別紙_テンプレート_DB!$J$3:$J$65423&"-"&別紙_テンプレート_DB!$M$3:$M$65423&"-"&別紙_テンプレート_DB!$N$3:$N$65423,),0)),0) -> 0 | J15: =IF(ISERROR(I15/K15),0,I15/K15) -> 0 | K15: =IFERROR(INDEX(別紙_テンプレート_DB!$O$3:$O$65423,MATCH($D15&"-"&I$2&"-"&$E15,INDEX(別紙_テンプレート_DB!$J$3:$J$65423&"-"&別紙_テンプレート_DB!$M$3:$M$65423&"-"&別紙_テンプレート_DB!$N$3:$N$65423,),0)),0) -> 0 | L15: =IFERROR(INDEX(別紙_テンプレート_DB!$P$3:$P$65423,MATCH($D15&"-"&L$2&"-"&$E15,INDEX(別紙_テンプレート_DB!$J$3:$J$65423&"-"&別紙_テンプレート_DB!$M$3:$M$65423&"-"&別紙_テンプレート_DB!$N$3:$N$65423,),0)),0) -> 0 | M15: =IF(ISERROR(L15/N15),0,L15/N15) -> 0 | N15: =IFERROR(INDEX(別紙_テンプレート_DB!$O$3:$O$65423,MATCH($D15&"-"&L$2&"-"&$E15,INDEX(別紙_テンプレート_DB!$J$3:$J$65423&"-"&別紙_テンプレート_DB!$M$3:$M$65423&"-"&別紙_テンプレート_DB!$N$3:$N$65423,),0)),0) -> 0
B16: 営業経費 | I16: =IFERROR(INDEX(別紙_テンプレート_DB!$DP$3:$DP$65423,MATCH($C16&"-"&I$2,INDEX(別紙_テンプレート_DB!$DM$3:$DM$65423&"-"&別紙_テンプレート_DB!$DN$3:$DN$65423,),0)),0) -> 0 | L16: =IFERROR(INDEX(別紙_テンプレート_DB!$DP$3:$DP$65423,MATCH($C16&"-"&L$2,INDEX(別紙_テンプレート_DB!$DM$3:$DM$65423&"-"&別紙_テンプレート_DB!$DN$3:$DN$65423,),0)),0) -> 0
B17: 工事 | D17: 119 | E17: 1 | F17: =SUMIF(I$3:N$3,$F$3,I17:N17) -> 0 | G17: =IF(ISERROR(F17/H17),0,F17/H17) -> 0 | H17: =SUMIF(I$3:N$3,$H$3,I17:N17) -> 0 | I17: =IFERROR(INDEX(別紙_テンプレート_DB!$P$3:$P$65423,MATCH($D17&"-"&I$2&"-"&$E17,INDEX(別紙_テンプレート_DB!$J$3:$J$65423&"-"&別紙_テンプレート_DB!$M$3:$M$65423&"-"&別紙_テンプレート_DB!$N$3:$N$65423,),0)),0) -> 0 | J17: =IF(ISERROR(I17/K17),0,I17/K17) -> 0 | K17: =IFERROR(INDEX(別紙_テンプレート_DB!$O$3:$O$65423,MATCH($D17&"-"&I$2&"-"&$E17,INDEX(別紙_テンプレート_DB!$J$3:$J$65423&"-"&別紙_テンプレート_DB!$M$3:$M$65423&"-"&別紙_テンプレート_DB!$N$3:$N$65423,),0)),0) -> 0 | L17: =IFERROR(INDEX(別紙_テンプレート_DB!$P$3:$P$65423,MATCH($D17&"-"&L$2&"-"&$E17,INDEX(別紙_テンプレート_DB!$J$3:$J$65423&"-"&別紙_テンプレート_DB!$M$3:$M$65423&"-"&別紙_テンプレート_DB!$N$3:$N$65423,),0)),0) -> 0 | M17: =IF(ISERROR(L17/N17),0,L17/N17) -> 0 | N17: =IFERROR(INDEX(別紙_テンプレート_DB!$O$3:$O$65423,MATCH($D17&"-"&L$2&"-"&$E17,INDEX(別紙_テンプレート_DB!$J$3:$J$65423&"-"&別紙_テンプレート_DB!$M$3:$M$65423&"-"&別紙_テンプレート_DB!$N$3:$N$65423,),0)),0) -> 0
B18: コール | D18: 119 | E18: 2 | F18: =SUMIF(I$3:N$3,$F$3,I18:N18) -> 0 | G18: =IF(ISERROR(F18/H18),0,F18/H18) -> 0 | H18: =SUMIF(I$3:N$3,$H$3,I18:N18) -> 0 | I18: =IFERROR(INDEX(別紙_テンプレート_DB!$P$3:$P$65423,MATCH($D18&"-"&I$2&"-"&$E18,INDEX(別紙_テンプレート_DB!$J$3:$J$65423&"-"&別紙_テンプレート_DB!$M$3:$M$65423&"-"&別紙_テンプレート_DB!$N$3:$N$65423,),0)),0) -> 0 | J18: =IF(ISERROR(I18/K18),0,I18/K18) -> 0 | K18: =IFERROR(INDEX(別紙_テンプレート_DB!$O$3:$O$65423,MATCH($D18&"-"&I$2&"-"&$E18,INDEX(別紙_テンプレート_DB!$J$3:$J$65423&"-"&別紙_テンプレート_DB!$M$3:$M$65423&"-"&別紙_テンプレート_DB!$N$3:$N$65423,),0)),0) -> 0 | L18: =IFERROR(INDEX(別紙_テンプレート_DB!$P$3:$P$65423,MATCH($D18&"-"&L$2&"-"&$E18,INDEX(別紙_テンプレート_DB!$J$3:$J$65423&"-"&別紙_テンプレート_DB!$M$3:$M$65423&"-"&別紙_テンプレート_DB!$N$3:$N$65423,),0)),0) -> 0 | M18: =IF(ISERROR(L18/N18),0,L18/N18) -> 0 | N18: =IFERROR(INDEX(別紙_テンプレート_DB!$O$3:$O$65423,MATCH($D18&"-"&L$2&"-"&$E18,INDEX(別紙_テンプレート_DB!$J$3:$J$65423&"-"&別紙_テンプレート_DB!$M$3:$M$65423&"-"&別紙_テンプレート_DB!$N$3:$N$65423,),0)),0) -> 0
B19: 内装 | D19: 119 | E19: 3 | F19: =SUMIF(I$3:N$3,$F$3,I19:N19) -> 0 | G19: =IF(ISERROR(F19/H19),0,F19/H19) -> 0 | H19: =SUMIF(I$3:N$3,$H$3,I19:N19) -> 0 | I19: =IFERROR(INDEX(別紙_テンプレート_DB!$P$3:$P$65423,MATCH($D19&"-"&I$2&"-"&$E19,INDEX(別紙_テンプレート_DB!$J$3:$J$65423&"-"&別紙_テンプレート_DB!$M$3:$M$65423&"-"&別紙_テンプレート_DB!$N$3:$N$65423,),0)),0) -> 0 | J19: =IF(ISERROR(I19/K19),0,I19/K19) -> 0 | K19: =IFERROR(INDEX(別紙_テンプレート_DB!$O$3:$O$65423,MATCH($D19&"-"&I$2&"-"&$E19,INDEX(別紙_テンプレート_DB!$J$3:$J$65423&"-"&別紙_テンプレート_DB!$M$3:$M$65423&"-"&別紙_テンプレート_DB!$N$3:$N$65423,),0)),0) -> 0 | L19: =IFERROR(INDEX(別紙_テンプレート_DB!$P$3:$P$65423,MATCH($D19&"-"&L$2&"-"&$E19,INDEX(別紙_テンプレート_DB!$J$3:$J$65423&"-"&別紙_テンプレート_DB!$M$3:$M$65423&"-"&別紙_テンプレート_DB!$N$3:$N$65423,),0)),0) -> 0 | M19: =IF(ISERROR(L19/N19),0,L19/N19) -> 0 | N19: =IFERROR(INDEX(別紙_テンプレート_DB!$O$3:$O$65423,MATCH($D19&"-"&L$2&"-"&$E19,INDEX(別紙_テンプレート_DB!$J$3:$J$65423&"-"&別紙_テンプレート_DB!$M$3:$M$65423&"-"&別紙_テンプレート_DB!$N$3:$N$65423,),0)),0) -> 0
B20: 委託 | D20: 119 | E20: 106 | F20: =SUMIF(I$3:N$3,$F$3,I20:N20) -> 0 | G20: =IF(ISERROR(F20/H20),0,F20/H20) -> 0 | H20: =SUMIF(I$3:N$3,$H$3,I20:N20) -> 0 | I20: =IFERROR(INDEX(別紙_テンプレート_DB!$P$3:$P$65423,MATCH($D20&"-"&I$2&"-"&$E20,INDEX(別紙_テンプレート_DB!$J$3:$J$65423&"-"&別紙_テンプレート_DB!$M$3:$M$65423&"-"&別紙_テンプレート_DB!$N$3:$N$65423,),0)),0) -> 0 | J20: =IF(ISERROR(I20/K20),0,I20/K20) -> 0 | K20: =IFERROR(INDEX(別紙_テンプレート_DB!$O$3:$O$65423,MATCH($D20&"-"&I$2&"-"&$E20,INDEX(別紙_テンプレート_DB!$J$3:$J$65423&"-"&別紙_テンプレート_DB!$M$3:$M$65423&"-"&別紙_テンプレート_DB!$N$3:$N$65423,),0)),0) -> 0 | L20: =IFERROR(INDEX(別紙_テンプレート_DB!$P$3:$P$65423,MATCH($D20&"-"&L$2&"-"&$E20,INDEX(別紙_テンプレート_DB!$J$3:$J$65423&"-"&別紙_テンプレート_DB!$M$3:$M$65423&"-"&別紙_テンプレート_DB!$N$3:$N$65423,),0)),0) -> 0 | M20: =IF(ISERROR(L20/N20),0,L20/N20) -> 0 | N20: =IFERROR(INDEX(別紙_テンプレート_DB!$O$3:$O$65423,MATCH($D20&"-"&L$2&"-"&$E20,INDEX(別紙_テンプレート_DB!$J$3:$J$65423&"-"&別紙_テンプレート_DB!$M$3:$M$65423&"-"&別紙_テンプレート_DB!$N$3:$N$65423,),0)),0) -> 0
B21: クレーム | D21: 119 | E21: 4 | F21: =SUMIF(I$3:N$3,$F$3,I21:N21) -> 0 | I21: =IFERROR(INDEX(別紙_テンプレート_DB!$P$3:$P$65423,MATCH($D21&"-"&I$2&"-"&$E21,INDEX(別紙_テンプレート_DB!$J$3:$J$65423&"-"&別紙_テンプレート_DB!$M$3:$M$65423&"-"&別紙_テンプレート_DB!$N$3:$N$65423,),0)),0) -> 0 | L21: =IFERROR(INDEX(別紙_テンプレート_DB!$P$3:$P$65423,MATCH($D21&"-"&L$2&"-"&$E21,INDEX(別紙_テンプレート_DB!$J$3:$J$65423&"-"&別紙_テンプレート_DB!$M$3:$M$65423&"-"&別紙_テンプレート_DB!$N$3:$N$65423,),0)),0) -> 0
A22: 原価 ／ 売価 | C22: 工事担当 | D22: 120 | F22: =SUMIF(I$3:N$3,$F$3,I22:N22) -> 0 | G22: =IF(ISERROR(F22/H22),0,F22/H22) -> 0 | H22: =SUMIF(I$3:N$3,$H$3,I22:N22) -> 0 | I22: =SUMIF($D24:$D30,$D22,I24:I30) -> 0 | J22: =IF(ISERROR(I22/K22),0,I22/K22) -> 0 | K22: =SUM(K24:K30) -> 0 | L22: =SUMIF($D24:$D30,$D22,L24:L30) -> 0 | M22: =IF(ISERROR(L22/N22),0,L22/N22) -> 0 | N22: =SUM(N24:N30) -> 0
A23: 粗利益 | F23: =SUMIF(I$3:N$3,$F$3,I23:N23) -> 0 | I23: =K22-I22-(I25) -> 0 | L23: =N22-L22-(L25) -> 0
A24: 小林 | B24: 営業 | D24: 120 | E24: 0 | F24: =SUMIF(I$3:N$3,$F$3,I24:N24) -> 0 | G24: =IF(ISERROR(F24/H24),0,F24/H24) -> 0 | H24: =SUMIF(I$3:N$3,$H$3,I24:N24) -> 0 | I24: =IFERROR(INDEX(別紙_テンプレート_DB!$P$3:$P$65423,MATCH($D24&"-"&I$2&"-"&$E24,INDEX(別紙_テンプレート_DB!$J$3:$J$65423&"-"&別紙_テンプレート_DB!$M$3:$M$65423&"-"&別紙_テンプレート_DB!$N$3:$N$65423,),0)),0) -> 0 | J24: =IF(ISERROR(I24/K24),0,I24/K24) -> 0 | K24: =IFERROR(INDEX(別紙_テンプレート_DB!$O$3:$O$65423,MATCH($D24&"-"&I$2&"-"&$E24,INDEX(別紙_テンプレート_DB!$J$3:$J$65423&"-"&別紙_テンプレート_DB!$M$3:$M$65423&"-"&別紙_テンプレート_DB!$N$3:$N$65423,),0)),0) -> 0 | L24: =IFERROR(INDEX(別紙_テンプレート_DB!$P$3:$P$65423,MATCH($D24&"-"&L$2&"-"&$E24,INDEX(別紙_テンプレート_DB!$J$3:$J$65423&"-"&別紙_テンプレート_DB!$M$3:$M$65423&"-"&別紙_テンプレート_DB!$N$3:$N$65423,),0)),0) -> 0 | M24: =IF(ISERROR(L24/N24),0,L24/N24) -> 0 | N24: =IFERROR(INDEX(別紙_テンプレート_DB!$O$3:$O$65423,MATCH($D24&"-"&L$2&"-"&$E24,INDEX(別紙_テンプレート_DB!$J$3:$J$65423&"-"&別紙_テンプレート_DB!$M$3:$M$65423&"-"&別紙_テンプレート_DB!$N$3:$N$65423,),0)),0) -> 0
B25: 営業経費 | I25: =IFERROR(INDEX(別紙_テンプレート_DB!$DP$3:$DP$65423,MATCH($C25&"-"&I$2,INDEX(別紙_テンプレート_DB!$DM$3:$DM$65423&"-"&別紙_テンプレート_DB!$DN$3:$DN$65423,),0)),0) -> 0 | L25: =IFERROR(INDEX(別紙_テンプレート_DB!$DP$3:$DP$65423,MATCH($C25&"-"&L$2,INDEX(別紙_テンプレート_DB!$DM$3:$DM$65423&"-"&別紙_テンプレート_DB!$DN$3:$DN$65423,),0)),0) -> 0
B26: 工事 | D26: 120 | E26: 1 | F26: =SUMIF(I$3:N$3,$F$3,I26:N26) -> 0 | G26: =IF(ISERROR(F26/H26),0,F26/H26) -> 0 | H26: =SUMIF(I$3:N$3,$H$3,I26:N26) -> 0 | I26: =IFERROR(INDEX(別紙_テンプレート_DB!$P$3:$P$65423,MATCH($D26&"-"&I$2&"-"&$E26,INDEX(別紙_テンプレート_DB!$J$3:$J$65423&"-"&別紙_テンプレート_DB!$M$3:$M$65423&"-"&別紙_テンプレート_DB!$N$3:$N$65423,),0)),0) -> 0 | J26: =IF(ISERROR(I26/K26),0,I26/K26) -> 0 | K26: =IFERROR(INDEX(別紙_テンプレート_DB!$O$3:$O$65423,MATCH($D26&"-"&I$2&"-"&$E26,INDEX(別紙_テンプレート_DB!$J$3:$J$65423&"-"&別紙_テンプレート_DB!$M$3:$M$65423&"-"&別紙_テンプレート_DB!$N$3:$N$65423,),0)),0) -> 0 | L26: =IFERROR(INDEX(別紙_テンプレート_DB!$P$3:$P$65423,MATCH($D26&"-"&L$2&"-"&$E26,INDEX(別紙_テンプレート_DB!$J$3:$J$65423&"-"&別紙_テンプレート_DB!$M$3:$M$65423&"-"&別紙_テンプレート_DB!$N$3:$N$65423,),0)),0) -> 0 | M26: =IF(ISERROR(L26/N26),0,L26/N26) -> 0 | N26: =IFERROR(INDEX(別紙_テンプレート_DB!$O$3:$O$65423,MATCH($D26&"-"&L$2&"-"&$E26,INDEX(別紙_テンプレート_DB!$J$3:$J$65423&"-"&別紙_テンプレート_DB!$M$3:$M$65423&"-"&別紙_テンプレート_DB!$N$3:$N$65423,),0)),0) -> 0
B27: コール | D27: 120 | E27: 2 | F27: =SUMIF(I$3:N$3,$F$3,I27:N27) -> 0 | G27: =IF(ISERROR(F27/H27),0,F27/H27) -> 0 | H27: =SUMIF(I$3:N$3,$H$3,I27:N27) -> 0 | I27: =IFERROR(INDEX(別紙_テンプレート_DB!$P$3:$P$65423,MATCH($D27&"-"&I$2&"-"&$E27,INDEX(別紙_テンプレート_DB!$J$3:$J$65423&"-"&別紙_テンプレート_DB!$M$3:$M$65423&"-"&別紙_テンプレート_DB!$N$3:$N$65423,),0)),0) -> 0 | J27: =IF(ISERROR(I27/K27),0,I27/K27) -> 0 | K27: =IFERROR(INDEX(別紙_テンプレート_DB!$O$3:$O$65423,MATCH($D27&"-"&I$2&"-"&$E27,INDEX(別紙_テンプレート_DB!$J$3:$J$65423&"-"&別紙_テンプレート_DB!$M$3:$M$65423&"-"&別紙_テンプレート_DB!$N$3:$N$65423,),0)),0) -> 0 | L27: =IFERROR(INDEX(別紙_テンプレート_DB!$P$3:$P$65423,MATCH($D27&"-"&L$2&"-"&$E27,INDEX(別紙_テンプレート_DB!$J$3:$J$65423&"-"&別紙_テンプレート_DB!$M$3:$M$65423&"-"&別紙_テンプレート_DB!$N$3:$N$65423,),0)),0) -> 0 | M27: =IF(ISERROR(L27/N27),0,L27/N27) -> 0 | N27: =IFERROR(INDEX(別紙_テンプレート_DB!$O$3:$O$65423,MATCH($D27&"-"&L$2&"-"&$E27,INDEX(別紙_テンプレート_DB!$J$3:$J$65423&"-"&別紙_テンプレート_DB!$M$3:$M$65423&"-"&別紙_テンプレート_DB!$N$3:$N$65423,),0)),0) -> 0
B28: 内装 | D28: 120 | E28: 3 | F28: =SUMIF(I$3:N$3,$F$3,I28:N28) -> 0 | G28: =IF(ISERROR(F28/H28),0,F28/H28) -> 0 | H28: =SUMIF(I$3:N$3,$H$3,I28:N28) -> 0 | I28: =IFERROR(INDEX(別紙_テンプレート_DB!$P$3:$P$65423,MATCH($D28&"-"&I$2&"-"&$E28,INDEX(別紙_テンプレート_DB!$J$3:$J$65423&"-"&別紙_テンプレート_DB!$M$3:$M$65423&"-"&別紙_テンプレート_DB!$N$3:$N$65423,),0)),0) -> 0 | J28: =IF(ISERROR(I28/K28),0,I28/K28) -> 0 | K28: =IFERROR(INDEX(別紙_テンプレート_DB!$O$3:$O$65423,MATCH($D28&"-"&I$2&"-"&$E28,INDEX(別紙_テンプレート_DB!$J$3:$J$65423&"-"&別紙_テンプレート_DB!$M$3:$M$65423&"-"&別紙_テンプレート_DB!$N$3:$N$65423,),0)),0) -> 0 | L28: =IFERROR(INDEX(別紙_テンプレート_DB!$P$3:$P$65423,MATCH($D28&"-"&L$2&"-"&$E28,INDEX(別紙_テンプレート_DB!$J$3:$J$65423&"-"&別紙_テンプレート_DB!$M$3:$M$65423&"-"&別紙_テンプレート_DB!$N$3:$N$65423,),0)),0) -> 0 | M28: =IF(ISERROR(L28/N28),0,L28/N28) -> 0 | N28: =IFERROR(INDEX(別紙_テンプレート_DB!$O$3:$O$65423,MATCH($D28&"-"&L$2&"-"&$E28,INDEX(別紙_テンプレート_DB!$J$3:$J$65423&"-"&別紙_テンプレート_DB!$M$3:$M$65423&"-"&別紙_テンプレート_DB!$N$3:$N$65423,),0)),0) -> 0
B29: 委託 | D29: 120 | E29: 106 | F29: =SUMIF(I$3:N$3,$F$3,I29:N29) -> 0 | G29: =IF(ISERROR(F29/H29),0,F29/H29) -> 0 | H29: =SUMIF(I$3:N$3,$H$3,I29:N29) -> 0 | I29: =IFERROR(INDEX(別紙_テンプレート_DB!$P$3:$P$65423,MATCH($D29&"-"&I$2&"-"&$E29,INDEX(別紙_テンプレート_DB!$J$3:$J$65423&"-"&別紙_テンプレート_DB!$M$3:$M$65423&"-"&別紙_テンプレート_DB!$N$3:$N$65423,),0)),0) -> 0 | J29: =IF(ISERROR(I29/K29),0,I29/K29) -> 0 | K29: =IFERROR(INDEX(別紙_テンプレート_DB!$O$3:$O$65423,MATCH($D29&"-"&I$2&"-"&$E29,INDEX(別紙_テンプレート_DB!$J$3:$J$65423&"-"&別紙_テンプレート_DB!$M$3:$M$65423&"-"&別紙_テンプレート_DB!$N$3:$N$65423,),0)),0) -> 0 | L29: =IFERROR(INDEX(別紙_テンプレート_DB!$P$3:$P$65423,MATCH($D29&"-"&L$2&"-"&$E29,INDEX(別紙_テンプレート_DB!$J$3:$J$65423&"-"&別紙_テンプレート_DB!$M$3:$M$65423&"-"&別紙_テンプレート_DB!$N$3:$N$65423,),0)),0) -> 0 | M29: =IF(ISERROR(L29/N29),0,L29/N29) -> 0 | N29: =IFERROR(INDEX(別紙_テンプレート_DB!$O$3:$O$65423,MATCH($D29&"-"&L$2&"-"&$E29,INDEX(別紙_テンプレート_DB!$J$3:$J$65423&"-"&別紙_テンプレート_DB!$M$3:$M$65423&"-"&別紙_テンプレート_DB!$N$3:$N$65423,),0)),0) -> 0
B30: クレーム | D30: 120 | E30: 4 | F30: =SUMIF(I$3:N$3,$F$3,I30:N30) -> 0 | I30: =IFERROR(INDEX(別紙_テンプレート_DB!$P$3:$P$65423,MATCH($D30&"-"&I$2&"-"&$E30,INDEX(別紙_テンプレート_DB!$J$3:$J$65423&"-"&別紙_テンプレート_DB!$M$3:$M$65423&"-"&別紙_テンプレート_DB!$N$3:$N$65423,),0)),0) -> 0 | L30: =IFERROR(INDEX(別紙_テンプレート_DB!$P$3:$P$65423,MATCH($D30&"-"&L$2&"-"&$E30,INDEX(別紙_テンプレート_DB!$J$3:$J$65423&"-"&別紙_テンプレート_DB!$M$3:$M$65423&"-"&別紙_テンプレート_DB!$N$3:$N$65423,),0)),0) -> 0
A31: 原価 ／ 売価 | C31: 工事担当 | D31: 101 | F31: =SUMIF(I$3:N$3,$F$3,I31:N31) -> 0 | G31: =IF(ISERROR(F31/H31),0,F31/H31) -> 0 | H31: =SUMIF(I$3:N$3,$H$3,I31:N31) -> 0 | I31: =SUMIF($D33:$D39,$D31,I33:I39) -> 0 | J31: =IF(ISERROR(I31/K31),0,I31/K31) -> 0 | K31: =SUM(K33:K39) -> 0 | L31: =SUMIF($D33:$D39,$D31,L33:L39) -> 0 | M31: =IF(ISERROR(L31/N31),0,L31/N31) -> 0 | N31: =SUM(N33:N39) -> 0
A32: 粗利益 | F32: =SUMIF(I$3:N$3,$F$3,I32:N32) -> 0 | I32: =K31-I31-(I34) -> 0 | L32: =N31-L31-(L34) -> 0
A33: 森田 | B33: 営業 | D33: 101 | E33: 0 | F33: =SUMIF(I$3:N$3,$F$3,I33:N33) -> 0 | G33: =IF(ISERROR(F33/H33),0,F33/H33) -> 0 | H33: =SUMIF(I$3:N$3,$H$3,I33:N33) -> 0 | I33: =IFERROR(INDEX(別紙_テンプレート_DB!$P$3:$P$65423,MATCH($D33&"-"&I$2&"-"&$E33,INDEX(別紙_テンプレート_DB!$J$3:$J$65423&"-"&別紙_テンプレート_DB!$M$3:$M$65423&"-"&別紙_テンプレート_DB!$N$3:$N$65423,),0)),0) -> 0 | J33: =IF(ISERROR(I33/K33),0,I33/K33) -> 0 | K33: =IFERROR(INDEX(別紙_テンプレート_DB!$O$3:$O$65423,MATCH($D33&"-"&I$2&"-"&$E33,INDEX(別紙_テンプレート_DB!$J$3:$J$65423&"-"&別紙_テンプレート_DB!$M$3:$M$65423&"-"&別紙_テンプレート_DB!$N$3:$N$65423,),0)),0) -> 0 | L33: =IFERROR(INDEX(別紙_テンプレート_DB!$P$3:$P$65423,MATCH($D33&"-"&L$2&"-"&$E33,INDEX(別紙_テンプレート_DB!$J$3:$J$65423&"-"&別紙_テンプレート_DB!$M$3:$M$65423&"-"&別紙_テンプレート_DB!$N$3:$N$65423,),0)),0) -> 0 | M33: =IF(ISERROR(L33/N33),0,L33/N33) -> 0 | N33: =IFERROR(INDEX(別紙_テンプレート_DB!$O$3:$O$65423,MATCH($D33&"-"&L$2&"-"&$E33,INDEX(別紙_テンプレート_DB!$J$3:$J$65423&"-"&別紙_テンプレート_DB!$M$3:$M$65423&"-"&別紙_テンプレート_DB!$N$3:$N$65423,),0)),0) -> 0
B34: 営業経費 | I34: =IFERROR(INDEX(別紙_テンプレート_DB!$DP$3:$DP$65423,MATCH($C34&"-"&I$2,INDEX(別紙_テンプレート_DB!$DM$3:$DM$65423&"-"&別紙_テンプレート_DB!$DN$3:$DN$65423,),0)),0) -> 0 | L34: =IFERROR(INDEX(別紙_テンプレート_DB!$DP$3:$DP$65423,MATCH($C34&"-"&L$2,INDEX(別紙_テンプレート_DB!$DM$3:$DM$65423&"-"&別紙_テンプレート_DB!$DN$3:$DN$65423,),0)),0) -> 0
B35: 工事 | D35: 101 | E35: 1 | F35: =SUMIF(I$3:N$3,$F$3,I35:N35) -> 0 | G35: =IF(ISERROR(F35/H35),0,F35/H35) -> 0 | H35: =SUMIF(I$3:N$3,$H$3,I35:N35) -> 0 | I35: =IFERROR(INDEX(別紙_テンプレート_DB!$P$3:$P$65423,MATCH($D35&"-"&I$2&"-"&$E35,INDEX(別紙_テンプレート_DB!$J$3:$J$65423&"-"&別紙_テンプレート_DB!$M$3:$M$65423&"-"&別紙_テンプレート_DB!$N$3:$N$65423,),0)),0) -> 0 | J35: =IF(ISERROR(I35/K35),0,I35/K35) -> 0 | K35: =IFERROR(INDEX(別紙_テンプレート_DB!$O$3:$O$65423,MATCH($D35&"-"&I$2&"-"&$E35,INDEX(別紙_テンプレート_DB!$J$3:$J$65423&"-"&別紙_テンプレート_DB!$M$3:$M$65423&"-"&別紙_テンプレート_DB!$N$3:$N$65423,),0)),0) -> 0 | L35: =IFERROR(INDEX(別紙_テンプレート_DB!$P$3:$P$65423,MATCH($D35&"-"&L$2&"-"&$E35,INDEX(別紙_テンプレート_DB!$J$3:$J$65423&"-"&別紙_テンプレート_DB!$M$3:$M$65423&"-"&別紙_テンプレート_DB!$N$3:$N$65423,),0)),0) -> 0 | M35: =IF(ISERROR(L35/N35),0,L35/N35) -> 0 | N35: =IFERROR(INDEX(別紙_テンプレート_DB!$O$3:$O$65423,MATCH($D35&"-"&L$2&"-"&$E35,INDEX(別紙_テンプレート_DB!$J$3:$J$65423&"-"&別紙_テンプレート_DB!$M$3:$M$65423&"-"&別紙_テンプレート_DB!$N$3:$N$65423,),0)),0) -> 0
B36: コール | D36: 101 | E36: 2 | F36: =SUMIF(I$3:N$3,$F$3,I36:N36) -> 0 | G36: =IF(ISERROR(F36/H36),0,F36/H36) -> 0 | H36: =SUMIF(I$3:N$3,$H$3,I36:N36) -> 0 | I36: =IFERROR(INDEX(別紙_テンプレート_DB!$P$3:$P$65423,MATCH($D36&"-"&I$2&"-"&$E36,INDEX(別紙_テンプレート_DB!$J$3:$J$65423&"-"&別紙_テンプレート_DB!$M$3:$M$65423&"-"&別紙_テンプレート_DB!$N$3:$N$65423,),0)),0) -> 0 | J36: =IF(ISERROR(I36/K36),0,I36/K36) -> 0 | K36: =IFERROR(INDEX(別紙_テンプレート_DB!$O$3:$O$65423,MATCH($D36&"-"&I$2&"-"&$E36,INDEX(別紙_テンプレート_DB!$J$3:$J$65423&"-"&別紙_テンプレート_DB!$M$3:$M$65423&"-"&別紙_テンプレート_DB!$N$3:$N$65423,),0)),0) -> 0 | L36: =IFERROR(INDEX(別紙_テンプレート_DB!$P$3:$P$65423,MATCH($D36&"-"&L$2&"-"&$E36,INDEX(別紙_テンプレート_DB!$J$3:$J$65423&"-"&別紙_テンプレート_DB!$M$3:$M$65423&"-"&別紙_テンプレート_DB!$N$3:$N$65423,),0)),0) -> 0 | M36: =IF(ISERROR(L36/N36),0,L36/N36) -> 0 | N36: =IFERROR(INDEX(別紙_テンプレート_DB!$O$3:$O$65423,MATCH($D36&"-"&L$2&"-"&$E36,INDEX(別紙_テンプレート_DB!$J$3:$J$65423&"-"&別紙_テンプレート_DB!$M$3:$M$65423&"-"&別紙_テンプレート_DB!$N$3:$N$65423,),0)),0) -> 0
B37: 内装 | D37: 101 | E37: 3 | F37: =SUMIF(I$3:N$3,$F$3,I37:N37) -> 0 | G37: =IF(ISERROR(F37/H37),0,F37/H37) -> 0 | H37: =SUMIF(I$3:N$3,$H$3,I37:N37) -> 0 | I37: =IFERROR(INDEX(別紙_テンプレート_DB!$P$3:$P$65423,MATCH($D37&"-"&I$2&"-"&$E37,INDEX(別紙_テンプレート_DB!$J$3:$J$65423&"-"&別紙_テンプレート_DB!$M$3:$M$65423&"-"&別紙_テンプレート_DB!$N$3:$N$65423,),0)),0) -> 0 | J37: =IF(ISERROR(I37/K37),0,I37/K37) -> 0 | K37: =IFERROR(INDEX(別紙_テンプレート_DB!$O$3:$O$65423,MATCH($D37&"-"&I$2&"-"&$E37,INDEX(別紙_テンプレート_DB!$J$3:$J$65423&"-"&別紙_テンプレート_DB!$M$3:$M$65423&"-"&別紙_テンプレート_DB!$N$3:$N$65423,),0)),0) -> 0 | L37: =IFERROR(INDEX(別紙_テンプレート_DB!$P$3:$P$65423,MATCH($D37&"-"&L$2&"-"&$E37,INDEX(別紙_テンプレート_DB!$J$3:$J$65423&"-"&別紙_テンプレート_DB!$M$3:$M$65423&"-"&別紙_テンプレート_DB!$N$3:$N$65423,),0)),0) -> 0 | M37: =IF(ISERROR(L37/N37),0,L37/N37) -> 0 | N37: =IFERROR(INDEX(別紙_テンプレート_DB!$O$3:$O$65423,MATCH($D37&"-"&L$2&"-"&$E37,INDEX(別紙_テンプレート_DB!$J$3:$J$65423&"-"&別紙_テンプレート_DB!$M$3:$M$65423&"-"&別紙_テンプレート_DB!$N$3:$N$65423,),0)),0) -> 0
B38: 委託 | D38: 101 | E38: 106 | F38: =SUMIF(I$3:N$3,$F$3,I38:N38) -> 0 | G38: =IF(ISERROR(F38/H38),0,F38/H38) -> 0 | H38: =SUMIF(I$3:N$3,$H$3,I38:N38) -> 0 | I38: =IFERROR(INDEX(別紙_テンプレート_DB!$P$3:$P$65423,MATCH($D38&"-"&I$2&"-"&$E38,INDEX(別紙_テンプレート_DB!$J$3:$J$65423&"-"&別紙_テンプレート_DB!$M$3:$M$65423&"-"&別紙_テンプレート_DB!$N$3:$N$65423,),0)),0) -> 0 | J38: =IF(ISERROR(I38/K38),0,I38/K38) -> 0 | K38: =IFERROR(INDEX(別紙_テンプレート_DB!$O$3:$O$65423,MATCH($D38&"-"&I$2&"-"&$E38,INDEX(別紙_テンプレート_DB!$J$3:$J$65423&"-"&別紙_テンプレート_DB!$M$3:$M$65423&"-"&別紙_テンプレート_DB!$N$3:$N$65423,),0)),0) -> 0 | L38: =IFERROR(INDEX(別紙_テンプレート_DB!$P$3:$P$65423,MATCH($D38&"-"&L$2&"-"&$E38,INDEX(別紙_テンプレート_DB!$J$3:$J$65423&"-"&別紙_テンプレート_DB!$M$3:$M$65423&"-"&別紙_テンプレート_DB!$N$3:$N$65423,),0)),0) -> 0 | M38: =IF(ISERROR(L38/N38),0,L38/N38) -> 0 | N38: =IFERROR(INDEX(別紙_テンプレート_DB!$O$3:$O$65423,MATCH($D38&"-"&L$2&"-"&$E38,INDEX(別紙_テンプレート_DB!$J$3:$J$65423&"-"&別紙_テンプレート_DB!$M$3:$M$65423&"-"&別紙_テンプレート_DB!$N$3:$N$65423,),0)),0) -> 0
B39: クレーム | D39: 101 | E39: 4 | F39: =SUMIF(I$3:N$3,$F$3,I39:N39) -> 0 | I39: =IFERROR(INDEX(別紙_テンプレート_DB!$P$3:$P$65423,MATCH($D39&"-"&I$2&"-"&$E39,INDEX(別紙_テンプレート_DB!$J$3:$J$65423&"-"&別紙_テンプレート_DB!$M$3:$M$65423&"-"&別紙_テンプレート_DB!$N$3:$N$65423,),0)),0) -> 0 | L39: =IFERROR(INDEX(別紙_テンプレート_DB!$P$3:$P$65423,MATCH($D39&"-"&L$2&"-"&$E39,INDEX(別紙_テンプレート_DB!$J$3:$J$65423&"-"&別紙_テンプレート_DB!$M$3:$M$65423&"-"&別紙_テンプレート_DB!$N$3:$N$65423,),0)),0) -> 0
A40: 原価 ／ 売価 | C40: 工事担当 | D40: 93 | F40: =SUMIF(I$3:N$3,$F$3,I40:N40) -> 0 | G40: =IF(ISERROR(F40/H40),0,F40/H40) -> 0 | H40: =SUMIF(I$3:N$3,$H$3,I40:N40) -> 0 | I40: =SUMIF($D42:$D48,$D40,I42:I48) -> 0 | J40: =IF(ISERROR(I40/K40),0,I40/K40) -> 0 | K40: =SUM(K42:K48) -> 0 | L40: =SUMIF($D42:$D48,$D40,L42:L48) -> 0 | M40: =IF(ISERROR(L40/N40),0,L40/N40) -> 0 | N40: =SUM(N42:N48) -> 0
A41: 粗利益 | F41: =SUMIF(I$3:N$3,$F$3,I41:N41) -> 0 | I41: =K40-I40-(I43) -> 0 | L41: =N40-L40-(L43) -> 0
A42: 岡田 | B42: 営業 | D42: 93 | E42: 0 | F42: =SUMIF(I$3:N$3,$F$3,I42:N42) -> 0 | G42: =IF(ISERROR(F42/H42),0,F42/H42) -> 0 | H42: =SUMIF(I$3:N$3,$H$3,I42:N42) -> 0 | I42: =IFERROR(INDEX(別紙_テンプレート_DB!$P$3:$P$65423,MATCH($D42&"-"&I$2&"-"&$E42,INDEX(別紙_テンプレート_DB!$J$3:$J$65423&"-"&別紙_テンプレート_DB!$M$3:$M$65423&"-"&別紙_テンプレート_DB!$N$3:$N$65423,),0)),0) -> 0 | J42: =IF(ISERROR(I42/K42),0,I42/K42) -> 0 | K42: =IFERROR(INDEX(別紙_テンプレート_DB!$O$3:$O$65423,MATCH($D42&"-"&I$2&"-"&$E42,INDEX(別紙_テンプレート_DB!$J$3:$J$65423&"-"&別紙_テンプレート_DB!$M$3:$M$65423&"-"&別紙_テンプレート_DB!$N$3:$N$65423,),0)),0) -> 0 | L42: =IFERROR(INDEX(別紙_テンプレート_DB!$P$3:$P$65423,MATCH($D42&"-"&L$2&"-"&$E42,INDEX(別紙_テンプレート_DB!$J$3:$J$65423&"-"&別紙_テンプレート_DB!$M$3:$M$65423&"-"&別紙_テンプレート_DB!$N$3:$N$65423,),0)),0) -> 0 | M42: =IF(ISERROR(L42/N42),0,L42/N42) -> 0 | N42: =IFERROR(INDEX(別紙_テンプレート_DB!$O$3:$O$65423,MATCH($D42&"-"&L$2&"-"&$E42,INDEX(別紙_テンプレート_DB!$J$3:$J$65423&"-"&別紙_テンプレート_DB!$M$3:$M$65423&"-"&別紙_テンプレート_DB!$N$3:$N$65423,),0)),0) -> 0
B43: 営業経費 | I43: =IFERROR(INDEX(別紙_テンプレート_DB!$DP$3:$DP$65423,MATCH($C43&"-"&I$2,INDEX(別紙_テンプレート_DB!$DM$3:$DM$65423&"-"&別紙_テンプレート_DB!$DN$3:$DN$65423,),0)),0) -> 0 | L43: =IFERROR(INDEX(別紙_テンプレート_DB!$DP$3:$DP$65423,MATCH($C43&"-"&L$2,INDEX(別紙_テンプレート_DB!$DM$3:$DM$65423&"-"&別紙_テンプレート_DB!$DN$3:$DN$65423,),0)),0) -> 0
B44: 工事 | D44: 93 | E44: 1 | F44: =SUMIF(I$3:N$3,$F$3,I44:N44) -> 0 | G44: =IF(ISERROR(F44/H44),0,F44/H44) -> 0 | H44: =SUMIF(I$3:N$3,$H$3,I44:N44) -> 0 | I44: =IFERROR(INDEX(別紙_テンプレート_DB!$P$3:$P$65423,MATCH($D44&"-"&I$2&"-"&$E44,INDEX(別紙_テンプレート_DB!$J$3:$J$65423&"-"&別紙_テンプレート_DB!$M$3:$M$65423&"-"&別紙_テンプレート_DB!$N$3:$N$65423,),0)),0) -> 0 | J44: =IF(ISERROR(I44/K44),0,I44/K44) -> 0 | K44: =IFERROR(INDEX(別紙_テンプレート_DB!$O$3:$O$65423,MATCH($D44&"-"&I$2&"-"&$E44,INDEX(別紙_テンプレート_DB!$J$3:$J$65423&"-"&別紙_テンプレート_DB!$M$3:$M$65423&"-"&別紙_テンプレート_DB!$N$3:$N$65423,),0)),0) -> 0 | L44: =IFERROR(INDEX(別紙_テンプレート_DB!$P$3:$P$65423,MATCH($D44&"-"&L$2&"-"&$E44,INDEX(別紙_テンプレート_DB!$J$3:$J$65423&"-"&別紙_テンプレート_DB!$M$3:$M$65423&"-"&別紙_テンプレート_DB!$N$3:$N$65423,),0)),0) -> 0 | M44: =IF(ISERROR(L44/N44),0,L44/N44) -> 0 | N44: =IFERROR(INDEX(別紙_テンプレート_DB!$O$3:$O$65423,MATCH($D44&"-"&L$2&"-"&$E44,INDEX(別紙_テンプレート_DB!$J$3:$J$65423&"-"&別紙_テンプレート_DB!$M$3:$M$65423&"-"&別紙_テンプレート_DB!$N$3:$N$65423,),0)),0) -> 0
B45: コール | D45: 93 | E45: 2 | F45: =SUMIF(I$3:N$3,$F$3,I45:N45) -> 0 | G45: =IF(ISERROR(F45/H45),0,F45/H45) -> 0 | H45: =SUMIF(I$3:N$3,$H$3,I45:N45) -> 0 | I45: =IFERROR(INDEX(別紙_テンプレート_DB!$P$3:$P$65423,MATCH($D45&"-"&I$2&"-"&$E45,INDEX(別紙_テンプレート_DB!$J$3:$J$65423&"-"&別紙_テンプレート_DB!$M$3:$M$65423&"-"&別紙_テンプレート_DB!$N$3:$N$65423,),0)),0) -> 0 | J45: =IF(ISERROR(I45/K45),0,I45/K45) -> 0 | K45: =IFERROR(INDEX(別紙_テンプレート_DB!$O$3:$O$65423,MATCH($D45&"-"&I$2&"-"&$E45,INDEX(別紙_テンプレート_DB!$J$3:$J$65423&"-"&別紙_テンプレート_DB!$M$3:$M$65423&"-"&別紙_テンプレート_DB!$N$3:$N$65423,),0)),0) -> 0 | L45: =IFERROR(INDEX(別紙_テンプレート_DB!$P$3:$P$65423,MATCH($D45&"-"&L$2&"-"&$E45,INDEX(別紙_テンプレート_DB!$J$3:$J$65423&"-"&別紙_テンプレート_DB!$M$3:$M$65423&"-"&別紙_テンプレート_DB!$N$3:$N$65423,),0)),0) -> 0 | M45: =IF(ISERROR(L45/N45),0,L45/N45) -> 0 | N45: =IFERROR(INDEX(別紙_テンプレート_DB!$O$3:$O$65423,MATCH($D45&"-"&L$2&"-"&$E45,INDEX(別紙_テンプレート_DB!$J$3:$J$65423&"-"&別紙_テンプレート_DB!$M$3:$M$65423&"-"&別紙_テンプレート_DB!$N$3:$N$65423,),0)),0) -> 0
B46: 内装 | D46: 93 | E46: 3 | F46: =SUMIF(I$3:N$3,$F$3,I46:N46) -> 0 | G46: =IF(ISERROR(F46/H46),0,F46/H46) -> 0 | H46: =SUMIF(I$3:N$3,$H$3,I46:N46) -> 0 | I46: =IFERROR(INDEX(別紙_テンプレート_DB!$P$3:$P$65423,MATCH($D46&"-"&I$2&"-"&$E46,INDEX(別紙_テンプレート_DB!$J$3:$J$65423&"-"&別紙_テンプレート_DB!$M$3:$M$65423&"-"&別紙_テンプレート_DB!$N$3:$N$65423,),0)),0) -> 0 | J46: =IF(ISERROR(I46/K46),0,I46/K46) -> 0 | K46: =IFERROR(INDEX(別紙_テンプレート_DB!$O$3:$O$65423,MATCH($D46&"-"&I$2&"-"&$E46,INDEX(別紙_テンプレート_DB!$J$3:$J$65423&"-"&別紙_テンプレート_DB!$M$3:$M$65423&"-"&別紙_テンプレート_DB!$N$3:$N$65423,),0)),0) -> 0 | L46: =IFERROR(INDEX(別紙_テンプレート_DB!$P$3:$P$65423,MATCH($D46&"-"&L$2&"-"&$E46,INDEX(別紙_テンプレート_DB!$J$3:$J$65423&"-"&別紙_テンプレート_DB!$M$3:$M$65423&"-"&別紙_テンプレート_DB!$N$3:$N$65423,),0)),0) -> 0 | M46: =IF(ISERROR(L46/N46),0,L46/N46) -> 0 | N46: =IFERROR(INDEX(別紙_テンプレート_DB!$O$3:$O$65423,MATCH($D46&"-"&L$2&"-"&$E46,INDEX(別紙_テンプレート_DB!$J$3:$J$65423&"-"&別紙_テンプレート_DB!$M$3:$M$65423&"-"&別紙_テンプレート_DB!$N$3:$N$65423,),0)),0) -> 0
B47: 委託 | D47: 93 | E47: 106 | F47: =SUMIF(I$3:N$3,$F$3,I47:N47) -> 0 | G47: =IF(ISERROR(F47/H47),0,F47/H47) -> 0 | H47: =SUMIF(I$3:N$3,$H$3,I47:N47) -> 0 | I47: =IFERROR(INDEX(別紙_テンプレート_DB!$P$3:$P$65423,MATCH($D47&"-"&I$2&"-"&$E47,INDEX(別紙_テンプレート_DB!$J$3:$J$65423&"-"&別紙_テンプレート_DB!$M$3:$M$65423&"-"&別紙_テンプレート_DB!$N$3:$N$65423,),0)),0) -> 0 | J47: =IF(ISERROR(I47/K47),0,I47/K47) -> 0 | K47: =IFERROR(INDEX(別紙_テンプレート_DB!$O$3:$O$65423,MATCH($D47&"-"&I$2&"-"&$E47,INDEX(別紙_テンプレート_DB!$J$3:$J$65423&"-"&別紙_テンプレート_DB!$M$3:$M$65423&"-"&別紙_テンプレート_DB!$N$3:$N$65423,),0)),0) -> 0 | L47: =IFERROR(INDEX(別紙_テンプレート_DB!$P$3:$P$65423,MATCH($D47&"-"&L$2&"-"&$E47,INDEX(別紙_テンプレート_DB!$J$3:$J$65423&"-"&別紙_テンプレート_DB!$M$3:$M$65423&"-"&別紙_テンプレート_DB!$N$3:$N$65423,),0)),0) -> 0 | M47: =IF(ISERROR(L47/N47),0,L47/N47) -> 0 | N47: =IFERROR(INDEX(別紙_テンプレート_DB!$O$3:$O$65423,MATCH($D47&"-"&L$2&"-"&$E47,INDEX(別紙_テンプレート_DB!$J$3:$J$65423&"-"&別紙_テンプレート_DB!$M$3:$M$65423&"-"&別紙_テンプレート_DB!$N$3:$N$65423,),0)),0) -> 0
B48: クレーム | D48: 93 | E48: 4 | F48: =SUMIF(I$3:N$3,$F$3,I48:N48) -> 0 | I48: =IFERROR(INDEX(別紙_テンプレート_DB!$P$3:$P$65423,MATCH($D48&"-"&I$2&"-"&$E48,INDEX(別紙_テンプレート_DB!$J$3:$J$65423&"-"&別紙_テンプレート_DB!$M$3:$M$65423&"-"&別紙_テンプレート_DB!$N$3:$N$65423,),0)),0) -> 0 | L48: =IFERROR(INDEX(別紙_テンプレート_DB!$P$3:$P$65423,MATCH($D48&"-"&L$2&"-"&$E48,INDEX(別紙_テンプレート_DB!$J$3:$J$65423&"-"&別紙_テンプレート_DB!$M$3:$M$65423&"-"&別紙_テンプレート_DB!$N$3:$N$65423,),0)),0) -> 0
A49: 原価 ／ 売価 | C49: 工事担当 | D49: 97 | F49: =SUMIF(I$3:N$3,$F$3,I49:N49) -> 0 | G49: =IF(ISERROR(F49/H49),0,F49/H49) -> 0 | H49: =SUMIF(I$3:N$3,$H$3,I49:N49) -> 0 | I49: =SUMIF($D51:$D57,$D49,I51:I57) -> 0 | J49: =IF(ISERROR(I49/K49),0,I49/K49) -> 0 | K49: =SUM(K51:K57) -> 0 | L49: =SUMIF($D51:$D57,$D49,L51:L57) -> 0 | M49: =IF(ISERROR(L49/N49),0,L49/N49) -> 0 | N49: =SUM(N51:N57) -> 0
A50: 粗利益 | F50: =SUMIF(I$3:N$3,$F$3,I50:N50) -> 0 | I50: =K49-I49-(I52) -> 0 | L50: =N49-L49-(L52) -> 0
A51: 内装 | B51: 営業 | D51: 97 | E51: 0 | F51: =SUMIF(I$3:N$3,$F$3,I51:N51) -> 0 | G51: =IF(ISERROR(F51/H51),0,F51/H51) -> 0 | H51: =SUMIF(I$3:N$3,$H$3,I51:N51) -> 0 | I51: =IFERROR(INDEX(別紙_テンプレート_DB!$P$3:$P$65423,MATCH($D51&"-"&I$2&"-"&$E51,INDEX(別紙_テンプレート_DB!$J$3:$J$65423&"-"&別紙_テンプレート_DB!$M$3:$M$65423&"-"&別紙_テンプレート_DB!$N$3:$N$65423,),0)),0) -> 0 | J51: =IF(ISERROR(I51/K51),0,I51/K51) -> 0 | K51: =IFERROR(INDEX(別紙_テンプレート_DB!$O$3:$O$65423,MATCH($D51&"-"&I$2&"-"&$E51,INDEX(別紙_テンプレート_DB!$J$3:$J$65423&"-"&別紙_テンプレート_DB!$M$3:$M$65423&"-"&別紙_テンプレート_DB!$N$3:$N$65423,),0)),0) -> 0 | L51: =IFERROR(INDEX(別紙_テンプレート_DB!$P$3:$P$65423,MATCH($D51&"-"&L$2&"-"&$E51,INDEX(別紙_テンプレート_DB!$J$3:$J$65423&"-"&別紙_テンプレート_DB!$M$3:$M$65423&"-"&別紙_テンプレート_DB!$N$3:$N$65423,),0)),0) -> 0 | M51: =IF(ISERROR(L51/N51),0,L51/N51) -> 0 | N51: =IFERROR(INDEX(別紙_テンプレート_DB!$O$3:$O$65423,MATCH($D51&"-"&L$2&"-"&$E51,INDEX(別紙_テンプレート_DB!$J$3:$J$65423&"-"&別紙_テンプレート_DB!$M$3:$M$65423&"-"&別紙_テンプレート_DB!$N$3:$N$65423,),0)),0) -> 0
B52: 営業経費 | I52: =IFERROR(INDEX(別紙_テンプレート_DB!$DP$3:$DP$65423,MATCH($C52&"-"&I$2,INDEX(別紙_テンプレート_DB!$DM$3:$DM$65423&"-"&別紙_テンプレート_DB!$DN$3:$DN$65423,),0)),0) -> 0 | L52: =IFERROR(INDEX(別紙_テンプレート_DB!$DP$3:$DP$65423,MATCH($C52&"-"&L$2,INDEX(別紙_テンプレート_DB!$DM$3:$DM$65423&"-"&別紙_テンプレート_DB!$DN$3:$DN$65423,),0)),0) -> 0
B53: 工事 | D53: 97 | E53: 1 | F53: =SUMIF(I$3:N$3,$F$3,I53:N53) -> 0 | G53: =IF(ISERROR(F53/H53),0,F53/H53) -> 0 | H53: =SUMIF(I$3:N$3,$H$3,I53:N53) -> 0 | I53: =IFERROR(INDEX(別紙_テンプレート_DB!$P$3:$P$65423,MATCH($D53&"-"&I$2&"-"&$E53,INDEX(別紙_テンプレート_DB!$J$3:$J$65423&"-"&別紙_テンプレート_DB!$M$3:$M$65423&"-"&別紙_テンプレート_DB!$N$3:$N$65423,),0)),0) -> 0 | J53: =IF(ISERROR(I53/K53),0,I53/K53) -> 0 | K53: =IFERROR(INDEX(別紙_テンプレート_DB!$O$3:$O$65423,MATCH($D53&"-"&I$2&"-"&$E53,INDEX(別紙_テンプレート_DB!$J$3:$J$65423&"-"&別紙_テンプレート_DB!$M$3:$M$65423&"-"&別紙_テンプレート_DB!$N$3:$N$65423,),0)),0) -> 0 | L53: =IFERROR(INDEX(別紙_テンプレート_DB!$P$3:$P$65423,MATCH($D53&"-"&L$2&"-"&$E53,INDEX(別紙_テンプレート_DB!$J$3:$J$65423&"-"&別紙_テンプレート_DB!$M$3:$M$65423&"-"&別紙_テンプレート_DB!$N$3:$N$65423,),0)),0) -> 0 | M53: =IF(ISERROR(L53/N53),0,L53/N53) -> 0 | N53: =IFERROR(INDEX(別紙_テンプレート_DB!$O$3:$O$65423,MATCH($D53&"-"&L$2&"-"&$E53,INDEX(別紙_テンプレート_DB!$J$3:$J$65423&"-"&別紙_テンプレート_DB!$M$3:$M$65423&"-"&別紙_テンプレート_DB!$N$3:$N$65423,),0)),0) -> 0
B54: コール | D54: 97 | E54: 2 | F54: =SUMIF(I$3:N$3,$F$3,I54:N54) -> 0 | G54: =IF(ISERROR(F54/H54),0,F54/H54) -> 0 | H54: =SUMIF(I$3:N$3,$H$3,I54:N54) -> 0 | I54: =IFERROR(INDEX(別紙_テンプレート_DB!$P$3:$P$65423,MATCH($D54&"-"&I$2&"-"&$E54,INDEX(別紙_テンプレート_DB!$J$3:$J$65423&"-"&別紙_テンプレート_DB!$M$3:$M$65423&"-"&別紙_テンプレート_DB!$N$3:$N$65423,),0)),0) -> 0 | J54: =IF(ISERROR(I54/K54),0,I54/K54) -> 0 | K54: =IFERROR(INDEX(別紙_テンプレート_DB!$O$3:$O$65423,MATCH($D54&"-"&I$2&"-"&$E54,INDEX(別紙_テンプレート_DB!$J$3:$J$65423&"-"&別紙_テンプレート_DB!$M$3:$M$65423&"-"&別紙_テンプレート_DB!$N$3:$N$65423,),0)),0) -> 0 | L54: =IFERROR(INDEX(別紙_テンプレート_DB!$P$3:$P$65423,MATCH($D54&"-"&L$2&"-"&$E54,INDEX(別紙_テンプレート_DB!$J$3:$J$65423&"-"&別紙_テンプレート_DB!$M$3:$M$65423&"-"&別紙_テンプレート_DB!$N$3:$N$65423,),0)),0) -> 0 | M54: =IF(ISERROR(L54/N54),0,L54/N54) -> 0 | N54: =IFERROR(INDEX(別紙_テンプレート_DB!$O$3:$O$65423,MATCH($D54&"-"&L$2&"-"&$E54,INDEX(別紙_テンプレート_DB!$J$3:$J$65423&"-"&別紙_テンプレート_DB!$M$3:$M$65423&"-"&別紙_テンプレート_DB!$N$3:$N$65423,),0)),0) -> 0
B55: 内装 | D55: 97 | E55: 3 | F55: =SUMIF(I$3:N$3,$F$3,I55:N55) -> 0 | G55: =IF(ISERROR(F55/H55),0,F55/H55) -> 0 | H55: =SUMIF(I$3:N$3,$H$3,I55:N55) -> 0 | I55: =IFERROR(INDEX(別紙_テンプレート_DB!$P$3:$P$65423,MATCH($D55&"-"&I$2&"-"&$E55,INDEX(別紙_テンプレート_DB!$J$3:$J$65423&"-"&別紙_テンプレート_DB!$M$3:$M$65423&"-"&別紙_テンプレート_DB!$N$3:$N$65423,),0)),0) -> 0 | J55: =IF(ISERROR(I55/K55),0,I55/K55) -> 0 | K55: =IFERROR(INDEX(別紙_テンプレート_DB!$O$3:$O$65423,MATCH($D55&"-"&I$2&"-"&$E55,INDEX(別紙_テンプレート_DB!$J$3:$J$65423&"-"&別紙_テンプレート_DB!$M$3:$M$65423&"-"&別紙_テンプレート_DB!$N$3:$N$65423,),0)),0) -> 0 | L55: =IFERROR(INDEX(別紙_テンプレート_DB!$P$3:$P$65423,MATCH($D55&"-"&L$2&"-"&$E55,INDEX(別紙_テンプレート_DB!$J$3:$J$65423&"-"&別紙_テンプレート_DB!$M$3:$M$65423&"-"&別紙_テンプレート_DB!$N$3:$N$65423,),0)),0) -> 0 | M55: =IF(ISERROR(L55/N55),0,L55/N55) -> 0 | N55: =IFERROR(INDEX(別紙_テンプレート_DB!$O$3:$O$65423,MATCH($D55&"-"&L$2&"-"&$E55,INDEX(別紙_テンプレート_DB!$J$3:$J$65423&"-"&別紙_テンプレート_DB!$M$3:$M$65423&"-"&別紙_テンプレート_DB!$N$3:$N$65423,),0)),0) -> 0
B56: 委託 | D56: 97 | E56: 106 | F56: =SUMIF(I$3:N$3,$F$3,I56:N56) -> 0 | G56: =IF(ISERROR(F56/H56),0,F56/H56) -> 0 | H56: =SUMIF(I$3:N$3,$H$3,I56:N56) -> 0 | I56: =IFERROR(INDEX(別紙_テンプレート_DB!$P$3:$P$65423,MATCH($D56&"-"&I$2&"-"&$E56,INDEX(別紙_テンプレート_DB!$J$3:$J$65423&"-"&別紙_テンプレート_DB!$M$3:$M$65423&"-"&別紙_テンプレート_DB!$N$3:$N$65423,),0)),0) -> 0 | J56: =IF(ISERROR(I56/K56),0,I56/K56) -> 0 | K56: =IFERROR(INDEX(別紙_テンプレート_DB!$O$3:$O$65423,MATCH($D56&"-"&I$2&"-"&$E56,INDEX(別紙_テンプレート_DB!$J$3:$J$65423&"-"&別紙_テンプレート_DB!$M$3:$M$65423&"-"&別紙_テンプレート_DB!$N$3:$N$65423,),0)),0) -> 0 | L56: =IFERROR(INDEX(別紙_テンプレート_DB!$P$3:$P$65423,MATCH($D56&"-"&L$2&"-"&$E56,INDEX(別紙_テンプレート_DB!$J$3:$J$65423&"-"&別紙_テンプレート_DB!$M$3:$M$65423&"-"&別紙_テンプレート_DB!$N$3:$N$65423,),0)),0) -> 0 | M56: =IF(ISERROR(L56/N56),0,L56/N56) -> 0 | N56: =IFERROR(INDEX(別紙_テンプレート_DB!$O$3:$O$65423,MATCH($D56&"-"&L$2&"-"&$E56,INDEX(別紙_テンプレート_DB!$J$3:$J$65423&"-"&別紙_テンプレート_DB!$M$3:$M$65423&"-"&別紙_テンプレート_DB!$N$3:$N$65423,),0)),0) -> 0
B57: クレーム | D57: 97 | E57: 4 | F57: =SUMIF(I$3:N$3,$F$3,I57:N57) -> 0 | I57: =IFERROR(INDEX(別紙_テンプレート_DB!$P$3:$P$65423,MATCH($D57&"-"&I$2&"-"&$E57,INDEX(別紙_テンプレート_DB!$J$3:$J$65423&"-"&別紙_テンプレート_DB!$M$3:$M$65423&"-"&別紙_テンプレート_DB!$N$3:$N$65423,),0)),0) -> 0 | L57: =IFERROR(INDEX(別紙_テンプレート_DB!$P$3:$P$65423,MATCH($D57&"-"&L$2&"-"&$E57,INDEX(別紙_テンプレート_DB!$J$3:$J$65423&"-"&別紙_テンプレート_DB!$M$3:$M$65423&"-"&別紙_テンプレート_DB!$N$3:$N$65423,),0)),0) -> 0
A58: 原価 ／ 売価 | C58: 工事担当 | D58: 98 | F58: =SUMIF(I$3:N$3,$F$3,I58:N58) -> 0 | G58: =IF(ISERROR(F58/H58),0,F58/H58) -> 0 | H58: =SUMIF(I$3:N$3,$H$3,I58:N58) -> 0 | I58: =SUMIF($D60:$D66,$D58,I60:I66) -> 0 | J58: =IF(ISERROR(I58/K58),0,I58/K58) -> 0 | K58: =SUM(K60:K66) -> 0 | L58: =SUMIF($D60:$D66,$D58,L60:L66) -> 0 | M58: =IF(ISERROR(L58/N58),0,L58/N58) -> 0 | N58: =SUM(N60:N66) -> 0
A59: 粗利益 | F59: =SUMIF(I$3:N$3,$F$3,I59:N59) -> 0 | I59: =K58-I58-(I61) -> 0 | L59: =N58-L58-(L61) -> 0
A60: サポート | B60: 営業 | D60: 98 | E60: 0 | F60: =SUMIF(I$3:N$3,$F$3,I60:N60) -> 0 | G60: =IF(ISERROR(F60/H60),0,F60/H60) -> 0 | H60: =SUMIF(I$3:N$3,$H$3,I60:N60) -> 0 | I60: =IFERROR(INDEX(別紙_テンプレート_DB!$P$3:$P$65423,MATCH($D60&"-"&I$2&"-"&$E60,INDEX(別紙_テンプレート_DB!$J$3:$J$65423&"-"&別紙_テンプレート_DB!$M$3:$M$65423&"-"&別紙_テンプレート_DB!$N$3:$N$65423,),0)),0) -> 0 | J60: =IF(ISERROR(I60/K60),0,I60/K60) -> 0 | K60: =IFERROR(INDEX(別紙_テンプレート_DB!$O$3:$O$65423,MATCH($D60&"-"&I$2&"-"&$E60,INDEX(別紙_テンプレート_DB!$J$3:$J$65423&"-"&別紙_テンプレート_DB!$M$3:$M$65423&"-"&別紙_テンプレート_DB!$N$3:$N$65423,),0)),0) -> 0 | L60: =IFERROR(INDEX(別紙_テンプレート_DB!$P$3:$P$65423,MATCH($D60&"-"&L$2&"-"&$E60,INDEX(別紙_テンプレート_DB!$J$3:$J$65423&"-"&別紙_テンプレート_DB!$M$3:$M$65423&"-"&別紙_テンプレート_DB!$N$3:$N$65423,),0)),0) -> 0 | M60: =IF(ISERROR(L60/N60),0,L60/N60) -> 0 | N60: =IFERROR(INDEX(別紙_テンプレート_DB!$O$3:$O$65423,MATCH($D60&"-"&L$2&"-"&$E60,INDEX(別紙_テンプレート_DB!$J$3:$J$65423&"-"&別紙_テンプレート_DB!$M$3:$M$65423&"-"&別紙_テンプレート_DB!$N$3:$N$65423,),0)),0) -> 0
B61: 営業経費 | E61: 6601 | I61: =IFERROR(INDEX(別紙_テンプレート_DB!$DP$3:$DP$65423,MATCH($C61&"-"&I$2,INDEX(別紙_テンプレート_DB!$DM$3:$DM$65423&"-"&別紙_テンプレート_DB!$DN$3:$DN$65423,),0)),0) -> 0 | L61: =IFERROR(INDEX(別紙_テンプレート_DB!$DP$3:$DP$65423,MATCH($C61&"-"&L$2,INDEX(別紙_テンプレート_DB!$DM$3:$DM$65423&"-"&別紙_テンプレート_DB!$DN$3:$DN$65423,),0)),0) -> 0
B62: 工事 | D62: 98 | E62: 1 | F62: =SUMIF(I$3:N$3,$F$3,I62:N62) -> 0 | G62: =IF(ISERROR(F62/H62),0,F62/H62) -> 0 | H62: =SUMIF(I$3:N$3,$H$3,I62:N62) -> 0 | I62: =IFERROR(INDEX(別紙_テンプレート_DB!$P$3:$P$65423,MATCH($D62&"-"&I$2&"-"&$E62,INDEX(別紙_テンプレート_DB!$J$3:$J$65423&"-"&別紙_テンプレート_DB!$M$3:$M$65423&"-"&別紙_テンプレート_DB!$N$3:$N$65423,),0)),0) -> 0 | J62: =IF(ISERROR(I62/K62),0,I62/K62) -> 0 | K62: =IFERROR(INDEX(別紙_テンプレート_DB!$O$3:$O$65423,MATCH($D62&"-"&I$2&"-"&$E62,INDEX(別紙_テンプレート_DB!$J$3:$J$65423&"-"&別紙_テンプレート_DB!$M$3:$M$65423&"-"&別紙_テンプレート_DB!$N$3:$N$65423,),0)),0) -> 0 | L62: =IFERROR(INDEX(別紙_テンプレート_DB!$P$3:$P$65423,MATCH($D62&"-"&L$2&"-"&$E62,INDEX(別紙_テンプレート_DB!$J$3:$J$65423&"-"&別紙_テンプレート_DB!$M$3:$M$65423&"-"&別紙_テンプレート_DB!$N$3:$N$65423,),0)),0) -> 0 | M62: =IF(ISERROR(L62/N62),0,L62/N62) -> 0 | N62: =IFERROR(INDEX(別紙_テンプレート_DB!$O$3:$O$65423,MATCH($D62&"-"&L$2&"-"&$E62,INDEX(別紙_テンプレート_DB!$J$3:$J$65423&"-"&別紙_テンプレート_DB!$M$3:$M$65423&"-"&別紙_テンプレート_DB!$N$3:$N$65423,),0)),0) -> 0
B63: コール | D63: 98 | E63: 2 | F63: =SUMIF(I$3:N$3,$F$3,I63:N63) -> 0 | G63: =IF(ISERROR(F63/H63),0,F63/H63) -> 0 | H63: =SUMIF(I$3:N$3,$H$3,I63:N63) -> 0 | I63: =IFERROR(INDEX(別紙_テンプレート_DB!$P$3:$P$65423,MATCH($D63&"-"&I$2&"-"&$E63,INDEX(別紙_テンプレート_DB!$J$3:$J$65423&"-"&別紙_テンプレート_DB!$M$3:$M$65423&"-"&別紙_テンプレート_DB!$N$3:$N$65423,),0)),0) -> 0 | J63: =IF(ISERROR(I63/K63),0,I63/K63) -> 0 | K63: =IFERROR(INDEX(別紙_テンプレート_DB!$O$3:$O$65423,MATCH($D63&"-"&I$2&"-"&$E63,INDEX(別紙_テンプレート_DB!$J$3:$J$65423&"-"&別紙_テンプレート_DB!$M$3:$M$65423&"-"&別紙_テンプレート_DB!$N$3:$N$65423,),0)),0) -> 0 | L63: =IFERROR(INDEX(別紙_テンプレート_DB!$P$3:$P$65423,MATCH($D63&"-"&L$2&"-"&$E63,INDEX(別紙_テンプレート_DB!$J$3:$J$65423&"-"&別紙_テンプレート_DB!$M$3:$M$65423&"-"&別紙_テンプレート_DB!$N$3:$N$65423,),0)),0) -> 0 | M63: =IF(ISERROR(L63/N63),0,L63/N63) -> 0 | N63: =IFERROR(INDEX(別紙_テンプレート_DB!$O$3:$O$65423,MATCH($D63&"-"&L$2&"-"&$E63,INDEX(別紙_テンプレート_DB!$J$3:$J$65423&"-"&別紙_テンプレート_DB!$M$3:$M$65423&"-"&別紙_テンプレート_DB!$N$3:$N$65423,),0)),0) -> 0
B64: 内装 | D64: 98 | E64: 3 | F64: =SUMIF(I$3:N$3,$F$3,I64:N64) -> 0 | G64: =IF(ISERROR(F64/H64),0,F64/H64) -> 0 | H64: =SUMIF(I$3:N$3,$H$3,I64:N64) -> 0 | I64: =IFERROR(INDEX(別紙_テンプレート_DB!$P$3:$P$65423,MATCH($D64&"-"&I$2&"-"&$E64,INDEX(別紙_テンプレート_DB!$J$3:$J$65423&"-"&別紙_テンプレート_DB!$M$3:$M$65423&"-"&別紙_テンプレート_DB!$N$3:$N$65423,),0)),0) -> 0 | J64: =IF(ISERROR(I64/K64),0,I64/K64) -> 0 | K64: =IFERROR(INDEX(別紙_テンプレート_DB!$O$3:$O$65423,MATCH($D64&"-"&I$2&"-"&$E64,INDEX(別紙_テンプレート_DB!$J$3:$J$65423&"-"&別紙_テンプレート_DB!$M$3:$M$65423&"-"&別紙_テンプレート_DB!$N$3:$N$65423,),0)),0) -> 0 | L64: =IFERROR(INDEX(別紙_テンプレート_DB!$P$3:$P$65423,MATCH($D64&"-"&L$2&"-"&$E64,INDEX(別紙_テンプレート_DB!$J$3:$J$65423&"-"&別紙_テンプレート_DB!$M$3:$M$65423&"-"&別紙_テンプレート_DB!$N$3:$N$65423,),0)),0) -> 0 | M64: =IF(ISERROR(L64/N64),0,L64/N64) -> 0 | N64: =IFERROR(INDEX(別紙_テンプレート_DB!$O$3:$O$65423,MATCH($D64&"-"&L$2&"-"&$E64,INDEX(別紙_テンプレート_DB!$J$3:$J$65423&"-"&別紙_テンプレート_DB!$M$3:$M$65423&"-"&別紙_テンプレート_DB!$N$3:$N$65423,),0)),0) -> 0
B65: 委託 | D65: 98 | E65: 106 | F65: =SUMIF(I$3:N$3,$F$3,I65:N65) -> 0 | G65: =IF(ISERROR(F65/H65),0,F65/H65) -> 0 | H65: =SUMIF(I$3:N$3,$H$3,I65:N65) -> 0 | I65: =IFERROR(INDEX(別紙_テンプレート_DB!$P$3:$P$65423,MATCH($D65&"-"&I$2&"-"&$E65,INDEX(別紙_テンプレート_DB!$J$3:$J$65423&"-"&別紙_テンプレート_DB!$M$3:$M$65423&"-"&別紙_テンプレート_DB!$N$3:$N$65423,),0)),0) -> 0 | J65: =IF(ISERROR(I65/K65),0,I65/K65) -> 0 | K65: =IFERROR(INDEX(別紙_テンプレート_DB!$O$3:$O$65423,MATCH($D65&"-"&I$2&"-"&$E65,INDEX(別紙_テンプレート_DB!$J$3:$J$65423&"-"&別紙_テンプレート_DB!$M$3:$M$65423&"-"&別紙_テンプレート_DB!$N$3:$N$65423,),0)),0) -> 0 | L65: =IFERROR(INDEX(別紙_テンプレート_DB!$P$3:$P$65423,MATCH($D65&"-"&L$2&"-"&$E65,INDEX(別紙_テンプレート_DB!$J$3:$J$65423&"-"&別紙_テンプレート_DB!$M$3:$M$65423&"-"&別紙_テンプレート_DB!$N$3:$N$65423,),0)),0) -> 0 | M65: =IF(ISERROR(L65/N65),0,L65/N65) -> 0 | N65: =IFERROR(INDEX(別紙_テンプレート_DB!$O$3:$O$65423,MATCH($D65&"-"&L$2&"-"&$E65,INDEX(別紙_テンプレート_DB!$J$3:$J$65423&"-"&別紙_テンプレート_DB!$M$3:$M$65423&"-"&別紙_テンプレート_DB!$N$3:$N$65423,),0)),0) -> 0
B66: クレーム | D66: 98 | E66: 4 | F66: =SUMIF(I$3:N$3,$F$3,I66:N66) -> 0 | I66: =IFERROR(INDEX(別紙_テンプレート_DB!$P$3:$P$65423,MATCH($D66&"-"&I$2&"-"&$E66,INDEX(別紙_テンプレート_DB!$J$3:$J$65423&"-"&別紙_テンプレート_DB!$M$3:$M$65423&"-"&別紙_テンプレート_DB!$N$3:$N$65423,),0)),0) -> 0 | L66: =IFERROR(INDEX(別紙_テンプレート_DB!$P$3:$P$65423,MATCH($D66&"-"&L$2&"-"&$E66,INDEX(別紙_テンプレート_DB!$J$3:$J$65423&"-"&別紙_テンプレート_DB!$M$3:$M$65423&"-"&別紙_テンプレート_DB!$N$3:$N$65423,),0)),0) -> 0
A67: 原価 ／ 売価 | C67: 工事担当 | D67: 999 | F67: =SUMIF(I$3:N$3,$F$3,I67:N67) -> 0 | G67: =IF(ISERROR(F67/H67),0,F67/H67) -> 0 | H67: =SUMIF(I$3:N$3,$H$3,I67:N67) -> 0 | I67: =SUMIF($D69:$D75,$D67,I69:I75) -> 0 | J67: =IF(ISERROR(I67/K67),0,I67/K67) -> 0 | K67: =SUM(K69:K75) -> 0 | L67: =SUMIF($D69:$D75,$D67,L69:L75) -> 0 | M67: =IF(ISERROR(L67/N67),0,L67/N67) -> 0 | N67: =SUM(N69:N75) -> 0
A68: 粗利益 | F68: =SUMIF(I$3:N$3,$F$3,I68:N68) -> 0 | I68: =K67-I67-(I70) -> 0 | L68: =N67-L67-(L70) -> 0
A69: コール センター | B69: 営業 | D69: 999 | E69: 0 | F69: =SUMIF(I$3:N$3,$F$3,I69:N69) -> 0 | G69: =IF(ISERROR(F69/H69),0,F69/H69) -> 0 | H69: =SUMIF(I$3:N$3,$H$3,I69:N69) -> 0 | I69: =IFERROR(INDEX(別紙_テンプレート_DB!$P$3:$P$65423,MATCH($D69&"-"&I$2&"-"&$E69,INDEX(別紙_テンプレート_DB!$J$3:$J$65423&"-"&別紙_テンプレート_DB!$M$3:$M$65423&"-"&別紙_テンプレート_DB!$N$3:$N$65423,),0)),0) -> 0 | J69: =IF(ISERROR(I69/K69),0,I69/K69) -> 0 | K69: =IFERROR(INDEX(別紙_テンプレート_DB!$O$3:$O$65423,MATCH($D69&"-"&I$2&"-"&$E69,INDEX(別紙_テンプレート_DB!$J$3:$J$65423&"-"&別紙_テンプレート_DB!$M$3:$M$65423&"-"&別紙_テンプレート_DB!$N$3:$N$65423,),0)),0) -> 0 | L69: =IFERROR(INDEX(別紙_テンプレート_DB!$P$3:$P$65423,MATCH($D69&"-"&L$2&"-"&$E69,INDEX(別紙_テンプレート_DB!$J$3:$J$65423&"-"&別紙_テンプレート_DB!$M$3:$M$65423&"-"&別紙_テンプレート_DB!$N$3:$N$65423,),0)),0) -> 0 | M69: =IF(ISERROR(L69/N69),0,L69/N69) -> 0 | N69: =IFERROR(INDEX(別紙_テンプレート_DB!$O$3:$O$65423,MATCH($D69&"-"&L$2&"-"&$E69,INDEX(別紙_テンプレート_DB!$J$3:$J$65423&"-"&別紙_テンプレート_DB!$M$3:$M$65423&"-"&別紙_テンプレート_DB!$N$3:$N$65423,),0)),0) -> 0
B70: 営業経費 | E70: 6601 | I70: =IFERROR(INDEX(別紙_テンプレート_DB!$DP$3:$DP$65423,MATCH($C70&"-"&I$2,INDEX(別紙_テンプレート_DB!$DM$3:$DM$65423&"-"&別紙_テンプレート_DB!$DN$3:$DN$65423,),0)),0) -> 0 | L70: =IFERROR(INDEX(別紙_テンプレート_DB!$DP$3:$DP$65423,MATCH($C70&"-"&L$2,INDEX(別紙_テンプレート_DB!$DM$3:$DM$65423&"-"&別紙_テンプレート_DB!$DN$3:$DN$65423,),0)),0) -> 0
B71: 工事 | D71: 999 | E71: 1 | F71: =SUMIF(I$3:N$3,$F$3,I71:N71) -> 0 | G71: =IF(ISERROR(F71/H71),0,F71/H71) -> 0 | H71: =SUMIF(I$3:N$3,$H$3,I71:N71) -> 0 | I71: =IFERROR(INDEX(別紙_テンプレート_DB!$P$3:$P$65423,MATCH($D71&"-"&I$2&"-"&$E71,INDEX(別紙_テンプレート_DB!$J$3:$J$65423&"-"&別紙_テンプレート_DB!$M$3:$M$65423&"-"&別紙_テンプレート_DB!$N$3:$N$65423,),0)),0) -> 0 | J71: =IF(ISERROR(I71/K71),0,I71/K71) -> 0 | K71: =IFERROR(INDEX(別紙_テンプレート_DB!$O$3:$O$65423,MATCH($D71&"-"&I$2&"-"&$E71,INDEX(別紙_テンプレート_DB!$J$3:$J$65423&"-"&別紙_テンプレート_DB!$M$3:$M$65423&"-"&別紙_テンプレート_DB!$N$3:$N$65423,),0)),0) -> 0 | L71: =IFERROR(INDEX(別紙_テンプレート_DB!$P$3:$P$65423,MATCH($D71&"-"&L$2&"-"&$E71,INDEX(別紙_テンプレート_DB!$J$3:$J$65423&"-"&別紙_テンプレート_DB!$M$3:$M$65423&"-"&別紙_テンプレート_DB!$N$3:$N$65423,),0)),0) -> 0 | M71: =IF(ISERROR(L71/N71),0,L71/N71) -> 0 | N71: =IFERROR(INDEX(別紙_テンプレート_DB!$O$3:$O$65423,MATCH($D71&"-"&L$2&"-"&$E71,INDEX(別紙_テンプレート_DB!$J$3:$J$65423&"-"&別紙_テンプレート_DB!$M$3:$M$65423&"-"&別紙_テンプレート_DB!$N$3:$N$65423,),0)),0) -> 0
B72: コール | D72: 999 | E72: 2 | F72: =SUMIF(I$3:N$3,$F$3,I72:N72) -> 0 | G72: =IF(ISERROR(F72/H72),0,F72/H72) -> 0 | H72: =SUMIF(I$3:N$3,$H$3,I72:N72) -> 0 | I72: =IFERROR(INDEX(別紙_テンプレート_DB!$P$3:$P$65423,MATCH($D72&"-"&I$2&"-"&$E72,INDEX(別紙_テンプレート_DB!$J$3:$J$65423&"-"&別紙_テンプレート_DB!$M$3:$M$65423&"-"&別紙_テンプレート_DB!$N$3:$N$65423,),0)),0) -> 0 | J72: =IF(ISERROR(I72/K72),0,I72/K72) -> 0 | K72: =IFERROR(INDEX(別紙_テンプレート_DB!$O$3:$O$65423,MATCH($D72&"-"&I$2&"-"&$E72,INDEX(別紙_テンプレート_DB!$J$3:$J$65423&"-"&別紙_テンプレート_DB!$M$3:$M$65423&"-"&別紙_テンプレート_DB!$N$3:$N$65423,),0)),0) -> 0 | L72: =IFERROR(INDEX(別紙_テンプレート_DB!$P$3:$P$65423,MATCH($D72&"-"&L$2&"-"&$E72,INDEX(別紙_テンプレート_DB!$J$3:$J$65423&"-"&別紙_テンプレート_DB!$M$3:$M$65423&"-"&別紙_テンプレート_DB!$N$3:$N$65423,),0)),0) -> 0 | M72: =IF(ISERROR(L72/N72),0,L72/N72) -> 0 | N72: =IFERROR(INDEX(別紙_テンプレート_DB!$O$3:$O$65423,MATCH($D72&"-"&L$2&"-"&$E72,INDEX(別紙_テンプレート_DB!$J$3:$J$65423&"-"&別紙_テンプレート_DB!$M$3:$M$65423&"-"&別紙_テンプレート_DB!$N$3:$N$65423,),0)),0) -> 0
B73: 内装 | D73: 999 | E73: 3 | F73: =SUMIF(I$3:N$3,$F$3,I73:N73) -> 0 | G73: =IF(ISERROR(F73/H73),0,F73/H73) -> 0 | H73: =SUMIF(I$3:N$3,$H$3,I73:N73) -> 0 | I73: =IFERROR(INDEX(別紙_テンプレート_DB!$P$3:$P$65423,MATCH($D73&"-"&I$2&"-"&$E73,INDEX(別紙_テンプレート_DB!$J$3:$J$65423&"-"&別紙_テンプレート_DB!$M$3:$M$65423&"-"&別紙_テンプレート_DB!$N$3:$N$65423,),0)),0) -> 0 | J73: =IF(ISERROR(I73/K73),0,I73/K73) -> 0 | K73: =IFERROR(INDEX(別紙_テンプレート_DB!$O$3:$O$65423,MATCH($D73&"-"&I$2&"-"&$E73,INDEX(別紙_テンプレート_DB!$J$3:$J$65423&"-"&別紙_テンプレート_DB!$M$3:$M$65423&"-"&別紙_テンプレート_DB!$N$3:$N$65423,),0)),0) -> 0 | L73: =IFERROR(INDEX(別紙_テンプレート_DB!$P$3:$P$65423,MATCH($D73&"-"&L$2&"-"&$E73,INDEX(別紙_テンプレート_DB!$J$3:$J$65423&"-"&別紙_テンプレート_DB!$M$3:$M$65423&"-"&別紙_テンプレート_DB!$N$3:$N$65423,),0)),0) -> 0 | M73: =IF(ISERROR(L73/N73),0,L73/N73) -> 0 | N73: =IFERROR(INDEX(別紙_テンプレート_DB!$O$3:$O$65423,MATCH($D73&"-"&L$2&"-"&$E73,INDEX(別紙_テンプレート_DB!$J$3:$J$65423&"-"&別紙_テンプレート_DB!$M$3:$M$65423&"-"&別紙_テンプレート_DB!$N$3:$N$65423,),0)),0) -> 0
B74: 委託 | D74: 999 | E74: 106 | F74: =SUMIF(I$3:N$3,$F$3,I74:N74) -> 0 | G74: =IF(ISERROR(F74/H74),0,F74/H74) -> 0 | H74: =SUMIF(I$3:N$3,$H$3,I74:N74) -> 0 | I74: =IFERROR(INDEX(別紙_テンプレート_DB!$P$3:$P$65423,MATCH($D74&"-"&I$2&"-"&$E74,INDEX(別紙_テンプレート_DB!$J$3:$J$65423&"-"&別紙_テンプレート_DB!$M$3:$M$65423&"-"&別紙_テンプレート_DB!$N$3:$N$65423,),0)),0) -> 0 | J74: =IF(ISERROR(I74/K74),0,I74/K74) -> 0 | K74: =IFERROR(INDEX(別紙_テンプレート_DB!$O$3:$O$65423,MATCH($D74&"-"&I$2&"-"&$E74,INDEX(別紙_テンプレート_DB!$J$3:$J$65423&"-"&別紙_テンプレート_DB!$M$3:$M$65423&"-"&別紙_テンプレート_DB!$N$3:$N$65423,),0)),0) -> 0 | L74: =IFERROR(INDEX(別紙_テンプレート_DB!$P$3:$P$65423,MATCH($D74&"-"&L$2&"-"&$E74,INDEX(別紙_テンプレート_DB!$J$3:$J$65423&"-"&別紙_テンプレート_DB!$M$3:$M$65423&"-"&別紙_テンプレート_DB!$N$3:$N$65423,),0)),0) -> 0 | M74: =IF(ISERROR(L74/N74),0,L74/N74) -> 0 | N74: =IFERROR(INDEX(別紙_テンプレート_DB!$O$3:$O$65423,MATCH($D74&"-"&L$2&"-"&$E74,INDEX(別紙_テンプレート_DB!$J$3:$J$65423&"-"&別紙_テンプレート_DB!$M$3:$M$65423&"-"&別紙_テンプレート_DB!$N$3:$N$65423,),0)),0) -> 0
B75: クレーム | D75: 999 | E75: 4 | F75: =SUMIF(I$3:N$3,$F$3,I75:N75) -> 0 | I75: =IFERROR(INDEX(別紙_テンプレート_DB!$P$3:$P$65423,MATCH($D75&"-"&I$2&"-"&$E75,INDEX(別紙_テンプレート_DB!$J$3:$J$65423&"-"&別紙_テンプレート_DB!$M$3:$M$65423&"-"&別紙_テンプレート_DB!$N$3:$N$65423,),0)),0) -> 0 | L75: =IFERROR(INDEX(別紙_テンプレート_DB!$P$3:$P$65423,MATCH($D75&"-"&L$2&"-"&$E75,INDEX(別紙_テンプレート_DB!$J$3:$J$65423&"-"&別紙_テンプレート_DB!$M$3:$M$65423&"-"&別紙_テンプレート_DB!$N$3:$N$65423,),0)),0) -> 0

Sheet 別紙_テンプレート_三和サービス
A1: 三和サービス
B2: 項目 | E2: =YEAR(H2)-1978+1&"期計" -> 43期計 | H2: 43921 | K2: 43920
E3: 原価 | G3: 売上 | H3: 原価 | J3: 売上 | K3: 原価 | M3: 売上
B4: 売/原 | E4: =SUMIF(H$3:M$3,$E$3,H4:M4) -> 0 | F4: =IF(ISERROR(E4/G4),0,E4/G4) -> 0 | G4: =SUMIF(H$3:M$3,$G$3,H4:M4) -> 0 | H4: =SUM(H11,H13,H15) -> 0 | I4: =IF(ISERROR(H4/J4),0,H4/J4) -> 0 | J4: =SUM(J11,J13,J15) -> 0 | K4: =SUM(K11,K13,K15) -> 0 | L4: =IF(ISERROR(K4/M4),0,K4/M4) -> 0 | M4: =SUM(M11,M13,M15) -> 0
B5: 昨対 | E5: =IF(ISERROR(E4/#REF!),0,IF(#REF!<=0,0,E4/#REF!)) -> 0 | H5: =IF(ISERROR(H4/#REF!),0,IF(#REF!<=0,0,H4/#REF!)) -> 0 | K5: =IF(ISERROR(K4/#REF!),0,IF(#REF!<=0,0,K4/#REF!)) -> 0
B6: 営利益 | D6: x | E6: =SUMIF(H$3:M$3,$E$3,H6:M6) -> 0 | F6: =IF(ISERROR(E6/G4),0,E6/G4) -> 0 | H6: =SUMIF($D$20:$D$54,$D$6,H$20:H$54) -> 0 | I6: =IF(ISERROR(H6/J6),0,H6/J6) -> 0 | K6: =SUMIF($D$20:$D$54,$D$6,K$20:K$54) -> 0 | L6: =IF(ISERROR(K6/M6),0,K6/M6) -> 0
B7: 昨対 | E7: =IF(ISERROR(E6/#REF!),"-",IF(OR(#REF!<=0,E6<=0),IF(E6<=#REF!,"-","+"),E6/#REF!)) -> - | G7: =IF(ISERROR(G4/#REF!),0,IF(#REF!=0,0,G4/#REF!)) -> 0 | H7: =IF(ISERROR(H6/#REF!),"-",IF(OR(#REF!<=0,H6<=0),IF(H6<=#REF!,"-","+"),H6/#REF!)) -> - | J7: =IF(ISERROR(J4/#REF!),0,IF(#REF!=0,0,J4/#REF!)) -> 0 | K7: =IF(ISERROR(K6/#REF!),"-",IF(OR(#REF!<=0,K6<=0),IF(K6<=#REF!,"-","+"),K6/#REF!)) -> - | M7: =IF(ISERROR(M4/#REF!),0,IF(#REF!=0,0,M4/#REF!)) -> 0
B8: 経利益 | D8: z | E8: =SUMIF(H$3:M$3,$E$3,H8:M8) -> 0 | F8: =IF(ISERROR(E8/G4),0,E8/G4) -> 0 | H8: =SUMIF($D$20:$D$54,$D$8,H$20:H$54) -> 0 | K8: =SUMIF($D$20:$D$54,$D$8,K$20:K$54) -> 0
B9: 昨対 | E9: =IF(ISERROR(E8/#REF!),"-",IF(OR(#REF!<=0,E8<=0),IF(E8<=#REF!,"-","+"),E8/#REF!)) -> - | H9: =IF(ISERROR(H8/#REF!),"-",IF(OR(#REF!<=0,H8<=0),IF(H8<=#REF!,"-","+"),H8/#REF!)) -> - | K9: =IF(ISERROR(K8/#REF!),"-",IF(OR(#REF!<=0,K8<=0),IF(K8<=#REF!,"-","+"),K8/#REF!)) -> -
B10: 入出庫 | E10: =SUMIF(H$3:M$3,$E$3,H10:M10) -> 0 | F10: =E10-G10 -> 0 | G10: =SUMIF(H$3:M$3,$G$3,H10:M10) -> 0
B11: 貨物 | D11: 1 | E11: =SUMIF(H$3:M$3,$E$3,H11:M11) -> 0 | F11: =IF(ISERROR(E11/G11),0,E11/G11) -> 0 | G11: =SUMIF(H$3:M$3,$G$3,H11:M11) -> 0 | H11: =SUMIF($D$26:$D$54,$D$11,H$26:H$54) -> 0 | I11: =IF(ISERROR(H11/J11),0,H11/J11) -> 0 | J11: =SUMIF($D$26:$D$54,$D$11,J$26:J$54) -> 0 | K11: =SUMIF($D$26:$D$54,$D$11,K$26:K$54) -> 0 | L11: =IF(ISERROR(K11/M11),0,K11/M11) -> 0 | M11: =SUMIF($D$26:$D$54,$D$11,M$26:M$54) -> 0
B12: 昨対 | E12: =IF(ISERROR(E11/#REF!),0,IF(#REF!<=0,0,E11/#REF!)) -> 0 | G12: =IF(ISERROR(G11/#REF!),0,IF(#REF!=0,0,G11/#REF!)) -> 0 | H12: =IF(ISERROR(H11/#REF!),0,IF(#REF!<=0,0,H11/#REF!)) -> 0 | J12: =IF(ISERROR(J11/#REF!),0,IF(#REF!=0,0,J11/#REF!)) -> 0 | K12: =IF(ISERROR(K11/#REF!),0,IF(#REF!<=0,0,K11/#REF!)) -> 0 | M12: =IF(ISERROR(M11/#REF!),0,IF(#REF!=0,0,M11/#REF!)) -> 0
B13: 物流 | D13: 2 | E13: =SUMIF(H$3:M$3,$E$3,H13:M13) -> 0 | F13: =IF(ISERROR(E13/G13),0,E13/G13) -> 0 | G13: =SUMIF(H$3:M$3,$G$3,H13:M13) -> 0 | H13: =SUMIF($D$26:$D$54,$D$13,H$26:H$54) -> 0 | I13: =IF(ISERROR(H13/J13),0,H13/J13) -> 0 | J13: =SUMIF($D$26:$D$54,$D$13,J$26:J$54) -> 0 | K13: =SUMIF($D$26:$D$54,$D$13,K$26:K$54) -> 0 | L13: =IF(ISERROR(K13/M13),0,K13/M13) -> 0 | M13: =SUMIF($D$26:$D$54,$D$13,M$26:M$54) -> 0
B14: 昨対 | E14: =IF(ISERROR(E13/#REF!),0,IF(#REF!<=0,0,E13/#REF!)) -> 0 | G14: =IF(ISERROR(G13/#REF!),0,IF(#REF!=0,0,G13/#REF!)) -> 0 | H14: =IF(ISERROR(H13/#REF!),0,IF(#REF!<=0,0,H13/#REF!)) -> 0 | J14: =IF(ISERROR(J13/#REF!),0,IF(#REF!=0,0,J13/#REF!)) -> 0 | K14: =IF(ISERROR(K13/#REF!),0,IF(#REF!<=0,0,K13/#REF!)) -> 0 | M14: =IF(ISERROR(M13/#REF!),0,IF(#REF!=0,0,M13/#REF!)) -> 0
B15: 事故 | D15: 9 | E15: =SUMIF(H$3:M$3,$E$3,H15:M15) -> 0 | F15: =IF(ISERROR(E15/G15),0,E15/G15) -> 0 | G15: =SUMIF(H$3:M$3,$G$3,H15:M15) -> 0 | H15: =SUMIF($D$26:$D$54,$D$15,H$26:H$54) -> 0 | I15: =IF(ISERROR(H15/J15),0,H15/J15) -> 0 | J15: =SUMIF($D$26:$D$54,$D$15,J$26:J$54) -> 0 | K15: =SUMIF($D$26:$D$54,$D$15,K$26:K$54) -> 0 | L15: =IF(ISERROR(K15/M15),0,K15/M15) -> 0 | M15: =SUMIF($D$26:$D$54,$D$15,M$26:M$54) -> 0
B16: 昨対 | E16: =IF(ISERROR(E15/#REF!),0,IF(#REF!<=0,0,E15/#REF!)) -> 0 | G16: =IF(ISERROR(G15/#REF!),0,IF(#REF!=0,0,G15/#REF!)) -> 0 | H16: =IF(ISERROR(H15/#REF!),0,IF(#REF!<=0,0,H15/#REF!)) -> 0 | J16: =IF(ISERROR(J15/#REF!),0,IF(#REF!=0,0,J15/#REF!)) -> 0 | K16: =IF(ISERROR(K15/#REF!),0,IF(#REF!<=0,0,K15/#REF!)) -> 0 | M16: =IF(ISERROR(M15/#REF!),0,IF(#REF!=0,0,M15/#REF!)) -> 0
B17: 予測 | E17: =SUMIF(H$3:M$3,$E$3,H17:M17) -> 0 | F17: =IF(ISERROR(E17/G17),0,E17/G17) -> 0 | G17: =SUMIF(H$3:M$3,$G$3,H17:M17) -> 0 | H17: =H42+H55 -> 0 | I17: =IF(ISERROR(H17/J17),0,H17/J17) -> 0 | J17: =J42+J55 -> 0 | K17: =K42+K55 -> 0 | L17: =IF(ISERROR(K17/M17),0,K17/M17) -> 0 | M17: =M42+M55 -> 0
B18: 差異 | E18: =E4-E17 -> 0 | F18: =IF(ISERROR(E18/G18),0,E18/G18) -> 0 | G18: =G4-G17 -> 0 | H18: =H4-H17 -> 0 | I18: =IF(ISERROR(H18/J18),0,H18/J18) -> 0 | J18: =J4-J17 -> 0 | K18: =K4-K17 -> 0 | L18: =IF(ISERROR(K18/M18),0,K18/M18) -> 0 | M18: =M4-M17 -> 0
B19: 貨物
B20: 売/原 | E20: =SUMIF(H$3:M$3,$E$3,H20:M20) -> 0 | F20: =IF(ISERROR(E20/G20),0,E20/G20) -> 0 | G20: =SUMIF(H$3:M$3,$G$3,H20:M20) -> 0 | H20: =SUM(H26,H34) -> 0 | I20: =IF(ISERROR(H20/J20),0,H20/J20) -> 0 | J20: =SUM(J26,J34) -> 0 | K20: =SUM(K26,K34) -> 0 | L20: =IF(ISERROR(K20/M20),0,K20/M20) -> 0 | M20: =SUM(M26,M34) -> 0
B21: 昨対 | E21: =IF(ISERROR(E20/#REF!),0,IF(#REF!<=0,0,E20/#REF!)) -> 0 | H21: =IF(ISERROR(H20/#REF!),0,IF(#REF!<=0,0,H20/#REF!)) -> 0 | K21: =IF(ISERROR(K20/#REF!),0,IF(#REF!<=0,0,K20/#REF!)) -> 0
B22: 営利益 | D22: x | E22: =SUMIF(H$3:M$3,$E$3,H22:M22) -> 0 | F22: =IF(ISERROR(E22/G20),0,E22/G20) -> 0 | H22: =J20-H20-(IFERROR(INDEX(別紙_テンプレート_DB!サービス_人件一般費_貨物,MATCH(H$2,INDEX(別紙_テンプレート_DB!サービス_年月,),0)),0)) -> 0 | I22: =IF(ISERROR(H22/J20),0,H22/J20) -> 0 | K22: =M20-K20-(IFERROR(INDEX(別紙_テンプレート_DB!サービス_人件一般費_貨物,MATCH(K$2,INDEX(別紙_テンプレート_DB!サービス_年月,),0)),0)) -> 0 | L22: =IF(ISERROR(K22/M20),0,K22/M20) -> 0
B23: 昨対 | E23: =IF(ISERROR(E22/#REF!),"-",IF(OR(#REF!<=0,E22<=0),IF(E22<=#REF!,"-","+"),E22/#REF!)) -> - | G23: =IF(ISERROR(G20/#REF!),0,IF(#REF!=0,0,G20/#REF!)) -> 0 | H23: =IF(ISERROR(H22/#REF!),"-",IF(OR(#REF!<=0,H22<=0),IF(H22<=#REF!,"-","+"),H22/#REF!)) -> - | J23: =IF(ISERROR(J20/#REF!),0,IF(#REF!=0,0,J20/#REF!)) -> 0 | K23: =IF(ISERROR(K22/#REF!),"-",IF(OR(#REF!<=0,K22<=0),IF(K22<=#REF!,"-","+"),K22/#REF!)) -> - | M23: =IF(ISERROR(M20/#REF!),0,IF(#REF!=0,0,M20/#REF!)) -> 0
B24: 経利益 | D24: ｚ | E24: =SUMIF(H$3:M$3,$E$3,H24:M24) -> 0 | F24: =IF(ISERROR(E24/G20),0,E24/G20) -> 0 | H24: =J20-H20-(IFERROR(INDEX(別紙_テンプレート_DB!サービス_人件一般費_貨物,MATCH(H$2,INDEX(別紙_テンプレート_DB!サービス_年月,),0)),0))-(IFERROR(INDEX(別紙_テンプレート_DB!サービス_営業外費_貨物,MATCH(H$2,INDEX(別紙_テンプレート_DB!サービス_年月,),0)),0)) -> 0 | K24: =M20-K20-(IFERROR(INDEX(別紙_テンプレート_DB!サービス_人件一般費_貨物,MATCH(K$2,INDEX(別紙_テンプレート_DB!サービス_年月,),0)),0))-(IFERROR(INDEX(別紙_テンプレート_DB!サービス_営業外費_貨物,MATCH(K$2,INDEX(別紙_テンプレート_DB!サービス_年月,),0)),0)) -> 0
B25: 昨対 | E25: =IF(ISERROR(E24/#REF!),"-",IF(OR(#REF!<=0,E24<=0),IF(E24<=#REF!,"-","+"),E24/#REF!)) -> - | H25: =IF(ISERROR(H24/#REF!),"-",IF(OR(#REF!<=0,H24<=0),IF(H24<=#REF!,"-","+"),H24/#REF!)) -> - | K25: =IF(ISERROR(K24/#REF!),"-",IF(OR(#REF!<=0,K24<=0),IF(K24<=#REF!,"-","+"),K24/#REF!)) -> -
B26: 自 社 | D26: 0 | E26: =SUMIF(H$3:M$3,$E$3,H26:M26) -> 0 | F26: =IF(ISERROR(E26/G26),0,E26/G26) -> 0 | G26: =SUMIF(H$3:M$3,$G$3,H26:M26) -> 0 | H26: =SUM(H27:H33) -> 0 | I26: =IF(ISERROR(H26/J26),0,H26/J26) -> 0 | J26: =SUM(J27:J33) -> 0 | K26: =SUM(K27:K33) -> 0 | L26: =IF(ISERROR(K26/M26),0,K26/M26) -> 0 | M26: =SUM(M27:M33) -> 0
B27: 三和商研 | D27: 1 | E27: =SUMIF(H$3:M$3,$E$3,H27:M27) -> 0 | F27: =IF(ISERROR(E27/G27),0,E27/G27) -> 0 | G27: =SUMIF(H$3:M$3,$G$3,H27:M27) -> 0 | H27: =IFERROR(INDEX(別紙_テンプレート_DB!サービス_原額_貨物自_三商,MATCH(H$2,INDEX(別紙_テンプレート_DB!サービス_年月,),0)),0) -> 0 | I27: =IF(ISERROR(H27/J27),0,H27/J27) -> 0 | J27: =IFERROR(INDEX(別紙_テンプレート_DB!サービス_売額_貨物自_三商,MATCH(H$2,INDEX(別紙_テンプレート_DB!サービス_年月,),0)),0) -> 0 | K27: =IFERROR(INDEX(別紙_テンプレート_DB!サービス_原額_貨物自_三商,MATCH(K$2,INDEX(別紙_テンプレート_DB!サービス_年月,),0)),0) -> 0 | L27: =IF(ISERROR(K27/M27),0,K27/M27) -> 0 | M27: =IFERROR(INDEX(別紙_テンプレート_DB!サービス_売額_貨物自_三商,MATCH(K$2,INDEX(別紙_テンプレート_DB!サービス_年月,),0)),0) -> 0
B28: 店装技研 | D28: 1 | E28: =SUMIF(H$3:M$3,$E$3,H28:M28) -> 0 | F28: =IF(ISERROR(E28/G28),0,E28/G28) -> 0 | G28: =SUMIF(H$3:M$3,$G$3,H28:M28) -> 0 | H28: =IFERROR(INDEX(別紙_テンプレート_DB!サービス_原額_貨物自_店装,MATCH(H$2,INDEX(別紙_テンプレート_DB!サービス_年月,),0)),0) -> 0 | I28: =IF(ISERROR(H28/J28),0,H28/J28) -> 0 | J28: =IFERROR(INDEX(別紙_テンプレート_DB!サービス_売額_貨物自_店装,MATCH(H$2,INDEX(別紙_テンプレート_DB!サービス_年月,),0)),0) -> 0 | K28: =IFERROR(INDEX(別紙_テンプレート_DB!サービス_原額_貨物自_店装,MATCH(K$2,INDEX(別紙_テンプレート_DB!サービス_年月,),0)),0) -> 0 | L28: =IF(ISERROR(K28/M28),0,K28/M28) -> 0 | M28: =IFERROR(INDEX(別紙_テンプレート_DB!サービス_売額_貨物自_店装,MATCH(K$2,INDEX(別紙_テンプレート_DB!サービス_年月,),0)),0) -> 0
B29: ｻﾝﾜﾌﾟﾗﾝﾆﾝｸﾞ | D29: 1 | E29: =SUMIF(H$3:M$3,$E$3,H29:M29) -> 0 | F29: =IF(ISERROR(E29/G29),0,E29/G29) -> 0 | G29: =SUMIF(H$3:M$3,$G$3,H29:M29) -> 0 | H29: =IFERROR(INDEX(別紙_テンプレート_DB!サービス_原額_貨物自_サンプラ,MATCH(H$2,INDEX(別紙_テンプレート_DB!サービス_年月,),0)),0) -> 0 | I29: =IF(ISERROR(H29/J29),0,H29/J29) -> 0 | J29: =IFERROR(INDEX(別紙_テンプレート_DB!サービス_売額_貨物自_サンプラ,MATCH(H$2,INDEX(別紙_テンプレート_DB!サービス_年月,),0)),0) -> 0 | K29: =IFERROR(INDEX(別紙_テンプレート_DB!サービス_原額_貨物自_サンプラ,MATCH(K$2,INDEX(別紙_テンプレート_DB!サービス_年月,),0)),0) -> 0 | L29: =IF(ISERROR(K29/M29),0,K29/M29) -> 0 | M29: =IFERROR(INDEX(別紙_テンプレート_DB!サービス_売額_貨物自_サンプラ,MATCH(K$2,INDEX(別紙_テンプレート_DB!サービス_年月,),0)),0) -> 0
B30: トランコム | D30: 1 | E30: =SUMIF(H$3:M$3,$E$3,H30:M30) -> 0 | F30: =IF(ISERROR(E30/G30),0,E30/G30) -> 0 | G30: =SUMIF(H$3:M$3,$G$3,H30:M30) -> 0 | H30: =IFERROR(INDEX(別紙_テンプレート_DB!サービス_原額_貨物自_トラン,MATCH(H$2,INDEX(別紙_テンプレート_DB!サービス_年月,),0)),0) -> 0 | I30: =IF(ISERROR(H30/J30),0,H30/J30) -> 0 | J30: =IFERROR(INDEX(別紙_テンプレート_DB!サービス_売額_貨物自_トラン,MATCH(H$2,INDEX(別紙_テンプレート_DB!サービス_年月,),0)),0) -> 0 | K30: =IFERROR(INDEX(別紙_テンプレート_DB!サービス_原額_貨物自_トラン,MATCH(K$2,INDEX(別紙_テンプレート_DB!サービス_年月,),0)),0) -> 0 | L30: =IF(ISERROR(K30/M30),0,K30/M30) -> 0 | M30: =IFERROR(INDEX(別紙_テンプレート_DB!サービス_売額_貨物自_トラン,MATCH(K$2,INDEX(別紙_テンプレート_DB!サービス_年月,),0)),0) -> 0
B31: 日本運輸荷造 | D31: 1 | E31: =SUMIF(H$3:M$3,$E$3,H31:M31) -> 0 | F31: =IF(ISERROR(E31/G31),0,E31/G31) -> 0 | G31: =SUMIF(H$3:M$3,$G$3,H31:M31) -> 0 | H31: =IFERROR(INDEX(別紙_テンプレート_DB!サービス_原額_貨物自_三シャ,MATCH(H$2,INDEX(別紙_テンプレート_DB!サービス_年月,),0)),0) -> 0 | I31: =IF(ISERROR(H31/J31),0,H31/J31) -> 0 | J31: =IFERROR(INDEX(別紙_テンプレート_DB!サービス_売額_貨物自_三シャ,MATCH(H$2,INDEX(別紙_テンプレート_DB!サービス_年月,),0)),0) -> 0 | K31: =IFERROR(INDEX(別紙_テンプレート_DB!サービス_原額_貨物自_三シャ,MATCH(K$2,INDEX(別紙_テンプレート_DB!サービス_年月,),0)),0) -> 0 | L31: =IF(ISERROR(K31/M31),0,K31/M31) -> 0 | M31: =IFERROR(INDEX(別紙_テンプレート_DB!サービス_売額_貨物自_三シャ,MATCH(K$2,INDEX(別紙_テンプレート_DB!サービス_年月,),0)),0) -> 0
B32: その他 | D32: 1 | E32: =SUMIF(H$3:M$3,$E$3,H32:M32) -> 0 | F32: =IF(ISERROR(E32/G32),0,E32/G32) -> 0 | G32: =SUMIF(H$3:M$3,$G$3,H32:M32) -> 0 | H32: =IFERROR(INDEX(別紙_テンプレート_DB!サービス_原額_貨物自_その他,MATCH(H$2,INDEX(別紙_テンプレート_DB!サービス_年月,),0)),0) -> 0 | I32: =IF(ISERROR(H32/J32),0,H32/J32) -> 0 | J32: =IFERROR(INDEX(別紙_テンプレート_DB!サービス_売額_貨物自_その他,MATCH(H$2,INDEX(別紙_テンプレート_DB!サービス_年月,),0)),0) -> 0 | K32: =IFERROR(INDEX(別紙_テンプレート_DB!サービス_原額_貨物自_その他,MATCH(K$2,INDEX(別紙_テンプレート_DB!サービス_年月,),0)),0) -> 0 | L32: =IF(ISERROR(K32/M32),0,K32/M32) -> 0 | M32: =IFERROR(INDEX(別紙_テンプレート_DB!サービス_売額_貨物自_その他,MATCH(K$2,INDEX(別紙_テンプレート_DB!サービス_年月,),0)),0) -> 0
B33: 事故 | D33: 9 | E33: =SUMIF(H$3:M$3,$E$3,H33:M33) -> 0 | F33: =IF(ISERROR(E33/G33),0,E33/G33) -> 0 | G33: =SUMIF(H$3:M$3,$G$3,H33:M33) -> 0 | H33: =IFERROR(INDEX(別紙_テンプレート_DB!サービス_原額_貨物自_事故,MATCH(H$2,INDEX(別紙_テンプレート_DB!サービス_年月,),0)),0) -> 0 | I33: =IF(ISERROR(H33/J33),0,H33/J33) -> 0 | J33: =IFERROR(INDEX(別紙_テンプレート_DB!サービス_売額_貨物自_事故,MATCH(H$2,INDEX(別紙_テンプレート_DB!サービス_年月,),0)),0) -> 0 | K33: =IFERROR(INDEX(別紙_テンプレート_DB!サービス_原額_貨物自_事故,MATCH(K$2,INDEX(別紙_テンプレート_DB!サービス_年月,),0)),0) -> 0 | L33: =IF(ISERROR(K33/M33),0,K33/M33) -> 0 | M33: =IFERROR(INDEX(別紙_テンプレート_DB!サービス_売額_貨物自_事故,MATCH(K$2,INDEX(別紙_テンプレート_DB!サービス_年月,),0)),0) -> 0
B34: 庸 車 | D34: 0 | E34: =SUMIF(H$3:M$3,$E$3,H34:M34) -> 0 | F34: =IF(ISERROR(E34/G34),0,E34/G34) -> 0 | G34: =SUMIF(H$3:M$3,$G$3,H34:M34) -> 0 | H34: =SUM(H35:H41) -> 0 | I34: =IF(ISERROR(H34/J34),0,H34/J34) -> 0 | J34: =SUM(J35:J41) -> 0 | K34: =SUM(K35:K41) -> 0 | L34: =IF(ISERROR(K34/M34),0,K34/M34) -> 0 | M34: =SUM(M35:M41) -> 0
B35: 三和商研 | D35: 1 | E35: =SUMIF(H$3:M$3,$E$3,H35:M35) -> 0 | F35: =IF(ISERROR(E35/G35),0,E35/G35) -> 0 | G35: =SUMIF(H$3:M$3,$G$3,H35:M35) -> 0 | H35: =IFERROR(INDEX(別紙_テンプレート_DB!サービス_原額_貨物庸_三商,MATCH(H$2,INDEX(別紙_テンプレート_DB!サービス_年月,),0)),0) -> 0 | I35: =IF(ISERROR(H35/J35),0,H35/J35) -> 0 | J35: =IFERROR(INDEX(別紙_テンプレート_DB!サービス_売額_貨物庸_三商,MATCH(H$2,INDEX(別紙_テンプレート_DB!サービス_年月,),0)),0) -> 0 | K35: =IFERROR(INDEX(別紙_テンプレート_DB!サービス_原額_貨物庸_三商,MATCH(K$2,INDEX(別紙_テンプレート_DB!サービス_年月,),0)),0) -> 0 | L35: =IF(ISERROR(K35/M35),0,K35/M35) -> 0 | M35: =IFERROR(INDEX(別紙_テンプレート_DB!サービス_売額_貨物庸_三商,MATCH(K$2,INDEX(別紙_テンプレート_DB!サービス_年月,),0)),0) -> 0
B36: 店装技研 | D36: 1 | E36: =SUMIF(H$3:M$3,$E$3,H36:M36) -> 0 | F36: =IF(ISERROR(E36/G36),0,E36/G36) -> 0 | G36: =SUMIF(H$3:M$3,$G$3,H36:M36) -> 0 | H36: =IFERROR(INDEX(別紙_テンプレート_DB!サービス_原額_貨物庸_店装,MATCH(H$2,INDEX(別紙_テンプレート_DB!サービス_年月,),0)),0) -> 0 | I36: =IF(ISERROR(H36/J36),0,H36/J36) -> 0 | J36: =IFERROR(INDEX(別紙_テンプレート_DB!サービス_売額_貨物庸_店装,MATCH(H$2,INDEX(別紙_テンプレート_DB!サービス_年月,),0)),0) -> 0 | K36: =IFERROR(INDEX(別紙_テンプレート_DB!サービス_原額_貨物庸_店装,MATCH(K$2,INDEX(別紙_テンプレート_DB!サービス_年月,),0)),0) -> 0 | L36: =IF(ISERROR(K36/M36),0,K36/M36) -> 0 | M36: =IFERROR(INDEX(別紙_テンプレート_DB!サービス_売額_貨物庸_店装,MATCH(K$2,INDEX(別紙_テンプレート_DB!サービス_年月,),0)),0) -> 0
B37: ｻﾝﾜﾌﾟﾗﾝﾆﾝｸﾞ | D37: 1 | E37: =SUMIF(H$3:M$3,$E$3,H37:M37) -> 0 | F37: =IF(ISERROR(E37/G37),0,E37/G37) -> 0 | G37: =SUMIF(H$3:M$3,$G$3,H37:M37) -> 0 | H37: =IFERROR(INDEX(別紙_テンプレート_DB!サービス_原額_貨物庸_サンプラ,MATCH(H$2,INDEX(別紙_テンプレート_DB!サービス_年月,),0)),0) -> 0 | I37: =IF(ISERROR(H37/J37),0,H37/J37) -> 0 | J37: =IFERROR(INDEX(別紙_テンプレート_DB!サービス_売額_貨物庸_サンプラ,MATCH(H$2,INDEX(別紙_テンプレート_DB!サービス_年月,),0)),0) -> 0 | K37: =IFERROR(INDEX(別紙_テンプレート_DB!サービス_原額_貨物庸_サンプラ,MATCH(K$2,INDEX(別紙_テンプレート_DB!サービス_年月,),0)),0) -> 0 | L37: =IF(ISERROR(K37/M37),0,K37/M37) -> 0 | M37: =IFERROR(INDEX(別紙_テンプレート_DB!サービス_売額_貨物庸_サンプラ,MATCH(K$2,INDEX(別紙_テンプレート_DB!サービス_年月,),0)),0) -> 0
B38: トランコム | D38: 1 | E38: =SUMIF(H$3:M$3,$E$3,H38:M38) -> 0 | F38: =IF(ISERROR(E38/G38),0,E38/G38) -> 0 | G38: =SUMIF(H$3:M$3,$G$3,H38:M38) -> 0 | H38: =IFERROR(INDEX(別紙_テンプレート_DB!サービス_原額_貨物庸_トラン,MATCH(H$2,INDEX(別紙_テンプレート_DB!サービス_年月,),0)),0) -> 0 | I38: =IF(ISERROR(H38/J38),0,H38/J38) -> 0 | J38: =IFERROR(INDEX(別紙_テンプレート_DB!サービス_売額_貨物庸_トラン,MATCH(H$2,INDEX(別紙_テンプレート_DB!サービス_年月,),0)),0) -> 0 | K38: =IFERROR(INDEX(別紙_テンプレート_DB!サービス_原額_貨物庸_トラン,MATCH(K$2,INDEX(別紙_テンプレート_DB!サービス_年月,),0)),0) -> 0 | L38: =IF(ISERROR(K38/M38),0,K38/M38) -> 0 | M38: =IFERROR(INDEX(別紙_テンプレート_DB!サービス_売額_貨物庸_トラン,MATCH(K$2,INDEX(別紙_テンプレート_DB!サービス_年月,),0)),0) -> 0
B39: 日本運輸荷造 | D39: 1 | E39: =SUMIF(H$3:M$3,$E$3,H39:M39) -> 0 | F39: =IF(ISERROR(E39/G39),0,E39/G39) -> 0 | G39: =SUMIF(H$3:M$3,$G$3,H39:M39) -> 0 | H39: =IFERROR(INDEX(別紙_テンプレート_DB!サービス_原額_貨物庸_三シャ,MATCH(H$2,INDEX(別紙_テンプレート_DB!サービス_年月,),0)),0) -> 0 | I39: =IF(ISERROR(H39/J39),0,H39/J39) -> 0 | J39: =IFERROR(INDEX(別紙_テンプレート_DB!サービス_売額_貨物庸_三シャ,MATCH(H$2,INDEX(別紙_テンプレート_DB!サービス_年月,),0)),0) -> 0 | K39: =IFERROR(INDEX(別紙_テンプレート_DB!サービス_原額_貨物庸_三シャ,MATCH(K$2,INDEX(別紙_テンプレート_DB!サービス_年月,),0)),0) -> 0 | L39: =IF(ISERROR(K39/M39),0,K39/M39) -> 0 | M39: =IFERROR(INDEX(別紙_テンプレート_DB!サービス_売額_貨物庸_三シャ,MATCH(K$2,INDEX(別紙_テンプレート_DB!サービス_年月,),0)),0) -> 0
B40: その他 | D40: 1 | E40: =SUMIF(H$3:M$3,$E$3,H40:M40) -> 0 | F40: =IF(ISERROR(E40/G40),0,E40/G40) -> 0 | G40: =SUMIF(H$3:M$3,$G$3,H40:M40) -> 0 | H40: =IFERROR(INDEX(別紙_テンプレート_DB!サービス_原額_貨物庸_その他,MATCH(H$2,INDEX(別紙_テンプレート_DB!サービス_年月,),0)),0) -> 0 | I40: =IF(ISERROR(H40/J40),0,H40/J40) -> 0 | J40: =IFERROR(INDEX(別紙_テンプレート_DB!サービス_売額_貨物庸_その他,MATCH(H$2,INDEX(別紙_テンプレート_DB!サービス_年月,),0)),0) -> 0 | K40: =IFERROR(INDEX(別紙_テンプレート_DB!サービス_原額_貨物庸_その他,MATCH(K$2,INDEX(別紙_テンプレート_DB!サービス_年月,),0)),0) -> 0 | L40: =IF(ISERROR(K40/M40),0,K40/M40) -> 0 | M40: =IFERROR(INDEX(別紙_テンプレート_DB!サービス_売額_貨物庸_その他,MATCH(K$2,INDEX(別紙_テンプレート_DB!サービス_年月,),0)),0) -> 0
B41: 事故 | D41: 9 | E41: =SUMIF(H$3:M$3,$E$3,H41:M41) -> 0 | F41: =IF(ISERROR(E41/G41),0,E41/G41) -> 0 | G41: =SUMIF(H$3:M$3,$G$3,H41:M41) -> 0 | H41: =IFERROR(INDEX(別紙_テンプレート_DB!サービス_原額_貨物庸_事故,MATCH(H$2,INDEX(別紙_テンプレート_DB!サービス_年月,),0)),0) -> 0 | I41: =IF(ISERROR(H41/J41),0,H41/J41) -> 0 | J41: =IFERROR(INDEX(別紙_テンプレート_DB!サービス_売額_貨物庸_事故,MATCH(H$2,INDEX(別紙_テンプレート_DB!サービス_年月,),0)),0) -> 0 | K41: =IFERROR(INDEX(別紙_テンプレート_DB!サービス_原額_貨物庸_事故,MATCH(K$2,INDEX(別紙_テンプレート_DB!サービス_年月,),0)),0) -> 0 | L41: =IF(ISERROR(K41/M41),0,K41/M41) -> 0 | M41: =IFERROR(INDEX(別紙_テンプレート_DB!サービス_売額_貨物庸_事故,MATCH(K$2,INDEX(別紙_テンプレート_DB!サービス_年月,),0)),0) -> 0
B42: 予測 | E42: =SUMIF(H$3:M$3,$E$3,H42:M42) -> 0 | F42: =IF(ISERROR(E42/G42),0,E42/G42) -> 0 | G42: =SUMIF(H$3:M$3,$G$3,H42:M42) -> 0 | H42: =IFERROR(INDEX(別紙_テンプレート_DB!サービス予測_予測原価金額_貨物,MATCH(H$2,INDEX(別紙_テンプレート_DB!サービス予測_年月,),0)),0) -> 0 | I42: =IF(ISERROR(H42/J42),0,H42/J42) -> 0 | J42: =IFERROR(INDEX(別紙_テンプレート_DB!サービス予測_予測売上金額_貨物,MATCH(H$2,INDEX(別紙_テンプレート_DB!サービス予測_年月,),0)),0) -> 0 | K42: =IFERROR(INDEX(別紙_テンプレート_DB!サービス予測_予測原価金額_貨物,MATCH(K$2,INDEX(別紙_テンプレート_DB!サービス予測_年月,),0)),0) -> 0 | L42: =IF(ISERROR(K42/M42),0,K42/M42) -> 0 | M42: =IFERROR(INDEX(別紙_テンプレート_DB!サービス予測_予測売上金額_貨物,MATCH(K$2,INDEX(別紙_テンプレート_DB!サービス予測_年月,),0)),0) -> 0
B43: 差異 | E43: =$E$20-E42 -> 0 | F43: =IF(ISERROR(E43/G43),0,E43/G43) -> 0 | G43: =G20-G42 -> 0 | H43: =H20-H42 -> 0 | I43: =IF(ISERROR(H43/J43),0,H43/J43) -> 0 | J43: =J20-J42 -> 0 | K43: =K20-K42 -> 0 | L43: =IF(ISERROR(K43/M43),0,K43/M43) -> 0 | M43: =M20-M42 -> 0
B44: 物流
B45: 売/原 | E45: =SUMIF(H$3:M$3,$E$3,H45:M45) -> 0 | F45: =IF(ISERROR(E45/G45),0,E45/G45) -> 0 | G45: =SUMIF(H$3:M$3,$G$3,H45:M45) -> 0 | H45: =SUM(H51:H54) -> 0 | I45: =IF(ISERROR(H45/J45),0,H45/J45) -> 0 | J45: =SUM(J51:J54) -> 0 | K45: =SUM(K51:K54) -> 0 | L45: =IF(ISERROR(K45/M45),0,K45/M45) -> 0 | M45: =SUM(M51:M54) -> 0
B46: 昨対 | E46: =IF(ISERROR(E45/#REF!),0,IF(#REF!<=0,0,E45/#REF!)) -> 0 | H46: =IF(ISERROR(H45/#REF!),0,IF(#REF!<=0,0,H45/#REF!)) -> 0 | K46: =IF(ISERROR(K45/#REF!),0,IF(#REF!<=0,0,K45/#REF!)) -> 0
B47: 営利益 | D47: x | E47: =SUMIF(H$3:M$3,$E$3,H47:M47) -> 0 | F47: =IF(ISERROR(E47/G45),0,E47/G45) -> 0 | H47: =J45-H45-(IFERROR(INDEX(別紙_テンプレート_DB!サービス_人件一般費_物流,MATCH(H$2,INDEX(別紙_テンプレート_DB!サービス_年月,),0)),0)) -> 0 | I47: =IF(ISERROR(H47/J45),0,H47/J45) -> 0 | K47: =M45-K45-(IFERROR(INDEX(別紙_テンプレート_DB!サービス_人件一般費_物流,MATCH(K$2,INDEX(別紙_テンプレート_DB!サービス_年月,),0)),0)) -> 0 | L47: =IF(ISERROR(K47/M45),0,K47/M45) -> 0
B48: 昨対 | E48: =IF(ISERROR(E47/#REF!),"-",IF(OR(#REF!<=0,E47<=0),IF(E47<=#REF!,"-","+"),E47/#REF!)) -> - | G48: =IF(ISERROR(G45/#REF!),0,IF(#REF!=0,0,G45/#REF!)) -> 0 | H48: =IF(ISERROR(H47/#REF!),"-",IF(OR(#REF!<=0,H47<=0),IF(H47<=#REF!,"-","+"),H47/#REF!)) -> - | J48: =IF(ISERROR(J45/#REF!),0,IF(#REF!=0,0,J45/#REF!)) -> 0 | K48: =IF(ISERROR(K47/#REF!),"-",IF(OR(#REF!<=0,K47<=0),IF(K47<=#REF!,"-","+"),K47/#REF!)) -> - | M48: =IF(ISERROR(M45/#REF!),0,IF(#REF!=0,0,M45/#REF!)) -> 0
B49: 経利益 | D49: z | E49: =SUMIF(H$3:M$3,$E$3,H49:M49) -> 0 | F49: =IF(ISERROR(E49/G45),0,E49/G45) -> 0 | H49: =J45-H45-(IFERROR(INDEX(別紙_テンプレート_DB!サービス_人件一般費_物流,MATCH(H$2,INDEX(別紙_テンプレート_DB!サービス_年月,),0)),0))-(IFERROR(INDEX(別紙_テンプレート_DB!サービス_営業外費_物流,MATCH(H$2,INDEX(別紙_テンプレート_DB!サービス_年月,),0)),0)) -> 0 | K49: =M45-K45-(IFERROR(INDEX(別紙_テンプレート_DB!サービス_人件一般費_物流,MATCH(K$2,INDEX(別紙_テンプレート_DB!サービス_年月,),0)),0))-(IFERROR(INDEX(別紙_テンプレート_DB!サービス_営業外費_物流,MATCH(K$2,INDEX(別紙_テンプレート_DB!サービス_年月,),0)),0)) -> 0
B50: 昨対 | E50: =IF(ISERROR(E49/#REF!),"-",IF(OR(#REF!<=0,E49<=0),IF(E49<=#REF!,"-","+"),E49/#REF!)) -> - | H50: =IF(ISERROR(H49/#REF!),"-",IF(OR(#REF!<=0,H49<=0),IF(H49<=#REF!,"-","+"),H49/#REF!)) -> - | K50: =IF(ISERROR(K49/#REF!),"-",IF(OR(#REF!<=0,K49<=0),IF(K49<=#REF!,"-","+"),K49/#REF!)) -> -
B51: ﾙｰﾄｻｰﾋﾞｽ | D51: 2 | E51: =SUMIF(H$3:M$3,$E$3,H51:M51) -> 0 | F51: =IF(ISERROR(E51/G51),0,E51/G51) -> 0 | G51: =SUMIF(H$3:M$3,$G$3,H51:M51) -> 0 | H51: =IFERROR(INDEX(別紙_テンプレート_DB!サービス_原額_物流_ルート,MATCH(H$2,INDEX(別紙_テンプレート_DB!サービス_年月,),0)),0) -> 0 | I51: =IF(ISERROR(H51/J51),0,H51/J51) -> 0 | J51: =IFERROR(INDEX(別紙_テンプレート_DB!サービス_売額_物流_ルート,MATCH(H$2,INDEX(別紙_テンプレート_DB!サービス_年月,),0)),0) -> 0 | K51: =IFERROR(INDEX(別紙_テンプレート_DB!サービス_原額_物流_ルート,MATCH(K$2,INDEX(別紙_テンプレート_DB!サービス_年月,),0)),0) -> 0 | L51: =IF(ISERROR(K51/M51),0,K51/M51) -> 0 | M51: =IFERROR(INDEX(別紙_テンプレート_DB!サービス_売額_物流_ルート,MATCH(K$2,INDEX(別紙_テンプレート_DB!サービス_年月,),0)),0) -> 0
B52: 丸和運輸 | D52: 2 | E52: =SUMIF(H$3:M$3,$E$3,H52:M52) -> 0 | F52: =IF(ISERROR(E52/G52),0,E52/G52) -> 0 | G52: =SUMIF(H$3:M$3,$G$3,H52:M52) -> 0 | H52: =IFERROR(INDEX(別紙_テンプレート_DB!サービス_原額_物流_丸和,MATCH(H$2,INDEX(別紙_テンプレート_DB!サービス_年月,),0)),0) -> 0 | I52: =IF(ISERROR(H52/J52),0,H52/J52) -> 0 | J52: =IFERROR(INDEX(別紙_テンプレート_DB!サービス_売額_物流_丸和,MATCH(H$2,INDEX(別紙_テンプレート_DB!サービス_年月,),0)),0) -> 0 | K52: =IFERROR(INDEX(別紙_テンプレート_DB!サービス_原額_物流_丸和,MATCH(K$2,INDEX(別紙_テンプレート_DB!サービス_年月,),0)),0) -> 0 | L52: =IF(ISERROR(K52/M52),0,K52/M52) -> 0 | M52: =IFERROR(INDEX(別紙_テンプレート_DB!サービス_売額_物流_丸和,MATCH(K$2,INDEX(別紙_テンプレート_DB!サービス_年月,),0)),0) -> 0
B53: その他 | D53: 2 | E53: =SUMIF(H$3:M$3,$E$3,H53:M53) -> 0 | F53: =IF(ISERROR(E53/G53),0,E53/G53) -> 0 | G53: =SUMIF(H$3:M$3,$G$3,H53:M53) -> 0 | H53: =IFERROR(INDEX(別紙_テンプレート_DB!サービス_原額_物流_その他,MATCH(H$2,INDEX(別紙_テンプレート_DB!サービス_年月,),0)),0) -> 0 | I53: =IF(ISERROR(H53/J53),0,H53/J53) -> 0 | J53: =IFERROR(INDEX(別紙_テンプレート_DB!サービス_売額_物流_その他,MATCH(H$2,INDEX(別紙_テンプレート_DB!サービス_年月,),0)),0) -> 0 | K53: =IFERROR(INDEX(別紙_テンプレート_DB!サービス_原額_物流_その他,MATCH(K$2,INDEX(別紙_テンプレート_DB!サービス_年月,),0)),0) -> 0 | L53: =IF(ISERROR(K53/M53),0,K53/M53) -> 0 | M53: =IFERROR(INDEX(別紙_テンプレート_DB!サービス_売額_物流_その他,MATCH(K$2,INDEX(別紙_テンプレート_DB!サービス_年月,),0)),0) -> 0
B54: 事故 | D54: 9 | E54: =SUMIF(H$3:M$3,$E$3,H54:M54) -> 0 | F54: =IF(ISERROR(E54/G54),0,E54/G54) -> 0 | G54: =SUMIF(H$3:M$3,$G$3,H54:M54) -> 0 | H54: =IFERROR(INDEX(別紙_テンプレート_DB!サービス_原額_物流_事故,MATCH(H$2,INDEX(別紙_テンプレート_DB!サービス_年月,),0)),0) -> 0 | I54: =IF(ISERROR(H54/J54),0,H54/J54) -> 0 | J54: =IFERROR(INDEX(別紙_テンプレート_DB!サービス_売額_物流_事故,MATCH(H$2,INDEX(別紙_テンプレート_DB!サービス_年月,),0)),0) -> 0 | K54: =IFERROR(INDEX(別紙_テンプレート_DB!サービス_原額_物流_事故,MATCH(K$2,INDEX(別紙_テンプレート_DB!サービス_年月,),0)),0) -> 0 | L54: =IF(ISERROR(K54/M54),0,K54/M54) -> 0 | M54: =IFERROR(INDEX(別紙_テンプレート_DB!サービス_売額_物流_事故,MATCH(K$2,INDEX(別紙_テンプレート_DB!サービス_年月,),0)),0) -> 0
B55: 予測 | E55: =SUMIF(H$3:M$3,$E$3,H55:M55) -> 0 | F55: =IF(ISERROR(E55/G55),0,E55/G55) -> 0 | G55: =SUMIF(H$3:M$3,$G$3,H55:M55) -> 0 | H55: =IFERROR(INDEX(別紙_テンプレート_DB!サービス予測_予測原価金額_物流,MATCH(H$2,INDEX(別紙_テンプレート_DB!サービス予測_年月,),0)),0) -> 0 | I55: =IF(ISERROR(H55/J55),0,H55/J55) -> 0 | J55: =IFERROR(INDEX(別紙_テンプレート_DB!サービス予測_予測売上金額_物流,MATCH(H$2,INDEX(別紙_テンプレート_DB!サービス予測_年月,),0)),0) -> 0 | K55: =IFERROR(INDEX(別紙_テンプレート_DB!サービス予測_予測原価金額_物流,MATCH(K$2,INDEX(別紙_テンプレート_DB!サービス予測_年月,),0)),0) -> 0 | L55: =IF(ISERROR(K55/M55),0,K55/M55) -> 0 | M55: =IFERROR(INDEX(別紙_テンプレート_DB!サービス予測_予測売上金額_物流,MATCH(K$2,INDEX(別紙_テンプレート_DB!サービス予測_年月,),0)),0) -> 0
B56: 差異 | E56: =$E$45-E55 -> 0 | F56: =IF(ISERROR(E56/G56),0,E56/G56) -> 0 | G56: =G45-G55 -> 0 | H56: =H45-H55 -> 0 | I56: =IF(ISERROR(H56/J56),0,H56/J56) -> 0 | J56: =J45-J55 -> 0 | K56: =K45-K55 -> 0 | L56: =IF(ISERROR(K56/M56),0,K56/M56) -> 0 | M56: =M45-M55 -> 0

Sheet 参照
A1: 数値
A2: ブール値
A3: 文字列
A4: 日付
A5: リスト
A6: 辞書配列
